Workbook
Name LT_CategoryUS: Backend!$A$26:$A$31
Name LT_MacroDir: Backend!$A$11:$A$19
Name LT_RatePolicy: Backend!$A$20:$A$22
Name LT_RiskEnv: Backend!$A$23:$A$25
Name LT_Speakers: Backend!$A$35:$A$55
Name LT_TrendBull: Backend!$A$2:$A$7
Name LT_WeekNum: Backend!$A$8:$A$10

Sheet Instructions
B1: FOREX TRADING WORKBOOK — USER GUIDE
B2: Version 1.0 | Ready for distribution
B4: SECTION 1 — COLOR GUIDE
B6: ■ INPUT CELL | E6: YOU enter data here — these are your inputs
B7: ■ FORMULA CELL | E7: Auto-calculated by the workbook — do NOT edit
B9: SECTION 2 — HOW THIS WORKBOOK WORKS
B11: This workbook has 5 tabs:
B13: 1. Instructions | E13: You are here. Read this first.
B14: 2. Summary | E14: Monthly performance dashboard. Fill once per month.
B15: 3. Daily Log | E15: Your daily trading journal. Fill each trading day.
B16: 4. Raw daily data | E16: Paste your broker trade history here daily.
B17: 5. Setup Planner | E17: Fill before each trading session for auto trade plan.
B19: Data Flow:
B20: Raw daily data ➜ Daily Log ➜ Summary (automatic aggregation)
B21: Your inputs ➜ Setup Planner ➜ Trade Plan (automatic calculation)
B23: SECTION 3 — SUMMARY TAB
B25: Fill these 6 cells at the start of each month:
B27: Monthly Target ($) | E27: How much you aim to make this month
B28: Active Trading Days | E28: How many days you plan to trade
B29: Weeks in Cycle | E29: Usually 4
B30: Risk % per trade | E30: e.g. 0.07 = 7% of NAV
B31: Max Daily Loss (R) | E31: e.g. 2 = stop after -2R intraday
B32: Current NAV ($) | E32: Your account balance on day 1
B34: Everything else auto-calculates:
B35: Projected P&L | E35: Forecast if you maintain current pace
B36: Required R/Day | E36: How many R you need each remaining day
B37: Weekly Table | E37: Auto-summary for each of the 4 weeks
B39: SECTION 4 — DAILY LOG TAB
B41: Each trading day, fill only these 4 columns:
B43: Column A | E43: Today's date
B44: Column B | E44: Week of the cycle (1, 2, 3, or 4)
B45: Column D | E45: Y if you traded, N if not
B46: Column M | E46: Notes — psychology, conditions, lessons
B48: ⚠ Do NOT touch columns E–L, N–Y — they auto-calculate.
B50: Column reference:
B51: E=NAV | F=Risk$ | G=MaxLoss | H=P&L | I=CumPnL | J=WeekPnL | K=Target | L=Variance
B52: N=#Trades | O=#Wins | P=#Loss | Q=Win$ | R=Loss$ | S=WinRate | T=R:R | U=DailyR | V=Loss%
B54: SECTION 5 — RAW DAILY DATA TAB
B56: How to import from your broker (MT4/MT5):
B58: Step 1: In MT4/MT5, go to Account History
B59: Step 2: Right-click → Save as Report → select date range
B60: Step 3: Open exported file, copy: Symbol | Name | Side | Qty | Price | Profit | DealID | Time
B61: Step 4: Delete rows 2+ in 'Raw daily data' tab
B62: Step 5: Paste data starting from row 2, columns A–H
B64: ⚠ IMPORTANT:
... B71: Fill this every morning before your trading session.
B73: Step 1 — EMAs | E73: EMA 9/21/50 (15m), SMA200 (15m), EMA50 (1H/4H), EMA 50/100/200 (1D), EMA50 (1W), EMA20 (1M), Current Price
B74: Step 2 — RSI & Vol | E74: RSI(14) from 15m, 1H, 4H | ATR(14) 15m | ADR(14)
B75: Step 3 — Levels | E75: PWH/PWL, PDH/PDL, EQH/EQL, 15m Swing Leg, Session H/L, 4H HTF Swing H/L
B76: Step 4 — FVG Zones | E76: Daily FVG high/low, 1H FVG high/low (leave blank if none)
B77: Step 5 — Gamma | E77: Up to 4 strikes + size in billions (optional)
B79: Step 6 — Read the Outputs (auto-calculated):
B81: SIDE | E81: LONG or SHORT — based on HTF EMA alignment
B82: TRADE MODE | E82: CoreLong / A+Long / CTshort / Avoid
B83: LADDERS | E83: Primary / Value / A+ / CT — Fibonacci entry rungs
B84: NARRATIVE | E84: Plain English macro + structure summary
B86: Trade Mode explained:
B88: CoreLong | E88: HTF trend aligned — standard continuation trade
B89: A+Long | E89: Premium deep zone — can size up slightly
B90: CTshort | E90: Counter-trend fade — reduce size
B91: Avoid | E91: Conditions not met — do NOT trade today
B93: SECTION 7 — MACRO DATA (advanced users)
B95: The macro scoring engine is pre-built. Update weekly on Mondays:
B96: · Add economic events (CPI, NFP, GDP, rate decisions)
B97: · Add central bank remarks: Hawkish / Neutral / Dovish
B98: → Contact your account manager for backend access.
B100: SECTION 8 — NEW MONTH RESET
B102: At the start of each new month:
B104: 1. Save current file as Trading_[Month][Year].xlsx
B105: 2. Open master template (this file)
B106: 3. Update Summary → Current NAV = last month's ending balance
B107: 4. Update Summary → Monthly Target if changed
B108: 5. Delete Daily Log columns A, B, D, M content (keep formulas)
... B128: QUICK NAVIGATION — CLICK TO JUMP
B130: → Summary | E130: → Daily Log | G130: → Raw Data | I130: → Setup Planner

Sheet Summary
A1: TRADING PERFORMANCE SUMMARY | B1: TRADING PERFORMANCE SUMMARY2
A2: Monthly Target ($) | B2: 2000
A3: Planned Active Trading Days | B3: 20
A4: Average Target per Trading Day ($) | B4: =IFERROR(B2/B3,"") -> 100
A5: Weeks in Cycle | B5: 4
A6: Average Target per Week ($) | B6: =IFERROR(B2/B5,"") -> 500
A7: Required R per week | B7: =IFERROR(B6/B17,"") -> 0.095238095
A8: Risk % of NAV per trade | B8: 0.05
A9: Max Daily Loss (R multiples) | B9: 2
A10: Starting NAV ($) | B10: 10000 | E10: Current NAV ➔ | F10: =B10+B11 -> 11050
A11: Cumulative P&L Month ($) | B11: =SUM('Daily Log'!$H$2:$H$100) -> 1050
A12: Remaining Target ($) | B12: =IFERROR(IF(B11="",B2,B2-B11),"") -> 950
A13: Trading Days Used | B13: =COUNTIFS('Daily Log'!D:D,"Y") -> 4
A14: Trading Days Remaining | B14: =B3-B13 -> 16
A15: Required P&L per Remaining Day | B15: =IFERROR(IF(B14>0,B12/B14,""),"") -> 59.375
A16: Target R per Day (approx) | B16: =IFERROR(IF(B8>0,B15/(B10*B8),""),"") -> 0.11875
A17: Projected Month P&L ($) | B17: =IFERROR(IF(B11="","",B11/MAX(1,B13)*B3),"") -> 5250
A18: Average R value ($) | B18: =IFERROR(IF(K22>0,B11/K22,""),"")
A19: Today’s expected plan P&L ($) | B19: ='Advanced Setup Planner'!EE18 -> 3796457.1
A21: Week # | B21: Active Days | C21: Total Trades | D21: Total Wins | E21: Total Losses | F21: Week Net P&L | G21: Weekly Target | H21: Week Variance ($) | I21: Avg Win Rate % | J21: Avg Reward:Risk | K21: Total R
A22: 1 | B22: =COUNTIFS('Daily Log'!$B:$B,$A22,'Daily Log'!$D:$D,"Y") -> 1 | C22: =SUMIFS('Daily Log'!N:N,'Daily Log'!B:B,$A22) -> 1 | D22: =SUMIFS('Daily Log'!O:O,'Daily Log'!B:B,$A22) -> 1 | E22: =SUMIFS('Daily Log'!P:P,'Daily Log'!B:B,$A22) -> 0 | F22: =SUMIFS('Daily Log'!H:H,'Daily Log'!B:B,$A22) -> 250 | G22: =$B$6 -> 500 | H22: =F22-G22 -> -250 | I22: =IFERROR(D22/C22,0) -> 1 | J22: =IFERROR(SUMIFS('Daily Log'!T:T,'Daily Log'!B:B,$A22)/B22,0) -> 0 | K22: =SUMIFS('Daily Log'!U:U,'Daily Log'!B:B,$A22) -> #VALUE!
A23: 2 | B23: =COUNTIFS('Daily Log'!$B:$B,$A23,'Daily Log'!$D:$D,"Y") -> 1 | C23: =SUMIFS('Daily Log'!N:N,'Daily Log'!B:B,$A23) -> 2 | D23: =SUMIFS('Daily Log'!O:O,'Daily Log'!B:B,$A23) -> 0 | E23: =SUMIFS('Daily Log'!P:P,'Daily Log'!B:B,$A23) -> 2 | F23: =SUMIFS('Daily Log'!H:H,'Daily Log'!B:B,$A23) -> -200 | G23: =$B$6 -> 500 | H23: =F23-G23 -> -700 | I23: =IFERROR(D23/C23,0) -> 0 | J23: =IFERROR(SUMIFS('Daily Log'!T:T,'Daily Log'!B:B,$A23)/B23,0) -> 0 | K23: =SUMIFS('Daily Log'!U:U,'Daily Log'!B:B,$A23) -> #VALUE!
A24: 3 | B24: =COUNTIFS('Daily Log'!$B:$B,$A24,'Daily Log'!$D:$D,"Y") -> 2 | C24: =SUMIFS('Daily Log'!N:N,'Daily Log'!B:B,$A24) -> 2 | D24: =SUMIFS('Daily Log'!O:O,'Daily Log'!B:B,$A24) -> 2 | E24: =SUMIFS('Daily Log'!P:P,'Daily Log'!B:B,$A24) -> 0 | F24: =SUMIFS('Daily Log'!H:H,'Daily Log'!B:B,$A24) -> 1000 | G24: =$B$6 -> 500 | H24: =F24-G24 -> 500 | I24: =IFERROR(D24/C24,0) -> 1 | J24: =IFERROR(SUMIFS('Daily Log'!T:T,'Daily Log'!B:B,$A24)/B24,0) -> 0 | K24: =SUMIFS('Daily Log'!U:U,'Daily Log'!B:B,$A24) -> #VALUE!
A25: 4 | B25: =COUNTIFS('Daily Log'!$B:$B,$A25,'Daily Log'!$D:$D,"Y") -> 0 | C25: =SUMIFS('Daily Log'!N:N,'Daily Log'!B:B,$A25) -> 0 | D25: =SUMIFS('Daily Log'!O:O,'Daily Log'!B:B,$A25) -> 0 | E25: =SUMIFS('Daily Log'!P:P,'Daily Log'!B:B,$A25) -> 0 | F25: =SUMIFS('Daily Log'!H:H,'Daily Log'!B:B,$A25) -> 0 | G25: =$B$6 -> 500 | H25: =F25-G25 -> -500 | I25: =IFERROR(D25/C25,0) -> 0 | J25: =IFERROR(SUMIFS('Daily Log'!T:T,'Daily Log'!B:B,$A25)/B25,0) -> 0 | K25: =SUMIFS('Daily Log'!U:U,'Daily Log'!B:B,$A25) -> 0

Sheet Daily Log
A1: Date | B1: Week # | C1: Day of Week | D1: Active Trading Day? (Y/N) | E1: Start NAV ($) | F1: Risk per Trade R ($) | G1: Max Daily Loss Cap ($) | H1: Net P&L ($) | I1: Cumulative P&L Month ($) | J1: Week P&L ($) | K1: Weekly Target ($) | L1: Week Variance vs Target ($) | M1: Notes | N1: # Trades | O1: # Wins | P1: # Losses | Q1: Total Wins ($) | R1: Total Losses ($) | S1: Win Rate (%) | T1: Reward:Risk | U1: Daily R-multiple | V1: Losses vs Cap | W1: Intraday Net P&L (so far) | X1: % of Cap Used (Net) | Y1: Worst Intraday DD % of Cap
A2: 46143 | B2: 1 | C2: =IF($A2="","",TEXT($A2,"dddd")) -> Friday | D2: Y | E2: =IF($A2="","", E1+H1) -> #VALUE! | F2: =IF($A2="","",$E2*Summary!$B$8) -> #VALUE! | G2: =IF($A2="","",F2*Summary!$B$9) -> #VALUE! | H2: =IF($A2="","",SUMIFS('Raw daily data'!$F:$F,'Raw daily data'!$I:$I,$A2)) -> 250 | I2: =IF($A2="","", I1+H2) -> #VALUE! | J2: =IF($A2="","",SUMIF($B$2:$B$100,B2,$H$2:$H$100)) -> 250 | K2: =IF($A2="","",Summary!$B$6) -> 500 | L2: =IF($A2="","",IFERROR(J2-K2,"")) -> -250 | N2: =IF($A2="","",COUNTIFS('Raw daily data'!$I:$I,$A2)) -> 1 | O2: =IF($A2="","",COUNTIFS('Raw daily data'!$I:$I,$A2,'Raw daily data'!$F:$F,">0")) -> 1 | P2: =IF($A2="","",COUNTIFS('Raw daily data'!$I:$I,$A2,'Raw daily data'!$F:$F,"<0")) -> 0 | Q2: =IF($A2="","",SUMIFS('Raw daily data'!$F:$F,'Raw daily data'!$I:$I,$A2,'Raw daily data'!$F:$F,">0")) -> 250 | R2: =IF($A2="","",ABS(SUMIFS('Raw daily data'!$F:$F,'Raw daily data'!$I:$I,$A2,'Raw daily data'!$F:$F,"<0"))) -> 0 | S2: =IF($A2="","",IF(N2>0,O2/N2,"")) -> 1 | T2: =IF($A2="","",IF(R2>0,Q2/ABS(R2),"")) | U2: =IF($A2="","",IF(F2>0,H2/F2,"")) -> #VALUE! | V2: =IF($A2="","",IFERROR(IF(H2<0,MIN(ABS(H2)/G2,1),0),"")) -> 0 | W2: =IF($A2="","",_xlfn.MAXIFS('Raw daily data'!$J:$J,'Raw daily data'!$I:$I,$A2)) -> 250 | X2: =IF($A2="","",IFERROR(IF(W2>=0,0,ABS(W2)/G2),"")) -> 0 | Y2: =IF($A2="","",IFERROR(ABS(MIN(0,_xlfn.MINIFS('Raw daily data'!$J:$J,'Raw daily data'!$I:$I,$A2)))/G2,""))
A3: 46151 | B3: 2 | C3: =IF($A3="","",TEXT($A3,"dddd")) -> Saturday | D3: Y | E3: =IF($A3="","", E2+H2) -> #VALUE! | F3: =IF($A3="","",$E3*Summary!$B$8) -> #VALUE! | G3: =IF($A3="","",F3*Summary!$B$9) -> #VALUE! | H3: =IF($A3="","",SUMIFS('Raw daily data'!$F:$F,'Raw daily data'!$I:$I,$A3)) -> -200 | I3: =IF($A3="","", I2+H3) -> #VALUE! | J3: =IF($A3="","",SUMIF($B$2:$B$100,B3,$H$2:$H$100)) -> -200 | K3: =IF($A3="","",Summary!$B$6) -> 500 | L3: =IF($A3="","",IFERROR(J3-K3,"")) -> -700 | N3: =IF($A3="","",COUNTIFS('Raw daily data'!$I:$I,$A3)) -> 2 | O3: =IF($A3="","",COUNTIFS('Raw daily data'!$I:$I,$A3,'Raw daily data'!$F:$F,">0")) -> 0 | P3: =IF($A3="","",COUNTIFS('Raw daily data'!$I:$I,$A3,'Raw daily data'!$F:$F,"<0")) -> 2 | Q3: =IF($A3="","",SUMIFS('Raw daily data'!$F:$F,'Raw daily data'!$I:$I,$A3,'Raw daily data'!$F:$F,">0")) -> 0 | R3: =IF($A3="","",ABS(SUMIFS('Raw daily data'!$F:$F,'Raw daily data'!$I:$I,$A3,'Raw daily data'!$F:$F,"<0"))) -> 200 | S3: =IF($A3="","",IF(N3>0,O3/N3,"")) -> 0 | T3: =IF($A3="","",IF(R3>0,Q3/ABS(R3),"")) -> 0 | U3: =IF($A3="","",IF(F3>0,H3/F3,"")) -> #VALUE! | V3: =IF($A3="","",IFERROR(IF(H3<0,MIN(ABS(H3)/G3,1),0),"")) | W3: =IF($A3="","",_xlfn.MAXIFS('Raw daily data'!$J:$J,'Raw daily data'!$I:$I,$A3)) -> -100 | X3: =IF($A3="","",IFERROR(IF(W3>=0,0,ABS(W3)/G3),"")) | Y3: =IF($A3="","",IFERROR(ABS(MIN(0,_xlfn.MINIFS('Raw daily data'!$J:$J,'Raw daily data'!$I:$I,$A3)))/G3,""))
A4: 46159 | B4: 3 | C4: =IF($A4="","",TEXT($A4,"dddd")) -> Sunday | D4: Y | E4: =IF($A4="","", E3+H3) -> #VALUE! | F4: =IF($A4="","",$E4*Summary!$B$8) -> #VALUE! | G4: =IF($A4="","",F4*Summary!$B$9) -> #VALUE! | H4: =IF($A4="","",SUMIFS('Raw daily data'!$F:$F,'Raw daily data'!$I:$I,$A4)) -> 800 | I4: =IF($A4="","", I3+H4) -> #VALUE! | J4: =IF($A4="","",SUMIF($B$2:$B$100,B4,$H$2:$H$100)) -> 1000 | K4: =IF($A4="","",Summary!$B$6) -> 500 | L4: =IF($A4="","",IFERROR(J4-K4,"")) -> 500 | N4: =IF($A4="","",COUNTIFS('Raw daily data'!$I:$I,$A4)) -> 1 | O4: =IF($A4="","",COUNTIFS('Raw daily data'!$I:$I,$A4,'Raw daily data'!$F:$F,">0")) -> 1 | P4: =IF($A4="","",COUNTIFS('Raw daily data'!$I:$I,$A4,'Raw daily data'!$F:$F,"<0")) -> 0 | Q4: =IF($A4="","",SUMIFS('Raw daily data'!$F:$F,'Raw daily data'!$I:$I,$A4,'Raw daily data'!$F:$F,">0")) -> 800 | R4: =IF($A4="","",ABS(SUMIFS('Raw daily data'!$F:$F,'Raw daily data'!$I:$I,$A4,'Raw daily data'!$F:$F,"<0"))) -> 0 | S4: =IF($A4="","",IF(N4>0,O4/N4,"")) -> 1 | T4: =IF($A4="","",IF(R4>0,Q4/ABS(R4),"")) | U4: =IF($A4="","",IF(F4>0,H4/F4,"")) -> #VALUE! | V4: =IF($A4="","",IFERROR(IF(H4<0,MIN(ABS(H4)/G4,1),0),"")) -> 0 | W4: =IF($A4="","",_xlfn.MAXIFS('Raw daily data'!$J:$J,'Raw daily data'!$I:$I,$A4)) -> 800 | X4: =IF($A4="","",IFERROR(IF(W4>=0,0,ABS(W4)/G4),"")) -> 0 | Y4: =IF($A4="","",IFERROR(ABS(MIN(0,_xlfn.MINIFS('Raw daily data'!$J:$J,'Raw daily data'!$I:$I,$A4)))/G4,""))
A5: 46160 | B5: 3 | C5: =IF($A5="","",TEXT($A5,"dddd")) -> Monday | D5: Y | E5: =IF($A5="","", E4+H4) -> #VALUE! | F5: =IF($A5="","",$E5*Summary!$B$8) -> #VALUE! | G5: =IF($A5="","",F5*Summary!$B$9) -> #VALUE! | H5: =IF($A5="","",SUMIFS('Raw daily data'!$F:$F,'Raw daily data'!$I:$I,$A5)) -> 200 | I5: =IF($A5="","", I4+H5) -> #VALUE! | J5: =IF($A5="","",SUMIF($B$2:$B$100,B5,$H$2:$H$100)) -> 1000 | K5: =IF($A5="","",Summary!$B$6) -> 500 | L5: =IF($A5="","",IFERROR(J5-K5,"")) -> 500 | N5: =IF($A5="","",COUNTIFS('Raw daily data'!$I:$I,$A5)) -> 1 | O5: =IF($A5="","",COUNTIFS('Raw daily data'!$I:$I,$A5,'Raw daily data'!$F:$F,">0")) -> 1 | P5: =IF($A5="","",COUNTIFS('Raw daily data'!$I:$I,$A5,'Raw daily data'!$F:$F,"<0")) -> 0 | Q5: =IF($A5="","",SUMIFS('Raw daily data'!$F:$F,'Raw daily data'!$I:$I,$A5,'Raw daily data'!$F:$F,">0")) -> 200 | R5: =IF($A5="","",ABS(SUMIFS('Raw daily data'!$F:$F,'Raw daily data'!$I:$I,$A5,'Raw daily data'!$F:$F,"<0"))) -> 0 | S5: =IF($A5="","",IF(N5>0,O5/N5,"")) -> 1 | T5: =IF($A5="","",IF(R5>0,Q5/ABS(R5),"")) | U5: =IF($A5="","",IF(F5>0,H5/F5,"")) -> #VALUE! | V5: =IF($A5="","",IFERROR(IF(H5<0,MIN(ABS(H5)/G5,1),0),"")) -> 0 | W5: =IF($A5="","",_xlfn.MAXIFS('Raw daily data'!$J:$J,'Raw daily data'!$I:$I,$A5)) -> 200 | X5: =IF($A5="","",IFERROR(IF(W5>=0,0,ABS(W5)/G5),"")) -> 0 | Y5: =IF($A5="","",IFERROR(ABS(MIN(0,_xlfn.MINIFS('Raw daily data'!$J:$J,'Raw daily data'!$I:$I,$A5)))/G5,""))
C6: =IF($A6="","",TEXT($A6,"dddd")) | E6: =IF($A6="","", E5+H5) | F6: =IF($A6="","",$E6*Summary!$B$8) | G6: =IF($A6="","",F6*Summary!$B$9) | H6: =IF($A6="","",SUMIFS('Raw daily data'!$F:$F,'Raw daily data'!$I:$I,$A6)) | I6: =IF($A6="","", I5+H6) | J6: =IF($A6="","",SUMIF($B$2:$B$100,B6,$H$2:$H$100)) | K6: =IF($A6="","",Summary!$B$6) | L6: =IF($A6="","",IFERROR(J6-K6,"")) | N6: =IF($A6="","",COUNTIFS('Raw daily data'!$I:$I,$A6)) | O6: =IF($A6="","",COUNTIFS('Raw daily data'!$I:$I,$A6,'Raw daily data'!$F:$F,">0")) | P6: =IF($A6="","",COUNTIFS('Raw daily data'!$I:$I,$A6,'Raw daily data'!$F:$F,"<0")) | Q6: =IF($A6="","",SUMIFS('Raw daily data'!$F:$F,'Raw daily data'!$I:$I,$A6,'Raw daily data'!$F:$F,">0")) | R6: =IF($A6="","",ABS(SUMIFS('Raw daily data'!$F:$F,'Raw daily data'!$I:$I,$A6,'Raw daily data'!$F:$F,"<0"))) | S6: =IF($A6="","",IF(N6>0,O6/N6,"")) | T6: =IF($A6="","",IF(R6>0,Q6/ABS(R6),"")) | U6: =IF($A6="","",IF(F6>0,H6/F6,"")) | V6: =IF($A6="","",IFERROR(IF(H6<0,MIN(ABS(H6)/G6,1),0),"")) | W6: =IF($A6="","",_xlfn.MAXIFS('Raw daily data'!$J:$J,'Raw daily data'!$I:$I,$A6)) | X6: =IF($A6="","",IFERROR(IF(W6>=0,0,ABS(W6)/G6),"")) | Y6: =IF($A6="","",IFERROR(ABS(MIN(0,_xlfn.MINIFS('Raw daily data'!$J:$J,'Raw daily data'!$I:$I,$A6)))/G6,""))
C7: =IF($A7="","",TEXT($A7,"dddd")) | E7: =IF($A7="","", E6+H6) | F7: =IF($A7="","",$E7*Summary!$B$8) | G7: =IF($A7="","",F7*Summary!$B$9) | H7: =IF($A7="","",SUMIFS('Raw daily data'!$F:$F,'Raw daily data'!$I:$I,$A7)) | I7: =IF($A7="","", I6+H7) | J7: =IF($A7="","",SUMIF($B$2:$B$100,B7,$H$2:$H$100)) | K7: =IF($A7="","",Summary!$B$6) | L7: =IF($A7="","",IFERROR(J7-K7,"")) | N7: =IF($A7="","",COUNTIFS('Raw daily data'!$I:$I,$A7)) | O7: =IF($A7="","",COUNTIFS('Raw daily data'!$I:$I,$A7,'Raw daily data'!$F:$F,">0")) | P7: =IF($A7="","",COUNTIFS('Raw daily data'!$I:$I,$A7,'Raw daily data'!$F:$F,"<0")) | Q7: =IF($A7="","",SUMIFS('Raw daily data'!$F:$F,'Raw daily data'!$I:$I,$A7,'Raw daily data'!$F:$F,">0")) | R7: =IF($A7="","",ABS(SUMIFS('Raw daily data'!$F:$F,'Raw daily data'!$I:$I,$A7,'Raw daily data'!$F:$F,"<0"))) | S7: =IF($A7="","",IF(N7>0,O7/N7,"")) | T7: =IF($A7="","",IF(R7>0,Q7/ABS(R7),"")) | U7: =IF($A7="","",IF(F7>0,H7/F7,"")) | V7: =IF($A7="","",IFERROR(IF(H7<0,MIN(ABS(H7)/G7,1),0),"")) | W7: =IF($A7="","",_xlfn.MAXIFS('Raw daily data'!$J:$J,'Raw daily data'!$I:$I,$A7)) | X7: =IF($A7="","",IFERROR(IF(W7>=0,0,ABS(W7)/G7),"")) | Y7: =IF($A7="","",IFERROR(ABS(MIN(0,_xlfn.MINIFS('Raw daily data'!$J:$J,'Raw daily data'!$I:$I,$A7)))/G7,""))
C8: =IF($A8="","",TEXT($A8,"dddd")) | E8: =IF($A8="","", E7+H7) | F8: =IF($A8="","",$E8*Summary!$B$8) | G8: =IF($A8="","",F8*Summary!$B$9) | H8: =IF($A8="","",SUMIFS('Raw daily data'!$F:$F,'Raw daily data'!$I:$I,$A8)) | I8: =IF($A8="","", I7+H8) | J8: =IF($A8="","",SUMIF($B$2:$B$100,B8,$H$2:$H$100)) | K8: =IF($A8="","",Summary!$B$6) | L8: =IF($A8="","",IFERROR(J8-K8,"")) | N8: =IF($A8="","",COUNTIFS('Raw daily data'!$I:$I,$A8)) | O8: =IF($A8="","",COUNTIFS('Raw daily data'!$I:$I,$A8,'Raw daily data'!$F:$F,">0")) | P8: =IF($A8="","",COUNTIFS('Raw daily data'!$I:$I,$A8,'Raw daily data'!$F:$F,"<0")) | Q8: =IF($A8="","",SUMIFS('Raw daily data'!$F:$F,'Raw daily data'!$I:$I,$A8,'Raw daily data'!$F:$F,">0")) | R8: =IF($A8="","",ABS(SUMIFS('Raw daily data'!$F:$F,'Raw daily data'!$I:$I,$A8,'Raw daily data'!$F:$F,"<0"))) | S8: =IF($A8="","",IF(N8>0,O8/N8,"")) | T8: =IF($A8="","",IF(R8>0,Q8/ABS(R8),"")) | U8: =IF($A8="","",IF(F8>0,H8/F8,"")) | V8: =IF($A8="","",IFERROR(IF(H8<0,MIN(ABS(H8)/G8,1),0),"")) | W8: =IF($A8="","",_xlfn.MAXIFS('Raw daily data'!$J:$J,'Raw daily data'!$I:$I,$A8)) | X8: =IF($A8="","",IFERROR(IF(W8>=0,0,ABS(W8)/G8),"")) | Y8: =IF($A8="","",IFERROR(ABS(MIN(0,_xlfn.MINIFS('Raw daily data'!$J:$J,'Raw daily data'!$I:$I,$A8)))/G8,""))
C9: =IF($A9="","",TEXT($A9,"dddd")) | E9: =IF($A9="","", E8+H8) | F9: =IF($A9="","",$E9*Summary!$B$8) | G9: =IF($A9="","",F9*Summary!$B$9) | H9: =IF($A9="","",SUMIFS('Raw daily data'!$F:$F,'Raw daily data'!$I:$I,$A9)) | I9: =IF($A9="","", I8+H9) | J9: =IF($A9="","",SUMIF($B$2:$B$100,B9,$H$2:$H$100)) | K9: =IF($A9="","",Summary!$B$6) | L9: =IF($A9="","",IFERROR(J9-K9,"")) | N9: =IF($A9="","",COUNTIFS('Raw daily data'!$I:$I,$A9)) | O9: =IF($A9="","",COUNTIFS('Raw daily data'!$I:$I,$A9,'Raw daily data'!$F:$F,">0")) | P9: =IF($A9="","",COUNTIFS('Raw daily data'!$I:$I,$A9,'Raw daily data'!$F:$F,"<0")) | Q9: =IF($A9="","",SUMIFS('Raw daily data'!$F:$F,'Raw daily data'!$I:$I,$A9,'Raw daily data'!$F:$F,">0")) | R9: =IF($A9="","",ABS(SUMIFS('Raw daily data'!$F:$F,'Raw daily data'!$I:$I,$A9,'Raw daily data'!$F:$F,"<0"))) | S9: =IF($A9="","",IF(N9>0,O9/N9,"")) | T9: =IF($A9="","",IF(R9>0,Q9/ABS(R9),"")) | U9: =IF($A9="","",IF(F9>0,H9/F9,"")) | V9: =IF($A9="","",IFERROR(IF(H9<0,MIN(ABS(H9)/G9,1),0),"")) | W9: =IF($A9="","",_xlfn.MAXIFS('Raw daily data'!$J:$J,'Raw daily data'!$I:$I,$A9)) | X9: =IF($A9="","",IFERROR(IF(W9>=0,0,ABS(W9)/G9),"")) | Y9: =IF($A9="","",IFERROR(ABS(MIN(0,_xlfn.MINIFS('Raw daily data'!$J:$J,'Raw daily data'!$I:$I,$A9)))/G9,""))
C10: =IF($A10="","",TEXT($A10,"dddd")) | E10: =IF($A10="","", E9+H9) | F10: =IF($A10="","",$E10*Summary!$B$8) | G10: =IF($A10="","",F10*Summary!$B$9) | H10: =IF($A10="","",SUMIFS('Raw daily data'!$F:$F,'Raw daily data'!$I:$I,$A10)) | I10: =IF($A10="","", I9+H10) | J10: =IF($A10="","",SUMIF($B$2:$B$100,B10,$H$2:$H$100)) | K10: =IF($A10="","",Summary!$B$6) | L10: =IF($A10="","",IFERROR(J10-K10,"")) | N10: =IF($A10="","",COUNTIFS('Raw daily data'!$I:$I,$A10)) | O10: =IF($A10="","",COUNTIFS('Raw daily data'!$I:$I,$A10,'Raw daily data'!$F:$F,">0")) | P10: =IF($A10="","",COUNTIFS('Raw daily data'!$I:$I,$A10,'Raw daily data'!$F:$F,"<0")) | Q10: =IF($A10="","",SUMIFS('Raw daily data'!$F:$F,'Raw daily data'!$I:$I,$A10,'Raw daily data'!$F:$F,">0")) | R10: =IF($A10="","",ABS(SUMIFS('Raw daily data'!$F:$F,'Raw daily data'!$I:$I,$A10,'Raw daily data'!$F:$F,"<0"))) | S10: =IF($A10="","",IF(N10>0,O10/N10,"")) | T10: =IF($A10="","",IF(R10>0,Q10/ABS(R10),"")) | U10: =IF($A10="","",IF(F10>0,H10/F10,"")) | V10: =IF($A10="","",IFERROR(IF(H10<0,MIN(ABS(H10)/G10,1),0),"")) | W10: =IF($A10="","",_xlfn.MAXIFS('Raw daily data'!$J:$J,'Raw daily data'!$I:$I,$A10)) | X10: =IF($A10="","",IFERROR(IF(W10>=0,0,ABS(W10)/G10),"")) | Y10: =IF($A10="","",IFERROR(ABS(MIN(0,_xlfn.MINIFS('Raw daily data'!$J:$J,'Raw daily data'!$I:$I,$A10)))/G10,""))
C11: =IF($A11="","",TEXT($A11,"dddd")) | E11: =IF($A11="","", E10+H10) | F11: =IF($A11="","",$E11*Summary!$B$8) | G11: =IF($A11="","",F11*Summary!$B$9) | H11: =IF($A11="","",SUMIFS('Raw daily data'!$F:$F,'Raw daily data'!$I:$I,$A11)) | I11: =IF($A11="","", I10+H11) | J11: =IF($A11="","",SUMIF($B$2:$B$100,B11,$H$2:$H$100)) | K11: =IF($A11="","",Summary!$B$6) | L11: =IF($A11="","",IFERROR(J11-K11,"")) | N11: =IF($A11="","",COUNTIFS('Raw daily data'!$I:$I,$A11)) | O11: =IF($A11="","",COUNTIFS('Raw daily data'!$I:$I,$A11,'Raw daily data'!$F:$F,">0")) | P11: =IF($A11="","",COUNTIFS('Raw daily data'!$I:$I,$A11,'Raw daily data'!$F:$F,"<0")) | Q11: =IF($A11="","",SUMIFS('Raw daily data'!$F:$F,'Raw daily data'!$I:$I,$A11,'Raw daily data'!$F:$F,">0")) | R11: =IF($A11="","",ABS(SUMIFS('Raw daily data'!$F:$F,'Raw daily data'!$I:$I,$A11,'Raw daily data'!$F:$F,"<0"))) | S11: =IF($A11="","",IF(N11>0,O11/N11,"")) | T11: =IF($A11="","",IF(R11>0,Q11/ABS(R11),"")) | U11: =IF($A11="","",IF(F11>0,H11/F11,"")) | V11: =IF($A11="","",IFERROR(IF(H11<0,MIN(ABS(H11)/G11,1),0),"")) | W11: =IF($A11="","",_xlfn.MAXIFS('Raw daily data'!$J:$J,'Raw daily data'!$I:$I,$A11)) | X11: =IF($A11="","",IFERROR(IF(W11>=0,0,ABS(W11)/G11),"")) | Y11: =IF($A11="","",IFERROR(ABS(MIN(0,_xlfn.MINIFS('Raw daily data'!$J:$J,'Raw daily data'!$I:$I,$A11)))/G11,""))
C12: =IF($A12="","",TEXT($A12,"dddd")) | E12: =IF($A12="","", E11+H11) | F12: =IF($A12="","",$E12*Summary!$B$8) | G12: =IF($A12="","",F12*Summary!$B$9) | H12: =IF($A12="","",SUMIFS('Raw daily data'!$F:$F,'Raw daily data'!$I:$I,$A12)) | I12: =IF($A12="","", I11+H12) | J12: =IF($A12="","",SUMIF($B$2:$B$100,B12,$H$2:$H$100)) | K12: =IF($A12="","",Summary!$B$6) | L12: =IF($A12="","",IFERROR(J12-K12,"")) | N12: =IF($A12="","",COUNTIFS('Raw daily data'!$I:$I,$A12)) | O12: =IF($A12="","",COUNTIFS('Raw daily data'!$I:$I,$A12,'Raw daily data'!$F:$F,">0")) | P12: =IF($A12="","",COUNTIFS('Raw daily data'!$I:$I,$A12,'Raw daily data'!$F:$F,"<0")) | Q12: =IF($A12="","",SUMIFS('Raw daily data'!$F:$F,'Raw daily data'!$I:$I,$A12,'Raw daily data'!$F:$F,">0")) | R12: =IF($A12="","",ABS(SUMIFS('Raw daily data'!$F:$F,'Raw daily data'!$I:$I,$A12,'Raw daily data'!$F:$F,"<0"))) | S12: =IF($A12="","",IF(N12>0,O12/N12,"")) | T12: =IF($A12="","",IF(R12>0,Q12/ABS(R12),"")) | U12: =IF($A12="","",IF(F12>0,H12/F12,"")) | V12: =IF($A12="","",IFERROR(IF(H12<0,MIN(ABS(H12)/G12,1),0),"")) | W12: =IF($A12="","",_xlfn.MAXIFS('Raw daily data'!$J:$J,'Raw daily data'!$I:$I,$A12)) | X12: =IF($A12="","",IFERROR(IF(W12>=0,0,ABS(W12)/G12),"")) | Y12: =IF($A12="","",IFERROR(ABS(MIN(0,_xlfn.MINIFS('Raw daily data'!$J:$J,'Raw daily data'!$I:$I,$A12)))/G12,""))
C13: =IF($A13="","",TEXT($A13,"dddd")) | E13: =IF($A13="","", E12+H12) | F13: =IF($A13="","",$E13*Summary!$B$8) | G13: =IF($A13="","",F13*Summary!$B$9) | H13: =IF($A13="","",SUMIFS('Raw daily data'!$F:$F,'Raw daily data'!$I:$I,$A13)) | I13: =IF($A13="","", I12+H13) | J13: =IF($A13="","",SUMIF($B$2:$B$100,B13,$H$2:$H$100)) | K13: =IF($A13="","",Summary!$B$6) | L13: =IF($A13="","",IFERROR(J13-K13,"")) | N13: =IF($A13="","",COUNTIFS('Raw daily data'!$I:$I,$A13)) | O13: =IF($A13="","",COUNTIFS('Raw daily data'!$I:$I,$A13,'Raw daily data'!$F:$F,">0")) | P13: =IF($A13="","",COUNTIFS('Raw daily data'!$I:$I,$A13,'Raw daily data'!$F:$F,"<0")) | Q13: =IF($A13="","",SUMIFS('Raw daily data'!$F:$F,'Raw daily data'!$I:$I,$A13,'Raw daily data'!$F:$F,">0")) | R13: =IF($A13="","",ABS(SUMIFS('Raw daily data'!$F:$F,'Raw daily data'!$I:$I,$A13,'Raw daily data'!$F:$F,"<0"))) | S13: =IF($A13="","",IF(N13>0,O13/N13,"")) | T13: =IF($A13="","",IF(R13>0,Q13/ABS(R13),"")) | U13: =IF($A13="","",IF(F13>0,H13/F13,"")) | V13: =IF($A13="","",IFERROR(IF(H13<0,MIN(ABS(H13)/G13,1),0),"")) | W13: =IF($A13="","",_xlfn.MAXIFS('Raw daily data'!$J:$J,'Raw daily data'!$I:$I,$A13)) | X13: =IF($A13="","",IFERROR(IF(W13>=0,0,ABS(W13)/G13),"")) | Y13: =IF($A13="","",IFERROR(ABS(MIN(0,_xlfn.MINIFS('Raw daily data'!$J:$J,'Raw daily data'!$I:$I,$A13)))/G13,""))
C14: =IF($A14="","",TEXT($A14,"dddd")) | E14: =IF($A14="","", E13+H13) | F14: =IF($A14="","",$E14*Summary!$B$8) | G14: =IF($A14="","",F14*Summary!$B$9) | H14: =IF($A14="","",SUMIFS('Raw daily data'!$F:$F,'Raw daily data'!$I:$I,$A14)) | I14: =IF($A14="","", I13+H14) | J14: =IF($A14="","",SUMIF($B$2:$B$100,B14,$H$2:$H$100)) | K14: =IF($A14="","",Summary!$B$6) | L14: =IF($A14="","",IFERROR(J14-K14,"")) | N14: =IF($A14="","",COUNTIFS('Raw daily data'!$I:$I,$A14)) | O14: =IF($A14="","",COUNTIFS('Raw daily data'!$I:$I,$A14,'Raw daily data'!$F:$F,">0")) | P14: =IF($A14="","",COUNTIFS('Raw daily data'!$I:$I,$A14,'Raw daily data'!$F:$F,"<0")) | Q14: =IF($A14="","",SUMIFS('Raw daily data'!$F:$F,'Raw daily data'!$I:$I,$A14,'Raw daily data'!$F:$F,">0")) | R14: =IF($A14="","",ABS(SUMIFS('Raw daily data'!$F:$F,'Raw daily data'!$I:$I,$A14,'Raw daily data'!$F:$F,"<0"))) | S14: =IF($A14="","",IF(N14>0,O14/N14,"")) | T14: =IF($A14="","",IF(R14>0,Q14/ABS(R14),"")) | U14: =IF($A14="","",IF(F14>0,H14/F14,"")) | V14: =IF($A14="","",IFERROR(IF(H14<0,MIN(ABS(H14)/G14,1),0),"")) | W14: =IF($A14="","",_xlfn.MAXIFS('Raw daily data'!$J:$J,'Raw daily data'!$I:$I,$A14)) | X14: =IF($A14="","",IFERROR(IF(W14>=0,0,ABS(W14)/G14),"")) | Y14: =IF($A14="","",IFERROR(ABS(MIN(0,_xlfn.MINIFS('Raw daily data'!$J:$J,'Raw daily data'!$I:$I,$A14)))/G14,""))
C15: =IF($A15="","",TEXT($A15,"dddd")) | E15: =IF($A15="","", E14+H14) | F15: =IF($A15="","",$E15*Summary!$B$8) | G15: =IF($A15="","",F15*Summary!$B$9) | H15: =IF($A15="","",SUMIFS('Raw daily data'!$F:$F,'Raw daily data'!$I:$I,$A15)) | I15: =IF($A15="","", I14+H15) | J15: =IF($A15="","",SUMIF($B$2:$B$100,B15,$H$2:$H$100)) | K15: =IF($A15="","",Summary!$B$6) | L15: =IF($A15="","",IFERROR(J15-K15,"")) | N15: =IF($A15="","",COUNTIFS('Raw daily data'!$I:$I,$A15)) | O15: =IF($A15="","",COUNTIFS('Raw daily data'!$I:$I,$A15,'Raw daily data'!$F:$F,">0")) | P15: =IF($A15="","",COUNTIFS('Raw daily data'!$I:$I,$A15,'Raw daily data'!$F:$F,"<0")) | Q15: =IF($A15="","",SUMIFS('Raw daily data'!$F:$F,'Raw daily data'!$I:$I,$A15,'Raw daily data'!$F:$F,">0")) | R15: =IF($A15="","",ABS(SUMIFS('Raw daily data'!$F:$F,'Raw daily data'!$I:$I,$A15,'Raw daily data'!$F:$F,"<0"))) | S15: =IF($A15="","",IF(N15>0,O15/N15,"")) | T15: =IF($A15="","",IF(R15>0,Q15/ABS(R15),"")) | U15: =IF($A15="","",IF(F15>0,H15/F15,"")) | V15: =IF($A15="","",IFERROR(IF(H15<0,MIN(ABS(H15)/G15,1),0),"")) | W15: =IF($A15="","",_xlfn.MAXIFS('Raw daily data'!$J:$J,'Raw daily data'!$I:$I,$A15)) | X15: =IF($A15="","",IFERROR(IF(W15>=0,0,ABS(W15)/G15),"")) | Y15: =IF($A15="","",IFERROR(ABS(MIN(0,_xlfn.MINIFS('Raw daily data'!$J:$J,'Raw daily data'!$I:$I,$A15)))/G15,""))
C16: =IF($A16="","",TEXT($A16,"dddd")) | E16: =IF($A16="","", E15+H15) | F16: =IF($A16="","",$E16*Summary!$B$8) | G16: =IF($A16="","",F16*Summary!$B$9) | H16: =IF($A16="","",SUMIFS('Raw daily data'!$F:$F,'Raw daily data'!$I:$I,$A16)) | I16: =IF($A16="","", I15+H16) | J16: =IF($A16="","",SUMIF($B$2:$B$100,B16,$H$2:$H$100)) | K16: =IF($A16="","",Summary!$B$6) | L16: =IF($A16="","",IFERROR(J16-K16,"")) | N16: =IF($A16="","",COUNTIFS('Raw daily data'!$I:$I,$A16)) | O16: =IF($A16="","",COUNTIFS('Raw daily data'!$I:$I,$A16,'Raw daily data'!$F:$F,">0")) | P16: =IF($A16="","",COUNTIFS('Raw daily data'!$I:$I,$A16,'Raw daily data'!$F:$F,"<0")) | Q16: =IF($A16="","",SUMIFS('Raw daily data'!$F:$F,'Raw daily data'!$I:$I,$A16,'Raw daily data'!$F:$F,">0")) | R16: =IF($A16="","",ABS(SUMIFS('Raw daily data'!$F:$F,'Raw daily data'!$I:$I,$A16,'Raw daily data'!$F:$F,"<0"))) | S16: =IF($A16="","",IF(N16>0,O16/N16,"")) | T16: =IF($A16="","",IF(R16>0,Q16/ABS(R16),"")) | U16: =IF($A16="","",IF(F16>0,H16/F16,"")) | V16: =IF($A16="","",IFERROR(IF(H16<0,MIN(ABS(H16)/G16,1),0),"")) | W16: =IF($A16="","",_xlfn.MAXIFS('Raw daily data'!$J:$J,'Raw daily data'!$I:$I,$A16)) | X16: =IF($A16="","",IFERROR(IF(W16>=0,0,ABS(W16)/G16),"")) | Y16: =IF($A16="","",IFERROR(ABS(MIN(0,_xlfn.MINIFS('Raw daily data'!$J:$J,'Raw daily data'!$I:$I,$A16)))/G16,""))
C17: =IF($A17="","",TEXT($A17,"dddd")) | E17: =IF($A17="","", E16+H16) | F17: =IF($A17="","",$E17*Summary!$B$8) | G17: =IF($A17="","",F17*Summary!$B$9) | H17: =IF($A17="","",SUMIFS('Raw daily data'!$F:$F,'Raw daily data'!$I:$I,$A17)) | I17: =IF($A17="","", I16+H17) | J17: =IF($A17="","",SUMIF($B$2:$B$100,B17,$H$2:$H$100)) | K17: =IF($A17="","",Summary!$B$6) | L17: =IF($A17="","",IFERROR(J17-K17,"")) | N17: =IF($A17="","",COUNTIFS('Raw daily data'!$I:$I,$A17)) | O17: =IF($A17="","",COUNTIFS('Raw daily data'!$I:$I,$A17,'Raw daily data'!$F:$F,">0")) | P17: =IF($A17="","",COUNTIFS('Raw daily data'!$I:$I,$A17,'Raw daily data'!$F:$F,"<0")) | Q17: =IF($A17="","",SUMIFS('Raw daily data'!$F:$F,'Raw daily data'!$I:$I,$A17,'Raw daily data'!$F:$F,">0")) | R17: =IF($A17="","",ABS(SUMIFS('Raw daily data'!$F:$F,'Raw daily data'!$I:$I,$A17,'Raw daily data'!$F:$F,"<0"))) | S17: =IF($A17="","",IF(N17>0,O17/N17,"")) | T17: =IF($A17="","",IF(R17>0,Q17/ABS(R17),"")) | U17: =IF($A17="","",IF(F17>0,H17/F17,"")) | V17: =IF($A17="","",IFERROR(IF(H17<0,MIN(ABS(H17)/G17,1),0),"")) | W17: =IF($A17="","",_xlfn.MAXIFS('Raw daily data'!$J:$J,'Raw daily data'!$I:$I,$A17)) | X17: =IF($A17="","",IFERROR(IF(W17>=0,0,ABS(W17)/G17),"")) | Y17: =IF($A17="","",IFERROR(ABS(MIN(0,_xlfn.MINIFS('Raw daily data'!$J:$J,'Raw daily data'!$I:$I,$A17)))/G17,""))
... C41: =IF($A41="","",TEXT($A41,"dddd")) | E41: =IF($A41="","", E40+H40) | F41: =IF($A41="","",$E41*Summary!$B$8) | G41: =IF($A41="","",F41*Summary!$B$9) | H41: =IF($A41="","",SUMIFS('Raw daily data'!$F:$F,'Raw daily data'!$I:$I,$A41)) | I41: =IF($A41="","", I40+H41) | J41: =IF($A41="","",SUMIF($B$2:$B$100,B41,$H$2:$H$100)) | K41: =IF($A41="","",Summary!$B$6) | L41: =IF($A41="","",IFERROR(J41-K41,"")) | N41: =IF($A41="","",COUNTIFS('Raw daily data'!$I:$I,$A41)) | O41: =IF($A41="","",COUNTIFS('Raw daily data'!$I:$I,$A41,'Raw daily data'!$F:$F,">0")) | P41: =IF($A41="","",COUNTIFS('Raw daily data'!$I:$I,$A41,'Raw daily data'!$F:$F,"<0")) | Q41: =IF($A41="","",SUMIFS('Raw daily data'!$F:$F,'Raw daily data'!$I:$I,$A41,'Raw daily data'!$F:$F,">0")) | R41: =IF($A41="","",ABS(SUMIFS('Raw daily data'!$F:$F,'Raw daily data'!$I:$I,$A41,'Raw daily data'!$F:$F,"<0"))) | S41: =IF($A41="","",IF(N41>0,O41/N41,"")) | T41: =IF($A41="","",IF(R41>0,Q41/ABS(R41),"")) | U41: =IF($A41="","",IF(F41>0,H41/F41,"")) | V41: =IF($A41="","",IFERROR(IF(H41<0,MIN(ABS(H41)/G41,1),0),"")) | W41: =IF($A41="","",_xlfn.MAXIFS('Raw daily data'!$J:$J,'Raw daily data'!$I:$I,$A41)) | X41: =IF($A41="","",IFERROR(IF(W41>=0,0,ABS(W41)/G41),"")) | Y41: =IF($A41="","",IFERROR(ABS(MIN(0,_xlfn.MINIFS('Raw daily data'!$J:$J,'Raw daily data'!$I:$I,$A41)))/G41,""))
C42: =IF($A42="","",TEXT($A42,"dddd")) | E42: =IF($A42="","", E41+H41) | F42: =IF($A42="","",$E42*Summary!$B$8) | G42: =IF($A42="","",F42*Summary!$B$9) | H42: =IF($A42="","",SUMIFS('Raw daily data'!$F:$F,'Raw daily data'!$I:$I,$A42)) | I42: =IF($A42="","", I41+H42) | J42: =IF($A42="","",SUMIF($B$2:$B$100,B42,$H$2:$H$100)) | K42: =IF($A42="","",Summary!$B$6) | L42: =IF($A42="","",IFERROR(J42-K42,"")) | N42: =IF($A42="","",COUNTIFS('Raw daily data'!$I:$I,$A42)) | O42: =IF($A42="","",COUNTIFS('Raw daily data'!$I:$I,$A42,'Raw daily data'!$F:$F,">0")) | P42: =IF($A42="","",COUNTIFS('Raw daily data'!$I:$I,$A42,'Raw daily data'!$F:$F,"<0")) | Q42: =IF($A42="","",SUMIFS('Raw daily data'!$F:$F,'Raw daily data'!$I:$I,$A42,'Raw daily data'!$F:$F,">0")) | R42: =IF($A42="","",ABS(SUMIFS('Raw daily data'!$F:$F,'Raw daily data'!$I:$I,$A42,'Raw daily data'!$F:$F,"<0"))) | S42: =IF($A42="","",IF(N42>0,O42/N42,"")) | T42: =IF($A42="","",IF(R42>0,Q42/ABS(R42),"")) | U42: =IF($A42="","",IF(F42>0,H42/F42,"")) | V42: =IF($A42="","",IFERROR(IF(H42<0,MIN(ABS(H42)/G42,1),0),"")) | W42: =IF($A42="","",_xlfn.MAXIFS('Raw daily data'!$J:$J,'Raw daily data'!$I:$I,$A42)) | X42: =IF($A42="","",IF(W42>=0,0,ABS(W42)/G42)) | Y42: =IFERROR(IF($A42="","",ABS(MIN(0,_xlfn.MINIFS('Raw daily data'!$J:$J,'Raw daily data'!$I:$I,$A42)))/G42),"")
C43: =IF($A43="","",TEXT($A43,"dddd")) | E43: =IF($A43="","", E42+H42) | F43: =IF($A43="","",$E43*Summary!$B$8) | G43: =IF($A43="","",F43*Summary!$B$9) | H43: =IF($A43="","",SUMIFS('Raw daily data'!$F:$F,'Raw daily data'!$I:$I,$A43)) | I43: =IF($A43="","", I42+H43) | J43: =IF($A43="","",SUMIF($B$2:$B$100,B43,$H$2:$H$100)) | K43: =IF($A43="","",Summary!$B$6) | L43: =IF($A43="","",IFERROR(J43-K43,"")) | N43: =IF($A43="","",COUNTIFS('Raw daily data'!$I:$I,$A43)) | O43: =IF($A43="","",COUNTIFS('Raw daily data'!$I:$I,$A43,'Raw daily data'!$F:$F,">0")) | P43: =IF($A43="","",COUNTIFS('Raw daily data'!$I:$I,$A43,'Raw daily data'!$F:$F,"<0")) | Q43: =IF($A43="","",SUMIFS('Raw daily data'!$F:$F,'Raw daily data'!$I:$I,$A43,'Raw daily data'!$F:$F,">0")) | R43: =IF($A43="","",ABS(SUMIFS('Raw daily data'!$F:$F,'Raw daily data'!$I:$I,$A43,'Raw daily data'!$F:$F,"<0"))) | S43: =IF($A43="","",IF(N43>0,O43/N43,"")) | T43: =IF($A43="","",IF(R43>0,Q43/ABS(R43),"")) | U43: =IF($A43="","",IF(F43>0,H43/F43,"")) | V43: =IF($A43="","",IFERROR(IF(H43<0,MIN(ABS(H43)/G43,1),0),"")) | W43: =IF($A43="","",_xlfn.MAXIFS('Raw daily data'!$J:$J,'Raw daily data'!$I:$I,$A43)) | X43: =IF($A43="","",IF(W43>=0,0,ABS(W43)/G43)) | Y43: =IFERROR(IF($A43="","",ABS(MIN(0,_xlfn.MINIFS('Raw daily data'!$J:$J,'Raw daily data'!$I:$I,$A43)))/G43),"")
C44: =IF($A44="","",TEXT($A44,"dddd")) | E44: =IF($A44="","", E43+H43) | F44: =IF($A44="","",$E44*Summary!$B$8) | G44: =IF($A44="","",F44*Summary!$B$9) | H44: =IF($A44="","",SUMIFS('Raw daily data'!$F:$F,'Raw daily data'!$I:$I,$A44)) | I44: =IF($A44="","", I43+H44) | J44: =IF($A44="","",SUMIF($B$2:$B$100,B44,$H$2:$H$100)) | K44: =IF($A44="","",Summary!$B$6) | L44: =IF($A44="","",IFERROR(J44-K44,"")) | N44: =IF($A44="","",COUNTIFS('Raw daily data'!$I:$I,$A44)) | O44: =IF($A44="","",COUNTIFS('Raw daily data'!$I:$I,$A44,'Raw daily data'!$F:$F,">0")) | P44: =IF($A44="","",COUNTIFS('Raw daily data'!$I:$I,$A44,'Raw daily data'!$F:$F,"<0")) | Q44: =IF($A44="","",SUMIFS('Raw daily data'!$F:$F,'Raw daily data'!$I:$I,$A44,'Raw daily data'!$F:$F,">0")) | R44: =IF($A44="","",ABS(SUMIFS('Raw daily data'!$F:$F,'Raw daily data'!$I:$I,$A44,'Raw daily data'!$F:$F,"<0"))) | S44: =IF($A44="","",IF(N44>0,O44/N44,"")) | T44: =IF($A44="","",IF(R44>0,Q44/ABS(R44),"")) | U44: =IF($A44="","",IF(F44>0,H44/F44,"")) | V44: =IF($A44="","",IFERROR(IF(H44<0,MIN(ABS(H44)/G44,1),0),"")) | W44: =IF($A44="","",_xlfn.MAXIFS('Raw daily data'!$J:$J,'Raw daily data'!$I:$I,$A44)) | X44: =IF($A44="","",IF(W44>=0,0,ABS(W44)/G44)) | Y44: =IFERROR(IF($A44="","",ABS(MIN(0,_xlfn.MINIFS('Raw daily data'!$J:$J,'Raw daily data'!$I:$I,$A44)))/G44),"")
C45: =IF($A45="","",TEXT($A45,"dddd")) | E45: =IF($A45="","", E44+H44) | F45: =IF($A45="","",$E45*Summary!$B$8) | G45: =IF($A45="","",F45*Summary!$B$9) | H45: =IF($A45="","",SUMIFS('Raw daily data'!$F:$F,'Raw daily data'!$I:$I,$A45)) | I45: =IF($A45="","", I44+H45) | J45: =IF($A45="","",SUMIF($B$2:$B$100,B45,$H$2:$H$100)) | K45: =IF($A45="","",Summary!$B$6) | L45: =IF($A45="","",IFERROR(J45-K45,"")) | N45: =IF($A45="","",COUNTIFS('Raw daily data'!$I:$I,$A45)) | O45: =IF($A45="","",COUNTIFS('Raw daily data'!$I:$I,$A45,'Raw daily data'!$F:$F,">0")) | P45: =IF($A45="","",COUNTIFS('Raw daily data'!$I:$I,$A45,'Raw daily data'!$F:$F,"<0")) | Q45: =IF($A45="","",SUMIFS('Raw daily data'!$F:$F,'Raw daily data'!$I:$I,$A45,'Raw daily data'!$F:$F,">0")) | R45: =IF($A45="","",ABS(SUMIFS('Raw daily data'!$F:$F,'Raw daily data'!$I:$I,$A45,'Raw daily data'!$F:$F,"<0"))) | S45: =IF($A45="","",IF(N45>0,O45/N45,"")) | T45: =IF($A45="","",IF(R45>0,Q45/ABS(R45),"")) | U45: =IF($A45="","",IF(F45>0,H45/F45,"")) | V45: =IF($A45="","",IFERROR(IF(H45<0,MIN(ABS(H45)/G45,1),0),"")) | W45: =IF($A45="","",_xlfn.MAXIFS('Raw daily data'!$J:$J,'Raw daily data'!$I:$I,$A45)) | X45: =IF($A45="","",IF(W45>=0,0,ABS(W45)/G45)) | Y45: =IFERROR(IF($A45="","",ABS(MIN(0,_xlfn.MINIFS('Raw daily data'!$J:$J,'Raw daily data'!$I:$I,$A45)))/G45),"")
C46: =IF($A46="","",TEXT($A46,"dddd")) | E46: =IF($A46="","", E45+H45) | F46: =IF($A46="","",$E46*Summary!$B$8) | G46: =IF($A46="","",F46*Summary!$B$9) | H46: =IF($A46="","",SUMIFS('Raw daily data'!$F:$F,'Raw daily data'!$I:$I,$A46)) | I46: =IF($A46="","", I45+H46) | J46: =IF($A46="","",SUMIF($B$2:$B$100,B46,$H$2:$H$100)) | K46: =IF($A46="","",Summary!$B$6) | L46: =IF($A46="","",IFERROR(J46-K46,"")) | N46: =IF($A46="","",COUNTIFS('Raw daily data'!$I:$I,$A46)) | O46: =IF($A46="","",COUNTIFS('Raw daily data'!$I:$I,$A46,'Raw daily data'!$F:$F,">0")) | P46: =IF($A46="","",COUNTIFS('Raw daily data'!$I:$I,$A46,'Raw daily data'!$F:$F,"<0")) | Q46: =IF($A46="","",SUMIFS('Raw daily data'!$F:$F,'Raw daily data'!$I:$I,$A46,'Raw daily data'!$F:$F,">0")) | R46: =IF($A46="","",ABS(SUMIFS('Raw daily data'!$F:$F,'Raw daily data'!$I:$I,$A46,'Raw daily data'!$F:$F,"<0"))) | S46: =IF($A46="","",IF(N46>0,O46/N46,"")) | T46: =IF($A46="","",IF(R46>0,Q46/ABS(R46),"")) | U46: =IF($A46="","",IF(F46>0,H46/F46,"")) | V46: =IF($A46="","",IFERROR(IF(H46<0,MIN(ABS(H46)/G46,1),0),"")) | W46: =IF($A46="","",_xlfn.MAXIFS('Raw daily data'!$J:$J,'Raw daily data'!$I:$I,$A46)) | X46: =IF($A46="","",IF(W46>=0,0,ABS(W46)/G46)) | Y46: =IFERROR(IF($A46="","",ABS(MIN(0,_xlfn.MINIFS('Raw daily data'!$J:$J,'Raw daily data'!$I:$I,$A46)))/G46),"")
C47: =IF($A47="","",TEXT($A47,"dddd")) | E47: =IF($A47="","", E46+H46) | F47: =IF($A47="","",$E47*Summary!$B$8) | G47: =IF($A47="","",F47*Summary!$B$9) | H47: =IF($A47="","",SUMIFS('Raw daily data'!$F:$F,'Raw daily data'!$I:$I,$A47)) | I47: =IF($A47="","", I46+H47) | J47: =IF($A47="","",SUMIF($B$2:$B$100,B47,$H$2:$H$100)) | K47: =IF($A47="","",Summary!$B$6) | L47: =IF($A47="","",IFERROR(J47-K47,"")) | N47: =IF($A47="","",COUNTIFS('Raw daily data'!$I:$I,$A47)) | O47: =IF($A47="","",COUNTIFS('Raw daily data'!$I:$I,$A47,'Raw daily data'!$F:$F,">0")) | P47: =IF($A47="","",COUNTIFS('Raw daily data'!$I:$I,$A47,'Raw daily data'!$F:$F,"<0")) | Q47: =IF($A47="","",SUMIFS('Raw daily data'!$F:$F,'Raw daily data'!$I:$I,$A47,'Raw daily data'!$F:$F,">0")) | R47: =IF($A47="","",ABS(SUMIFS('Raw daily data'!$F:$F,'Raw daily data'!$I:$I,$A47,'Raw daily data'!$F:$F,"<0"))) | S47: =IF($A47="","",IF(N47>0,O47/N47,"")) | T47: =IF($A47="","",IF(R47>0,Q47/ABS(R47),"")) | U47: =IF($A47="","",IF(F47>0,H47/F47,"")) | V47: =IF($A47="","",IFERROR(IF(H47<0,MIN(ABS(H47)/G47,1),0),"")) | W47: =IF($A47="","",_xlfn.MAXIFS('Raw daily data'!$J:$J,'Raw daily data'!$I:$I,$A47)) | X47: =IF($A47="","",IF(W47>=0,0,ABS(W47)/G47)) | Y47: =IFERROR(IF($A47="","",ABS(MIN(0,_xlfn.MINIFS('Raw daily data'!$J:$J,'Raw daily data'!$I:$I,$A47)))/G47),"")
C48: =IF($A48="","",TEXT($A48,"dddd")) | E48: =IF($A48="","", E47+H47) | F48: =IF($A48="","",$E48*Summary!$B$8) | G48: =IF($A48="","",F48*Summary!$B$9) | H48: =IF($A48="","",SUMIFS('Raw daily data'!$F:$F,'Raw daily data'!$I:$I,$A48)) | I48: =IF($A48="","", I47+H48) | J48: =IF($A48="","",SUMIF($B$2:$B$100,B48,$H$2:$H$100)) | K48: =IF($A48="","",Summary!$B$6) | L48: =IF($A48="","",IFERROR(J48-K48,"")) | N48: =IF($A48="","",COUNTIFS('Raw daily data'!$I:$I,$A48)) | O48: =IF($A48="","",COUNTIFS('Raw daily data'!$I:$I,$A48,'Raw daily data'!$F:$F,">0")) | P48: =IF($A48="","",COUNTIFS('Raw daily data'!$I:$I,$A48,'Raw daily data'!$F:$F,"<0")) | Q48: =IF($A48="","",SUMIFS('Raw daily data'!$F:$F,'Raw daily data'!$I:$I,$A48,'Raw daily data'!$F:$F,">0")) | R48: =IF($A48="","",ABS(SUMIFS('Raw daily data'!$F:$F,'Raw daily data'!$I:$I,$A48,'Raw daily data'!$F:$F,"<0"))) | S48: =IF($A48="","",IF(N48>0,O48/N48,"")) | T48: =IF($A48="","",IF(R48>0,Q48/ABS(R48),"")) | U48: =IF($A48="","",IF(F48>0,H48/F48,"")) | V48: =IF($A48="","",IFERROR(IF(H48<0,MIN(ABS(H48)/G48,1),0),"")) | W48: =IF($A48="","",_xlfn.MAXIFS('Raw daily data'!$J:$J,'Raw daily data'!$I:$I,$A48)) | X48: =IF($A48="","",IF(W48>=0,0,ABS(W48)/G48)) | Y48: =IFERROR(IF($A48="","",ABS(MIN(0,_xlfn.MINIFS('Raw daily data'!$J:$J,'Raw daily data'!$I:$I,$A48)))/G48),"")
C49: =IF($A49="","",TEXT($A49,"dddd")) | E49: =IF($A49="","", E48+H48) | F49: =IF($A49="","",$E49*Summary!$B$8) | G49: =IF($A49="","",F49*Summary!$B$9) | H49: =IF($A49="","",SUMIFS('Raw daily data'!$F:$F,'Raw daily data'!$I:$I,$A49)) | I49: =IF($A49="","", I48+H49) | J49: =IF($A49="","",SUMIF($B$2:$B$100,B49,$H$2:$H$100)) | K49: =IF($A49="","",Summary!$B$6) | L49: =IF($A49="","",IFERROR(J49-K49,"")) | N49: =IF($A49="","",COUNTIFS('Raw daily data'!$I:$I,$A49)) | O49: =IF($A49="","",COUNTIFS('Raw daily data'!$I:$I,$A49,'Raw daily data'!$F:$F,">0")) | P49: =IF($A49="","",COUNTIFS('Raw daily data'!$I:$I,$A49,'Raw daily data'!$F:$F,"<0")) | Q49: =IF($A49="","",SUMIFS('Raw daily data'!$F:$F,'Raw daily data'!$I:$I,$A49,'Raw daily data'!$F:$F,">0")) | R49: =IF($A49="","",ABS(SUMIFS('Raw daily data'!$F:$F,'Raw daily data'!$I:$I,$A49,'Raw daily data'!$F:$F,"<0"))) | S49: =IF($A49="","",IF(N49>0,O49/N49,"")) | T49: =IF($A49="","",IF(R49>0,Q49/ABS(R49),"")) | U49: =IF($A49="","",IF(F49>0,H49/F49,"")) | V49: =IF($A49="","",IFERROR(IF(H49<0,MIN(ABS(H49)/G49,1),0),"")) | W49: =IF($A49="","",_xlfn.MAXIFS('Raw daily data'!$J:$J,'Raw daily data'!$I:$I,$A49)) | X49: =IF($A49="","",IF(W49>=0,0,ABS(W49)/G49)) | Y49: =IFERROR(IF($A49="","",ABS(MIN(0,_xlfn.MINIFS('Raw daily data'!$J:$J,'Raw daily data'!$I:$I,$A49)))/G49),"")
C50: =IF($A50="","",TEXT($A50,"dddd")) | E50: =IF($A50="","", E49+H49) | F50: =IF($A50="","",$E50*Summary!$B$8) | G50: =IF($A50="","",F50*Summary!$B$9) | H50: =IF($A50="","",SUMIFS('Raw daily data'!$F:$F,'Raw daily data'!$I:$I,$A50)) | I50: =IF($A50="","", I49+H50) | J50: =IF($A50="","",SUMIF($B$2:$B$100,B50,$H$2:$H$100)) | K50: =IF($A50="","",Summary!$B$6) | L50: =IF($A50="","",IFERROR(J50-K50,"")) | N50: =IF($A50="","",COUNTIFS('Raw daily data'!$I:$I,$A50)) | O50: =IF($A50="","",COUNTIFS('Raw daily data'!$I:$I,$A50,'Raw daily data'!$F:$F,">0")) | P50: =IF($A50="","",COUNTIFS('Raw daily data'!$I:$I,$A50,'Raw daily data'!$F:$F,"<0")) | Q50: =IF($A50="","",SUMIFS('Raw daily data'!$F:$F,'Raw daily data'!$I:$I,$A50,'Raw daily data'!$F:$F,">0")) | R50: =IF($A50="","",ABS(SUMIFS('Raw daily data'!$F:$F,'Raw daily data'!$I:$I,$A50,'Raw daily data'!$F:$F,"<0"))) | S50: =IF($A50="","",IF(N50>0,O50/N50,"")) | T50: =IF($A50="","",IF(R50>0,Q50/ABS(R50),"")) | U50: =IF($A50="","",IF(F50>0,H50/F50,"")) | V50: =IF($A50="","",IFERROR(IF(H50<0,MIN(ABS(H50)/G50,1),0),"")) | W50: =IF($A50="","",_xlfn.MAXIFS('Raw daily data'!$J:$J,'Raw daily data'!$I:$I,$A50)) | X50: =IF($A50="","",IF(W50>=0,0,ABS(W50)/G50)) | Y50: =IFERROR(IF($A50="","",ABS(MIN(0,_xlfn.MINIFS('Raw daily data'!$J:$J,'Raw daily data'!$I:$I,$A50)))/G50),"")
C51: =IF($A51="","",TEXT($A51,"dddd")) | E51: =IF($A51="","", E50+H50) | F51: =IF($A51="","",$E51*Summary!$B$8) | G51: =IF($A51="","",F51*Summary!$B$9) | H51: =IF($A51="","",SUMIFS('Raw daily data'!$F:$F,'Raw daily data'!$I:$I,$A51)) | I51: =IF($A51="","", I50+H51) | J51: =IF($A51="","",SUMIF($B$2:$B$100,B51,$H$2:$H$100)) | K51: =IF($A51="","",Summary!$B$6) | L51: =IF($A51="","",IFERROR(J51-K51,"")) | N51: =IF($A51="","",COUNTIFS('Raw daily data'!$I:$I,$A51)) | O51: =IF($A51="","",COUNTIFS('Raw daily data'!$I:$I,$A51,'Raw daily data'!$F:$F,">0")) | P51: =IF($A51="","",COUNTIFS('Raw daily data'!$I:$I,$A51,'Raw daily data'!$F:$F,"<0")) | Q51: =IF($A51="","",SUMIFS('Raw daily data'!$F:$F,'Raw daily data'!$I:$I,$A51,'Raw daily data'!$F:$F,">0")) | R51: =IF($A51="","",ABS(SUMIFS('Raw daily data'!$F:$F,'Raw daily data'!$I:$I,$A51,'Raw daily data'!$F:$F,"<0"))) | S51: =IF($A51="","",IF(N51>0,O51/N51,"")) | T51: =IF($A51="","",IF(R51>0,Q51/ABS(R51),"")) | U51: =IF($A51="","",IF(F51>0,H51/F51,"")) | V51: =IF($A51="","",IFERROR(IF(H51<0,MIN(ABS(H51)/G51,1),0),"")) | W51: =IF($A51="","",_xlfn.MAXIFS('Raw daily data'!$J:$J,'Raw daily data'!$I:$I,$A51)) | X51: =IF($A51="","",IF(W51>=0,0,ABS(W51)/G51)) | Y51: =IFERROR(IF($A51="","",ABS(MIN(0,_xlfn.MINIFS('Raw daily data'!$J:$J,'Raw daily data'!$I:$I,$A51)))/G51),"")
C52: =IF($A52="","",TEXT($A52,"dddd")) | E52: =IF($A52="","", E51+H51) | F52: =IF($A52="","",$E52*Summary!$B$8) | G52: =IF($A52="","",F52*Summary!$B$9) | H52: =IF($A52="","",SUMIFS('Raw daily data'!$F:$F,'Raw daily data'!$I:$I,$A52)) | I52: =IF($A52="","", I51+H52) | J52: =IF($A52="","",SUMIF($B$2:$B$100,B52,$H$2:$H$100)) | K52: =IF($A52="","",Summary!$B$6) | L52: =IF($A52="","",IFERROR(J52-K52,"")) | N52: =IF($A52="","",COUNTIFS('Raw daily data'!$I:$I,$A52)) | O52: =IF($A52="","",COUNTIFS('Raw daily data'!$I:$I,$A52,'Raw daily data'!$F:$F,">0")) | P52: =IF($A52="","",COUNTIFS('Raw daily data'!$I:$I,$A52,'Raw daily data'!$F:$F,"<0")) | Q52: =IF($A52="","",SUMIFS('Raw daily data'!$F:$F,'Raw daily data'!$I:$I,$A52,'Raw daily data'!$F:$F,">0")) | R52: =IF($A52="","",ABS(SUMIFS('Raw daily data'!$F:$F,'Raw daily data'!$I:$I,$A52,'Raw daily data'!$F:$F,"<0"))) | S52: =IF($A52="","",IF(N52>0,O52/N52,"")) | T52: =IF($A52="","",IF(R52>0,Q52/ABS(R52),"")) | U52: =IF($A52="","",IF(F52>0,H52/F52,"")) | V52: =IF($A52="","",IFERROR(IF(H52<0,MIN(ABS(H52)/G52,1),0),"")) | W52: =IF($A52="","",_xlfn.MAXIFS('Raw daily data'!$J:$J,'Raw daily data'!$I:$I,$A52)) | X52: =IF($A52="","",IF(W52>=0,0,ABS(W52)/G52)) | Y52: =IFERROR(IF($A52="","",ABS(MIN(0,_xlfn.MINIFS('Raw daily data'!$J:$J,'Raw daily data'!$I:$I,$A52)))/G52),"")
C53: =IF($A53="","",TEXT($A53,"dddd")) | E53: =IF($A53="","", E52+H52) | F53: =IF($A53="","",$E53*Summary!$B$8) | G53: =IF($A53="","",F53*Summary!$B$9) | H53: =IF($A53="","",SUMIFS('Raw daily data'!$F:$F,'Raw daily data'!$I:$I,$A53)) | I53: =IF($A53="","", I52+H53) | J53: =IF($A53="","",SUMIF($B$2:$B$100,B53,$H$2:$H$100)) | K53: =IF($A53="","",Summary!$B$6) | L53: =IF($A53="","",IFERROR(J53-K53,"")) | N53: =IF($A53="","",COUNTIFS('Raw daily data'!$I:$I,$A53)) | O53: =IF($A53="","",COUNTIFS('Raw daily data'!$I:$I,$A53,'Raw daily data'!$F:$F,">0")) | P53: =IF($A53="","",COUNTIFS('Raw daily data'!$I:$I,$A53,'Raw daily data'!$F:$F,"<0")) | Q53: =IF($A53="","",SUMIFS('Raw daily data'!$F:$F,'Raw daily data'!$I:$I,$A53,'Raw daily data'!$F:$F,">0")) | R53: =IF($A53="","",ABS(SUMIFS('Raw daily data'!$F:$F,'Raw daily data'!$I:$I,$A53,'Raw daily data'!$F:$F,"<0"))) | S53: =IF($A53="","",IF(N53>0,O53/N53,"")) | T53: =IF($A53="","",IF(R53>0,Q53/ABS(R53),"")) | U53: =IF($A53="","",IF(F53>0,H53/F53,"")) | V53: =IF($A53="","",IFERROR(IF(H53<0,MIN(ABS(H53)/G53,1),0),"")) | W53: =IF($A53="","",_xlfn.MAXIFS('Raw daily data'!$J:$J,'Raw daily data'!$I:$I,$A53)) | X53: =IF($A53="","",IF(W53>=0,0,ABS(W53)/G53)) | Y53: =IFERROR(IF($A53="","",ABS(MIN(0,_xlfn.MINIFS('Raw daily data'!$J:$J,'Raw daily data'!$I:$I,$A53)))/G53),"")
... C100: =IF($A100="","",TEXT($A100,"dddd")) | E100: =IF($A100="","", E99+H99) | F100: =IF($A100="","",$E100*Summary!$B$8) | G100: =IF($A100="","",F100*Summary!$B$9) | H100: =IF($A100="","",SUMIFS('Raw daily data'!$F:$F,'Raw daily data'!$I:$I,$A100)) | I100: =IF($A100="","", I99+H100) | J100: =IF($A100="","",SUMIF($B$2:$B$100,B100,$H$2:$H$100)) | K100: =IF($A100="","",Summary!$B$6) | L100: =IF($A100="","",IFERROR(J100-K100,"")) | N100: =IF($A100="","",COUNTIFS('Raw daily data'!$I:$I,$A100)) | O100: =IF($A100="","",COUNTIFS('Raw daily data'!$I:$I,$A100,'Raw daily data'!$F:$F,">0")) | P100: =IF($A100="","",COUNTIFS('Raw daily data'!$I:$I,$A100,'Raw daily data'!$F:$F,"<0")) | Q100: =IF($A100="","",SUMIFS('Raw daily data'!$F:$F,'Raw daily data'!$I:$I,$A100,'Raw daily data'!$F:$F,">0")) | R100: =IF($A100="","",ABS(SUMIFS('Raw daily data'!$F:$F,'Raw daily data'!$I:$I,$A100,'Raw daily data'!$F:$F,"<0"))) | S100: =IF($A100="","",IF(N100>0,O100/N100,"")) | T100: =IF($A100="","",IF(R100>0,Q100/ABS(R100),"")) | U100: =IF($A100="","",IF(F100>0,H100/F100,"")) | V100: =IF($A100="","",IFERROR(IF(H100<0,MIN(ABS(H100)/G100,1),0),"")) | W100: =IF($A100="","",_xlfn.MAXIFS('Raw daily data'!$J:$J,'Raw daily data'!$I:$I,$A100)) | X100: =IF($A100="","",IF(W100>=0,0,ABS(W100)/G100)) | Y100: =IFERROR(IF($A100="","",ABS(MIN(0,_xlfn.MINIFS('Raw daily data'!$J:$J,'Raw daily data'!$I:$I,$A100)))/G100),"")
C101: =IF($A101="","",TEXT($A101,"dddd")) | E101: =IF($A101="","",E41+H41)
C102: =IF($A102="","",TEXT($A102,"dddd")) | E102: =IF($A102="","",E101+H101)
C103: =IF($A103="","",TEXT($A103,"dddd")) | E103: =IF($A103="","",E102+H102)
C104: =IF($A104="","",TEXT($A104,"dddd")) | E104: =IF($A104="","",E103+H103)
C105: =IF($A105="","",TEXT($A105,"dddd")) | E105: =IF($A105="","",E104+H104)
C106: =IF($A106="","",TEXT($A106,"dddd")) | E106: =IF($A106="","",E105+H105)
C107: =IF($A107="","",TEXT($A107,"dddd")) | E107: =IF($A107="","",E106+H106)
C108: =IF($A108="","",TEXT($A108,"dddd")) | E108: =IF($A108="","",E107+H107)
C109: =IF($A109="","",TEXT($A109,"dddd")) | E109: =IF($A109="","",E108+H108)
C110: =IF($A110="","",TEXT($A110,"dddd")) | E110: =IF($A110="","",E109+H109)
C111: =IF($A111="","",TEXT($A111,"dddd")) | E111: =IF($A111="","",E110+H110)
C112: =IF($A112="","",TEXT($A112,"dddd")) | E112: =IF($A112="","",E111+H111)
C113: =IF($A113="","",TEXT($A113,"dddd")) | E113: =IF($A113="","",E112+H112)
... C159: =IF($A159="","",TEXT($A159,"dddd")) | E159: =IF($A159="","",E158+H158)

Sheet Raw daily data
A1: Symbol ← Paste broker data into columns A–H only. Do not edit I–J → | B1: Name | C1: Side | D1: Quantity | E1: Price | F1: Profit | G1: Deal ID | H1: Time | I1: Trade Date | J1: Cumulative P&L for the day
A2: EURUSD | B2: EURUSD | C2: Buy | D2: 0.5 | E2: 1.156 | F2: 250 | G2: 101 | H2: Mon, 01 May 2026 09:00:00 GMT | I2: =IF(H2="","",IFERROR(IF(H2="","",IFERROR(IF(H2="","",IFERROR(IF(H2="","",IFERROR(IF(H2="","",IFERROR(IF(H2="","",IFERROR(IF(H2="","",IFERROR(IF(H2="","",IFERROR(IF(H2="","",IFERROR(IF(H2="","",IFERROR(IF(H2="","",IFERROR(IF(H2="","",IFERROR(IF(H2="","",IFERROR(IF(H2="","",IFERROR(IF(H2="","",IFERROR(IF(H2="","",IFERROR(IF(H2="","",IFERROR(IF(H2="","",IFERROR(IF(H2="","",IFERROR(IF(H2="","",IFERROR(IF(H2="","",IFERROR(IF(H2="","",IFERROR(IF(H2="","",IFERROR(IF(H2="","",IFERROR(IF(H2="","",IFERROR(IF(H2="","",IFERROR(IF(H2="","",IFERROR(IF(H2="","",IFERROR(IF(H2="","",IFERROR(IF(H2="","",IFERROR(IFERROR(IF(H2="","",DATEVALUE(MID(H2,6,11))),"Check date format"),"")),"")),"")),"")),"")),"")),"")),"")),"")),"")),"")),"")),"")),"")),"")),"")),"")),"")),"")),"")),"")),"")),"")),"")),"")),"")),"")),"")),"")),"")) -> 46143 | J2: =IF(OR(F2="",I2=""),"",F2+IF(I2=I1,N(J1),0)) -> 250
A3: EURUSD | B3: EURUSD | C3: Sell | D3: 1 | E3: 1.16 | F3: -100 | G3: 102 | H3: Tue, 09 May 2026 10:00:00 GMT | I3: =IF(H3="","",IFERROR(IF(H3="","",IFERROR(IF(H3="","",IFERROR(IF(H3="","",IFERROR(IF(H3="","",IFERROR(IF(H3="","",IFERROR(IF(H3="","",IFERROR(IF(H3="","",IFERROR(IF(H3="","",IFERROR(IF(H3="","",IFERROR(IF(H3="","",IFERROR(IF(H3="","",IFERROR(IF(H3="","",IFERROR(IF(H3="","",IFERROR(IF(H3="","",IFERROR(IF(H3="","",IFERROR(IF(H3="","",IFERROR(IF(H3="","",IFERROR(IF(H3="","",IFERROR(IF(H3="","",IFERROR(IF(H3="","",IFERROR(IF(H3="","",IFERROR(IF(H3="","",IFERROR(IF(H3="","",IFERROR(IF(H3="","",IFERROR(IF(H3="","",IFERROR(IF(H3="","",IFERROR(IF(H3="","",IFERROR(IF(H3="","",IFERROR(IF(H3="","",IFERROR(IFERROR(IF(H3="","",DATEVALUE(MID(H3,6,11))),"Check date format"),"")),"")),"")),"")),"")),"")),"")),"")),"")),"")),"")),"")),"")),"")),"")),"")),"")),"")),"")),"")),"")),"")),"")),"")),"")),"")),"")),"")),"")),"")) -> 46151 | J3: =IF(OR(F3="",I3=""),"",F3+IF(I3=I2,N(J2),0)) -> -100
A4: EURUSD | B4: EURUSD | C4: Sell | D4: 1 | E4: 1.162 | F4: -100 | G4: 103 | H4: Tue, 09 May 2026 15:00:00 GMT | I4: =IF(H4="","",IFERROR(IF(H4="","",IFERROR(IF(H4="","",IFERROR(IF(H4="","",IFERROR(IF(H4="","",IFERROR(IF(H4="","",IFERROR(IF(H4="","",IFERROR(IF(H4="","",IFERROR(IF(H4="","",IFERROR(IF(H4="","",IFERROR(IF(H4="","",IFERROR(IF(H4="","",IFERROR(IF(H4="","",IFERROR(IF(H4="","",IFERROR(IF(H4="","",IFERROR(IF(H4="","",IFERROR(IF(H4="","",IFERROR(IF(H4="","",IFERROR(IF(H4="","",IFERROR(IF(H4="","",IFERROR(IF(H4="","",IFERROR(IF(H4="","",IFERROR(IF(H4="","",IFERROR(IF(H4="","",IFERROR(IF(H4="","",IFERROR(IF(H4="","",IFERROR(IF(H4="","",IFERROR(IF(H4="","",IFERROR(IF(H4="","",IFERROR(IF(H4="","",IFERROR(IFERROR(IF(H4="","",DATEVALUE(MID(H4,6,11))),"Check date format"),"")),"")),"")),"")),"")),"")),"")),"")),"")),"")),"")),"")),"")),"")),"")),"")),"")),"")),"")),"")),"")),"")),"")),"")),"")),"")),"")),"")),"")),"")) -> 46151 | J4: =IF(OR(F4="",I4=""),"",F4+IF(I4=I3,N(J3),0)) -> -200
A5: EURUSD | B5: EURUSD | C5: Buy | D5: 2 | E5: 1.15 | F5: 800 | G5: 104 | H5: Wed, 17 May 2026 09:00:00 GMT | I5: =IF(H5="","",IFERROR(IF(H5="","",IFERROR(IF(H5="","",IFERROR(IF(H5="","",IFERROR(IF(H5="","",IFERROR(IF(H5="","",IFERROR(IF(H5="","",IFERROR(IF(H5="","",IFERROR(IF(H5="","",IFERROR(IF(H5="","",IFERROR(IF(H5="","",IFERROR(IF(H5="","",IFERROR(IF(H5="","",IFERROR(IF(H5="","",IFERROR(IF(H5="","",IFERROR(IF(H5="","",IFERROR(IF(H5="","",IFERROR(IF(H5="","",IFERROR(IF(H5="","",IFERROR(IF(H5="","",IFERROR(IF(H5="","",IFERROR(IF(H5="","",IFERROR(IF(H5="","",IFERROR(IF(H5="","",IFERROR(IF(H5="","",IFERROR(IF(H5="","",IFERROR(IF(H5="","",IFERROR(IF(H5="","",IFERROR(IF(H5="","",IFERROR(IF(H5="","",IFERROR(IFERROR(IF(H5="","",DATEVALUE(MID(H5,6,11))),"Check date format"),"")),"")),"")),"")),"")),"")),"")),"")),"")),"")),"")),"")),"")),"")),"")),"")),"")),"")),"")),"")),"")),"")),"")),"")),"")),"")),"")),"")),"")),"")) -> 46159 | J5: =IF(OR(F5="",I5=""),"",F5+IF(I5=I4,N(J4),0)) -> 800
A6: EURUSD | B6: EURUSD | C6: Buy | D6: 1 | E6: 1.155 | F6: 200 | G6: 105 | H6: Thu, 18 May 2026 14:00:00 GMT | I6: =IF(H6="","",IFERROR(IF(H6="","",IFERROR(IF(H6="","",IFERROR(IF(H6="","",IFERROR(IF(H6="","",IFERROR(IF(H6="","",IFERROR(IF(H6="","",IFERROR(IF(H6="","",IFERROR(IF(H6="","",IFERROR(IF(H6="","",IFERROR(IF(H6="","",IFERROR(IF(H6="","",IFERROR(IF(H6="","",IFERROR(IF(H6="","",IFERROR(IF(H6="","",IFERROR(IF(H6="","",IFERROR(IF(H6="","",IFERROR(IF(H6="","",IFERROR(IF(H6="","",IFERROR(IF(H6="","",IFERROR(IF(H6="","",IFERROR(IF(H6="","",IFERROR(IF(H6="","",IFERROR(IF(H6="","",IFERROR(IF(H6="","",IFERROR(IF(H6="","",IFERROR(IF(H6="","",IFERROR(IF(H6="","",IFERROR(IF(H6="","",IFERROR(IF(H6="","",IFERROR(IFERROR(IF(H6="","",DATEVALUE(MID(H6,6,11))),"Check date format"),"")),"")),"")),"")),"")),"")),"")),"")),"")),"")),"")),"")),"")),"")),"")),"")),"")),"")),"")),"")),"")),"")),"")),"")),"")),"")),"")),"")),"")),"")) -> 46160 | J6: =IF(OR(F6="",I6=""),"",F6+IF(I6=I5,N(J5),0)) -> 200
I7: =IF(H7="","",IFERROR(IF(H7="","",IFERROR(IF(H7="","",IFERROR(IF(H7="","",IFERROR(IF(H7="","",IFERROR(IF(H7="","",IFERROR(IF(H7="","",IFERROR(IF(H7="","",IFERROR(IF(H7="","",IFERROR(IF(H7="","",IFERROR(IF(H7="","",IFERROR(IF(H7="","",IFERROR(IF(H7="","",IFERROR(IF(H7="","",IFERROR(IF(H7="","",IFERROR(IF(H7="","",IFERROR(IF(H7="","",IFERROR(IF(H7="","",IFERROR(IF(H7="","",IFERROR(IF(H7="","",IFERROR(IF(H7="","",IFERROR(IF(H7="","",IFERROR(IF(H7="","",IFERROR(IF(H7="","",IFERROR(IF(H7="","",IFERROR(IF(H7="","",IFERROR(IF(H7="","",IFERROR(IF(H7="","",IFERROR(IF(H7="","",IFERROR(IF(H7="","",IFERROR(IFERROR(IF(H7="","",DATEVALUE(MID(H7,6,11))),"Check date format"),"")),"")),"")),"")),"")),"")),"")),"")),"")),"")),"")),"")),"")),"")),"")),"")),"")),"")),"")),"")),"")),"")),"")),"")),"")),"")),"")),"")),"")),"")) | J7: =IF(OR(F7="",I7=""),"",F7+IF(I7=I6,N(J6),0))
I8: =IF(H8="","",IFERROR(IF(H8="","",IFERROR(IF(H8="","",IFERROR(IF(H8="","",IFERROR(IF(H8="","",IFERROR(IF(H8="","",IFERROR(IF(H8="","",IFERROR(IF(H8="","",IFERROR(IF(H8="","",IFERROR(IF(H8="","",IFERROR(IF(H8="","",IFERROR(IF(H8="","",IFERROR(IF(H8="","",IFERROR(IF(H8="","",IFERROR(IF(H8="","",IFERROR(IF(H8="","",IFERROR(IF(H8="","",IFERROR(IF(H8="","",IFERROR(IF(H8="","",IFERROR(IF(H8="","",IFERROR(IF(H8="","",IFERROR(IF(H8="","",IFERROR(IF(H8="","",IFERROR(IF(H8="","",IFERROR(IF(H8="","",IFERROR(IF(H8="","",IFERROR(IF(H8="","",IFERROR(IF(H8="","",IFERROR(IF(H8="","",IFERROR(IF(H8="","",IFERROR(IFERROR(IF(H8="","",DATEVALUE(MID(H8,6,11))),"Check date format"),"")),"")),"")),"")),"")),"")),"")),"")),"")),"")),"")),"")),"")),"")),"")),"")),"")),"")),"")),"")),"")),"")),"")),"")),"")),"")),"")),"")),"")),"")) | J8: =IF(OR(F8="",I8=""),"",F8+IF(I8=I7,N(J7),0))
I9: =IF(H9="","",IFERROR(IF(H9="","",IFERROR(IF(H9="","",IFERROR(IF(H9="","",IFERROR(IF(H9="","",IFERROR(IF(H9="","",IFERROR(IF(H9="","",IFERROR(IF(H9="","",IFERROR(IF(H9="","",IFERROR(IF(H9="","",IFERROR(IF(H9="","",IFERROR(IF(H9="","",IFERROR(IF(H9="","",IFERROR(IF(H9="","",IFERROR(IF(H9="","",IFERROR(IF(H9="","",IFERROR(IF(H9="","",IFERROR(IF(H9="","",IFERROR(IF(H9="","",IFERROR(IF(H9="","",IFERROR(IF(H9="","",IFERROR(IF(H9="","",IFERROR(IF(H9="","",IFERROR(IF(H9="","",IFERROR(IF(H9="","",IFERROR(IF(H9="","",IFERROR(IF(H9="","",IFERROR(IF(H9="","",IFERROR(IF(H9="","",IFERROR(IF(H9="","",IFERROR(IFERROR(IF(H9="","",DATEVALUE(MID(H9,6,11))),"Check date format"),"")),"")),"")),"")),"")),"")),"")),"")),"")),"")),"")),"")),"")),"")),"")),"")),"")),"")),"")),"")),"")),"")),"")),"")),"")),"")),"")),"")),"")),"")) | J9: =IF(OR(F9="",I9=""),"",F9+IF(I9=I8,N(J8),0))
I10: =IF(H10="","",IFERROR(IF(H10="","",IFERROR(IF(H10="","",IFERROR(IF(H10="","",IFERROR(IF(H10="","",IFERROR(IF(H10="","",IFERROR(IF(H10="","",IFERROR(IF(H10="","",IFERROR(IF(H10="","",IFERROR(IF(H10="","",IFERROR(IF(H10="","",IFERROR(IF(H10="","",IFERROR(IF(H10="","",IFERROR(IF(H10="","",IFERROR(IF(H10="","",IFERROR(IF(H10="","",IFERROR(IF(H10="","",IFERROR(IF(H10="","",IFERROR(IF(H10="","",IFERROR(IF(H10="","",IFERROR(IF(H10="","",IFERROR(IF(H10="","",IFERROR(IF(H10="","",IFERROR(IF(H10="","",IFERROR(IF(H10="","",IFERROR(IF(H10="","",IFERROR(IF(H10="","",IFERROR(IF(H10="","",IFERROR(IF(H10="","",IFERROR(IF(H10="","",IFERROR(IFERROR(IF(H10="","",DATEVALUE(MID(H10,6,11))),"Check date format"),"")),"")),"")),"")),"")),"")),"")),"")),"")),"")),"")),"")),"")),"")),"")),"")),"")),"")),"")),"")),"")),"")),"")),"")),"")),"")),"")),"")),"")),"")) | J10: =IF(OR(F10="",I10=""),"",F10+IF(I10=I9,N(J9),0))
I11: =IF(H11="","",IFERROR(IF(H11="","",IFERROR(IF(H11="","",IFERROR(IF(H11="","",IFERROR(IF(H11="","",IFERROR(IF(H11="","",IFERROR(IF(H11="","",IFERROR(IF(H11="","",IFERROR(IF(H11="","",IFERROR(IF(H11="","",IFERROR(IF(H11="","",IFERROR(IF(H11="","",IFERROR(IF(H11="","",IFERROR(IF(H11="","",IFERROR(IF(H11="","",IFERROR(IF(H11="","",IFERROR(IF(H11="","",IFERROR(IF(H11="","",IFERROR(IF(H11="","",IFERROR(IF(H11="","",IFERROR(IF(H11="","",IFERROR(IF(H11="","",IFERROR(IF(H11="","",IFERROR(IF(H11="","",IFERROR(IF(H11="","",IFERROR(IF(H11="","",IFERROR(IF(H11="","",IFERROR(IF(H11="","",IFERROR(IF(H11="","",IFERROR(IF(H11="","",IFERROR(IFERROR(IF(H11="","",DATEVALUE(MID(H11,6,11))),"Check date format"),"")),"")),"")),"")),"")),"")),"")),"")),"")),"")),"")),"")),"")),"")),"")),"")),"")),"")),"")),"")),"")),"")),"")),"")),"")),"")),"")),"")),"")),"")) | J11: =IF(OR(F11="",I11=""),"",F11+IF(I11=I10,N(J10),0))
I12: =IF(H12="","",IFERROR(IF(H12="","",IFERROR(IF(H12="","",IFERROR(IF(H12="","",IFERROR(IF(H12="","",IFERROR(IF(H12="","",IFERROR(IF(H12="","",IFERROR(IF(H12="","",IFERROR(IF(H12="","",IFERROR(IF(H12="","",IFERROR(IF(H12="","",IFERROR(IF(H12="","",IFERROR(IF(H12="","",IFERROR(IF(H12="","",IFERROR(IF(H12="","",IFERROR(IF(H12="","",IFERROR(IF(H12="","",IFERROR(IF(H12="","",IFERROR(IF(H12="","",IFERROR(IF(H12="","",IFERROR(IF(H12="","",IFERROR(IF(H12="","",IFERROR(IF(H12="","",IFERROR(IF(H12="","",IFERROR(IF(H12="","",IFERROR(IF(H12="","",IFERROR(IF(H12="","",IFERROR(IF(H12="","",IFERROR(IF(H12="","",IFERROR(IF(H12="","",IFERROR(IFERROR(IF(H12="","",DATEVALUE(MID(H12,6,11))),"Check date format"),"")),"")),"")),"")),"")),"")),"")),"")),"")),"")),"")),"")),"")),"")),"")),"")),"")),"")),"")),"")),"")),"")),"")),"")),"")),"")),"")),"")),"")),"")) | J12: =IF(OR(F12="",I12=""),"",F12+IF(I12=I11,N(J11),0))
I13: =IF(H13="","",IFERROR(IF(H13="","",IFERROR(IF(H13="","",IFERROR(IF(H13="","",IFERROR(IF(H13="","",IFERROR(IF(H13="","",IFERROR(IF(H13="","",IFERROR(IF(H13="","",IFERROR(IF(H13="","",IFERROR(IF(H13="","",IFERROR(IF(H13="","",IFERROR(IF(H13="","",IFERROR(IF(H13="","",IFERROR(IF(H13="","",IFERROR(IF(H13="","",IFERROR(IF(H13="","",IFERROR(IF(H13="","",IFERROR(IF(H13="","",IFERROR(IF(H13="","",IFERROR(IF(H13="","",IFERROR(IF(H13="","",IFERROR(IF(H13="","",IFERROR(IF(H13="","",IFERROR(IF(H13="","",IFERROR(IF(H13="","",IFERROR(IF(H13="","",IFERROR(IF(H13="","",IFERROR(IF(H13="","",IFERROR(IF(H13="","",IFERROR(IF(H13="","",IFERROR(IFERROR(IF(H13="","",DATEVALUE(MID(H13,6,11))),"Check date format"),"")),"")),"")),"")),"")),"")),"")),"")),"")),"")),"")),"")),"")),"")),"")),"")),"")),"")),"")),"")),"")),"")),"")),"")),"")),"")),"")),"")),"")),"")) | J13: =IF(OR(F13="",I13=""),"",F13+IF(I13=I12,N(J12),0))
I14: =IF(H14="","",IFERROR(IF(H14="","",IFERROR(IF(H14="","",IFERROR(IF(H14="","",IFERROR(IF(H14="","",IFERROR(IF(H14="","",IFERROR(IF(H14="","",IFERROR(IF(H14="","",IFERROR(IF(H14="","",IFERROR(IF(H14="","",IFERROR(IF(H14="","",IFERROR(IF(H14="","",IFERROR(IF(H14="","",IFERROR(IF(H14="","",IFERROR(IF(H14="","",IFERROR(IF(H14="","",IFERROR(IF(H14="","",IFERROR(IF(H14="","",IFERROR(IF(H14="","",IFERROR(IF(H14="","",IFERROR(IF(H14="","",IFERROR(IF(H14="","",IFERROR(IF(H14="","",IFERROR(IF(H14="","",IFERROR(IF(H14="","",IFERROR(IF(H14="","",IFERROR(IF(H14="","",IFERROR(IF(H14="","",IFERROR(IF(H14="","",IFERROR(IF(H14="","",IFERROR(IFERROR(IF(H14="","",DATEVALUE(MID(H14,6,11))),"Check date format"),"")),"")),"")),"")),"")),"")),"")),"")),"")),"")),"")),"")),"")),"")),"")),"")),"")),"")),"")),"")),"")),"")),"")),"")),"")),"")),"")),"")),"")),"")) | J14: =IF(OR(F14="",I14=""),"",F14+IF(I14=I13,N(J13),0))
I15: =IF(H15="","",IFERROR(IF(H15="","",IFERROR(IF(H15="","",IFERROR(IF(H15="","",IFERROR(IF(H15="","",IFERROR(IF(H15="","",IFERROR(IF(H15="","",IFERROR(IF(H15="","",IFERROR(IF(H15="","",IFERROR(IF(H15="","",IFERROR(IF(H15="","",IFERROR(IF(H15="","",IFERROR(IF(H15="","",IFERROR(IF(H15="","",IFERROR(IF(H15="","",IFERROR(IF(H15="","",IFERROR(IF(H15="","",IFERROR(IF(H15="","",IFERROR(IF(H15="","",IFERROR(IF(H15="","",IFERROR(IF(H15="","",IFERROR(IF(H15="","",IFERROR(IF(H15="","",IFERROR(IF(H15="","",IFERROR(IF(H15="","",IFERROR(IF(H15="","",IFERROR(IF(H15="","",IFERROR(IF(H15="","",IFERROR(IF(H15="","",IFERROR(IF(H15="","",IFERROR(IFERROR(IF(H15="","",DATEVALUE(MID(H15,6,11))),"Check date format"),"")),"")),"")),"")),"")),"")),"")),"")),"")),"")),"")),"")),"")),"")),"")),"")),"")),"")),"")),"")),"")),"")),"")),"")),"")),"")),"")),"")),"")),"")) | J15: =IF(OR(F15="",I15=""),"",F15+IF(I15=I14,N(J14),0))
I16: =IF(H16="","",IFERROR(IF(H16="","",IFERROR(IF(H16="","",IFERROR(IF(H16="","",IFERROR(IF(H16="","",IFERROR(IF(H16="","",IFERROR(IF(H16="","",IFERROR(IF(H16="","",IFERROR(IF(H16="","",IFERROR(IF(H16="","",IFERROR(IF(H16="","",IFERROR(IF(H16="","",IFERROR(IF(H16="","",IFERROR(IF(H16="","",IFERROR(IF(H16="","",IFERROR(IF(H16="","",IFERROR(IF(H16="","",IFERROR(IF(H16="","",IFERROR(IF(H16="","",IFERROR(IF(H16="","",IFERROR(IF(H16="","",IFERROR(IF(H16="","",IFERROR(IF(H16="","",IFERROR(IF(H16="","",IFERROR(IF(H16="","",IFERROR(IF(H16="","",IFERROR(IF(H16="","",IFERROR(IF(H16="","",IFERROR(IF(H16="","",IFERROR(IF(H16="","",IFERROR(IFERROR(IF(H16="","",DATEVALUE(MID(H16,6,11))),"Check date format"),"")),"")),"")),"")),"")),"")),"")),"")),"")),"")),"")),"")),"")),"")),"")),"")),"")),"")),"")),"")),"")),"")),"")),"")),"")),"")),"")),"")),"")),"")) | J16: =IF(OR(F16="",I16=""),"",F16+IF(I16=I15,N(J15),0))
I17: =IF(H17="","",IFERROR(IF(H17="","",IFERROR(IF(H17="","",IFERROR(IF(H17="","",IFERROR(IF(H17="","",IFERROR(IF(H17="","",IFERROR(IF(H17="","",IFERROR(IF(H17="","",IFERROR(IF(H17="","",IFERROR(IF(H17="","",IFERROR(IF(H17="","",IFERROR(IF(H17="","",IFERROR(IF(H17="","",IFERROR(IF(H17="","",IFERROR(IF(H17="","",IFERROR(IF(H17="","",IFERROR(IF(H17="","",IFERROR(IF(H17="","",IFERROR(IF(H17="","",IFERROR(IF(H17="","",IFERROR(IF(H17="","",IFERROR(IF(H17="","",IFERROR(IF(H17="","",IFERROR(IF(H17="","",IFERROR(IF(H17="","",IFERROR(IF(H17="","",IFERROR(IF(H17="","",IFERROR(IF(H17="","",IFERROR(IF(H17="","",IFERROR(IF(H17="","",IFERROR(IFERROR(IF(H17="","",DATEVALUE(MID(H17,6,11))),"Check date format"),"")),"")),"")),"")),"")),"")),"")),"")),"")),"")),"")),"")),"")),"")),"")),"")),"")),"")),"")),"")),"")),"")),"")),"")),"")),"")),"")),"")),"")),"")) | J17: =IF(OR(F17="",I17=""),"",F17+IF(I17=I16,N(J16),0))
I18: =IF(H18="","",IFERROR(IF(H18="","",IFERROR(IF(H18="","",IFERROR(IF(H18="","",IFERROR(IF(H18="","",IFERROR(IF(H18="","",IFERROR(IF(H18="","",IFERROR(IF(H18="","",IFERROR(IF(H18="","",IFERROR(IF(H18="","",IFERROR(IF(H18="","",IFERROR(IF(H18="","",IFERROR(IF(H18="","",IFERROR(IF(H18="","",IFERROR(IF(H18="","",IFERROR(IF(H18="","",IFERROR(IF(H18="","",IFERROR(IF(H18="","",IFERROR(IF(H18="","",IFERROR(IF(H18="","",IFERROR(IF(H18="","",IFERROR(IF(H18="","",IFERROR(IF(H18="","",IFERROR(IF(H18="","",IFERROR(IF(H18="","",IFERROR(IF(H18="","",IFERROR(IF(H18="","",IFERROR(IF(H18="","",IFERROR(IF(H18="","",IFERROR(IF(H18="","",IFERROR(IFERROR(IF(H18="","",DATEVALUE(MID(H18,6,11))),"Check date format"),"")),"")),"")),"")),"")),"")),"")),"")),"")),"")),"")),"")),"")),"")),"")),"")),"")),"")),"")),"")),"")),"")),"")),"")),"")),"")),"")),"")),"")),"")) | J18: =IF(OR(F18="",I18=""),"",F18+IF(I18=I17,N(J17),0))
... I52: =IF(H52="","",IFERROR(IF(H52="","",IFERROR(IF(H52="","",IFERROR(IF(H52="","",IFERROR(IF(H52="","",IFERROR(IF(H52="","",IFERROR(IF(H52="","",IFERROR(IF(H52="","",IFERROR(IF(H52="","",IFERROR(IF(H52="","",IFERROR(IF(H52="","",IFERROR(IF(H52="","",IFERROR(IF(H52="","",IFERROR(IF(H52="","",IFERROR(IF(H52="","",IFERROR(IF(H52="","",IFERROR(IF(H52="","",IFERROR(IF(H52="","",IFERROR(IF(H52="","",IFERROR(IF(H52="","",IFERROR(IF(H52="","",IFERROR(IF(H52="","",IFERROR(IF(H52="","",IFERROR(IF(H52="","",IFERROR(IF(H52="","",IFERROR(IF(H52="","",IFERROR(IF(H52="","",IFERROR(IF(H52="","",IFERROR(IF(H52="","",IFERROR(IF(H52="","",IFERROR(IFERROR(IF(H52="","",DATEVALUE(MID(H52,6,11))),"Check date format"),"")),"")),"")),"")),"")),"")),"")),"")),"")),"")),"")),"")),"")),"")),"")),"")),"")),"")),"")),"")),"")),"")),"")),"")),"")),"")),"")),"")),"")),"")) | J52: =IF(OR(F52="",I52=""),"",F52+IF(I52=I51,N(J51),0))
I53: =IFERROR(IF(H53="","",DATEVALUE(MID(H53,6,11))),"Check date format") | J53: =IF(OR(F53="",I53=""),"",F53+IF(I53=I52,N(J52),0))
I54: =IFERROR(IF(H54="","",DATEVALUE(MID(H54,6,11))),"Check date format") | J54: =IF(OR(F54="",I54=""),"",F54+IF(I54=I53,N(J53),0))
I55: =IFERROR(IF(H55="","",DATEVALUE(MID(H55,6,11))),"Check date format") | J55: =IF(OR(F55="",I55=""),"",F55+IF(I55=I54,N(J54),0))
I56: =IFERROR(IF(H56="","",DATEVALUE(MID(H56,6,11))),"Check date format") | J56: =IF(OR(F56="",I56=""),"",F56+IF(I56=I55,N(J55),0))
I57: =IFERROR(IF(H57="","",DATEVALUE(MID(H57,6,11))),"Check date format") | J57: =IF(OR(F57="",I57=""),"",F57+IF(I57=I56,N(J56),0))
I58: =IFERROR(IF(H58="","",DATEVALUE(MID(H58,6,11))),"Check date format") | J58: =IF(OR(F58="",I58=""),"",F58+IF(I58=I57,N(J57),0))
I59: =IFERROR(IF(H59="","",DATEVALUE(MID(H59,6,11))),"Check date format") | J59: =IF(OR(F59="",I59=""),"",F59+IF(I59=I58,N(J58),0))
I60: =IFERROR(IF(H60="","",DATEVALUE(MID(H60,6,11))),"Check date format") | J60: =IF(OR(F60="",I60=""),"",F60+IF(I60=I59,N(J59),0))
I61: =IFERROR(IF(H61="","",DATEVALUE(MID(H61,6,11))),"Check date format") | J61: =IF(OR(F61="",I61=""),"",F61+IF(I61=I60,N(J60),0))
I62: =IFERROR(IF(H62="","",DATEVALUE(MID(H62,6,11))),"Check date format") | J62: =IF(OR(F62="",I62=""),"",F62+IF(I62=I61,N(J61),0))
I63: =IFERROR(IF(H63="","",DATEVALUE(MID(H63,6,11))),"Check date format") | J63: =IF(OR(F63="",I63=""),"",F63+IF(I63=I62,N(J62),0))
I64: =IFERROR(IF(H64="","",DATEVALUE(MID(H64,6,11))),"Check date format") | J64: =IF(OR(F64="",I64=""),"",F64+IF(I64=I63,N(J63),0))
... I500: =IFERROR(IF(H500="","",DATEVALUE(MID(H500,6,11))),"Check date format") | J500: =IF(OR(F500="",I500=""),"",F500+IF(I500=I499,N(J499),0))

Sheet Advanced Setup Planner
A1: ADVANCED SETUP PLANNER | N1: BACKEND CALC — Use Planner_HUD (inputs & ladders) | S1: Structure (SMC) – D1 / H4 / H1 / 15m | X1: Side | Y1: =IF(AND($T$8,NOT($T$9)),"LONG",IF(AND($T$9,NOT($T$8)),"SHORT","")) -> LONG | AC1: PRIMARY LADDER | AD1: Entry | AE1: TP | AF1: SL | AG1: Pips to TP1 | AH1: Eff Pips to SL | AI1: Weight | AJ1: Risk $ | AK1: Reward $ | AL1: Units | AM1: R per rung | EH1: CT_Entry | EI1: =IF(SUM($AI$28:$AI$30)=0,"",SUMPRODUCT($AD$28:$AD$30,$AI$28:$AI$30)/SUM($AI$28:$AI$30)) -> 1.156025
A2: Edit BLUE cells only. Planner_v2 reads from here. | N2: Market snapshot (15m + HTF EMAs & ATR) | S2: TF | T2: Trend | U2: Last BOS | V2: Last CHOCH | X2: Risk per Trade R ($) | Y2: =Summary!B10*Summary!B8 -> 500 | AC2: Entry 0.382 | AD2: =IF($Y$1="LONG",IF($ED$58,$T$19,$O$7),IF($Y$1="SHORT",$Q$23,"")) -> 1.145 | AE2: =IF(AD2="","",$ED$40) -> 0.0008 | AF2: =IF($Y$1="LONG",IF(OR($ED$58,$O$3>=$T$19),$ED$27,$T$20-0.0002),IF($Y$1="SHORT",IF($ED$58,MAX($O$39,$O$7)+0.0002,$T$19+0.0002),"")) -> -0.00025 | AG2: =IF(OR(AD2="",AE2=""),"",ABS((AE2-AD2)*10000)) -> 11442 | AH2: =IF(OR(AD2="",AF2=""),"",MAX(ABS((AD2-AF2)*10000),$ED$19)) -> 11452.5 | AI2: =$Y$7 -> 0.2 | AJ2: =IF(OR(AI2=0,$ED$11=0,AD2=""),"",$Y$2*$ED$8*AI2/$ED$11) -> 100 | AK2: =IF(OR(AJ2="",AJ2=0,AG2=""),"",AJ2*AG2/MAX(AH2,$ED$19)) -> 99.908317 | AL2: =IF(OR(AD2="",AH2="",AJ2=""),"",AJ2/(MAX(AH2,$ED$19)*$ED$3)) -> 87.31718 | AM2: =IF(OR(AG2="",AH2=""),"",AG2/MAX(AH2,$ED$19)) -> 0.99908317 | AN2: =IF(AH2="","",MAX(AH2,$ED$7)) -> 11452.5 | EA2: Scoring & HUD | EC2: Ladder Controls | EE2: Big Picture | EF2: =IF($EB$25,"Avoid trading this leg – system rules (R, room, macro) are not met.",IF($EB$56=1,"HTF up, shallow pullback in Tier 1 (15m 0.382–0.618). Long bias but less room; prefer buying dips closer to Tier 2/3.",IF($EB$56=2,"HTF up, intraday pullback trading in Tier 2 (4H FVG + HTF 0.382 + EMA50D). Macro bias: buy dips; this is a B-grade but tradable zone when ladder and R/room are valid.",IF($EB$56=3,"HTF up, deep discount near structural support (Tier 3). If trend remains intact, this is a high-value region.","Price is above all discount tiers (premium) near PMH/PDH/EQH. This is not a location for fresh longs; either manage existing longs or wait for a pullback into Tier 2/3 or a clearly defined CT short setup.")))) -> HTF up, shallow pullback in Tier 1 (15m 0.382–0.618). Long bias but less room; prefer buying dips closer to Tier 2/3. | EH2: CT_SL | EI2: =$EB$48+0.0008 -> 1.1566
N3: Current Price | O3: ='Advanced Setup Planner'!B5 -> 1.155 | S3: 1D | T3: =IF($O$12="","",IF(AND($O$12>$O$13,$O$13>$O$14,$O$3>$O$12+0.0002),"Bull",IF(AND($O$12<$O$13,$O$13<$O$14,$O$3<$O$12-0.0002),"Bear","Range"))) -> Bull | U3: ='Advanced Setup Planner'!C24 -> 0 | V3: ='Advanced Setup Planner'!D24 -> 0 | X3: TP1 Price | Y3: =IF($Y$1="LONG",MIN(IF($T$15>$O$3,$T$15,10^6),IF($T$17>$O$3,$T$17,10^6),IF($T$19>$O$3,$T$19,10^6),IF($T$21>$O$3,$T$21,10^6)),IF($Y$1="SHORT",MAX(IF($T$16<$O$3,$T$16,-10^6),IF($T$18<$O$3,$T$18,-10^6),IF($T$20<$O$3,$T$20,-10^6),IF($T$22<$O$3,$T$22,-10^6)),"")) -> 1000000 | AC3: Entry 0.500 | AD3: =IF($Y$1="LONG",IF($ED$58,AVERAGE($O$39,$O$40),$O$8),IF($Y$1="SHORT",$Q$24,"")) -> 1.14 | AE3: =IF(AD3="","",$ED$40) -> 0.0008 | AF3: =IF($Y$1="LONG",IF(OR($ED$58,$O$3>=$T$19),$ED$27,$T$20-0.0002),IF($Y$1="SHORT",IF($ED$58,MAX($O$39,$O$7)+0.0002,$T$19+0.0002),"")) -> -0.00025 | AG3: =IF(OR(AD3="",AE3=""),"",ABS((AE3-AD3)*10000)) -> 11392 | AH3: =IF(OR(AD3="",AF3=""),"",MAX(ABS((AD3-AF3)*10000),$ED$19)) -> 11402.5 | AI3: =$Y$8 -> 0.35 | AJ3: =IF(OR(AI3=0,$ED$11=0,AD3=""),"",$Y$2*$ED$8*AI3/$ED$11) -> 175 | AK3: =IF(OR(AJ3="",AJ3=0,AG3=""),"",AJ3*AG3/MAX(AH3,$ED$19)) -> 174.83885 | AL3: =IF(OR(AD3="",AH3="",AJ3=""),"",AJ3/(MAX(AH3,$ED$19)*$ED$3)) -> 153.47512 | AM3: =IF(OR(AG3="",AH3=""),"",AG3/MAX(AH3,$ED$19)) -> 0.99907915 | AN3: =IF(AH3="","",MAX(AH3,$ED$7)) -> 11402.5 | EC3: PipSize | ED3: 0.0001 | EF3: =IFERROR(IF(EB23<>"CoreLong","",IF($EB$55=1,"Shallow long zone (Tier 1): "&TEXT(EB51,"0.00000")&" → "&TEXT(EC51,"0.00000")&" (15m fib 0.382–0.618, less room).",IF($EB$55=2,"Main long zone (Tier 2): "&TEXT(EB52,"0.00000")&" → "&TEXT(EC52,"0.00000")&" (4H FVG + HTF 0.382 + EMA50D).",IF($EB$55=3,"Deep long zone (Tier 3): "&TEXT(EB53,"0.00000")&" → "&TEXT(EC53,"0.00000")&" (EMA100D + PWL + HTF fib).","")))),"") -> Shallow long zone (Tier 1): 1.15382 → 1.15618 (15m fib 0.382–0.618, less room). | EH3: CT_TP1 | EI3: =$EB$32
A4: Market snapshot (update from chart) | D4: Liquidity / Session levels | G4: FVG / value blocks | J4: Options expiry + risk/weights | S4: 4H | T4: =IF($O$11="","",IF($O$3>$O$11+0.0002,"Bull",IF($O$3<$O$11-0.0002,"Bear","Range"))) -> Bull | U4: ='Advanced Setup Planner'!C25 -> 0 | V4: ='Advanced Setup Planner'!D25 -> 0 | X4: SL Price (Auto) | Y4: =IF($Y$5<>"",$Y$5,IF($Y$1="LONG",IF($Y$22="","",$Y$22-0.0003),IF($Y$1="SHORT",IF($Y$23="","",$Y$23+0.0003),""))) -> 1.15352 | AC4: Entry 0.618 | AD4: =IF($Y$1="LONG",IF($ED$58,MIN($O$40,$O$7),$O$10),IF($Y$1="SHORT",$Q$25,"")) -> 1.135 | AE4: =IF(AD4="","",$ED$40) -> 0.0008 | AF4: =IF($Y$1="LONG",IF(OR($ED$58,$O$3>=$T$19),$ED$27,$T$20-0.0002),IF($Y$1="SHORT",IF($ED$58,MAX($O$39,$O$7)+0.0002,$T$19+0.0002),"")) -> -0.00025 | AG4: =IF(OR(AD4="",AE4=""),"",ABS((AE4-AD4)*10000)) -> 11342 | AH4: =IF(OR(AD4="",AF4=""),"",MAX(ABS((AD4-AF4)*10000),$ED$19)) -> 11352.5 | AI4: =$Y$9 -> 0.45 | AJ4: =IF(OR(AI4=0,$ED$11=0,AD4=""),"",$Y$2*$ED$8*AI4/$ED$11) -> 225 | AK4: =IF(OR(AJ4="",AJ4=0,AG4=""),"",AJ4*AG4/MAX(AH4,$ED$19)) -> 224.7919 | AL4: =IF(OR(AD4="",AH4="",AJ4=""),"",AJ4/(MAX(AH4,$ED$19)*$ED$3)) -> 198.19423 | AM4: =IF(OR(AG4="",AH4=""),"",AG4/MAX(AH4,$ED$19)) -> 0.99907509 | AN4: =IF(AH4="","",MAX(AH4,$ED$7)) -> 11352.5 | EA4: PipTol_Value | EB4: =ROUND($O$18*10000*0.8,0) -> 0 | EC4: MinStopPips | ED4: 8 | EE4: Long Zone (A+) | EF4: ="Deep A+ long pocket candidate (Tier 3): "&TEXT($EB$53,"0.00000")&" → "&TEXT($EC$53,"0.00000")&". Ladder (upper/mid/deep): "&TEXT($AD$15,"0.00000")&"/"&TEXT($AD$16,"0.00000")&"/"&TEXT($AD$17,"0.00000")&", SL "&TEXT($AF$15,"0.00000")&", TP1 "&TEXT($AE$15,"0.00000")&". Use this only if price flushes into Tier 3 with HTF trend intact and R/room are satisfied." -> Deep A+ long pocket candidate (Tier 3): 1.12000 → 1.12500. Ladder (upper/mid/deep): 0.00000/0.00000/0.00025, SL -0.00025, TP1 1000000.00000. Use this only if price flushes into Tier 3 with HTF trend intact and R/room are satisfied. | EH4: CT_TP2 | EI4: =IF($Y$1="SHORT",$Y$3,"")
A5: Current Price | B5: 1.155 | N5: EMA9 15m | O5: ='Advanced Setup Planner'!B6 -> 1.15 | S5: 1H | T5: =IF($O$10="","",IF($O$3>$O$10+0.0002,"Bull",IF($O$3<$O$10-0.0002,"Bear","Range"))) -> Bull | U5: ='Advanced Setup Planner'!C26 -> 0 | V5: ='Advanced Setup Planner'!D26 -> 0 | X5: Manual SL override? | EA5: PipTol_Fib | EB5: =ROUND($O$18*10000*0.5,0) -> 0 | EC5: ATR_StopMult | ED5: 1.5 | EE5: Trend Long Plan | EF5: =IFERROR(IF(AND($EB$23="CoreLong",NOT($EB$25)),"Trend long plan (current tier "&$EB$56&"): ladder at "&TEXT($AD$2,"0.00000")&"/"&TEXT($AD$3,"0.00000")&"/"&TEXT($AD$4,"0.00000")&", SL "&TEXT($AF$2,"0.00000")&", TP1 "&TEXT($AE$2,"0.00000")&". Confirm 15m/1H CHOCH up in this tier, then manage toward TP1 (and potentially PDH/PWH) using the ladder.",""),"") -> Trend long plan (current tier 1): ladder at 1.14500/1.14000/1.13500, SL -0.00025, TP1 0.00080. Confirm 15m/1H CHOCH up in this tier, then manage toward TP1 (and potentially PDH/PWH) using the ladder. | EH5: CT_Risk$ | EI5: =$Y$2*0.5 -> 250 | EJ5: =IFERROR(IF(EI9=0,"",(EI1-EI3)*EI9),"")
A6: EMA9 15m | B6: 1.15 | N6: EMA21 15m | O6: ='Advanced Setup Planner'!B7 -> 1.148 | S6: 15M | T6: =IF($O$5="","",IF(AND($O$5>$O$6,$O$6>$O$7,$O$7>$O$8),"Bull",IF(AND($O$5<$O$6,$O$6<$O$7,$O$7<$O$8),"Bear","Range"))) -> Bull | U6: ='Advanced Setup Planner'!C27 -> 0 | V6: ='Advanced Setup Planner'!D27 -> 0 | AC6: Avg Pips to SL | AD6: =IF(SUM(AL2:AL4)=0,0,SUMPRODUCT(AN2:AN4,AL2:AL4)/SUM(AL2:AL4)) -> 11389.871 | EA6: PipTol_Mid | EB6: =ROUND($O$18*10000*1,0) -> 0 | EC6: ATR15m_pips | ED6: =ROUND($O$18*10000,1) -> 0 | EH6: CT_PipsSL | EI6: =IF(OR(EI1="",EI2=""),"",ABS((EI1-EI2)*10000)) -> 5.75
A7: EMA21 15m | B7: 1.148 | N7: EMA50 15m | O7: ='Advanced Setup Planner'!B8 -> 1.145 | X7: Weight 0.382 | Y7: ='Advanced Setup Planner'!K16 -> 0.2 | AC7: Total Units | AD7: =SUM(AL2:AL4) -> 438.98653 | EA7: Long_EMAScore | EB7: =0.25*COUNTIF($O$10:$O$16,"<"&$O$3) -> 1.5 | EC7: StopFloorPips | ED7: =MAX(ED4,ROUNDUP(ED6*ED5,0)) -> 8 | EE7: CT Zone | EF7: =IFERROR(IF(AND($EB$23="CTshort",NOT($EB$25)),"CT short zone: "&TEXT($EB$47,"0.00000")&" → "&TEXT($EB$48,"0.00000")&" (premium liquidity cluster: PMH/PDH/EQH/PWH).",""),"") | EH7: CT_PipsTP | EI7: =IF(OR(EI3="",EI1=""),"",ABS((EI3-EI1)*10000))
A8: EMA50 15m | B8: 1.145 | N8: SMA200 15m | O8: ='Advanced Setup Planner'!B9 -> 1.14 | S8: HTF_Long_OK | T8: =AND(T3="Bull",T4="Bull") -> TRUE | X8: Weight 0.500 | Y8: ='Advanced Setup Planner'!K17 -> 0.35 | AC8: Avg Entry | AD8: =IF(AD7=0,"",SUMPRODUCT(AD2:AD4,AL2:AL4)/AD7) -> 1.1387371 | EA8: Short_EMAScore | EB8: =0.25*COUNTIF($O$10:$O$16,">"&$O$3) -> 0 | EC8: PrimaryRiskMult | ED8: 1 | EE8: CT Short Plan | EF8: =IFERROR(IF(AND($EB$23="CTshort",NOT($EB$25)),"CT short plan: ladder shorts at "&TEXT($EB$48,"0.00000")&"/"&TEXT($EB$49,"0.00000")&"/"&TEXT($EB$47,"0.00000")&", SL "&TEXT($EB$48+0.0008,"0.00000")&", TP1 "&TEXT($EB$35,"0.00000")&IF($EB$32<>""," (golden mid)."," (Tier1 top; no golden overlap).")&" Size small; countertrend — only take on clear exhaustion near PDH/EQH.",""),"") | EH8: CT_Rmult | EI8: =IF(OR(EI6="",EI7="",EI6=0),"",EI7/EI6)
A9: SMA200 15m | B9: 1.14 | S9: HTF_Short_OK | T9: =AND(T3="Bear",T4="Bear") -> FALSE | X9: Weight 0.618 | Y9: ='Advanced Setup Planner'!K18 -> 0.45 | AC9: Pips to TP1 | AD9: =IF(OR(AD8="",$Y$3=""),"",ABS(($Y$3-AD8)*10000)) -> 9.9999886e+09 | EA9: Long_RSIScore | EB9: =IF($O$20<45,0.5,0)+IF($O$21<45,0.25,0)+IF($O$17<45,0.25,0) -> 1 | EC9: APlusRiskMult | ED9: 1 | EH9: CT_Units | EI9: =IF(OR(EI5="",EI6="",EI6=0),"",EI5/(EI6*0.0001)) -> 434782.61
A10: EMA50 1H | B10: 1.135 | N10: EMA50 1H | O10: ='Advanced Setup Planner'!B10 -> 1.135 | S10: LTF_Long_OK | T10: =AND(OR(T5="Bull",T5="Range"),NOT(T6="Bear")) -> TRUE | AC10: Reward at TP1 $ | AD10: =IF(OR(AD7=0,AD8="",$Y$3=""),"",ABS(($Y$3-AD8)*AD7)) -> 4.3898603e+08 | EA10: Short_RSIScore | EB10: =IF($O$20>55,0.5,0)+IF($O$21>55,0.25,0)+IF($O$17>55,0.25,0) -> 0 | EC10: CTRiskMult | ED10: 0.6 | EE10: Avoid | EF10: =IFERROR(IF($EB$25,"Avoid new trades – R multiple, room, or macro gate not satisfied. Wait for conditions to improve and reassess.",""),"") | EH10: CT_NoTradeFlag | EI10: =NOT($T$11) -> TRUE
A11: EMA50 4H | B11: 1.13 | N11: EMA50 4H | O11: ='Advanced Setup Planner'!B11 -> 1.13 | S11: LTF_Short_OK | T11: =AND(OR(T5="Bear",T5="Range"),NOT(T6="Bull")) -> FALSE | X11: Ticket Size | Y11: ='Advanced Setup Planner'!K19 -> 0 | AC11: R multiple at TP1 | AD11: =IF(SUM($AJ$2:$AJ$4)=0,"",SUM($AK$2:$AK$4)/SUM($AJ$2:$AJ$4)) -> 0.99907813 | EA11: Long_StructScore | EB11: =0.25*COUNTIF($T$3:$T$6,"Bull") -> 1 | EC11: PrimaryWgtSum | ED11: =SUM($AI$2:$AI$4) -> 1
A12: EMA50 1D | B12: 1.125 | N12: EMA50 1D | O12: ='Advanced Setup Planner'!B12 -> 1.125 | X12: Min R (R multiple) | Y12: ='Advanced Setup Planner'!K20 -> 3 | AC12: Avg Eff Pips to SL | AD12: =IF(SUM(AL2:AL4)=0,"",(AL2*MAX(AH2,$ED$19)+AL3*MAX(AH3,$ED$19)+AL4*MAX(AH4,$ED$19))/SUM(AL2:AL4)) -> 11389.871 | EA12: Short_StructScore | EB12: =0.25*COUNTIF($T$3:$T$6,"Bear") -> 0 | EC12: APlusWgtSum | ED12: =SUM($AI$15:$AI$17) -> 1.5
A13: EMA100 1D | B13: 1.12 | E13: 1.15 | J13: Magnet Range (pips) | K13: 20 | N13: EMA100 1D | O13: ='Advanced Setup Planner'!B13 -> 1.12 | EA13: Long_FVGScore | EB13: =MIN(1,IF(ABS(($O$3-$O$36)*10000)<=EB4,1,0)+IF(ABS(($O$3-$O$38)*10000)<=EB4,1,0)+IF(ABS(($O$3-$O$40)*10000)<=EB4,1,0)) -> 0 | EC13: CTWgtSum | ED13: =SUM($AI$28:$AI$30) -> 1
A14: EMA200 1D | B14: 1.115 | E14: 1.16 | J14: Options Clamp % | K14: 0.3 | N14: EMA200 1D | O14: ='Advanced Setup Planner'!B14 -> 1.115 | S14: Liquidity levels | X14: Active Zone | Y14: =IF(AND($O$3>=Z17-$X$20,$O$3<=AA17+$X$20),1,IF(AND($O$3>=Z18-$X$20,$O$3<=AA18+$X$20),2,IF(AND($O$3>=Z19-$X$20,$O$3<=AA19+$X$20),3,""))) -> 1 | AC14: A+ LADDER | AD14: Entry | AE14: TP | AF14: SL | AG14: Pips to TP1 | AH14: Eff Pips to SL | AI14: Weight | AJ14: Risk $ | AK14: Reward $ | AL14: Units | AM14: R per rung | AN14: =IF(AH15="","",MAX(AH15,$ED$7)) -> 8 | EA14: Short_FVGScore | EB14: =MIN(1,IF(ABS(($O$3-$O$35)*10000)<=EB4,1,0)+IF(ABS(($O$3-$O$37)*10000)<=EB4,1,0)+IF(ABS(($O$3-$O$39)*10000)<=EB4,1,0)) -> 0 | EC14: Primary_MinStopPips | ED14: 12
A15: EMA50 1W | B15: 1.11 | J15: Zone tolerance | K15: 0.0002 | N15: EMA50 1W | O15: ='Advanced Setup Planner'!B15 -> 1.11 | S15: PMH | T15: ='Advanced Setup Planner'!E5 -> 0 | X15: =IF(AND($O$3>=Z17-$X$20,$O$3<=AA17+$X$20),1,IF(AND($O$3>=Z18-$X$20,$O$3<=AA18+$X$20),2,IF(AND($O$3>=Z19-$X$20,$O$3<=AA19+$X$20),3,0))) -> 1 | AC15: upper rung | AD15: =IF($Y$1<>"LONG","",$O$35) -> 0 | AE15: =IF(AD15="","",$ED$41) -> 1000000 | AF15: =IF(AD15="","",$ED$30) -> -0.00025 | AG15: =IF(OR(AD15="",AE15=""),"",ABS((AE15-AD15)*10000)) -> 10000000000 | AH15: =IF(OR(AD15="",AF15=""),"",MAX(ABS((AD15-AF15)*10000),$ED$20)) -> 8 | AI15: 0.4 | AJ15: =IF(OR(AI15=0,$ED$12=0,AD15=""),"",$Y$2*$ED$9*AI15/$ED$12) -> 133.33333 | AK15: =IF(OR(AJ15="",AJ15=0,AG15=""),"",AJ15*AG15/MAX(AH15,$ED$20)) -> 1.6666667e+11 | AL15: =IF(OR(AD15="",AH15="",AJ15=""),"",AJ15/(MAX(AH15,$ED$20)*$ED$3)) -> 166666.67 | AM15: =IF(OR(AG15="",AH15=""),"",AG15/MAX(AH15,$ED$20)) -> 1250000000 | AN15: =IF(AH16="","",MAX(AH16,$ED$7)) -> 8 | EA15: LongScore | EB15: =IFERROR((1-$T$37*$T$36)*(EB7+EB9+EB11+EB13+EB42),"") -> 3.5 | EC15: APlus_MinStopPips | ED15: 8
A16: EMA20 1M | J16: Weight 0.382 | K16: 0.2 | N16: EMA20 1M | O16: ='Advanced Setup Planner'!#REF! -> #REF! | S16: PML | T16: ='Advanced Setup Planner'!E6 -> 0 | X16: Zone | Y16: Role | Z16: Low | AA16: High | AC16: middle rung | AD16: =IF($Y$1<>"LONG","",$O$36) -> 0 | AE16: =IF(AD16="","",$ED$41) -> 1000000 | AF16: =IF(AD16="","",$ED$30) -> -0.00025 | AG16: =IF(OR(AD16="",AE16=""),"",ABS((AE16-AD16)*10000)) -> 10000000000 | AH16: =IF(OR(AD16="",AF16=""),"",MAX(ABS((AD16-AF16)*10000),$ED$20)) -> 8 | AI16: 0.5 | AJ16: =IF(OR(AI16=0,$ED$12=0,AD16=""),"",$Y$2*$ED$9*AI16/$ED$12) -> 166.66667 | AK16: =IF(OR(AJ16="",AJ16=0,AG16=""),"",AJ16*AG16/MAX(AH16,$ED$20)) -> 2.0833333e+11 | AL16: =IF(OR(AD16="",AH16="",AJ16=""),"",AJ16/(MAX(AH16,$ED$20)*$ED$3)) -> 208333.33 | AM16: =IF(OR(AG16="",AH16=""),"",AG16/MAX(AH16,$ED$20)) -> 1250000000 | AN16: =IF(AH17="","",MAX(AH17,$ED$7)) -> 8 | EA16: ShortScore | EB16: =IFERROR((1-$T$37*$T$36)*(EB8+EB10+EB12+EB14+EB42),"") -> 0 | EC16: CT_MinStopPips | ED16: 8
A17: RSI 15M | J17: Weight 0.500 | K17: 0.35 | N17: RSI 4HR | O17: ='Advanced Setup Planner'!B19 -> 0 | S17: PWH | T17: ='Advanced Setup Planner'!E7 -> 0 | X17: 1 | Y17: Shallow | Z17: =MIN($Q$24,$Q$23) -> 1.155 | AA17: =MAX($Q$24,$Q$23) -> 1.15618 | AC17: deep rung | AD17: =IF($Y$1<>"LONG","",$O$38+$ED$29) -> 0.00025 | AE17: =IF(AD17="","",$ED$41) -> 1000000 | AF17: =IF(AD17="","",$ED$30) -> -0.00025 | AG17: =IF(OR(AD16="",AE16=""),"",ABS((AE16-AD16)*10000)) -> 10000000000 | AH17: =IF(OR(AD17="",AF17=""),"",MAX(ABS((AD17-AF17)*10000),$ED$20)) -> 8 | AI17: 0.6 | AJ17: =IF(OR(AI17=0,$ED$12=0,AD17=""),"",$Y$2*$ED$9*AI17/$ED$12) -> 200 | AK17: =IF(OR(AJ17="",AJ17=0,AG17=""),"",AJ17*AG17/MAX(AH17,$ED$20)) -> 250000000000 | AL17: =IF(OR(AD17="",AH17="",AJ17=""),"",AJ17/(MAX(AH17,$ED$20)*$ED$3)) -> 250000 | AM17: =IF(OR(AG17="",AH17=""),"",AG17/MAX(AH17,$ED$20)) -> 1250000000 | EA17: MaxScore | EB17: =0.25*COUNTA($O$10:$O$16)+3.5 -> 5.25 | EC17: WinProb | ED17: Expected_R | EE17: Expected_$
A18: RSI 1H | J18: Weight 0.618 | K18: 0.45 | N18: ATR(14) 15m | O18: ='Advanced Setup Planner'!B20 -> 0 | S18: PWL | T18: ='Advanced Setup Planner'!E8 -> 0 | X18: 2 | Y18: Main | Z18: =MIN(Q25,Q24) -> 1.15382 | AA18: =MAX(Q25,Q24) -> 1.155 | EA18: LongScore_pct | EB18: =IFERROR(IF(EB17=0,"",EB15/EB17),"") -> 0.66666667 | EC18: =IF($Y$1<>"LONG","",MIN(0.8,0.4+0.4*IFERROR(EB18,0)+0.1*IFERROR(EB42,0))) -> 0.66666667 | ED18: =IF($Y$1="","",IF($Y$1="LONG",IF(OR(EC18="",EB20=""),"",EC18*EB20-(1-EC18)*1),IF(OR(EC19="",EB20=""),"",EC19*EB20-(1-EC19)*1))) -> 7592.9142 | EE18: =IF(ED18="","",ED18*$Y$2) -> 3796457.1
A19: RSI 4HR | J19: Ticket Size | K19: 0 | N19: ADR(14) | O19: ='Advanced Setup Planner'!B21 -> 0 | S19: PDH | T19: ='Advanced Setup Planner'!E9 -> 0 | X19: 3 | Y19: HTF | Z19: =MIN(Q31,Q29) -> 0 | AA19: =MAX(Q31,Q29) -> 0 | AC19: Avg Pips to SL | AD19: =IF(SUM(AL15:AL17)=0,0,SUMPRODUCT(AN14:AN16,AL15:AL17)/SUM(AL15:AL17)) -> 8 | EA19: ShortScore_pct | EB19: =IFERROR(IF(EB17=0,"",EB16/EB17),"") -> 0 | EC19: Primary_StopFloorPips | ED19: =MAX(ED14,ROUNDUP(ED6*ED5,0)) -> 12
A20: ATR(14) 15m | J20: Min R (R multiple) | K20: 3 | N20: RSI 15M | O20: ='Advanced Setup Planner'!B16 -> 0 | S20: PDL | T20: ='Advanced Setup Planner'!E10 -> 0 | W20: Zone tolerance | X20: ='Advanced Setup Planner'!K15 -> 0.0002 | AC20: Total Units | AD20: =SUM(AL15:AL17) -> 625000 | EB20: =IF(OR($EB$55=0,$AD$7<=0,$AD$12=""),"",$AD$12) -> 11389.871 | EC20: APlus_StopFloorPips | ED20: =MAX(ED15,ROUNDUP(ED6*ED5,0)) -> 8
A21: ADR(14) | N21: RSI 1H | O21: ='Advanced Setup Planner'!B18 -> 0 | S21: EQH_above | T21: ='Advanced Setup Planner'!E11 -> 0 | X21: zone-specific fibs for SL/entries | AC21: Avg Entry | AD21: =IF(AD20=0,"",SUMPRODUCT(AD15:AD17,AL15:AL17)/AD20) -> 0.0001 | EA21: Trend Mode | EB21: =IF($Y$1="","No bias",IF($Y$1="LONG",IF($T$8,"Trend-aligned","Counter-trend"),IF($Y$1="SHORT",IF($T$9,"Trend-aligned","Counter-trend"),"No bias"))) -> Trend-aligned | EC21: CT_StopFloorPips | ED21: =MAX(ED16,ROUNDUP(ED6*ED5,0)) -> 8
A22: Structure (SMC) – D1 / 4H / 1H / 15m | N22: Legs (Intraday / Session / HTF) | Q22: Fib outputs | S22: EQL_below | T22: ='Advanced Setup Planner'!E12 -> 0 | X22: Zone_618 | Y22: =IF($Y$1="LONG",$EB$30,"") -> 1.15382 | AC22: Pips to TP1 | AD22: =IF(OR(AD21="",$Y$3=""),"",ABS(($Y$3-AD21)*10000)) -> 9999999999 | EA22: Setup Type | EB22: =IF(AND(T3="Bull",T4="Bull",T5="Bear",T6="Bear"),"Trend Pullback","Mixed") -> Mixed | EC22: CT_ActiveWgtSum | ED22: =SUMPRODUCT(($AD$28:$AD$30<>"")*($AI$28:$AI$30)) -> 1
A23: TF | B23: Trend (auto) | C23: Last BOS (manual) | D23: Last CHOCH (manual) | N23: LTF Leg Low (15m | O23: ='Advanced Setup Planner'!E13 -> 1.15 | P23: L1 0.382 | Q23: =IF($Y$1="SHORT",$O$23+($O$24-$O$23)*0.382,$O$24-($O$24-$O$23)*0.382) -> 1.15618 | S23: Distances to nearest liquidity | X23: Zone_500 | Y23: =IF($Y$1="SHORT",$EB$31,"") | AC23: Reward at TP1 $ | AD23: =IF(OR(AD20=0,AD21="",$Y$3=""),"",ABS(($Y$3-AD21)*AD20)) -> 6.25e+11 | EA23: TradeMode | EB23: =IFERROR(IF(EE52,"CoreLong",IF(EE53,"CTshort","Avoid")),"") -> CoreLong | EC23: CT_ATRMult | ED23: 1.5
A24: 1D | B24: ='Advanced Setup Planner'!T3 -> Bull | N24: LTF Leg High (15m) | O24: ='Advanced Setup Planner'!E14 -> 1.16 | P24: L1 0.500 | Q24: =IF($Y$1="SHORT",$O$23+($O$24-$O$23)*0.5,$O$24-($O$24-$O$23)*0.5) -> 1.155 | S24: Dist_Above (pips) | T24: =MIN(IF(T15>$O$3,ABS((T15-$O$3)*10000),1000000000),IF(T17>$O$3,ABS((T17-$O$3)*10000),1000000000),IF(T19>$O$3,ABS((T19-$O$3)*10000),1000000000),IF(T21>$O$3,ABS((T21-$O$3)*10000),1000000000)) -> 1000000000 | AC24: R multiple at TP1 | AD24: =IF(SUM($AJ$15:$AJ$17)=0,"",SUM($AK$15:$AK$17)/SUM($AJ$15:$AJ$17)) -> 1250000000 | EA24: Grade | EB24: =IF($Y$1="","N/A",IF($EB$25,"B",IF(EB34<0.4,"B",IF(EB18>=0.7,"A+",IF(EB18>=0.4,"B","C"))))) -> B | EC24: CT_RangePips | ED24: =MAX(6,ROUND($O$18*10000*$ED$23,0)) -> 6
A25: 4H | B25: ='Advanced Setup Planner'!T4 -> Bull | P25: L1 0.618 | Q25: =IF($Y$1="SHORT",$O$23+($O$24-$O$23)*0.618,$O$24-($O$24-$O$23)*0.618) -> 1.15382 | S25: Dist_Below (pips) | T25: =MIN(IF(T16<$O$3,ABS((T16-$O$3)*10000),1000000000),IF(T18<$O$3,ABS((T18-$O$3)*10000),1000000000),IF(T20<$O$3,ABS((T20-$O$3)*10000),1000000000),IF(T22<$O$3,ABS((T22-$O$3)*10000),1000000000)) -> 11550 | AC25: Avg Eff Pips to SL | AD25: =IF(SUM(AL15:AL17)=0,"",(AL15*MAX(AH15,$ED$20)+AL16*MAX(AH16,$ED$20)+AL17*MAX(AH17,$ED$20))/SUM(AL15:AL17)) -> 8 | EA25: NoTradeFlag | EB25: =IFERROR(OR($Y$1="",AND(EB23="CoreLong",OR(EE48=FALSE,$AD$12="",$AD$12<$Y$12)),AND(EB23="CTshort",OR(EE49=FALSE,$O$21<=65)),FALSE),"") -> FALSE | ED25: =IF($Y$1="LONG",IF(OR($ED$58,$O$3>$T$19),MAX($O$27,$O$24),$T$19),IF($Y$1="SHORT",IF(OR($ED$58,$O$3<$T$20),MIN($O$26,$O$23),$T$20),"")) -> 1.16
A26: 1H | B26: ='Advanced Setup Planner'!T5 -> Bull | N26: Session Low | O26: ='Advanced Setup Planner'!E15 -> 0 | P26: L2 0.382 | Q26: =IF($Y$1="SHORT",$O$26+($O$27-$O$26)*0.382,$O$27-($O$27-$O$26)*0.382) -> 0 | AN26: =IF(AH28="","",MAX(AH28,$ED$7)) -> 14 | EA26: MasterSignal | EB26: =IF($Y$1="","NO SIDE – neither core long nor CT short setup is active.",IF(EB23="CoreLong",IF(EB25,"AVOID CORE LONG – not in discount or 3R not available.","CORE LONG SETUP – buy dip in active tier. Ladder entries "&TEXT($AD$2,"0.00000")&"/"&TEXT($AD$3,"0.00000")&"/"&TEXT($AD$4,"0.00000")&", SL "&TEXT($AF$2,"0.00000")&", TP1 "&TEXT($Y$3,"0.00000")&"."),IF(EB23="CTshort",IF(EB25,"AVOID CT SHORT – conditions for scalp fade not met.","OPTIONAL CT SHORT – scalp fade only. Short zone near PDH/CT highs; see CT ladder for entries, SL and TPs."),"AVOID – nothing to do here. Stand aside and wait for either discount buy or CT fade zone."))) -> CORE LONG SETUP – buy dip in active tier. Ladder entries 1.14500/1.14000/1.13500, SL -0.00025, TP1 1000000.00000. | ED26: =IF($Y$1="LONG",IF(MAX($O$27,$O$24)>0,MAX($O$27,$O$24),$T$19),IF($Y$1="SHORT",IF(MIN($O$26,$O$23)>0,MIN($O$26,$O$23),$T$20),"")) -> 1.16
A27: 15M | B27: ='Advanced Setup Planner'!T6 -> Bull | N27: Session High | O27: ='Advanced Setup Planner'!E16 -> 0 | P27: L2 0.500 | Q27: =IF($Y$1="SHORT",$O$26+($O$27-$O$26)*0.5,$O$27-($O$27-$O$26)*0.5) -> 0 | S27: Long_RoomOK | T27: =IF($AD$6="",FALSE,$T$24>=3*$AD$6) -> TRUE | AC27: CT LADDER | AD27: Entry | AE27: TP | AF27: SL | AG27: Pips to TP1 | AH27: Eff Pips to SL | AI27: Weight | AJ27: Risk $ | AK27: Reward $ | AL27: Units | AM27: R per rung | AN27: =IF(AH29="","",MAX(AH29,$ED$7)) -> 11 | EA27: Setup Summary | EB27: =IFERROR(IF(EB23="CoreLong",IF(EB25,"NO CORE LONG – wait for proper discount and 3R.","CORE LONG OK – follow MasterSignal & Trade Plan."),IF(EB23="CTshort",IF(EB25,"NO CT SHORT – CT scalp conditions incomplete.","CT SHORT OK – scalp only, log as counter-trend."),"NO TRADE – neither core nor CT setup active.")),"") -> CORE LONG OK – follow MasterSignal & Trade Plan. | EC27: Primary_SL_Cont | ED27: =$O$40-$ED$28 -> -0.00025
P28: L2 0.618 | Q28: =IF($Y$1="SHORT",$O$26+($O$27-$O$26)*0.618,$O$27-($O$27-$O$26)*0.618) -> 0 | S28: Short_RoomOK | T28: =IF(AD6="",FALSE,T25>=3*AD6) -> FALSE | AC28: deep rung | AD28: =IF(EB48="","",EB48) -> 1.1558 | AE28: =IF(AD28="","",IFERROR(_xlfn.AGGREGATE(14,6,CHOOSE({1,2,3,4},'Advanced Setup Planner'!$E$12,'Advanced Setup Planner'!$E$10,'Advanced Setup Planner'!$E$15,'Advanced Setup Planner'!$H$10)/(CHOOSE({1,2,3,4},'Advanced Setup Planner'!$E$12,'Advanced Setup Planner'!$E$10,'Advanced Setup Planner'!$E$15,'Advanced Setup Planner'!$H$10)<AD28),1)-$ED$3,AD28-($ED$24*$ED$3))) -> -0.0001 | AF28: =IF(AD30="","",AD30+0.0008) -> 1.1572 | AG28: =IF(OR(AD28="",AE28=""),"",ABS((AE28-AD28)*10000)) -> 11559 | AH28: =IF(OR(AD28="",AF28=""),"",MAX(ABS((AD28-AF28)*10000),$ED$21)) -> 14 | AI28: 0.45 | AJ28: =IF(OR(AI28=0,$ED$22=0,AD28=""),"",$Y$2*$ED$10*AI28/$ED$22) -> 135 | AK28: =IF(OR(AJ28="",AJ28=0,AG28=""),"",AJ28*AG28/MAX(AH28,$ED$21)) -> 111461.79 | AL28: =IF(OR(AD28="",AH28="",AJ28=""),"",AJ28/(MAX(AH28,$ED$21)*$ED$3)) -> 96428.571 | AM28: =IF(OR(AG28="",AH28=""),"",AG28/MAX(AH28,$ED$21)) -> 825.64286 | AN28: =IF(AH30="","",MAX(AH30,$ED$7)) -> 8 | EA28: Trade Plan | EB28: =IFERROR(IF(EB25,"Stand aside or observation-only. Location: "&EE54&".",IF(EB23="CoreLong","CORE LONG EXECUTION – Mode: "&EB21&", Grade: "&EB24&". Bias: LONG (trend/macro). Buy active tier with ladder "&TEXT($AD$2,"0.00000")&"/"&TEXT($AD$3,"0.00000")&"/"&TEXT($AD$4,"0.00000")&". SL "&TEXT($AF$2,"0.00000")&". TP1 "&TEXT($Y$3,"0.00000")&".","CT SHORT EXECUTION – Counter-trend scalp. Short near PDH/CT zone. Use CT ladder for entries with reduced risk (0.25–0.5R). Stop above 1.1725–1.1730; TP1 back into 1.1670–1.1660, TP2 into 1.1645–1.1635.")),"") -> CORE LONG EXECUTION – Mode: Trend-aligned, Grade: B. Bias: LONG (trend/macro). Buy active tier with ladder 1.14500/1.14000/1.13500. SL -0.00025. TP1 1000000.00000. | EC28: Primary_SL_Buffer | ED28: =MAX(0.00025,$O$18*0.5) -> 0.00025
N29: HTF Swing Low (4H) | O29: ='Advanced Setup Planner'!E17 -> 0 | P29: L3 0.382 | Q29: =IF($Y$1="SHORT",$O$29+($O$30-$O$29)*0.382,$O$30-($O$30-$O$29)*0.382) -> 0 | S29: Strike 1 | T29: ='Advanced Setup Planner'!K5 -> 0 | U29: Size 1 (bn) | V29: ='Advanced Setup Planner'!K6 -> 0 | W29: =IF(T29="","",ABS(T29-$O$3)) -> 1.155 | AC29: middle rung | AD29: =IF(EB49="","",EB49) -> 1.1561 | AE29: =IF(AD29="","",IFERROR(_xlfn.AGGREGATE(14,6,CHOOSE({1,2,3,4},'Advanced Setup Planner'!$E$12,'Advanced Setup Planner'!$E$10,'Advanced Setup Planner'!$E$15,'Advanced Setup Planner'!$H$10)/(CHOOSE({1,2,3,4},'Advanced Setup Planner'!$E$12,'Advanced Setup Planner'!$E$10,'Advanced Setup Planner'!$E$15,'Advanced Setup Planner'!$H$10)<AD29),1)-$ED$3,AD29-($ED$24*$ED$3))) -> -0.0001 | AF29: =AF28 -> 1.1572 | AG29: =IF(OR(AD29="",AE29=""),"",ABS((AE29-AD29)*10000)) -> 11562 | AH29: =IF(OR(AD29="",AF29=""),"",MAX(ABS((AD29-AF29)*10000),$ED$21)) -> 11 | AI29: 0.35 | AJ29: =IF(OR(AI29=0,$ED$22=0,AD29=""),"",$Y$2*$ED$10*AI29/$ED$22) -> 105 | AK29: =IF(OR(AJ29="",AJ29=0,AG29=""),"",AJ29*AG29/MAX(AH29,$ED$21)) -> 110364.55 | AL29: =IF(OR(AD29="",AH29="",AJ29=""),"",AJ29/(MAX(AH29,$ED$21)*$ED$3)) -> 95454.545 | AM29: =IF(OR(AG29="",AH29=""),"",AG29/MAX(AH29,$ED$21)) -> 1051.0909 | EA29: Go/No-Go | EB29: =IF($Y$1="","NO SETUP",IF(EB25,"NO TRADE – "&EE54,IF(EB23="CoreLong","GO (CORE LONG) – trend/macro aligned.","GO (CT SCALP) – small risk only."))) -> GO (CORE LONG) – trend/macro aligned. | EC29: Aplus_SL_Buffer | ED29: =MAX(0.00025,$O$18*0.5) -> 0.00025
A30: Outputs (auto) | N30: HTF Swing High (4H) | O30: ='Advanced Setup Planner'!E18 -> 0 | P30: L3 0.500 | Q30: =IF($Y$1="SHORT",$O$29+($O$30-$O$29)*0.5,$O$30-($O$30-$O$29)*0.5) -> 0 | S30: Strike 2 | T30: ='Advanced Setup Planner'!K7 -> 0 | U30: Size 2 (bn) | V30: ='Advanced Setup Planner'!K8 -> 0 | W30: =IF(T30="","",ABS(T30-$O$3)) -> 1.155 | AC30: shallow rung | AD30: =IF(EB47="","",EB47) -> 1.1564 | AE30: =IF(AD30="","",IFERROR(_xlfn.AGGREGATE(14,6,CHOOSE({1,2,3,4},'Advanced Setup Planner'!$E$12,'Advanced Setup Planner'!$E$10,'Advanced Setup Planner'!$E$15,'Advanced Setup Planner'!$H$10)/(CHOOSE({1,2,3,4},'Advanced Setup Planner'!$E$12,'Advanced Setup Planner'!$E$10,'Advanced Setup Planner'!$E$15,'Advanced Setup Planner'!$H$10)<AD30),1)-$ED$3,AD30-($ED$24*$ED$3))) -> -0.0001 | AF30: =AF28 -> 1.1572 | AG30: =IF(OR(AD30="",AE30=""),"",ABS((AE30-AD30)*10000)) -> 11565 | AH30: =IF(OR(AD30="",AF30=""),"",MAX(ABS((AD30-AF30)*10000),$ED$21)) -> 8 | AI30: 0.2 | AJ30: =IF(OR(AI30=0,$ED$22=0,AD30=""),"",$Y$2*$ED$10*AI30/$ED$22) -> 60 | AK30: =IF(OR(AJ30="",AJ30=0,AG30=""),"",AJ30*AG30/MAX(AH30,$ED$21)) -> 86737.5 | AL30: =IF(OR(AD30="",AH30="",AJ30=""),"",AJ30/(MAX(AH30,$ED$21)*$ED$3)) -> 75000 | AM30: =IF(OR(AG30="",AH30=""),"",AG30/MAX(AH30,$ED$21)) -> 1445.625 | EA30: Golden_Low (Overlap L1/L3) | EB30: =IF(OR($Q$23="",$Q$25="",$Q$29="",$Q$31=""),"",MAX(MIN($Q$23,$Q$25),MIN($Q$29,$Q$31))) -> 1.15382 | EC30: Aplus_SL | ED30: =$O$38-$ED$29 -> -0.00025
A31: Side (LONG/SHORT) | B31: ='Advanced Setup Planner'!Y1 -> LONG | P31: L3 0.618 | Q31: =IF($Y$1="SHORT",$O$29+($O$30-$O$29)*0.618,$O$30-($O$30-$O$29)*0.618) -> 0 | S31: Strike 3 | T31: ='Advanced Setup Planner'!K9 -> 0 | U31: Size 3 (bn) | V31: ='Advanced Setup Planner'!K10 -> 0 | W31: =IF(T31="","",ABS(T31-$O$3)) -> 1.155 | EA31: Golden_High (Overlap L1/L3) | EB31: =IF(OR($Q$23="",$Q$25="",$Q$29="",$Q$31=""),"",MIN(MAX($Q$23,$Q$25),MAX($Q$29,$Q$31))) -> 0 | EC31: (Pips_to_Entry_500) | ED31: =IF(AD3="","",($O$3-AD3)*10000) -> 150
A32: Setup Summary | B32: =IFERROR(IF('Advanced Setup Planner'!EB18="","",TEXT('Advanced Setup Planner'!EB18,"0%")&" ("&Backend!B83&") — "&Backend!B84),"") -> 67% (B) — Tradable but selective: wait for confirmation / smaller size. | S32: Strike 4 | U32: Size 4 (bn) | W32: =IF(T32="","",ABS(T32-$O$3)) | AC32: Avg Pips to SL | AD32: =IF(SUM(AL28:AL30)=0,0,SUMPRODUCT(AN26:AN28,AL28:AL30)/SUM(AL28:AL30)) -> 11.240876 | EA32: Golden_Mid | EB32: =IF(OR(EB30="",EB31="",EB30>EB31),"",(EB30+EB31)/2) | EC32: (Pips_to_Entry_618) | ED32: =IF(AD4="","",($O$3-AD4)*10000) -> 200 | EE32: =IF($Y$1<>"LONG","","Dist to entries (pips): 0.382="&TEXT(ED30,"0.0")&", 0.5="&TEXT(ED31,"0.0")&", 0.618="&TEXT(ED32,"0.0")) -> Dist to entries (pips): 0.382=0.0, 0.5=150.0, 0.618=200.0
A33: Trade Mode | B33: ='Advanced Setup Planner'!EB23 -> CoreLong | S33: Magnet Strike | T33: =IF(COUNTA(T29:T32)=0,"",INDEX(T29:T32,MATCH(MIN(W29:W32),W29:W32,0))) -> 0 | AC33: Total Units | AD33: =SUM(AL28:AL30) -> 266883.12 | EA33: In_GoldenPocket_Flag | EB33: =IF(OR(EB30="",EB31="",EB30>EB31),FALSE,AND($O$3>=EB30,$O$3<=EB31)) -> FALSE | EC33: ValueRiskMult | ED33: 1
A34: Macro Bias (EURUSD) | B34: =IFERROR(Backend!B338,"") -> Buy dips | N34: FVGs (4H / Daily / 1H) | S34: Magnet Range (pips) | T34: ='Advanced Setup Planner'!K13 -> 20 | AC34: Avg Entry | AD34: =IF(AD33=0,"",SUMPRODUCT(AD28:AD30,AL28:AL30)/AD33) -> 1.1560759 | EA34: GoldenProx_Score | EB34: =IF(OR(EB30="",EB31="",EB30>EB31),0,IF(OR($O$3<EB30,$O$3>EB31),0,MAX(0,1-(ABS($O$3-EB32)/((EB31-EB30)/2))))) -> 0 | EC34: Value_MinStopPips | ED34: 10
A35: Rate diff (NOW) | B35: =IF(Backend!B86="","",TEXT(Backend!B86,"0.00")&" ("&Backend!B90&")") -> 2.37 (USD advantage now) | N35: 4H FVG high | O35: ='Advanced Setup Planner'!H5 -> 0 | S35: Distance to Magnet (pips) | T35: =IF(T33="","",ABS((T33-$O$3)*10000)) -> 11550 | AC35: Pips to TP1 | AD35: =IF(OR(AD34="",$AE$28=""),"",ABS(($AE$28-AD34)*10000)) -> 11561.759 | EA35: CT_TP1 (magnet below entry) | EB35: =IF($Y$1<>"SHORT","",IF(COUNT($AD$28:$AD$30)=0,"",IF(MAX(IF('Advanced Setup Planner'!$E$12<$EB$46,'Advanced Setup Planner'!$E$12,0),IF('Advanced Setup Planner'!$E$10<$EB$46,'Advanced Setup Planner'!$E$10,0),IF('Advanced Setup Planner'!$H$10<$EB$46,'Advanced Setup Planner'!$H$10,0))=0,$EB$46-MAX($X$20,$ED$24*$ED$3),MAX(IF('Advanced Setup Planner'!$E$12<$EB$46,'Advanced Setup Planner'!$E$12,0),IF('Advanced Setup Planner'!$E$10<$EB$46,'Advanced Setup Planner'!$E$10,0),IF('Advanced Setup Planner'!$H$10<$EB$46,'Advanced Setup Planner'!$H$10,0))))) | EC35: Value_StopFloorPips | ED35: =MAX($ED$34,ROUNDUP($ED$6*$ED$5,0)) -> 10
A36: Rate diff change (6M vs NOW) | B36: =IF(Backend!B88="","",TEXT(Backend!B88,"0")&" steps (~"&TEXT(Backend!B89,"0")&"bp) — "&Backend!B91) | N36: 4H FVG low | O36: ='Advanced Setup Planner'!H6 -> 0 | S36: Within Magnet? 0/1 | T36: =IF(AND(T33<>"",T35<=T34),1,0) -> 0 | AC36: Reward at TP1 $ | AD36: =IF(OR(AD33=0,AD34="",$AE$28=""),"",ABS(($AE$28-AD34)*AD33)) -> 308563.83 | EC36: Value_SL_Buffer | ED36: =MAX(0.00025,$O$18*0.5,$ED$34*$ED$3) -> 0.001
A37: Yield Narrative | B37: =Backend!B356 -> US yields: 2Y 3.50% (-2bp 1d) — 2Y falling → easier Fed priced → USD headwind. Curve (2s10s): 1bp — Curve normal → growth ok | N37: Daily FVG high | O37: ='Advanced Setup Planner'!H7 -> 0 | S37: Options Clamp % | T37: ='Advanced Setup Planner'!K14 -> 0.3 | AC37: R multiple at TP1 | AD37: =IF(SUM($AJ$28:$AJ$30)=0,"",SUM($AK$28:$AK$30)/SUM($AJ$28:$AJ$30)) -> 1028.5461 | EA37: MacroBiasScore | EB37: =IFERROR(Backend!$B$338,"") -> Buy dips | EC37: Value_SL | ED37: =$O$40-$ED$36 -> -0.001
A38: Narrative (plain English) | B38: =IFERROR(Backend!B110,"") -> 1) Macro bias: Buy dips. Rate gap NOW 2.37 (USD advantage now). 2) Yields: US yields: 2Y 3.50% (-2bp 1d) — 2Y falling → easier Fed priced → USD headwind. Curve (2s10s): 1bp — Curve normal → growth ok. 3) Speakers: Fed neutral (daily -0.08), ; ECB hawkish (daily 0.25), . | N38: Daily FVG low | O38: ='Advanced Setup Planner'!H8 -> 0 | AC38: Avg Eff Pips to SL | AD38: =IF(SUM(AL28:AL30)=0,"",(AL28*MAX(AH28,$ED$21)+AL29*MAX(AH29,$ED$21)+AL30*MAX(AH30,$ED$21))/SUM(AL28:AL30)) -> 11.240876 | EA38: MacroBias_Direction | EB38: =IFERROR(IF(EB37="Buy dips",1,IF(EB37="Sell rallies",-1,0)),"") -> 1 | EC38: ValueWgtSum | ED38: =SUM($AI$42:$AI$44) -> 1
A39: Action (what to do) | B39: =Backend!B112 -> Misaligned: macro Buy dips vs technical 1.155 — Action: prefer LONG pullbacks into support (Primary/Value). Avoid chasing highs. Reduce size; demand stronger confirmation (e.g., BOS/CHOCH + rejection/acceptance). | N39: 1H FVG high | O39: ='Advanced Setup Planner'!H9 -> 0 | EA39: MacroToneAdj | EB39: =IF(Backend!$B$350>0.3,-0.5,IF(Backend!$B$350<-0.3,0.5,0)) -> -0.5 | ED39: 8
A40: Notes | B40: =Backend!B114 -> Steps = 25bp moves (quarter‑point). Example: -4 steps ≈ -100bp of USD-vs-EUR advantage compressing over ~6 months. | N40: 1H FVG low | O40: ='Advanced Setup Planner'!H10 -> 0 | EA40: MacroPolicyAdj | EB40: =IF(Backend!$B$347<=-2,0.5,IF(Backend!$B$347>=2,-0.5,0)) -> -0.5 | ED40: =MAX($O$27,$T$19,$T$17)+$ED$39*$ED$3 -> 0.0008
A41: Definitions | B41: =IF(B40="","",IF(B40="Aligned","Trade direction matches macro bias.","Macro bias disagrees — reduce size or demand stronger technical confirmation.")) -> Macro bias disagrees — reduce size or demand stronger technical confirmation. | AC41: VALUE LADDER | AD41: Entry | AE41: TP | AF41: SL | AG41: Pips to TP1 | AH41: Eff Pips to SL | AI41: Weight | AJ41: Risk $ | AK41: Reward $ | AL41: Units | AM41: R per rung | AN41: =IF(AH42="","",MAX(AH42,$ED$7)) -> 11410 | EA41: Macro_TotalBias | EB41: =MAX(-1,MIN(1,EB38+EB39+EB40)) -> 0 | ED41: =IF($Y$1<>"LONG","",MIN(IF($T$17>$O$3,$T$17,10^6),IF($T$19>$O$3,$T$19,10^6),IF($O$27>$O$3,$O$27,10^6))) -> 1000000
A42: Execution ladders (auto from Planner_v2) | AC42: Entry SMA200 | AD42: =IF($Y$1<>"LONG","",IF($O$8<=$O$3,$O$8,"")) -> 1.14 | AE42: =IF(AD42="","",$ED$41) -> 1000000 | AF42: =IF(AD42="","",$ED$37) -> -0.001 | AG42: =IF(OR(AD42="",AE42=""),"",ABS((AE42-AD42)*10000)) -> 9999988600 | AH42: =IF(OR(AD42="",AF42=""),"",MAX(ABS((AD42-AF42)*10000),$ED$35)) -> 11410 | AI42: 0.35 | AJ42: =IF(OR(AI42=0,$ED$38=0,AD42=""),"",$Y$2*$ED$33*AI42/$ED$38) -> 175 | AK42: =IF(OR(AJ42="",AJ42=0,AG42=""),"",AJ42*AG42/MAX(AH42,$ED$35)) -> 1.5337406e+08 | AL42: =IF(OR(AD42="",AH42="",AJ42=""),"",AJ42/(MAX(AH42,$ED$35)*$ED$3)) -> 153.37423 | AM42: =IF(OR(AG42="",AH42=""),"",AG42/MAX(AH42,$ED$35)) -> 876423.19 | AN42: =IF(AH43="","",MAX(AH43,$ED$7)) -> 11360 | EA42: MacroBiasScore | EB42: =0.5*EB41 -> 0
A43: Primary Ladder (Shallow / Continuation) | AC43: Entry EMA50_1H | AD43: =IF($Y$1<>"LONG","",IF($O$10<=$O$3,$O$10,"")) -> 1.135 | AE43: =IF(AD43="","",$ED$41) -> 1000000 | AF43: =IF(AD43="","",$ED$37) -> -0.001 | AG43: =IF(OR(AD43="",AE43=""),"",ABS((AE43-AD43)*10000)) -> 9999988650 | AH43: =IF(OR(AD43="",AF43=""),"",MAX(ABS((AD43-AF43)*10000),$ED$35)) -> 11360 | AI43: 0.4 | AJ43: =IF(OR(AI43=0,$ED$38=0,AD43=""),"",$Y$2*$ED$33*AI43/$ED$38) -> 200 | AK43: =IF(OR(AJ43="",AJ43=0,AG43=""),"",AJ43*AG43/MAX(AH43,$ED$35)) -> 1.7605614e+08 | AL43: =IF(OR(AD43="",AH43="",AJ43=""),"",AJ43/(MAX(AH43,$ED$35)*$ED$3)) -> 176.05634 | AM43: =IF(OR(AG43="",AH43=""),"",AG43/MAX(AH43,$ED$35)) -> 880280.69 | AN43: =IF(AH44="","",MAX(AH44,$ED$7)) -> 10
A44: Rung | B44: Entry | C44: TP | D44: SL | E44: Pips→TP | F44: EffPips→SL | G44: Units | H44: Risk $ | I44: Reward $ | J44: R | K44: R2 | AC44: Entry 1H_FVG_L | AD44: =IF($Y$1<>"LONG","",IF($O$40<=$O$3,$O$40,"")) -> 0 | AE44: =IF(AD44="","",$ED$41) -> 1000000 | AF44: =IF(AD44="","",$ED$37) -> -0.001 | AG44: =IF(OR(AD44="",AE44=""),"",ABS((AE44-AD44)*10000)) -> 10000000000 | AH44: =IF(OR(AD44="",AF44=""),"",MAX(ABS((AD44-AF44)*10000),$ED$35)) -> 10 | AI44: 0.25 | AJ44: =IF(OR(AI44=0,$ED$38=0,AD44=""),"",$Y$2*$ED$33*AI44/$ED$38) -> 125 | AK44: =IF(OR(AJ44="",AJ44=0,AG44=""),"",AJ44*AG44/MAX(AH44,$ED$35)) -> 125000000000 | AL44: =IF(OR(AD44="",AH44="",AJ44=""),"",AJ44/(MAX(AH44,$ED$35)*$ED$3)) -> 125000 | AM44: =IF(OR(AG44="",AH44=""),"",AG44/MAX(AH44,$ED$35)) -> 1000000000
A45: Shallow | B45: ='Advanced Setup Planner'!AD2 -> 1.145 | C45: ='Advanced Setup Planner'!AE2 -> 0.0008 | D45: ='Advanced Setup Planner'!AF2 -> -0.00025 | E45: ='Advanced Setup Planner'!AG2 -> 11442 | F45: ='Advanced Setup Planner'!AH2 -> 11452.5 | G45: ='Advanced Setup Planner'!AL2 -> 87.31718 | H45: ='Advanced Setup Planner'!AJ2 -> 100 | I45: ='Advanced Setup Planner'!AK2 -> 99.908317 | J45: ='Advanced Setup Planner'!AM2 -> 0.99908317 | K45: ='Advanced Setup Planner'!AM2 -> 0.99908317 | ED45: In_Tier1 | EE45: =AND($O$3>=EB51,$O$3<=EC51) -> TRUE
A46: Mid | B46: ='Advanced Setup Planner'!AD3 -> 1.14 | C46: ='Advanced Setup Planner'!AE3 -> 0.0008 | D46: ='Advanced Setup Planner'!AF3 -> -0.00025 | E46: ='Advanced Setup Planner'!AG3 -> 11392 | F46: ='Advanced Setup Planner'!AH3 -> 11402.5 | G46: ='Advanced Setup Planner'!AL3 -> 153.47512 | H46: ='Advanced Setup Planner'!AJ3 -> 175 | I46: ='Advanced Setup Planner'!AK3 -> 174.83885 | J46: ='Advanced Setup Planner'!AM3 -> 0.99907915 | K46: ='Advanced Setup Planner'!AM3 -> 0.99907915 | AC46: Avg Pips to SL | AD46: =IF(SUM(AL42:AL44)=0,0,SUMPRODUCT(AN41:AN43,AL42:AL44)/SUM(AL42:AL44)) -> 39.894859 | EA46: CT_MinEntry | EB46: =MIN(IF($AD$28="",1000000000,$AD$28),IF($AD$29="",1000000000,$AD$29),IF($AD$30="",1000000000,$AD$30)) -> 1.1558 | ED46: In_Tier2 | EE46: =AND($O$3>=EB52,$O$3<=EC52) -> FALSE
A47: Deep | B47: ='Advanced Setup Planner'!AD4 -> 1.135 | C47: ='Advanced Setup Planner'!AE4 -> 0.0008 | D47: ='Advanced Setup Planner'!AF4 -> -0.00025 | E47: ='Advanced Setup Planner'!AG4 -> 11342 | F47: ='Advanced Setup Planner'!AH4 -> 11352.5 | G47: ='Advanced Setup Planner'!AL4 -> 198.19423 | H47: ='Advanced Setup Planner'!AJ4 -> 225 | I47: ='Advanced Setup Planner'!AK4 -> 224.7919 | J47: ='Advanced Setup Planner'!AM4 -> 0.99907509 | K47: ='Advanced Setup Planner'!AM4 -> 0.99907509 | AC47: Total Units | AD47: =SUM(AL42:AL44) -> 125329.43 | EA47: CT_Low | EB47: =IF(EB48="","",EB48+($ED$24*$ED$3)) -> 1.1564 | ED47: In_Tier3 | EE47: =IF('Advanced Setup Planner'!$E$7>$O$3,'Advanced Setup Planner'!$E$7,"")
A48: Total | B48: =IFERROR(SUBTOTAL(101,Table16[Entry]),"") -> 1.14 | C48: =IFERROR(SUBTOTAL(101,Table16[TP]),"") -> 0.0008 | D48: =IFERROR(SUBTOTAL(101,Table16[SL]),"") -> -0.00025 | E48: =IFERROR(SUBTOTAL(101,Table16[Pips→TP]),"") -> 11392 | F48: =IFERROR(SUBTOTAL(101,Table16[EffPips→SL]),"") -> 11402.5 | G48: =SUBTOTAL(109,Table16[Units]) -> 438.98653 | H48: =SUBTOTAL(109,Table16[Risk $]) -> 500 | I48: =SUBTOTAL(109,Table16[Reward $]) -> 499.53906 | J48: =IFERROR(Table16[[#Totals],[Reward $]]/Table16[[#Totals],[Risk $]],"") -> 0.99907813 | AC48: Avg Entry | AD48: =IF(AD47=0,"",SUMPRODUCT(AD42:AD44,AL42:AL44)/AD47) -> 0.0029894859 | EA48: CT_High | EB48: =IF(EE51="","",EE51+$X$20) -> 1.1558 | ED48: In_Discount | EE48: =IF('Advanced Setup Planner'!$E$9>$O$3,'Advanced Setup Planner'!$E$9,"")
AC49: Pips to TP1 | AD49: =IF(OR(AD48="",$Y$3=""),"",ABS(($Y$3-AD48)*10000)) -> 1e+10 | EA49: CT_Mid | EB49: =IF(EB48="","",EB48+((($ED$24/2)*$ED$3))) -> 1.1561 | ED49: In_CT_Zone | EE49: =IF('Advanced Setup Planner'!$E$16>$O$3,'Advanced Setup Planner'!$E$16,"")
A50: Value Ladder (Mid-depth supports) | AC50: Reward at TP1 $ | AD50: =IF(OR(AD47=0,AD48="",$Y$3=""),"",ABS(($Y$3-AD48)*AD47)) -> 1.2532943e+11 | AN50: =O3 -> 1.155 | EA50: Tier | EB50: =IF($Y$1<>"LONG","",MAX($O$3,IF(AND($T$21<>"",ABS($T$21-IF($O$27<>"",$O$27,$T$17))<=0.0025),$T$21,IF($O$27<>"",$O$27,$T$17)))) -> 1.155 | EC50: High | ED50: In_Premium | EE50: =IF(AND('Advanced Setup Planner'!$E$11>$O$3,('Advanced Setup Planner'!$E$11-$O$3)*10000<=40),'Advanced Setup Planner'!$E$11,"")
A51: Rung | B51: Entry | C51: TP | D51: SL | E51: Pips→TP | F51: EffPips→SL | G51: Units | H51: Risk $ | I51: Reward $ | J51: R | K51: R2 | AC51: R multiple at TP1 | AD51: =IF(SUM($AJ$42:$AJ$44)=0,"",SUM($AK$42:$AK$44)/SUM($AJ$42:$AJ$44)) -> 2.5065886e+08 | AN51: L1_0.618-L1_0.382 | EA51: Tier1 Low | EB51: =MIN($Q$23,$Q$25) -> 1.15382 | EC51: =MAX($Q$23,$Q$25) -> 1.15618 | EE51: =IFERROR(_xlfn.AGGREGATE(15,6,EE47:EE50/(EE47:EE50<>""),1),$O$3+($ED$24*$ED$3)) -> 1.1556
A52: Shallow | B52: ='Advanced Setup Planner'!AD42 -> 1.14 | C52: ='Advanced Setup Planner'!AE42 -> 1000000 | D52: ='Advanced Setup Planner'!AF42 -> -0.001 | E52: ='Advanced Setup Planner'!AG42 -> 9999988600 | F52: ='Advanced Setup Planner'!AH42 -> 11410 | G52: ='Advanced Setup Planner'!AL42 -> 153.37423 | H52: ='Advanced Setup Planner'!AJ42 -> 175 | I52: ='Advanced Setup Planner'!AK42 -> 1.5337406e+08 | J52: ='Advanced Setup Planner'!AM42 -> 876423.19 | K52: ='Advanced Setup Planner'!AM42 -> 876423.19 | AC52: Avg Eff Pips to SL | AD52: =IF(SUM(AL42:AL44)=0,"",(AL42*MAX(AH42,$ED$35)+AL43*MAX(AH43,$ED$35)+AL44*MAX(AH44,$ED$35))/SUM(AL42:AL44)) -> 39.894859 | AN52: 4H_FVG_low-4H_FVG_high | EA52: 2 | EB52: =O36 -> 0 | EC52: =O35 -> 0 | ED52: CoreLong_Flag | EE52: =AND($EB$38>=0,T8=TRUE,NOT(T9),EE48) -> TRUE
A53: Mid | B53: ='Advanced Setup Planner'!AD43 -> 1.135 | C53: ='Advanced Setup Planner'!AE43 -> 1000000 | D53: ='Advanced Setup Planner'!AF43 -> -0.001 | E53: ='Advanced Setup Planner'!AG43 -> 9999988650 | F53: ='Advanced Setup Planner'!AH43 -> 11360 | G53: ='Advanced Setup Planner'!AL43 -> 176.05634 | H53: ='Advanced Setup Planner'!AJ43 -> 200 | I53: ='Advanced Setup Planner'!AK43 -> 1.7605614e+08 | J53: ='Advanced Setup Planner'!AM43 -> 880280.69 | K53: ='Advanced Setup Planner'!AM43 -> 880280.69 | AN53: DeepLow-High | EA53: 3 | EB53: =O13 -> 1.12 | EC53: =O12 -> 1.125 | ED53: CTShort_Flag | EE53: =AND(N($EB$38)<=0,T8=TRUE,T11=TRUE,EE49=TRUE,$O$21>70,$O$20>65) -> FALSE
A54: Deep | B54: ='Advanced Setup Planner'!AD44 -> 0 | C54: ='Advanced Setup Planner'!AE44 -> 1000000 | D54: ='Advanced Setup Planner'!AF44 -> -0.001 | E54: ='Advanced Setup Planner'!AG44 -> 10000000000 | F54: ='Advanced Setup Planner'!AH44 -> 10 | G54: ='Advanced Setup Planner'!AL44 -> 125000 | H54: ='Advanced Setup Planner'!AJ44 -> 125 | I54: ='Advanced Setup Planner'!AK44 -> 125000000000 | J54: ='Advanced Setup Planner'!AM44 -> 1000000000 | K54: ='Advanced Setup Planner'!AM44 -> 1000000000 | ED54: LocationLabel | EE54: =IF(EE48,"DISCOUNT",IF(EE49,"CT_ZONE",IF(EE50,"PREMIUM","MID"))) -> #VALUE!
A55: Total | B55: =IFERROR(SUBTOTAL(101,Table17[Entry]),"") -> 0.75833333 | C55: =IFERROR(SUBTOTAL(101,Table17[TP]),"") -> 1000000 | D55: =IFERROR(SUBTOTAL(101,Table17[SL]),"") -> -0.001 | E55: =IFERROR(SUBTOTAL(101,Table17[Pips→TP]),"") -> 9.9999924e+09 | F55: =IFERROR(SUBTOTAL(101,Table17[EffPips→SL]),"") -> 7593.3333 | G55: =SUBTOTAL(109,Table17[Units]) -> 125329.43 | H55: =SUBTOTAL(109,Table17[Risk $]) -> 500 | I55: =SUBTOTAL(109,Table17[Reward $]) -> 1.2532943e+11 | J55: =IFERROR(Table17[[#Totals],[Reward $]]/Table17[[#Totals],[Risk $]],"") -> 2.5065886e+08 | EA55: ActiveTier | EB55: =IF(AND($O$3>=EB51,$O$3<=EC51),1,IF(AND($O$3>=EB52,$O$3<=EC52),2,IF(AND($O$3>=EB53,$O$3<=EC53),3,0))) -> 1
EB56: =EB55 -> 1
A57: A+ Ladder (Deep value block) | EA57: Primary_ViewTier (1/2/3, blank=auto) | EC57: Resolved_PrimaryTier | ED57: =IF($EB$57<>"",$EB$57,IF($EB$55=0,1,$EB$55)) -> 1
A58: Rung | B58: Entry | C58: TP | D58: SL | E58: Pips→TP | F58: EffPips→SL | G58: Units | H58: Risk $ | I58: Reward $ | J58: R | K58: R2
A59: Shallow | B59: ='Advanced Setup Planner'!AD15 -> 0 | C59: ='Advanced Setup Planner'!AE15 -> 1000000 | D59: ='Advanced Setup Planner'!AF15 -> -0.00025 | E59: ='Advanced Setup Planner'!AG15 -> 10000000000 | F59: ='Advanced Setup Planner'!AH15 -> 8 | G59: ='Advanced Setup Planner'!AL15 -> 166666.67 | H59: ='Advanced Setup Planner'!AJ15 -> 133.33333 | I59: ='Advanced Setup Planner'!AK15 -> 1.6666667e+11 | J59: ='Advanced Setup Planner'!AM15 -> 1250000000 | K59: ='Advanced Setup Planner'!AM15 -> 1250000000
A60: Mid | B60: ='Advanced Setup Planner'!AD16 -> 0 | C60: ='Advanced Setup Planner'!AE16 -> 1000000 | D60: ='Advanced Setup Planner'!AF16 -> -0.00025 | E60: ='Advanced Setup Planner'!AG16 -> 10000000000 | F60: ='Advanced Setup Planner'!AH16 -> 8 | G60: ='Advanced Setup Planner'!AL16 -> 208333.33 | H60: ='Advanced Setup Planner'!AJ16 -> 166.66667 | I60: ='Advanced Setup Planner'!AK16 -> 2.0833333e+11 | J60: ='Advanced Setup Planner'!AM16 -> 1250000000 | K60: ='Advanced Setup Planner'!AM16 -> 1250000000
A61: Deep | B61: ='Advanced Setup Planner'!AD17 -> 0.00025 | C61: ='Advanced Setup Planner'!AE17 -> 1000000 | D61: ='Advanced Setup Planner'!AF17 -> -0.00025 | E61: ='Advanced Setup Planner'!AG17 -> 10000000000 | F61: ='Advanced Setup Planner'!AH17 -> 8 | G61: ='Advanced Setup Planner'!AL17 -> 250000 | H61: ='Advanced Setup Planner'!AJ17 -> 200 | I61: ='Advanced Setup Planner'!AK17 -> 250000000000 | J61: ='Advanced Setup Planner'!AM17 -> 1250000000 | K61: ='Advanced Setup Planner'!AM17 -> 1250000000
A62: Total | B62: =IFERROR(SUBTOTAL(101,Table18[Entry]),"") -> 8.3333333e-05 | C62: =IFERROR(SUBTOTAL(101,Table18[TP]),"") -> 1000000 | D62: =IFERROR(SUBTOTAL(101,Table18[SL]),"") -> -0.00025 | E62: =IFERROR(SUBTOTAL(101,Table18[Pips→TP]),"") -> 10000000000 | F62: =IFERROR(SUBTOTAL(101,Table18[EffPips→SL]),"") -> 8 | G62: =SUBTOTAL(109,Table18[Units]) -> 625000 | H62: =SUBTOTAL(109,Table18[Risk $]) -> 500 | I62: =SUBTOTAL(109,Table18[Reward $]) -> 625000000000 | J62: =IFERROR(Table18[[#Totals],[Reward $]]/Table18[[#Totals],[Risk $]],"") -> 1250000000
A64: CT Ladder (Fade ceiling; only on rejection) | L64: =IF('Advanced Setup Planner'!Y1<>"SHORT","CT inactive (Side is "&'Advanced Setup Planner'!Y1&"). Switch Side to SHORT to use CT.","") -> CT inactive (Side is LONG). Switch Side to SHORT to use CT.
A65: Rung | B65: Entry | C65: TP | D65: SL | E65: Pips→TP | F65: EffPips→SL | G65: Units | H65: Risk $ | I65: Reward $ | J65: R | K65: Column1
A66: Shallow | B66: ='Advanced Setup Planner'!AD28 -> 1.1558 | C66: ='Advanced Setup Planner'!AE28 -> -0.0001 | D66: ='Advanced Setup Planner'!AF28 -> 1.1572 | E66: ='Advanced Setup Planner'!AG28 -> 11559 | F66: ='Advanced Setup Planner'!AH28 -> 14 | G66: ='Advanced Setup Planner'!AL28 -> 96428.571 | H66: ='Advanced Setup Planner'!AJ28 -> 135 | I66: ='Advanced Setup Planner'!AK28 -> 111461.79 | J66: ='Advanced Setup Planner'!AM28 -> 825.64286
A67: Mid | B67: ='Advanced Setup Planner'!AD29 -> 1.1561 | C67: ='Advanced Setup Planner'!AE29 -> -0.0001 | D67: ='Advanced Setup Planner'!AF29 -> 1.1572 | E67: ='Advanced Setup Planner'!AG29 -> 11562 | F67: ='Advanced Setup Planner'!AH29 -> 11 | G67: ='Advanced Setup Planner'!AL29 -> 95454.545 | H67: ='Advanced Setup Planner'!AJ29 -> 105 | I67: ='Advanced Setup Planner'!AK29 -> 110364.55 | J67: ='Advanced Setup Planner'!AM29 -> 1051.0909
A68: Deep | B68: ='Advanced Setup Planner'!AD30 -> 1.1564 | C68: ='Advanced Setup Planner'!AE30 -> -0.0001 | D68: ='Advanced Setup Planner'!AF30 -> 1.1572 | E68: ='Advanced Setup Planner'!AG30 -> 11565 | F68: ='Advanced Setup Planner'!AH30 -> 8 | G68: ='Advanced Setup Planner'!AL30 -> 75000 | H68: ='Advanced Setup Planner'!AJ30 -> 60 | I68: ='Advanced Setup Planner'!AK30 -> 86737.5 | J68: ='Advanced Setup Planner'!AM30 -> 1445.625
A69: Total | B69: =IFERROR(SUBTOTAL(101,Table19[Entry]),"") -> 1.1561 | C69: =IFERROR(SUBTOTAL(101,Table19[TP]),"") -> -0.0001 | D69: =IFERROR(SUBTOTAL(101,Table19[SL]),"") -> 1.1572 | E69: =IFERROR(SUBTOTAL(101,Table19[Pips→TP]),"") -> 11562 | F69: =IFERROR(SUBTOTAL(101,Table19[EffPips→SL]),"") -> 11 | G69: =SUBTOTAL(109,Table19[Units]) -> 266883.12 | H69: =SUBTOTAL(109,Table19[Risk $]) -> 300 | I69: =SUBTOTAL(109,Table19[Reward $]) -> 308563.83 | J69: =IFERROR(Table19[[#Totals],[Reward $]]/Table19[[#Totals],[Risk $]],"") -> 1028.5461

Sheet Backend
A1: List
A2: Bull
A3: Bear
A4: Range
A5: Up
A6: Down
A7: None
A8: 1
A9: 2
A10: 3
A11: Falling
A12: Neutral
A13: Rising
A14: Softening
A15: Mixed
A16: Tight
A17: Slowing
A18: Stable
A19: Accelerating
A20: More cuts
A21: Hold/uncertain
A22: Fewer cuts
... A80: Narrative Engine (do not edit)
A82: SetupScore | B82: =IFERROR('Advanced Setup Planner'!EB18,"") -> 0.66666667
A83: SetupGrade | B83: =IFERROR(IF(B82="","",IF(B82>=0.8,"A",IF(B82>=0.65,"B",IF(B82>=0.5,"C","D")))),"") -> B
A84: SetupMeaning | B84: =IFERROR(IF(B83="","",IF(B83="A","High quality: ok to execute if plan rules are met.",IF(B83="B","Tradable but selective: wait for confirmation / smaller size.",IF(B83="C","Weak: wait for better location or stronger confirmation.","Avoid: observation only.")))),"") -> Tradable but selective: wait for confirmation / smaller size.
A86: RateDiff_Now | B86: =IF(OR(Backend!Z211="",Backend!Z212=""),"",Backend!Z211-Backend!Z212) -> 2.37
A87: RateDiff_6M | B87: =IF(Backend!B346="","",Backend!B346)
A88: RateDiff_ChangeSteps | B88: =IF(Backend!B347="","",Backend!B347)
A89: RateDiff_ChangeBP | B89: =IF(B88="","",B88*25)
A90: RateDiff_NowLabel | B90: =IF(B86="","",IF(B86>0,"USD advantage now","EUR advantage now")) -> USD advantage now
A91: RateDiff_ChangeLabel | B91: =IF(B88="","",IF(B88<0,"USD advantage shrinking over ~6M","USD advantage widening over ~6M"))
A93: FedTone | B93: =IF(Backend!B349="","",IF(Backend!B349>=0.25,"hawkish",IF(Backend!B349<=-0.25,"dovish","neutral"))&" (daily "&TEXT(Backend!B349,"0.00")&")") -> neutral (daily -0.08)
A94: ECBTone | B94: =IF(Backend!B351="","",IF(Backend!B351>=0.25,"hawkish",IF(Backend!B351<=-0.25,"dovish","neutral"))&" (daily "&TEXT(Backend!B351,"0.00")&")") -> hawkish (daily 0.25)
B95: =IF(Backend!B350="","",IF(Backend!B350>=0.25,"hawkish",IF(Backend!B350<=-0.25,"dovish","neutral"))&" (30d "&TEXT(Backend!B350,"0.00")&")")
B96: =IF(Backend!B352="","",IF(Backend!B352>=0.25,"hawkish",IF(Backend!B352<=-0.25,"dovish","neutral"))&" (30d "&TEXT(Backend!B352,"0.00")&")")
B97: =IFERROR(IF(Backend!B338="Buy dips","LONG",IF(Backend!B338="Sell rallies","SHORT","NEUTRAL")),"") -> LONG
A98: Price | B98: ='Advanced Setup Planner'!B5 -> 1.155
B99: =IFERROR(IF(OR(B97="NEUTRAL",B98=""),"",IF(B97=B98,"Aligned: macro "&Backend!B338&" matches technical "&B98,"Misaligned: macro "&Backend!B338&" vs technical "&B98)),"") -> Misaligned: macro Buy dips vs technical 1.155
A100: Strike1 | B100: =IF('Advanced Setup Planner'!K5="","",'Advanced Setup Planner'!K5) | C100: =IFERROR(IF(B100="",1E+99,ABS(B100-B98)),"") -> 1e+99 | D100: =IF('Advanced Setup Planner'!K6="","",'Advanced Setup Planner'!K6)
A101: Strike2 | B101: =IF('Advanced Setup Planner'!K7="","",'Advanced Setup Planner'!K7) | C101: =IFERROR(IF(B101="",1E+99,ABS(B101-B98)),"") -> 1e+99 | D101: =IF('Advanced Setup Planner'!K8="","",'Advanced Setup Planner'!K8)
A102: Strike3 | B102: =IF('Advanced Setup Planner'!K9="","",'Advanced Setup Planner'!K9) | C102: =IFERROR(IF(B102="",1E+99,ABS(B102-B98)),"") -> 1e+99 | D102: =IF('Advanced Setup Planner'!K10="","",'Advanced Setup Planner'!K10)
A103: Strike4 | B103: =IF('Advanced Setup Planner'!K11="","",'Advanced Setup Planner'!K11) | C103: =IFERROR(IF(B103="",1E+99,ABS(B103-B98)),"") -> 1e+99 | D103: =IF('Advanced Setup Planner'!K12="","",'Advanced Setup Planner'!K12)
A105: NearestStrike | B105: =IFERROR(INDEX(B100:B103,MATCH(MIN(C100:C103),C100:C103,0)),"")
A106: NearestSize | B106: =IF(B105="","",INDEX(D100:D103,MATCH(B105,B100:B103,0)))
A107: NearestPips | B107: =IF(B105="","",ABS(B105-B98)*10000)
A108: StrikeNote | B108: =IF(B105="","",IF(B107<=15,"Options magnet nearby: strike "&TEXT(B105,"0.0000")&" (~"&TEXT(B107,"0")&" pips, size "&TEXT(B106,"0.00")&"bn).","Options strikes not near price (nearest "&TEXT(B105,"0.0000")&", ~"&TEXT(B107,"0")&" pips)."))
A110: Narrative | B110: =IFERROR(IF('Advanced Setup Planner'!B5="","","1) Macro bias: "&Backend!B338&". "&IF(B86="","","Rate gap NOW "&TEXT(B86,"0.00")&" ("&B90&"). ")&IF(B88="","","Expected 6M change "&TEXT(B88,"0")&" steps ("&TEXT(B89,"0")&"bp) — "&B91&". ")&"2) Yields: "&Backend!B356&". "&"3) Speakers: Fed "&IF(B93<>"",B93&", ","")&IF(B95<>"",B95,"")&"; ECB "&IF(B94<>"",B94&", ","")&IF(B96<>"",B96,"")&". "&IF(B108="","",B108)),"") -> 1) Macro bias: Buy dips. Rate gap NOW 2.37 (USD advantage now). 2) Yields: US yields: 2Y 3.50% (-2bp 1d) — 2Y falling → easier Fed priced → USD headwind. Curve (2s10s): 1bp — Curve normal → growth ok. 3) Speakers: Fed neutral (daily -0.08), ; ECB hawkish (daily 0.25), .
A112: Action | B112: =IFERROR(IF('Advanced Setup Planner'!B5="","",IF(B99="","",B99&" — ")&IF(Backend!B338="Buy dips","Action: prefer LONG pullbacks into support (Primary/Value). Avoid chasing highs. ",IF(Backend!B338="Sell rallies","Action: prefer SHORT rallies into resistance (CT/Primary-short). Avoid selling lows. ","Action: macro neutral — lean on structure/levels, trade smaller."))&IF(OR(B97="NEUTRAL",B98=""),"",IF(B97<>B98," Reduce size; demand stronger confirmation (e.g., BOS/CHOCH + rejection/acceptance).",""))),"") -> Misaligned: macro Buy dips vs technical 1.155 — Action: prefer LONG pullbacks into support (Primary/Value). Avoid chasing highs. Reduce size; demand stronger confirmation (e.g., BOS/CHOCH + rejection/acceptance).
A114: Glossary | B114: ="Steps = 25bp moves (quarter‑point). Example: -4 steps ≈ -100bp of USD-vs-EUR advantage compressing over ~6 months." -> Steps = 25bp moves (quarter‑point). Example: -4 steps ≈ -100bp of USD-vs-EUR advantage compressing over ~6 months.
A130: Date | B130: CentralBank | C130: Person | D130: Role | E130: Event | F130: Topic | G130: Tone | H130: Tone_Score | I130: Notes | J130: Link/Source | L130: Hawkish | M130: 1 | P130: FED
A131: 45959 | B131: FED | C131: Powell | G131: Neutral | H131: =IF(G131="","",VLOOKUP(G131,$L$130:$M$132,2,FALSE)) -> 0 | L131: Neutral | M131: 0 | P131: BOJ
A132: 45967 | B132: FED | C132: Goolsbee | G132: Hawkish | H132: =IF(G132="","",VLOOKUP(G132,$L$130:$M$132,2,FALSE)) -> 1 | L132: Dovish | M132: -1 | P132: ECB
A133: 45967 | B133: FED | C133: Hammack | G133: Hawkish | H133: =IF(G133="","",VLOOKUP(G133,$L$130:$M$132,2,FALSE)) -> 1
A134: 45971 | B134: FED | C134: Musalem | G134: Hawkish | H134: =IF(G134="","",VLOOKUP(G134,$L$130:$M$132,2,FALSE)) -> 1
A135: 45971 | B135: FED | C135: Miran | G135: Dovish | H135: =IF(G135="","",VLOOKUP(G135,$L$130:$M$132,2,FALSE)) -> -1
A136: 45974 | B136: FED | C136: Kashkari | G136: Neutral | H136: =IF(G136="","",VLOOKUP(G136,$L$130:$M$132,2,FALSE)) -> 0
A137: 45979 | B137: FED | C137: Barkin | G137: Neutral | H137: =IF(G137="","",VLOOKUP(G137,$L$130:$M$132,2,FALSE)) -> 0
A138: 45982 | B138: FED | C138: Logan | G138: Hawkish | H138: =IF(G138="","",VLOOKUP(G138,$L$130:$M$132,2,FALSE)) -> 1
A139: 45982 | B139: FED | C139: Collins | G139: Hawkish | H139: =IF(G139="","",VLOOKUP(G139,$L$130:$M$132,2,FALSE)) -> 1
A140: 45982 | B140: FED | C140: Daly | G140: Dovish | H140: =IF(G140="","",VLOOKUP(G140,$L$130:$M$132,2,FALSE)) -> -1
A141: 45982 | B141: FED | C141: Williams | G141: Dovish | H141: =IF(G141="","",VLOOKUP(G141,$L$130:$M$132,2,FALSE)) -> -1
A142: 45985 | B142: FED | C142: Waller | G142: Dovish | H142: =IF(G142="","",VLOOKUP(G142,$L$130:$M$132,2,FALSE)) -> -1
A143: 45999 | B143: ECB | C143: Schnabel | G143: Hawkish | H143: =IF(G143="","",VLOOKUP(G143,$L$130:$M$132,2,FALSE)) -> 1
A144: 45999 | B144: ECB | C144: Rehn | G144: Dovish | H144: =IF(G144="","",VLOOKUP(G144,$L$130:$M$132,2,FALSE)) -> -1
... A163: 46008 | B163: BOJ | C163: Takashi | G163: Hawkish | H163: =IF(G163="","",VLOOKUP(G163,$L$130:$M$132,2,FALSE)) -> 1
A180: Date | B180: Currency | C180: Rate1_mid 350-375) | D180: Prob1 | E180: Rate2_mid (375-400) | F180: Prob2 | G180: Rate3_mid (325-350) | H180: Prob3 | I180: ExpRate | J180: CutsVsToday
A181: 46050 | B181: US | C181: 3.625 | D181: 0.756 | E181: 3.875 | F181: 0 | G181: 3.375 | H181: 0.244 | I181: =IF(B181="","",IF(SUM(D181,F181,H181)=0,"",(C181*D181+E181*F181+G181*H181)/SUM(D181,F181,H181))) -> 3.564 | J181: =IF(I181="","",ROUND((IF(B181="US",Backend!$Z$211,IF(B181="ECB",Backend!$Z$212,""))-I181)/0.25,0)) -> 3
A182: 46082 | B182: US | C182: 3.625 | D182: 0.505 | E182: 3.875 | F182: 0 | G182: 3.375 | H182: 0.414 | I182: =IF(B182="","",IF(SUM(D182,F182,H182)=0,"",(C182*D182+E182*F182+G182*H182)/SUM(D182,F182,H182))) -> 3.5123776 | J182: =IF(I182="","",ROUND((IF(B182="US",Backend!$Z$211,IF(B182="ECB",Backend!$Z$212,""))-I182)/0.25,0)) -> 3
A183: 46141 | B183: US | C183: 3.625 | D183: 0.39 | E183: 3.875 | F183: 0 | G183: 3.375 | H183: 0.157 | I183: =IF(B183="","",IF(SUM(D183,F183,H183)=0,"",(C183*D183+E183*F183+G183*H183)/SUM(D183,F183,H183))) -> 3.553245 | J183: =IF(I183="","",ROUND((IF(B183="US",Backend!$Z$211,IF(B183="ECB",Backend!$Z$212,""))-I183)/0.25,0)) -> 3
A184: 46190 | B184: US | C184: 3.625 | D184: 0.186 | E184: 3.875 | F184: 0 | G184: 3.375 | H184: 0.39 | I184: =IF(B184="","",IF(SUM(D184,F184,H184)=0,"",(C184*D184+E184*F184+G184*H184)/SUM(D184,F184,H184))) -> 3.4557292 | J184: =IF(I184="","",ROUND((IF(B184="US",Backend!$Z$211,IF(B184="ECB",Backend!$Z$212,""))-I184)/0.25,0)) -> 4
A185: 46232 | B185: US | C185: 3.625 | D185: 0.135 | E185: 3.875 | F185: 0 | G185: 3.375 | H185: 0.355 | I185: =IF(B185="","",IF(SUM(D185,F185,H185)=0,"",(C185*D185+E185*F185+G185*H185)/SUM(D185,F185,H185))) -> 3.4438776 | J185: =IF(I185="","",ROUND((IF(B185="US",Backend!$Z$211,IF(B185="ECB",Backend!$Z$212,""))-I185)/0.25,0)) -> 4
A186: 46056 | B186: ECB | C186: 1.75 | D186: 0 | E186: 2 | F186: 0.847 | G186: 2.25 | H186: 0.018 | I186: =IF(B186="","",IF(SUM(D186,F186,H186)=0,"",(C186*D186+E186*F186+G186*H186)/SUM(D186,F186,H186))) -> 2.0052023 | J186: =IF(I186="","",ROUND((IF(B186="US",Backend!$Z$211,IF(B186="ECB",Backend!$Z$212,""))-I186)/0.25,0)) -> 0
A187: 46098 | B187: ECB | C187: 1.75 | D187: 0.243 | E187: 2 | F187: 0.721 | G187: 2.25 | H187: 0.016 | I187: =IF(B187="","",IF(SUM(D187,F187,H187)=0,"",(C187*D187+E187*F187+G187*H187)/SUM(D187,F187,H187))) -> 1.9420918 | J187: =IF(I187="","",ROUND((IF(B187="US",Backend!$Z$211,IF(B187="ECB",Backend!$Z$212,""))-I187)/0.25,0)) -> 0
A188: 46140 | B188: ECB | C188: 1.75 | D188: 0.288 | E188: 2 | F188: 0.655 | G188: 2.25 | H188: 0.014 | I188: =IF(B188="","",IF(SUM(D188,F188,H188)=0,"",(C188*D188+E188*F188+G188*H188)/SUM(D188,F188,H188))) -> 1.9284222 | J188: =IF(I188="","",ROUND((IF(B188="US",Backend!$Z$211,IF(B188="ECB",Backend!$Z$212,""))-I188)/0.25,0)) -> 0
A189: 46182 | B189: ECB | C189: 1.75 | D189: 0.304 | E189: 2 | F189: 0.627 | G189: 2.25 | H189: 0.014 | I189: =IF(B189="","",IF(SUM(D189,F189,H189)=0,"",(C189*D189+E189*F189+G189*H189)/SUM(D189,F189,H189))) -> 1.9232804 | J189: =IF(I189="","",ROUND((IF(B189="US",Backend!$Z$211,IF(B189="ECB",Backend!$Z$212,""))-I189)/0.25,0)) -> 0
A190: 46224 | B190: ECB | C190: 1.75 | D190: 0.31 | E190: 2 | F190: 0.614 | G190: 2.25 | H190: 0.013 | I190: =IF(B190="","",IF(SUM(D190,F190,H190)=0,"",(C190*D190+E190*F190+G190*H190)/SUM(D190,F190,H190))) -> 1.9207577 | J190: =IF(I190="","",ROUND((IF(B190="US",Backend!$Z$211,IF(B190="ECB",Backend!$Z$212,""))-I190)/0.25,0)) -> 0
A191: 46274 | B191: ECB | C191: 1.75 | D191: 0.312 | E191: 2 | F191: 0.612 | G191: 2.25 | H191: 0.013 | I191: =IF(B191="","",IF(SUM(D191,F191,H191)=0,"",(C191*D191+E191*F191+G191*H191)/SUM(D191,F191,H191))) -> 1.9202241 | J191: =IF(I191="","",ROUND((IF(B191="US",Backend!$Z$211,IF(B191="ECB",Backend!$Z$212,""))-I191)/0.25,0)) -> 0
A210: Date | B210: Category | C210: Event | D210: Actual | E210: Forecast | F210: Previous | G210: Surprise vs Forecast | H210: Change vs Prev | I210: Qualitative | J210: EffectDirection | K210: Adj_Surprise | L210: Adj_ChangeAdj_ChangeAdj_ChangeAdj_ChangeAdj_ChangeAdj_ChangeAdj_ChangeAdj_ChangeAdj_Change | N210: Date | O210: Tenor | P210: Column1 | Q210: Column2 | R210: Column3 | S210: Column4 | T210: Δd (1d) | U210: Δ5d | V210: Column5 | W210: Column6 | X210: Column7
A211: 45985 | B211: Growth - EUR | C211: German ifo Business Climate | D211: 88.1 | E211: 88.6 | F211: 88.4 | G211: =IF(NOT(ISNUMBER(D211)),"",IF(NOT(ISNUMBER(E211)),"",D211-E211)) -> -0.5 | H211: =IF(NOT(ISNUMBER(D211)),"",IF(NOT(ISNUMBER(F211)),"",D211-F211)) -> -0.3 | I211: =IF(AND(K211="",L211=""),"N/A",IF(AND(ABS(N(K211))<0.0005,ABS(N(L211))<0.0005),"Stable",IF(AND(L211="",ABS(N(K211))>=0.0005),IF(N(K211)>0,"Accelerating","Slowing"),IF(AND(K211="",ABS(N(L211))>=0.0005),IF(N(L211)>0,"Accelerating","Slowing"),IF(AND(N(K211)>0,N(L211)>=0),"Accelerating",IF(AND(N(K211)<0,N(L211)<=0),"Slowing","Mixed")))))) -> Slowing | J211: =IF(OR(ISNUMBER(SEARCH("Unemployment",C211)),ISNUMBER(SEARCH("Claims",C211)),ISNUMBER(SEARCH("Jobless",C211)),ISNUMBER(SEARCH("Inventories",C211)),ISNUMBER(SEARCH("Wholesale Inventories",C211)),ISNUMBER(SEARCH("JOLTS Job Openings",C211)),ISNUMBER(SEARCH("Inflation Expectations",C211))),-1,1) -> 1 | K211: =IF(OR(G211="",G211="(NA)"),"",J211*G211) -> -0.5 | L211: =IF(OR(H211="",H211="(NA)"),"",J211*H211) -> -0.3 | N211: 46006 | O211: US 2y | P211: 3.497 | Q211: 3.519 | R211: 3.61 | S211: 3.612 | T211: =IF(OR(P211="",Q211=""),"",P211-Q211) -> -0.022 | U211: =IF(OR(P211="",R211=""),"",P211-R211) -> -0.113 | V211: =IF(OR(P211="",S211=""),"",P211-S211) -> -0.115 | W211: =IF(P211="","",IF(AND(U211>0.03,V211>0),"Rising",IF(AND(U211<-0.03,V211<0),"Falling","Flat"))) -> Falling | X211: =IF(W211="","",IFERROR(VLOOKUP(W211,Backend!$D$324:$E$337,2,FALSE)*1,0)) -> -1 | Z211: =(3.75+4.99)/2 -> 4.37 | AA211: Fed_CurrentRate
A212: 45986 | B212: Growth - US | C212: ADP Weekly Employment Change | D212: -13000 | E212: -2500 | G212: =IF(NOT(ISNUMBER(D212)),"",IF(NOT(ISNUMBER(E212)),"",D212-E212)) -> -10500 | H212: =IF(NOT(ISNUMBER(D212)),"",IF(NOT(ISNUMBER(F212)),"",D212-F212)) | I212: =IF(AND(K212="",L212=""),"N/A",IF(AND(ABS(N(K212))<0.0005,ABS(N(L212))<0.0005),"Stable",IF(AND(L212="",ABS(N(K212))>=0.0005),IF(N(K212)>0,"Accelerating","Slowing"),IF(AND(K212="",ABS(N(L212))>=0.0005),IF(N(L212)>0,"Accelerating","Slowing"),IF(AND(N(K212)>0,N(L212)>=0),"Accelerating",IF(AND(N(K212)<0,N(L212)<=0),"Slowing","Mixed")))))) -> Slowing | J212: =IF(OR(ISNUMBER(SEARCH("Unemployment",C212)),ISNUMBER(SEARCH("Claims",C212)),ISNUMBER(SEARCH("Jobless",C212)),ISNUMBER(SEARCH("Inventories",C212)),ISNUMBER(SEARCH("Wholesale Inventories",C212)),ISNUMBER(SEARCH("JOLTS Job Openings",C212)),ISNUMBER(SEARCH("Inflation Expectations",C212))),-1,1) -> 1 | K212: =IF(OR(G212="",G212="(NA)"),"",J212*G212) -> -10500 | L212: =IF(OR(H212="",H212="(NA)"),"",J212*H212) | N212: 46006 | O212: US 5y | P212: 3.719 | Q212: 3.741 | R212: 3.783 | S212: 3.704 | T212: =IF(OR(P212="",Q212=""),"",P212-Q212) -> -0.022 | U212: =IF(OR(P212="",R212=""),"",P212-R212) -> -0.064 | V212: =IF(OR(P212="",S212=""),"",P212-S212) -> 0.015 | W212: =IF(P212="","",IF(AND(U212>0.03,V212>0),"Rising",IF(AND(U212<-0.03,V212<0),"Falling","Flat"))) -> Flat | X212: =IF(W212="","",IFERROR(VLOOKUP(W212,Backend!$D$324:$E$337,2,FALSE)*1,0)) -> 0 | Z212: 2 | AA212: ECB_CurrentRate
A213: 45986 | B213: Growth - US | C213: Core Retail Sales m/m | D213: 0.003 | E213: 0.003 | F213: 0.006 | G213: =IF(NOT(ISNUMBER(D213)),"",IF(NOT(ISNUMBER(E213)),"",D213-E213)) -> 0 | H213: =IF(NOT(ISNUMBER(D213)),"",IF(NOT(ISNUMBER(F213)),"",D213-F213)) -> -0.003 | I213: =IF(AND(K213="",L213=""),"N/A",IF(AND(ABS(N(K213))<0.0005,ABS(N(L213))<0.0005),"Stable",IF(AND(L213="",ABS(N(K213))>=0.0005),IF(N(K213)>0,"Accelerating","Slowing"),IF(AND(K213="",ABS(N(L213))>=0.0005),IF(N(L213)>0,"Accelerating","Slowing"),IF(AND(N(K213)>0,N(L213)>=0),"Accelerating",IF(AND(N(K213)<0,N(L213)<=0),"Slowing","Mixed")))))) -> Mixed | J213: =IF(OR(ISNUMBER(SEARCH("Unemployment",C213)),ISNUMBER(SEARCH("Claims",C213)),ISNUMBER(SEARCH("Jobless",C213)),ISNUMBER(SEARCH("Inventories",C213)),ISNUMBER(SEARCH("Wholesale Inventories",C213)),ISNUMBER(SEARCH("JOLTS Job Openings",C213)),ISNUMBER(SEARCH("Inflation Expectations",C213))),-1,1) -> 1 | K213: =IF(OR(G213="",G213="(NA)"),"",J213*G213) -> 0 | L213: =IF(OR(H213="",H213="(NA)"),"",J213*H213) -> -0.003 | N213: 46006 | O213: US 10y | P213: 4.168 | Q213: 4.183 | R213: 4.188 | S213: 4.116 | T213: =IF(OR(P213="",Q213=""),"",P213-Q213) -> -0.015 | U213: =IF(OR(P213="",R213=""),"",P213-R213) -> -0.02 | V213: =IF(OR(P213="",S213=""),"",P213-S213) -> 0.052 | W213: =IF(P213="","",IF(AND(U213>0.03,V213>0),"Rising",IF(AND(U213<-0.03,V213<0),"Falling","Flat"))) -> Flat | X213: =IF(W213="","",IFERROR(VLOOKUP(W213,Backend!$D$324:$E$337,2,FALSE)*1,0)) -> 0 | Z213: 0 | AA213: JPY_CurrentRate
A214: 45986 | B214: Growth - US | C214: Retail Sales m/m | D214: 0.002 | E214: 0.004 | F214: -0.001 | G214: =IF(NOT(ISNUMBER(D214)),"",IF(NOT(ISNUMBER(E214)),"",D214-E214)) -> -0.002 | H214: =IF(NOT(ISNUMBER(D214)),"",IF(NOT(ISNUMBER(F214)),"",D214-F214)) -> 0.003 | I214: =IF(AND(K214="",L214=""),"N/A",IF(AND(ABS(N(K214))<0.0005,ABS(N(L214))<0.0005),"Stable",IF(AND(L214="",ABS(N(K214))>=0.0005),IF(N(K214)>0,"Accelerating","Slowing"),IF(AND(K214="",ABS(N(L214))>=0.0005),IF(N(L214)>0,"Accelerating","Slowing"),IF(AND(N(K214)>0,N(L214)>=0),"Accelerating",IF(AND(N(K214)<0,N(L214)<=0),"Slowing","Mixed")))))) -> Mixed | J214: =IF(OR(ISNUMBER(SEARCH("Unemployment",C214)),ISNUMBER(SEARCH("Claims",C214)),ISNUMBER(SEARCH("Jobless",C214)),ISNUMBER(SEARCH("Inventories",C214)),ISNUMBER(SEARCH("Wholesale Inventories",C214)),ISNUMBER(SEARCH("JOLTS Job Openings",C214)),ISNUMBER(SEARCH("Inflation Expectations",C214))),-1,1) -> 1 | K214: =IF(OR(G214="",G214="(NA)"),"",J214*G214) -> -0.002 | L214: =IF(OR(H214="",H214="(NA)"),"",J214*H214) -> 0.003 | N214: 46006 | O214: US 30y | P214: 4.844 | Q214: 4.58 | R214: 4.808 | S214: 4.753 | T214: =IF(OR(P214="",Q214=""),"",P214-Q214) -> 0.264 | U214: =IF(OR(P214="",R214=""),"",P214-R214) -> 0.036 | V214: =IF(OR(P214="",S214=""),"",P214-S214) -> 0.091 | W214: =IF(P214="","",IF(AND(U214>0.03,V214>0),"Rising",IF(AND(U214<-0.03,V214<0),"Falling","Flat"))) -> Rising | X214: =IF(W214="","",IFERROR(VLOOKUP(W214,Backend!$D$324:$E$337,2,FALSE)*1,0)) -> 1
A215: 45986 | B215: Growth - US | C215: CB Consumer Confidence | D215: 88.7 | E215: 93.4 | F215: 95.5 | G215: =IF(NOT(ISNUMBER(D215)),"",IF(NOT(ISNUMBER(E215)),"",D215-E215)) -> -4.7 | H215: =IF(NOT(ISNUMBER(D215)),"",IF(NOT(ISNUMBER(F215)),"",D215-F215)) -> -6.8 | I215: =IF(AND(K215="",L215=""),"N/A",IF(AND(ABS(N(K215))<0.0005,ABS(N(L215))<0.0005),"Stable",IF(AND(L215="",ABS(N(K215))>=0.0005),IF(N(K215)>0,"Accelerating","Slowing"),IF(AND(K215="",ABS(N(L215))>=0.0005),IF(N(L215)>0,"Accelerating","Slowing"),IF(AND(N(K215)>0,N(L215)>=0),"Accelerating",IF(AND(N(K215)<0,N(L215)<=0),"Slowing","Mixed")))))) -> Slowing | J215: =IF(OR(ISNUMBER(SEARCH("Unemployment",C215)),ISNUMBER(SEARCH("Claims",C215)),ISNUMBER(SEARCH("Jobless",C215)),ISNUMBER(SEARCH("Inventories",C215)),ISNUMBER(SEARCH("Wholesale Inventories",C215)),ISNUMBER(SEARCH("JOLTS Job Openings",C215)),ISNUMBER(SEARCH("Inflation Expectations",C215))),-1,1) -> 1 | K215: =IF(OR(G215="",G215="(NA)"),"",J215*G215) -> -4.7 | L215: =IF(OR(H215="",H215="(NA)"),"",J215*H215) -> -6.8 | N215: Date | O215: Tenor | P215: Column1 | Q215: Column2 | R215: Column3 | S215: Column4 | T215: Δd (1d) | U215: Δ5d | V215: Column5 | W215: Column6 | X215: Column7
A216: 45986 | B216: Inflation – US | C216: Core PPI m/m | D216: 0.001 | E216: 0.002 | F216: -0.001 | G216: =IF(NOT(ISNUMBER(D216)),"",IF(NOT(ISNUMBER(E216)),"",D216-E216)) -> -0.001 | H216: =IF(NOT(ISNUMBER(D216)),"",IF(NOT(ISNUMBER(F216)),"",D216-F216)) -> 0.002 | I216: =IF(AND(K216="",L216=""),"N/A",IF(AND(ABS(N(K216))<0.0005,ABS(N(L216))<0.0005),"Stable",IF(AND(L216="",ABS(N(K216))>=0.0005),IF(N(K216)>0,"Accelerating","Slowing"),IF(AND(K216="",ABS(N(L216))>=0.0005),IF(N(L216)>0,"Accelerating","Slowing"),IF(AND(N(K216)>0,N(L216)>=0),"Accelerating",IF(AND(N(K216)<0,N(L216)<=0),"Slowing","Mixed")))))) -> Mixed | J216: =IF(OR(ISNUMBER(SEARCH("Unemployment",C216)),ISNUMBER(SEARCH("Claims",C216)),ISNUMBER(SEARCH("Jobless",C216)),ISNUMBER(SEARCH("Inventories",C216)),ISNUMBER(SEARCH("Wholesale Inventories",C216)),ISNUMBER(SEARCH("JOLTS Job Openings",C216)),ISNUMBER(SEARCH("Inflation Expectations",C216))),-1,1) -> 1 | K216: =IF(OR(G216="",G216="(NA)"),"",J216*G216) -> -0.001 | L216: =IF(OR(H216="",H216="(NA)"),"",J216*H216) -> 0.002 | N216: 46006 | O216: US 2s10s | P216: =IF(OR(P211="",P213=""),"",P213-P211) -> 0.671 | Q216: =IF(OR(Q211="",Q213=""),"",Q213-Q211) -> 0.664 | R216: =IF(OR(R211="",R213=""),"",R213-R211) -> 0.578 | S216: =IF(OR(S211="",S213=""),"",S213-S211) -> 0.504 | T216: =IF(OR(P216="",Q216=""),"",P216-Q216) -> 0.007 | U216: =IF(OR(P216="",R216=""),"",P216-R216) -> 0.093 | V216: =IF(OR(P216="",S216=""),"",P216-S216) -> 0.167 | W216: =IF(P216="","",IF(AND(U216>0.03,V216>0),"Rising",IF(AND(U216<-0.03,V216<0),"Falling","Flat"))) -> Rising | X216: =IF(W216="","",IFERROR(VLOOKUP(W216,Backend!$D$324:$E$337,2,FALSE)*1,0)) -> 1
A217: 45987 | B217: Growth - US | C217: Core Durable Goods Orders m/m | D217: 0.006 | E217: 0.002 | F217: 0.003 | G217: =IF(NOT(ISNUMBER(D217)),"",IF(NOT(ISNUMBER(E217)),"",D217-E217)) -> 0.004 | H217: =IF(NOT(ISNUMBER(D217)),"",IF(NOT(ISNUMBER(F217)),"",D217-F217)) -> 0.003 | I217: =IF(AND(K217="",L217=""),"N/A",IF(AND(ABS(N(K217))<0.0005,ABS(N(L217))<0.0005),"Stable",IF(AND(L217="",ABS(N(K217))>=0.0005),IF(N(K217)>0,"Accelerating","Slowing"),IF(AND(K217="",ABS(N(L217))>=0.0005),IF(N(L217)>0,"Accelerating","Slowing"),IF(AND(N(K217)>0,N(L217)>=0),"Accelerating",IF(AND(N(K217)<0,N(L217)<=0),"Slowing","Mixed")))))) -> Accelerating | J217: =IF(OR(ISNUMBER(SEARCH("Unemployment",C217)),ISNUMBER(SEARCH("Claims",C217)),ISNUMBER(SEARCH("Jobless",C217)),ISNUMBER(SEARCH("Inventories",C217)),ISNUMBER(SEARCH("Wholesale Inventories",C217)),ISNUMBER(SEARCH("JOLTS Job Openings",C217)),ISNUMBER(SEARCH("Inflation Expectations",C217))),-1,1) -> 1 | K217: =IF(OR(G217="",G217="(NA)"),"",J217*G217) -> 0.004 | L217: =IF(OR(H217="",H217="(NA)"),"",J217*H217) -> 0.003 | N217: 46006 | O217: US 5s30s | P217: =IF(OR(P212="",P214=""),"",P214-P212) -> 1.125 | Q217: =IF(OR(Q212="",Q214=""),"",Q214-Q212) -> 0.839 | R217: =IF(OR(R212="",R214=""),"",R214-R212) -> 1.025 | S217: =IF(OR(S212="",S214=""),"",S214-S212) -> 1.049 | T217: =IF(OR(P217="",Q217=""),"",P217-Q217) -> 0.286 | U217: =IF(OR(P217="",R217=""),"",P217-R217) -> 0.1 | V217: =IF(OR(P217="",S217=""),"",P217-S217) -> 0.076 | W217: =IF(P217="","",IF(AND(U217>0.03,V217>0),"Rising",IF(AND(U217<-0.03,V217<0),"Falling","Flat"))) -> Rising | X217: =IF(W217="","",IFERROR(VLOOKUP(W217,Backend!$D$324:$E$337,2,FALSE)*1,0)) -> 1
A218: 45987 | B218: Growth - US | C218: Durable Goods Orders m/m | D218: 0.005 | E218: 0.005 | F218: 0.03 | G218: =IF(NOT(ISNUMBER(D218)),"",IF(NOT(ISNUMBER(E218)),"",D218-E218)) -> 0 | H218: =IF(NOT(ISNUMBER(D218)),"",IF(NOT(ISNUMBER(F218)),"",D218-F218)) -> -0.025 | I218: =IF(AND(K218="",L218=""),"N/A",IF(AND(ABS(N(K218))<0.0005,ABS(N(L218))<0.0005),"Stable",IF(AND(L218="",ABS(N(K218))>=0.0005),IF(N(K218)>0,"Accelerating","Slowing"),IF(AND(K218="",ABS(N(L218))>=0.0005),IF(N(L218)>0,"Accelerating","Slowing"),IF(AND(N(K218)>0,N(L218)>=0),"Accelerating",IF(AND(N(K218)<0,N(L218)<=0),"Slowing","Mixed")))))) -> Mixed | J218: =IF(OR(ISNUMBER(SEARCH("Unemployment",C218)),ISNUMBER(SEARCH("Claims",C218)),ISNUMBER(SEARCH("Jobless",C218)),ISNUMBER(SEARCH("Inventories",C218)),ISNUMBER(SEARCH("Wholesale Inventories",C218)),ISNUMBER(SEARCH("JOLTS Job Openings",C218)),ISNUMBER(SEARCH("Inflation Expectations",C218))),-1,1) -> 1 | K218: =IF(OR(G218="",G218="(NA)"),"",J218*G218) -> 0 | L218: =IF(OR(H218="",H218="(NA)"),"",J218*H218) -> -0.025
A219: 45987 | B219: Labour – US | C219: Unemployment Claims | D219: 216000 | E219: 226000 | F219: 222000 | G219: =IF(NOT(ISNUMBER(D219)),"",IF(NOT(ISNUMBER(E219)),"",D219-E219)) -> -10000 | H219: =IF(NOT(ISNUMBER(D219)),"",IF(NOT(ISNUMBER(F219)),"",D219-F219)) -> -6000 | I219: =IF(AND(K219="",L219=""),"N/A",IF(AND(ABS(N(K219))<0.0005,ABS(N(L219))<0.0005),"Stable",IF(AND(L219="",ABS(N(K219))>=0.0005),IF(N(K219)>0,"Accelerating","Slowing"),IF(AND(K219="",ABS(N(L219))>=0.0005),IF(N(L219)>0,"Accelerating","Slowing"),IF(AND(N(K219)>0,N(L219)>=0),"Accelerating",IF(AND(N(K219)<0,N(L219)<=0),"Slowing","Mixed")))))) -> Accelerating | J219: =IF(OR(ISNUMBER(SEARCH("Unemployment",C219)),ISNUMBER(SEARCH("Claims",C219)),ISNUMBER(SEARCH("Jobless",C219)),ISNUMBER(SEARCH("Inventories",C219)),ISNUMBER(SEARCH("Wholesale Inventories",C219)),ISNUMBER(SEARCH("JOLTS Job Openings",C219)),ISNUMBER(SEARCH("Inflation Expectations",C219))),-1,1) -> -1 | K219: =IF(OR(G219="",G219="(NA)"),"",J219*G219) -> 10000 | L219: =IF(OR(H219="",H219="(NA)"),"",J219*H219) -> 6000 | N219: Date | O219: Tenor | P219: Column1 | Q219: Column2 | R219: Column3 | S219: Column4 | T219: Δd (1d) | U219: Δ5d | V219: Column5 | W219: Column6 | X219: Column7
A220: 45988 | B220: Growth - EUR | C220: German GfK Consumer Climate | D220: -23.2 | E220: -23.6 | F220: -24.1 | G220: =IF(NOT(ISNUMBER(D220)),"",IF(NOT(ISNUMBER(E220)),"",D220-E220)) -> 0.4 | H220: =IF(NOT(ISNUMBER(D220)),"",IF(NOT(ISNUMBER(F220)),"",D220-F220)) -> 0.9 | I220: =IF(AND(K220="",L220=""),"N/A",IF(AND(ABS(N(K220))<0.0005,ABS(N(L220))<0.0005),"Stable",IF(AND(L220="",ABS(N(K220))>=0.0005),IF(N(K220)>0,"Accelerating","Slowing"),IF(AND(K220="",ABS(N(L220))>=0.0005),IF(N(L220)>0,"Accelerating","Slowing"),IF(AND(N(K220)>0,N(L220)>=0),"Accelerating",IF(AND(N(K220)<0,N(L220)<=0),"Slowing","Mixed")))))) -> Accelerating | J220: =IF(OR(ISNUMBER(SEARCH("Unemployment",C220)),ISNUMBER(SEARCH("Claims",C220)),ISNUMBER(SEARCH("Jobless",C220)),ISNUMBER(SEARCH("Inventories",C220)),ISNUMBER(SEARCH("Wholesale Inventories",C220)),ISNUMBER(SEARCH("JOLTS Job Openings",C220)),ISNUMBER(SEARCH("Inflation Expectations",C220))),-1,1) -> 1 | K220: =IF(OR(G220="",G220="(NA)"),"",J220*G220) -> 0.4 | L220: =IF(OR(H220="",H220="(NA)"),"",J220*H220) -> 0.9 | N220: 46006 | O220: DE 2y | T220: =IF(OR(P220="",Q220=""),"",P220-Q220) | U220: =IF(OR(P220="",R220=""),"",P220-R220) | V220: =IF(OR(P220="",S220=""),"",P220-S220) | W220: =IF(P220="","",IF(AND(U220>0.03,V220>0),"Rising",IF(AND(U220<-0.03,V220<0),"Falling","Flat")))
A221: 45989 | B221: Inflation – EUR | C221: German Prelim CPI m/m | D221: 0.002 | E221: 0 | F221: 0.003 | G221: =IF(NOT(ISNUMBER(D221)),"",IF(NOT(ISNUMBER(E221)),"",D221-E221)) -> 0.002 | H221: =IF(NOT(ISNUMBER(D221)),"",IF(NOT(ISNUMBER(F221)),"",D221-F221)) -> -0.001 | I221: =IF(AND(K221="",L221=""),"N/A",IF(AND(ABS(N(K221))<0.0005,ABS(N(L221))<0.0005),"Stable",IF(AND(L221="",ABS(N(K221))>=0.0005),IF(N(K221)>0,"Accelerating","Slowing"),IF(AND(K221="",ABS(N(L221))>=0.0005),IF(N(L221)>0,"Accelerating","Slowing"),IF(AND(N(K221)>0,N(L221)>=0),"Accelerating",IF(AND(N(K221)<0,N(L221)<=0),"Slowing","Mixed")))))) -> Mixed | J221: =IF(OR(ISNUMBER(SEARCH("Unemployment",C221)),ISNUMBER(SEARCH("Claims",C221)),ISNUMBER(SEARCH("Jobless",C221)),ISNUMBER(SEARCH("Inventories",C221)),ISNUMBER(SEARCH("Wholesale Inventories",C221)),ISNUMBER(SEARCH("JOLTS Job Openings",C221)),ISNUMBER(SEARCH("Inflation Expectations",C221))),-1,1) -> 1 | K221: =IF(OR(G221="",G221="(NA)"),"",J221*G221) -> 0.002 | L221: =IF(OR(H221="",H221="(NA)"),"",J221*H221) -> -0.001 | N221: 46006 | O221: DE 5y | T221: =IF(OR(P221="",Q221=""),"",P221-Q221) | U221: =IF(OR(P221="",R221=""),"",P221-R221) | V221: =IF(OR(P221="",S221=""),"",P221-S221) | W221: =IF(P221="","",IF(AND(U221>0.03,V221>0),"Rising",IF(AND(U221<-0.03,V221<0),"Falling","Flat")))
A222: 45989 | B222: Labour – EUR | C222: German Unemployment Change | D222: 1000 | E222: 4000 | F222: -2000 | G222: =IF(NOT(ISNUMBER(D222)),"",IF(NOT(ISNUMBER(E222)),"",D222-E222)) -> -3000 | H222: =IF(NOT(ISNUMBER(D222)),"",IF(NOT(ISNUMBER(F222)),"",D222-F222)) -> 3000 | I222: =IF(AND(K222="",L222=""),"N/A",IF(AND(ABS(N(K222))<0.0005,ABS(N(L222))<0.0005),"Stable",IF(AND(L222="",ABS(N(K222))>=0.0005),IF(N(K222)>0,"Accelerating","Slowing"),IF(AND(K222="",ABS(N(L222))>=0.0005),IF(N(L222)>0,"Accelerating","Slowing"),IF(AND(N(K222)>0,N(L222)>=0),"Accelerating",IF(AND(N(K222)<0,N(L222)<=0),"Slowing","Mixed")))))) -> Mixed | J222: =IF(OR(ISNUMBER(SEARCH("Unemployment",C222)),ISNUMBER(SEARCH("Claims",C222)),ISNUMBER(SEARCH("Jobless",C222)),ISNUMBER(SEARCH("Inventories",C222)),ISNUMBER(SEARCH("Wholesale Inventories",C222)),ISNUMBER(SEARCH("JOLTS Job Openings",C222)),ISNUMBER(SEARCH("Inflation Expectations",C222))),-1,1) -> -1 | K222: =IF(OR(G222="",G222="(NA)"),"",J222*G222) -> 3000 | L222: =IF(OR(H222="",H222="(NA)"),"",J222*H222) -> -3000 | N222: 46006 | O222: DE 10y | T222: =IF(OR(P222="",Q222=""),"",P222-Q222) | U222: =IF(OR(P222="",R222=""),"",P222-R222) | V222: =IF(OR(P222="",S222=""),"",P222-S222) | W222: =IF(P222="","",IF(AND(U222>0.03,V222>0),"Rising",IF(AND(U222<-0.03,V222<0),"Falling","Flat")))
A223: 45992 | B223: Growth - US | C223: Final Manufacturing PMI | D223: 52.2 | E223: 51.9 | F223: 51.9 | G223: =IF(NOT(ISNUMBER(D223)),"",IF(NOT(ISNUMBER(E223)),"",D223-E223)) -> 0.3 | H223: =IF(NOT(ISNUMBER(D223)),"",IF(NOT(ISNUMBER(F223)),"",D223-F223)) -> 0.3 | I223: =IF(AND(K223="",L223=""),"N/A",IF(AND(ABS(N(K223))<0.0005,ABS(N(L223))<0.0005),"Stable",IF(AND(L223="",ABS(N(K223))>=0.0005),IF(N(K223)>0,"Accelerating","Slowing"),IF(AND(K223="",ABS(N(L223))>=0.0005),IF(N(L223)>0,"Accelerating","Slowing"),IF(AND(N(K223)>0,N(L223)>=0),"Accelerating",IF(AND(N(K223)<0,N(L223)<=0),"Slowing","Mixed")))))) -> Accelerating | J223: =IF(OR(ISNUMBER(SEARCH("Unemployment",C223)),ISNUMBER(SEARCH("Claims",C223)),ISNUMBER(SEARCH("Jobless",C223)),ISNUMBER(SEARCH("Inventories",C223)),ISNUMBER(SEARCH("Wholesale Inventories",C223)),ISNUMBER(SEARCH("JOLTS Job Openings",C223)),ISNUMBER(SEARCH("Inflation Expectations",C223))),-1,1) -> 1 | K223: =IF(OR(G223="",G223="(NA)"),"",J223*G223) -> 0.3 | L223: =IF(OR(H223="",H223="(NA)"),"",J223*H223) -> 0.3 | N223: 46006 | O223: DE 30y | T223: =IF(OR(P223="",Q223=""),"",P223-Q223) | U223: =IF(OR(P223="",R223=""),"",P223-R223) | V223: =IF(OR(P223="",S223=""),"",P223-S223) | W223: =IF(P223="","",IF(AND(U223>0.03,V223>0),"Rising",IF(AND(U223<-0.03,V223<0),"Falling","Flat")))
A224: 45992 | B224: Growth - US | C224: ISM Manufacturing Prices | D224: 58.5 | E224: 59.5 | F224: 58 | G224: =IF(NOT(ISNUMBER(D224)),"",IF(NOT(ISNUMBER(E224)),"",D224-E224)) -> -1 | H224: =IF(NOT(ISNUMBER(D224)),"",IF(NOT(ISNUMBER(F224)),"",D224-F224)) -> 0.5 | I224: =IF(AND(K224="",L224=""),"N/A",IF(AND(ABS(N(K224))<0.0005,ABS(N(L224))<0.0005),"Stable",IF(AND(L224="",ABS(N(K224))>=0.0005),IF(N(K224)>0,"Accelerating","Slowing"),IF(AND(K224="",ABS(N(L224))>=0.0005),IF(N(L224)>0,"Accelerating","Slowing"),IF(AND(N(K224)>0,N(L224)>=0),"Accelerating",IF(AND(N(K224)<0,N(L224)<=0),"Slowing","Mixed")))))) -> Mixed | J224: =IF(OR(ISNUMBER(SEARCH("Unemployment",C224)),ISNUMBER(SEARCH("Claims",C224)),ISNUMBER(SEARCH("Jobless",C224)),ISNUMBER(SEARCH("Inventories",C224)),ISNUMBER(SEARCH("Wholesale Inventories",C224)),ISNUMBER(SEARCH("JOLTS Job Openings",C224)),ISNUMBER(SEARCH("Inflation Expectations",C224))),-1,1) -> 1 | K224: =IF(OR(G224="",G224="(NA)"),"",J224*G224) -> -1 | L224: =IF(OR(H224="",H224="(NA)"),"",J224*H224) -> 0.5 | N224: Date | O224: Tenor | T224: Δd (1d) | U224: Δ5d
A225: 45992 | B225: Growth - US | C225: ISM Manufacturing PMI | D225: 48.2 | E225: 49 | F225: 48.7 | G225: =IF(NOT(ISNUMBER(D225)),"",IF(NOT(ISNUMBER(E225)),"",D225-E225)) -> -0.8 | H225: =IF(NOT(ISNUMBER(D225)),"",IF(NOT(ISNUMBER(F225)),"",D225-F225)) -> -0.5 | I225: =IF(AND(K225="",L225=""),"N/A",IF(AND(ABS(N(K225))<0.0005,ABS(N(L225))<0.0005),"Stable",IF(AND(L225="",ABS(N(K225))>=0.0005),IF(N(K225)>0,"Accelerating","Slowing"),IF(AND(K225="",ABS(N(L225))>=0.0005),IF(N(L225)>0,"Accelerating","Slowing"),IF(AND(N(K225)>0,N(L225)>=0),"Accelerating",IF(AND(N(K225)<0,N(L225)<=0),"Slowing","Mixed")))))) -> Slowing | J225: =IF(OR(ISNUMBER(SEARCH("Unemployment",C225)),ISNUMBER(SEARCH("Claims",C225)),ISNUMBER(SEARCH("Jobless",C225)),ISNUMBER(SEARCH("Inventories",C225)),ISNUMBER(SEARCH("Wholesale Inventories",C225)),ISNUMBER(SEARCH("JOLTS Job Openings",C225)),ISNUMBER(SEARCH("Inflation Expectations",C225))),-1,1) -> 1 | K225: =IF(OR(G225="",G225="(NA)"),"",J225*G225) -> -0.8 | L225: =IF(OR(H225="",H225="(NA)"),"",J225*H225) -> -0.5 | N225: 46006 | O225: DE 2s10s | P225: =IF(OR(P220="",P222=""),"",(P222-P220)*100) | Q225: =IF(OR(Q220="",Q222=""),"",(Q222-Q220)*100) | R225: =IF(OR(R220="",R222=""),"",(R222-R220)*100) | S225: =IF(OR(S220="",S222=""),"",(S222-S220)*100) | T225: =IF(OR(P225="",Q225=""),"",P225-Q225) | U225: =IF(OR(P225="",R225=""),"",P225-R225) | V225: =IF(OR(P225="",S225=""),"",P225-S225) | W225: =IF(P225="","",IF(AND(U225>3,V225>0),"Rising",IF(AND(U225<-3,V225<0),"Falling","Flat")))
A226: 45992 | B226: Growth - US | C226: Final Manufacturing PMI | D226: 52.2 | E226: 51.9 | F226: 51.9 | G226: =IF(NOT(ISNUMBER(D226)),"",IF(NOT(ISNUMBER(E226)),"",D226-E226)) -> 0.3 | H226: =IF(NOT(ISNUMBER(D226)),"",IF(NOT(ISNUMBER(F226)),"",D226-F226)) -> 0.3 | I226: =IF(AND(K226="",L226=""),"N/A",IF(AND(ABS(N(K226))<0.0005,ABS(N(L226))<0.0005),"Stable",IF(AND(L226="",ABS(N(K226))>=0.0005),IF(N(K226)>0,"Accelerating","Slowing"),IF(AND(K226="",ABS(N(L226))>=0.0005),IF(N(L226)>0,"Accelerating","Slowing"),IF(AND(N(K226)>0,N(L226)>=0),"Accelerating",IF(AND(N(K226)<0,N(L226)<=0),"Slowing","Mixed")))))) -> Accelerating | J226: =IF(OR(ISNUMBER(SEARCH("Unemployment",C226)),ISNUMBER(SEARCH("Claims",C226)),ISNUMBER(SEARCH("Jobless",C226)),ISNUMBER(SEARCH("Inventories",C226)),ISNUMBER(SEARCH("Wholesale Inventories",C226)),ISNUMBER(SEARCH("JOLTS Job Openings",C226)),ISNUMBER(SEARCH("Inflation Expectations",C226))),-1,1) -> 1 | K226: =IF(OR(G226="",G226="(NA)"),"",J226*G226) -> 0.3 | L226: =IF(OR(H226="",H226="(NA)"),"",J226*H226) -> 0.3 | N226: 46006 | O226: DE 5s30s | P226: =IF(OR(P221="",P223=""),"",(P223-P221)*100) | Q226: =IF(OR(Q221="",Q223=""),"",(Q223-Q221)*100) | R226: =IF(OR(R221="",R223=""),"",(R223-R221)*100) | S226: =IF(OR(S221="",S223=""),"",(S223-S221)*100) | T226: =IF(OR(P226="",Q226=""),"",P226-Q226) | U226: =IF(OR(P226="",R226=""),"",P226-R226) | V226: =IF(OR(P226="",S226=""),"",P226-S226) | W226: =IF(P226="","",IF(AND(U226>3,V226>0),"Rising",IF(AND(U226<-3,V226<0),"Falling","Flat")))
A227: 45992 | B227: Growth - US | C227: ISM Manufacturing Prices | D227: 58.5 | E227: 59.5 | F227: 58 | G227: =IF(NOT(ISNUMBER(D227)),"",IF(NOT(ISNUMBER(E227)),"",D227-E227)) -> -1 | H227: =IF(NOT(ISNUMBER(D227)),"",IF(NOT(ISNUMBER(F227)),"",D227-F227)) -> 0.5 | I227: =IF(AND(K227="",L227=""),"N/A",IF(AND(ABS(N(K227))<0.0005,ABS(N(L227))<0.0005),"Stable",IF(AND(L227="",ABS(N(K227))>=0.0005),IF(N(K227)>0,"Accelerating","Slowing"),IF(AND(K227="",ABS(N(L227))>=0.0005),IF(N(L227)>0,"Accelerating","Slowing"),IF(AND(N(K227)>0,N(L227)>=0),"Accelerating",IF(AND(N(K227)<0,N(L227)<=0),"Slowing","Mixed")))))) -> Mixed | J227: =IF(OR(ISNUMBER(SEARCH("Unemployment",C227)),ISNUMBER(SEARCH("Claims",C227)),ISNUMBER(SEARCH("Jobless",C227)),ISNUMBER(SEARCH("Inventories",C227)),ISNUMBER(SEARCH("Wholesale Inventories",C227)),ISNUMBER(SEARCH("JOLTS Job Openings",C227)),ISNUMBER(SEARCH("Inflation Expectations",C227))),-1,1) -> 1 | K227: =IF(OR(G227="",G227="(NA)"),"",J227*G227) -> -1 | L227: =IF(OR(H227="",H227="(NA)"),"",J227*H227) -> 0.5
A228: 45992 | B228: Growth - US | C228: ISM Manufacturing PMI | D228: 48.2 | E228: 49 | F228: 48.7 | G228: =IF(NOT(ISNUMBER(D228)),"",IF(NOT(ISNUMBER(E228)),"",D228-E228)) -> -0.8 | H228: =IF(NOT(ISNUMBER(D228)),"",IF(NOT(ISNUMBER(F228)),"",D228-F228)) -> -0.5 | I228: =IF(AND(K228="",L228=""),"N/A",IF(AND(ABS(N(K228))<0.0005,ABS(N(L228))<0.0005),"Stable",IF(AND(L228="",ABS(N(K228))>=0.0005),IF(N(K228)>0,"Accelerating","Slowing"),IF(AND(K228="",ABS(N(L228))>=0.0005),IF(N(L228)>0,"Accelerating","Slowing"),IF(AND(N(K228)>0,N(L228)>=0),"Accelerating",IF(AND(N(K228)<0,N(L228)<=0),"Slowing","Mixed")))))) -> Slowing | J228: =IF(OR(ISNUMBER(SEARCH("Unemployment",C228)),ISNUMBER(SEARCH("Claims",C228)),ISNUMBER(SEARCH("Jobless",C228)),ISNUMBER(SEARCH("Inventories",C228)),ISNUMBER(SEARCH("Wholesale Inventories",C228)),ISNUMBER(SEARCH("JOLTS Job Openings",C228)),ISNUMBER(SEARCH("Inflation Expectations",C228))),-1,1) -> 1 | K228: =IF(OR(G228="",G228="(NA)"),"",J228*G228) -> -0.8 | L228: =IF(OR(H228="",H228="(NA)"),"",J228*H228) -> -0.5 | N228: Date | O228: Tenor | P228: Column1 | Q228: Column2 | R228: Column3 | S228: Column4 | T228: Δd (1d) | U228: Δ5d | V228: Column5 | W228: Column6 | X228: Column7
A229: 45993 | B229: Growth - US | C229: FOMC Member Bowman Speaks | D229: (NA) | E229: (NA) | F229: (NA) | G229: =IF(NOT(ISNUMBER(D229)),"",IF(NOT(ISNUMBER(E229)),"",D229-E229)) | H229: =IF(NOT(ISNUMBER(D229)),"",IF(NOT(ISNUMBER(F229)),"",D229-F229)) | I229: =IF(AND(K229="",L229=""),"N/A",IF(AND(ABS(N(K229))<0.0005,ABS(N(L229))<0.0005),"Stable",IF(AND(L229="",ABS(N(K229))>=0.0005),IF(N(K229)>0,"Accelerating","Slowing"),IF(AND(K229="",ABS(N(L229))>=0.0005),IF(N(L229)>0,"Accelerating","Slowing"),IF(AND(N(K229)>0,N(L229)>=0),"Accelerating",IF(AND(N(K229)<0,N(L229)<=0),"Slowing","Mixed")))))) -> N/A | J229: =IF(OR(ISNUMBER(SEARCH("Unemployment",C229)),ISNUMBER(SEARCH("Claims",C229)),ISNUMBER(SEARCH("Jobless",C229)),ISNUMBER(SEARCH("Inventories",C229)),ISNUMBER(SEARCH("Wholesale Inventories",C229)),ISNUMBER(SEARCH("JOLTS Job Openings",C229)),ISNUMBER(SEARCH("Inflation Expectations",C229))),-1,1) -> 1 | K229: =IF(OR(G229="",G229="(NA)"),"",J229*G229) | L229: =IF(OR(H229="",H229="(NA)"),"",J229*H229) | N229: 46006 | O229: JP 2y | T229: =IF(OR(P229="",Q229=""),"",P229-Q229) | U229: =IF(OR(P229="",R229=""),"",P229-R229) | V229: =IF(OR(P229="",S229=""),"",P229-S229) | W229: =IF(P229="","",IF(AND(U229>0.03,V229>0),"Rising",IF(AND(U229<-0.03,V229<0),"Falling","Flat")))
A230: 45993 | B230: Growth - US | C230: Import Prices m/m | D230: 0 | E230: 0.001 | F230: 0.001 | G230: =IF(NOT(ISNUMBER(D230)),"",IF(NOT(ISNUMBER(E230)),"",D230-E230)) -> -0.001 | H230: =IF(NOT(ISNUMBER(D230)),"",IF(NOT(ISNUMBER(F230)),"",D230-F230)) -> -0.001 | I230: =IF(AND(K230="",L230=""),"N/A",IF(AND(ABS(N(K230))<0.0005,ABS(N(L230))<0.0005),"Stable",IF(AND(L230="",ABS(N(K230))>=0.0005),IF(N(K230)>0,"Accelerating","Slowing"),IF(AND(K230="",ABS(N(L230))>=0.0005),IF(N(L230)>0,"Accelerating","Slowing"),IF(AND(N(K230)>0,N(L230)>=0),"Accelerating",IF(AND(N(K230)<0,N(L230)<=0),"Slowing","Mixed")))))) -> Slowing | J230: =IF(OR(ISNUMBER(SEARCH("Unemployment",C230)),ISNUMBER(SEARCH("Claims",C230)),ISNUMBER(SEARCH("Jobless",C230)),ISNUMBER(SEARCH("Inventories",C230)),ISNUMBER(SEARCH("Wholesale Inventories",C230)),ISNUMBER(SEARCH("JOLTS Job Openings",C230)),ISNUMBER(SEARCH("Inflation Expectations",C230))),-1,1) -> 1 | K230: =IF(OR(G230="",G230="(NA)"),"",J230*G230) -> -0.001 | L230: =IF(OR(H230="",H230="(NA)"),"",J230*H230) -> -0.001 | N230: 46006 | O230: JP 5y | T230: =IF(OR(P230="",Q230=""),"",P230-Q230) | U230: =IF(OR(P230="",R230=""),"",P230-R230) | V230: =IF(OR(P230="",S230=""),"",P230-S230) | W230: =IF(P230="","",IF(AND(U230>0.03,V230>0),"Rising",IF(AND(U230<-0.03,V230<0),"Falling","Flat")))
A231: 45993 | B231: Growth - US | C231: Capacity Utilization Rate | D231: 0.759 | E231: 0.769 | F231: 0.759 | G231: =IF(NOT(ISNUMBER(D231)),"",IF(NOT(ISNUMBER(E231)),"",D231-E231)) -> -0.01 | H231: =IF(NOT(ISNUMBER(D231)),"",IF(NOT(ISNUMBER(F231)),"",D231-F231)) -> 0 | I231: =IF(AND(K231="",L231=""),"N/A",IF(AND(ABS(N(K231))<0.0005,ABS(N(L231))<0.0005),"Stable",IF(AND(L231="",ABS(N(K231))>=0.0005),IF(N(K231)>0,"Accelerating","Slowing"),IF(AND(K231="",ABS(N(L231))>=0.0005),IF(N(L231)>0,"Accelerating","Slowing"),IF(AND(N(K231)>0,N(L231)>=0),"Accelerating",IF(AND(N(K231)<0,N(L231)<=0),"Slowing","Mixed")))))) -> Slowing | J231: =IF(OR(ISNUMBER(SEARCH("Unemployment",C231)),ISNUMBER(SEARCH("Claims",C231)),ISNUMBER(SEARCH("Jobless",C231)),ISNUMBER(SEARCH("Inventories",C231)),ISNUMBER(SEARCH("Wholesale Inventories",C231)),ISNUMBER(SEARCH("JOLTS Job Openings",C231)),ISNUMBER(SEARCH("Inflation Expectations",C231))),-1,1) -> 1 | K231: =IF(OR(G231="",G231="(NA)"),"",J231*G231) -> -0.01 | L231: =IF(OR(H231="",H231="(NA)"),"",J231*H231) -> 0 | N231: 46006 | O231: JP 10y | T231: =IF(OR(P231="",Q231=""),"",P231-Q231) | U231: =IF(OR(P231="",R231=""),"",P231-R231) | V231: =IF(OR(P231="",S231=""),"",P231-S231) | W231: =IF(P231="","",IF(AND(U231>0.03,V231>0),"Rising",IF(AND(U231<-0.03,V231<0),"Falling","Flat")))
...
