Workbook
Name LT_CategoryUS: Backend!$A$26:$A$31
Name LT_MacroDir: Backend!$A$11:$A$19
Name LT_RatePolicy: Backend!$A$20:$A$22
Name LT_RiskEnv: Backend!$A$23:$A$25
Name LT_Speakers: Backend!$A$35:$A$55
Name LT_TrendBull: Backend!$A$2:$A$7
Name LT_WeekNum: Backend!$A$8:$A$10

Sheet Instructions
A1: FOREX TRADING WORKBOOK — USER GUIDE
A2: Version 1.0 | Ready for distribution
A4: SECTION 1 — COLOR GUIDE
A5: Blue cells = YOU enter data here — click and type freely
A6: Grey cells = Auto-calculated — do NOT edit
A8: SECTION 2 — THE 5 TABS (what each one does)
A9: Instructions | B9: This page. Read first.
A10: Summary | B10: Monthly performance dashboard. Fill 6 cells at start of month.
A11: Daily Log | B11: Daily trading journal. Fill 4 columns per day.
A12: Raw daily data | B12: Paste broker export here daily. Columns A–H only.
A13: Advanced Setup Planner | B13: Fill every morning before your session.
A15: SECTION 3 — SUMMARY TAB
A16: Fill these 6 blue cells at the start of each month:
A17: Monthly Profit Target ($) → How much you aim to make
A18: Planned Active Trading Days → Days you plan to trade
A19: Weeks in Cycle → Usually 4
A20: Risk % per trade → e.g. 0.07 = 7% of NAV
A21: Max Daily Loss (R multiples) → e.g. 2 = stop after losing 2R
A22: Current NAV ($) → Account balance on day 1
A24: SECTION 4 — DAILY LOG TAB
A25: Each trading day, fill ONLY these 4 columns:
A26: Column A → Today's date
A27: Column B → Week number in cycle (1, 2, 3 or 4)
... A40: Fill this every morning BEFORE your trading session.
A41: Step 1 — EMAs | B41: EMA9/21/50 on 15m, SMA200 on 15m, EMA50 on 1H/4H/1D/1W, EMA100/200 on 1D, EMA20 on 1M, Current Price
A42: Step 2 — RSI & ATR | B42: RSI(14) from 15m, 1H, 4H. ATR(14) from 15m. ADR(14).
A43: Step 3 — Price Levels | B43: PWH/PWL, PDH/PDL, EQH/EQL, LTF Leg, Session High/Low, HTF Swing High/Low.
A44: Step 4 — FVG Zones | B44: Daily FVG high/low, 1H FVG high/low. Leave blank if no clear FVG.
A45: Step 5 — Options Gamma | B45: Up to 4 strike prices with open interest (bn). Leave blank if unavailable.
A46: Step 6 — Outputs | B46: SIDE, TRADE MODE, 4 LADDERS, NARRATIVE are auto-calculated — do not edit.
A48: SECTION 7 — NEW MONTH RESET
A49: 1. Save current file as Trading_[Month][Year].xlsx (e.g. Trading_Apr2026.xlsx)
A50: 2. Open this master template
A51: 3. Update Summary → Current NAV = ending balance of last month
A52: 4. Clear Daily Log columns A, B, D, M (keep formulas in other columns)
A53: 5. Delete rows 2+ in Raw daily data
A54: 6. Clear all blue input cells in Advanced Setup Planner
A55: 7. Save — ready for new month
A57: SECTION 8 — FAQs
A58: Q: Some cells show "" (empty) — is that a bug?
A59: A: No. Cells are intentionally blank until you enter data.
A60: Q: CT Ladder shows "CT inactive"?
... A67: NAVIGATION
A68: Summary!A1 | C68: Daily Log'!A1 | E68: Raw daily data'!A1 | G68: Advanced Setup Planner'!A1

Sheet Summary
A1: Label | B1: Value
A2: Monthly Target ($) | B2: 20000
A3: Planned Active Trading Days | B3: 17
A4: Average Target per Trading Day ($) | B4: =B2/B3
A5: Weeks in Cycle | B5: 4
A6: Average Target per Week ($) | B6: =B2/B5
A7: Required R per week | B7: =B6/B17
A8: Risk % of NAV per trade | B8: 0.07
A9: Max Daily Loss (R multiples) | B9: 2
A10: Current NAV ($) | B10: 7175.38
A11: Cumulative P&L Month ($) | B11: =IFERROR(LOOKUP(2,1/('Daily Log'!$I:$I<>""),'Daily Log'!$I:$I),"")
A12: Remaining Target ($) | B12: =B2-B11
A13: Trading Days Used | B13: =COUNTIFS('Daily Log'!D:D,"Y")
A14: Trading Days Remaining | B14: =B3-B13
A15: Required P&L per Remaining Day | B15: =IF(B14>0,B12/B14,"")
A16: Target R per Day (approx) | B16: =IF(AND(B14>0,B18>0),B15/B18,"")
A17: Projected Month P&L ($) | B17: =B11+(B14*B16)
A18: Average R value ($) | B18: =IF(K22>0,B11/K22,"")
A19: Today’s expected plan P&L ($) | B19: ='Advanced Setup Planner'!EE18
A21: Week # | B21: Active Days | C21: Total Trades | D21: Total Wins | E21: Total Losses | F21: Week Net P&L | G21: Weekly Target | H21: Week Variance ($) | I21: Avg Win Rate % | J21: Avg Reward:Risk | K21: Total R | L21: Avg R per Day
A22: 1 | B22: =COUNTIFS('Daily Log'!$B:$B,$A22,'Daily Log'!$D:$D,"Y") | C22: =SUMIFS('Daily Log'!$N:$N,'Daily Log'!$B:$B,$A22) | D22: =SUMIFS('Daily Log'!$O:$O,'Daily Log'!$B:$B,$A22) | E22: =SUMIFS('Daily Log'!$P:$P,'Daily Log'!$B:$B,$A22) | F22: =SUMIFS('Daily Log'!$H:$H,'Daily Log'!$B:$B,$A22) | G22: =$B$6 | H22: =F22-G22 | I22: =IF(B22>0,AVERAGEIFS('Daily Log'!$S:$S,'Daily Log'!$B:$B,$A22,'Daily Log'!$D:$D,"Y"),"") | J22: =IF(B22>0,IFERROR(AVERAGEIFS('Daily Log'!$T:$T,'Daily Log'!$B:$B,$A22,'Daily Log'!$D:$D,"Y",'Daily Log'!$T:$T,">0"),""),"") | K22: =SUMIFS('Daily Log'!$U:$U,'Daily Log'!$B:$B,$A22,'Daily Log'!$D:$D,"Y") | L22: =IF(B22>0,K22/B22,"")
A23: 2 | B23: =COUNTIFS('Daily Log'!$B:$B,$A23,'Daily Log'!$D:$D,"Y") | C23: =SUMIFS('Daily Log'!$N:$N,'Daily Log'!$B:$B,$A23) | D23: =SUMIFS('Daily Log'!$O:$O,'Daily Log'!$B:$B,$A23) | E23: =SUMIFS('Daily Log'!$P:$P,'Daily Log'!$B:$B,$A23) | F23: =SUMIFS('Daily Log'!$H:$H,'Daily Log'!$B:$B,$A23) | G23: =$B$6 | H23: =F23-G23 | I23: =IF(B23>0,AVERAGEIFS('Daily Log'!$S:$S,'Daily Log'!$B:$B,$A23,'Daily Log'!$D:$D,"Y"),"") | J23: =IF(B23>0,AVERAGEIFS('Daily Log'!$T:$T,'Daily Log'!$B:$B,$A23,'Daily Log'!$D:$D,"Y",'Daily Log'!$T:$T,">0"),"") | K23: =SUMIFS('Daily Log'!$U:$U,'Daily Log'!$B:$B,$A23,'Daily Log'!$D:$D,"Y") | L23: =IF(B23>0,K23/B23,"")
A24: 3 | B24: =COUNTIFS('Daily Log'!$B:$B,$A24,'Daily Log'!$D:$D,"Y") | C24: =SUMIFS('Daily Log'!$N:$N,'Daily Log'!$B:$B,$A24) | D24: =SUMIFS('Daily Log'!$O:$O,'Daily Log'!$B:$B,$A24) | E24: =SUMIFS('Daily Log'!$P:$P,'Daily Log'!$B:$B,$A24) | F24: =SUMIFS('Daily Log'!$H:$H,'Daily Log'!$B:$B,$A24) | G24: =$B$6 | H24: =F24-G24 | I24: =IF(B24>0,AVERAGEIFS('Daily Log'!$S:$S,'Daily Log'!$B:$B,$A24,'Daily Log'!$D:$D,"Y"),"") | J24: =IF(B24>0,AVERAGEIFS('Daily Log'!$T:$T,'Daily Log'!$B:$B,$A24,'Daily Log'!$D:$D,"Y",'Daily Log'!$T:$T,">0"),"") | K24: =SUMIFS('Daily Log'!$U:$U,'Daily Log'!$B:$B,$A24,'Daily Log'!$D:$D,"Y") | L24: =IF(B24>0,K24/B24,"")
A25: 4 | B25: =COUNTIFS('Daily Log'!$B:$B,$A25,'Daily Log'!$D:$D,"Y") | C25: =SUMIFS('Daily Log'!$N:$N,'Daily Log'!$B:$B,$A25) | D25: =SUMIFS('Daily Log'!$O:$O,'Daily Log'!$B:$B,$A25) | E25: =SUMIFS('Daily Log'!$P:$P,'Daily Log'!$B:$B,$A25) | F25: =SUMIFS('Daily Log'!$H:$H,'Daily Log'!$B:$B,$A25) | G25: =$B$6 | H25: =F25-G25 | I25: =IF(B25>0,AVERAGEIFS('Daily Log'!$S:$S,'Daily Log'!$B:$B,$A25,'Daily Log'!$D:$D,"Y"),"") | J25: =IF(B25>0,AVERAGEIFS('Daily Log'!$T:$T,'Daily Log'!$B:$B,$A25,'Daily Log'!$D:$D,"Y",'Daily Log'!$T:$T,">0"),"") | K25: =SUMIFS('Daily Log'!$U:$U,'Daily Log'!$B:$B,$A25,'Daily Log'!$D:$D,"Y") | L25: =IF(B25>0,K25/B25,"")

Sheet Daily Log
A1: Date | B1: Week # | C1: Day of Week | D1: Active Trading Day? (Y/N) | E1: Start NAV ($) | F1: Risk per Trade R ($) | G1: Max Daily Loss Cap ($) | H1: Net P&L ($) | I1: Cumulative P&L Month ($) | J1: Week P&L ($) | K1: Weekly Target ($) | L1: Week Variance vs Target ($) | M1: Notes | N1: # Trades | O1: # Wins | P1: # Losses | Q1: Total Wins ($) | R1: Total Losses ($) | S1: Win Rate (%) | T1: Reward:Risk | U1: Daily R-multiple | V1: Losses vs Cap | W1: Intraday Net P&L (so far) | X1: % of Cap Used (Net) | Y1: Worst Intraday DD % of Cap
A2: 46033 | B2: 1 | C2: =TEXT(A2,"dddd") | D2: Y | E2: 7175.38 | F2: =IF($A2="","",$E2*Summary!$B$8) | G2: =IF($A2="","",F2*Summary!$B$9) | H2: =IF($A2="","",SUMIFS('Raw daily data'!$F:$F,'Raw daily data'!$I:$I,$A2)) | I2: =H2 | J2: =SUMIF($B$2:$B$41,B2,$H$2:$H$41) | K2: =Summary!$B$6 | L2: =J2-K2 | N2: =IF($A2="","",COUNTIFS('Raw daily data'!$I:$I,$A2)) | O2: =IF($A2="","",COUNTIFS('Raw daily data'!$I:$I,$A2,'Raw daily data'!$F:$F,">0")) | P2: =IF($A2="","",COUNTIFS('Raw daily data'!$I:$I,$A2,'Raw daily data'!$F:$F,"<0")) | Q2: =IF($A2="","",SUMIFS('Raw daily data'!$F:$F,'Raw daily data'!$I:$I,$A2,'Raw daily data'!$F:$F,">0")) | R2: =IF($A2="","",ABS(SUMIFS('Raw daily data'!$F:$F,'Raw daily data'!$I:$I,$A2,'Raw daily data'!$F:$F,"<0"))) | S2: =IF(N2>0,O2/N2,"") | T2: =IF(R2>0,Q2/ABS(R2),"") | U2: =IF(F2>0,H2/F2,"") | V2: =IF(H2<0,MIN(ABS(H2)/G2,1),0) | W2: =IF($A2="","",_xlfn.MAXIFS('Raw daily data'!$J:$J,'Raw daily data'!$I:$I,$A2)) | X2: =IF(W2>=0,0,ABS(W2)/G2) | Y2: =IF($A2="","",ABS(MIN(0,_xlfn.MINIFS('Raw daily data'!$J:$J,'Raw daily data'!$I:$I,$A2)))/G2)
A3: 46034 | B3: 1 | C3: =TEXT(A3,"dddd") | D3: Y | E3: =E2+H2 | F3: =IF($A3="","",$E3*Summary!$B$8) | G3: =IF($A3="","",F3*Summary!$B$9) | H3: =IF($A3="","",SUMIFS('Raw daily data'!$F:$F,'Raw daily data'!$I:$I,$A3)) | I3: =I2+H3 | J3: =SUMIF($B$2:$B$41,B3,$H$2:$H$41) | K3: =Summary!$B$6 | L3: =J3-K3 | N3: =IF($A3="","",COUNTIFS('Raw daily data'!$I:$I,$A3)) | O3: =IF($A3="","",COUNTIFS('Raw daily data'!$I:$I,$A3,'Raw daily data'!$F:$F,">0")) | P3: =IF($A3="","",COUNTIFS('Raw daily data'!$I:$I,$A3,'Raw daily data'!$F:$F,"<0")) | Q3: =IF($A3="","",SUMIFS('Raw daily data'!$F:$F,'Raw daily data'!$I:$I,$A3,'Raw daily data'!$F:$F,">0")) | R3: =IF($A3="","",ABS(SUMIFS('Raw daily data'!$F:$F,'Raw daily data'!$I:$I,$A3,'Raw daily data'!$F:$F,"<0"))) | S3: =IF(N3>0,O3/N3,"") | T3: =IF(R3>0,Q3/ABS(R3),"") | U3: =IF(F3>0,H3/F3,"") | V3: =IF(H3<0,MIN(ABS(H3)/G3,1),0) | W3: =IF($A3="","",_xlfn.MAXIFS('Raw daily data'!$J:$J,'Raw daily data'!$I:$I,$A3)) | X3: =IF(W3>=0,0,ABS(W3)/G3) | Y3: =IF($A3="","",ABS(MIN(0,_xlfn.MINIFS('Raw daily data'!$J:$J,'Raw daily data'!$I:$I,$A3)))/G3)
A4: 46035 | B4: 1 | C4: =TEXT(A4,"dddd") | D4: N | E4: =E3+H3 | F4: =IF($A4="","",$E4*Summary!$B$8) | G4: =IF($A4="","",F4*Summary!$B$9) | H4: =IF($A4="","",SUMIFS('Raw daily data'!$F:$F,'Raw daily data'!$I:$I,$A4)) | I4: =I3+H4 | J4: =SUMIF($B$2:$B$41,B4,$H$2:$H$41) | K4: =Summary!$B$6 | L4: =J4-K4 | N4: =IF($A4="","",COUNTIFS('Raw daily data'!$I:$I,$A4)) | O4: =IF($A4="","",COUNTIFS('Raw daily data'!$I:$I,$A4,'Raw daily data'!$F:$F,">0")) | P4: =IF($A4="","",COUNTIFS('Raw daily data'!$I:$I,$A4,'Raw daily data'!$F:$F,"<0")) | Q4: =IF($A4="","",SUMIFS('Raw daily data'!$F:$F,'Raw daily data'!$I:$I,$A4,'Raw daily data'!$F:$F,">0")) | R4: =IF($A4="","",ABS(SUMIFS('Raw daily data'!$F:$F,'Raw daily data'!$I:$I,$A4,'Raw daily data'!$F:$F,"<0"))) | S4: =IF(N4>0,O4/N4,"") | T4: =IF(R4>0,Q4/ABS(R4),"") | U4: =IF(F4>0,H4/F4,"") | V4: =IF(H4<0,MIN(ABS(H4)/G4,1),0) | W4: =IF($A4="","",_xlfn.MAXIFS('Raw daily data'!$J:$J,'Raw daily data'!$I:$I,$A4)) | X4: =IF(W4>=0,0,ABS(W4)/G4) | Y4: =IF($A4="","",ABS(MIN(0,_xlfn.MINIFS('Raw daily data'!$J:$J,'Raw daily data'!$I:$I,$A4)))/G4)
A5: 46036 | B5: 1 | C5: =TEXT(A5,"dddd") | D5: N | E5: =E4+H4 | F5: =IF($A5="","",$E5*Summary!$B$8) | G5: =IF($A5="","",F5*Summary!$B$9) | H5: =IF($A5="","",SUMIFS('Raw daily data'!$F:$F,'Raw daily data'!$I:$I,$A5)) | I5: =I4+H5 | J5: =SUMIF($B$2:$B$41,B5,$H$2:$H$41) | K5: =Summary!$B$6 | L5: =J5-K5 | N5: =IF($A5="","",COUNTIFS('Raw daily data'!$I:$I,$A5)) | O5: =IF($A5="","",COUNTIFS('Raw daily data'!$I:$I,$A5,'Raw daily data'!$F:$F,">0")) | P5: =IF($A5="","",COUNTIFS('Raw daily data'!$I:$I,$A5,'Raw daily data'!$F:$F,"<0")) | Q5: =IF($A5="","",SUMIFS('Raw daily data'!$F:$F,'Raw daily data'!$I:$I,$A5,'Raw daily data'!$F:$F,">0")) | R5: =IF($A5="","",ABS(SUMIFS('Raw daily data'!$F:$F,'Raw daily data'!$I:$I,$A5,'Raw daily data'!$F:$F,"<0"))) | S5: =IF(N5>0,O5/N5,"") | T5: =IF(R5>0,Q5/ABS(R5),"") | U5: =IF(F5>0,H5/F5,"") | V5: =IF(H5<0,MIN(ABS(H5)/G5,1),0) | W5: =IF($A5="","",_xlfn.MAXIFS('Raw daily data'!$J:$J,'Raw daily data'!$I:$I,$A5)) | X5: =IF(W5>=0,0,ABS(W5)/G5) | Y5: =IF($A5="","",ABS(MIN(0,_xlfn.MINIFS('Raw daily data'!$J:$J,'Raw daily data'!$I:$I,$A5)))/G5)
A6: 46037 | B6: 1 | C6: =TEXT(A6,"dddd") | D6: N | E6: =E5+H5 | F6: =IF($A6="","",$E6*Summary!$B$8) | G6: =IF($A6="","",F6*Summary!$B$9) | H6: =IF($A6="","",SUMIFS('Raw daily data'!$F:$F,'Raw daily data'!$I:$I,$A6)) | I6: =I5+H6 | J6: =SUMIF($B$2:$B$41,B6,$H$2:$H$41) | K6: =Summary!$B$6 | L6: =J6-K6 | N6: =IF($A6="","",COUNTIFS('Raw daily data'!$I:$I,$A6)) | O6: =IF($A6="","",COUNTIFS('Raw daily data'!$I:$I,$A6,'Raw daily data'!$F:$F,">0")) | P6: =IF($A6="","",COUNTIFS('Raw daily data'!$I:$I,$A6,'Raw daily data'!$F:$F,"<0")) | Q6: =IF($A6="","",SUMIFS('Raw daily data'!$F:$F,'Raw daily data'!$I:$I,$A6,'Raw daily data'!$F:$F,">0")) | R6: =IF($A6="","",ABS(SUMIFS('Raw daily data'!$F:$F,'Raw daily data'!$I:$I,$A6,'Raw daily data'!$F:$F,"<0"))) | S6: =IF(N6>0,O6/N6,"") | T6: =IF(R6>0,Q6/ABS(R6),"") | U6: =IF(F6>0,H6/F6,"") | V6: =IF(H6<0,MIN(ABS(H6)/G6,1),0) | W6: =IF($A6="","",_xlfn.MAXIFS('Raw daily data'!$J:$J,'Raw daily data'!$I:$I,$A6)) | X6: =IF(W6>=0,0,ABS(W6)/G6) | Y6: =IF($A6="","",ABS(MIN(0,_xlfn.MINIFS('Raw daily data'!$J:$J,'Raw daily data'!$I:$I,$A6)))/G6)
A7: 46038 | B7: 1 | C7: =TEXT(A7,"dddd") | D7: N | E7: =E6+H6 | F7: =IF($A7="","",$E7*Summary!$B$8) | G7: =IF($A7="","",F7*Summary!$B$9) | H7: =IF($A7="","",SUMIFS('Raw daily data'!$F:$F,'Raw daily data'!$I:$I,$A7)) | I7: =I6+H7 | J7: =SUMIF($B$2:$B$41,B7,$H$2:$H$41) | K7: =Summary!$B$6 | L7: =J7-K7 | N7: =IF($A7="","",COUNTIFS('Raw daily data'!$I:$I,$A7)) | O7: =IF($A7="","",COUNTIFS('Raw daily data'!$I:$I,$A7,'Raw daily data'!$F:$F,">0")) | P7: =IF($A7="","",COUNTIFS('Raw daily data'!$I:$I,$A7,'Raw daily data'!$F:$F,"<0")) | Q7: =IF($A7="","",SUMIFS('Raw daily data'!$F:$F,'Raw daily data'!$I:$I,$A7,'Raw daily data'!$F:$F,">0")) | R7: =IF($A7="","",ABS(SUMIFS('Raw daily data'!$F:$F,'Raw daily data'!$I:$I,$A7,'Raw daily data'!$F:$F,"<0"))) | S7: =IF(N7>0,O7/N7,"") | T7: =IF(R7>0,Q7/ABS(R7),"") | U7: =IF(F7>0,H7/F7,"") | V7: =IF(H7<0,MIN(ABS(H7)/G7,1),0) | W7: =IF($A7="","",_xlfn.MAXIFS('Raw daily data'!$J:$J,'Raw daily data'!$I:$I,$A7)) | X7: =IF(W7>=0,0,ABS(W7)/G7) | Y7: =IF($A7="","",ABS(MIN(0,_xlfn.MINIFS('Raw daily data'!$J:$J,'Raw daily data'!$I:$I,$A7)))/G7)
A8: 46039 | B8: 1 | C8: =TEXT(A8,"dddd") | D8: N | E8: =E7+H7 | F8: =IF($A8="","",$E8*Summary!$B$8) | G8: =IF($A8="","",F8*Summary!$B$9) | H8: =IF($A8="","",SUMIFS('Raw daily data'!$F:$F,'Raw daily data'!$I:$I,$A8)) | I8: =I7+H8 | J8: =SUMIF($B$2:$B$41,B8,$H$2:$H$41) | K8: =Summary!$B$6 | L8: =J8-K8 | N8: =IF($A8="","",COUNTIFS('Raw daily data'!$I:$I,$A8)) | O8: =IF($A8="","",COUNTIFS('Raw daily data'!$I:$I,$A8,'Raw daily data'!$F:$F,">0")) | P8: =IF($A8="","",COUNTIFS('Raw daily data'!$I:$I,$A8,'Raw daily data'!$F:$F,"<0")) | Q8: =IF($A8="","",SUMIFS('Raw daily data'!$F:$F,'Raw daily data'!$I:$I,$A8,'Raw daily data'!$F:$F,">0")) | R8: =IF($A8="","",ABS(SUMIFS('Raw daily data'!$F:$F,'Raw daily data'!$I:$I,$A8,'Raw daily data'!$F:$F,"<0"))) | S8: =IF(N8>0,O8/N8,"") | T8: =IF(R8>0,Q8/ABS(R8),"") | U8: =IF(F8>0,H8/F8,"") | V8: =IF(H8<0,MIN(ABS(H8)/G8,1),0) | W8: =IF($A8="","",_xlfn.MAXIFS('Raw daily data'!$J:$J,'Raw daily data'!$I:$I,$A8)) | X8: =IF(W8>=0,0,ABS(W8)/G8) | Y8: =IF($A8="","",ABS(MIN(0,_xlfn.MINIFS('Raw daily data'!$J:$J,'Raw daily data'!$I:$I,$A8)))/G8)
A9: 46040 | B9: 2 | C9: =TEXT(A9,"dddd") | D9: N | E9: =E8+H8 | F9: =IF($A9="","",$E9*Summary!$B$8) | G9: =IF($A9="","",F9*Summary!$B$9) | H9: =IF($A9="","",SUMIFS('Raw daily data'!$F:$F,'Raw daily data'!$I:$I,$A9)) | I9: =I8+H9 | J9: =SUMIF($B$2:$B$41,B9,$H$2:$H$41) | K9: =Summary!$B$6 | L9: =J9-K9 | N9: =IF($A9="","",COUNTIFS('Raw daily data'!$I:$I,$A9)) | O9: =IF($A9="","",COUNTIFS('Raw daily data'!$I:$I,$A9,'Raw daily data'!$F:$F,">0")) | P9: =IF($A9="","",COUNTIFS('Raw daily data'!$I:$I,$A9,'Raw daily data'!$F:$F,"<0")) | Q9: =IF($A9="","",SUMIFS('Raw daily data'!$F:$F,'Raw daily data'!$I:$I,$A9,'Raw daily data'!$F:$F,">0")) | R9: =IF($A9="","",ABS(SUMIFS('Raw daily data'!$F:$F,'Raw daily data'!$I:$I,$A9,'Raw daily data'!$F:$F,"<0"))) | S9: =IF(N9>0,O9/N9,"") | T9: =IF(R9>0,Q9/ABS(R9),"") | U9: =IF(F9>0,H9/F9,"") | V9: =IF(H9<0,MIN(ABS(H9)/G9,1),0) | W9: =IF($A9="","",_xlfn.MAXIFS('Raw daily data'!$J:$J,'Raw daily data'!$I:$I,$A9)) | X9: =IF(W9>=0,0,ABS(W9)/G9) | Y9: =IF($A9="","",ABS(MIN(0,_xlfn.MINIFS('Raw daily data'!$J:$J,'Raw daily data'!$I:$I,$A9)))/G9)
A10: 46041 | B10: 2 | C10: =TEXT(A10,"dddd") | E10: =E9+H9 | F10: =IF($A10="","",$E10*Summary!$B$8) | G10: =IF($A10="","",F10*Summary!$B$9) | H10: =IF($A10="","",SUMIFS('Raw daily data'!$F:$F,'Raw daily data'!$I:$I,$A10)) | I10: =I9+H10 | J10: =SUMIF($B$2:$B$41,B10,$H$2:$H$41) | K10: =Summary!$B$6 | L10: =J10-K10 | N10: =IF($A10="","",COUNTIFS('Raw daily data'!$I:$I,$A10)) | O10: =IF($A10="","",COUNTIFS('Raw daily data'!$I:$I,$A10,'Raw daily data'!$F:$F,">0")) | P10: =IF($A10="","",COUNTIFS('Raw daily data'!$I:$I,$A10,'Raw daily data'!$F:$F,"<0")) | Q10: =IF($A10="","",SUMIFS('Raw daily data'!$F:$F,'Raw daily data'!$I:$I,$A10,'Raw daily data'!$F:$F,">0")) | R10: =IF($A10="","",ABS(SUMIFS('Raw daily data'!$F:$F,'Raw daily data'!$I:$I,$A10,'Raw daily data'!$F:$F,"<0"))) | S10: =IF(N10>0,O10/N10,"") | T10: =IF(R10>0,Q10/ABS(R10),"") | U10: =IF(F10>0,H10/F10,"") | V10: =IF(H10<0,MIN(ABS(H10)/G10,1),0) | W10: =IF($A10="","",_xlfn.MAXIFS('Raw daily data'!$J:$J,'Raw daily data'!$I:$I,$A10)) | X10: =IF(W10>=0,0,ABS(W10)/G10) | Y10: =IF($A10="","",ABS(MIN(0,_xlfn.MINIFS('Raw daily data'!$J:$J,'Raw daily data'!$I:$I,$A10)))/G10)
A11: 46042 | B11: 2 | C11: =TEXT(A11,"dddd") | E11: =E10+H10 | F11: =IF($A11="","",$E11*Summary!$B$8) | G11: =IF($A11="","",F11*Summary!$B$9) | H11: =IF($A11="","",SUMIFS('Raw daily data'!$F:$F,'Raw daily data'!$I:$I,$A11)) | I11: =I10+H11 | J11: =SUMIF($B$2:$B$41,B11,$H$2:$H$41) | K11: =Summary!$B$6 | L11: =J11-K11 | N11: =IF($A11="","",COUNTIFS('Raw daily data'!$I:$I,$A11)) | O11: =IF($A11="","",COUNTIFS('Raw daily data'!$I:$I,$A11,'Raw daily data'!$F:$F,">0")) | P11: =IF($A11="","",COUNTIFS('Raw daily data'!$I:$I,$A11,'Raw daily data'!$F:$F,"<0")) | Q11: =IF($A11="","",SUMIFS('Raw daily data'!$F:$F,'Raw daily data'!$I:$I,$A11,'Raw daily data'!$F:$F,">0")) | R11: =IF($A11="","",ABS(SUMIFS('Raw daily data'!$F:$F,'Raw daily data'!$I:$I,$A11,'Raw daily data'!$F:$F,"<0"))) | S11: =IF(N11>0,O11/N11,"") | T11: =IF(R11>0,Q11/ABS(R11),"") | U11: =IF(F11>0,H11/F11,"") | V11: =IF(H11<0,MIN(ABS(H11)/G11,1),0) | W11: =IF($A11="","",_xlfn.MAXIFS('Raw daily data'!$J:$J,'Raw daily data'!$I:$I,$A11)) | X11: =IF(W11>=0,0,ABS(W11)/G11) | Y11: =IF($A11="","",ABS(MIN(0,_xlfn.MINIFS('Raw daily data'!$J:$J,'Raw daily data'!$I:$I,$A11)))/G11)
A12: 46043 | B12: 2 | C12: =TEXT(A12,"dddd") | E12: =E11+H11 | F12: =IF($A12="","",$E12*Summary!$B$8) | G12: =IF($A12="","",F12*Summary!$B$9) | H12: =IF($A12="","",SUMIFS('Raw daily data'!$F:$F,'Raw daily data'!$I:$I,$A12)) | I12: =I11+H12 | J12: =SUMIF($B$2:$B$41,B12,$H$2:$H$41) | K12: =Summary!$B$6 | L12: =J12-K12 | N12: =IF($A12="","",COUNTIFS('Raw daily data'!$I:$I,$A12)) | O12: =IF($A12="","",COUNTIFS('Raw daily data'!$I:$I,$A12,'Raw daily data'!$F:$F,">0")) | P12: =IF($A12="","",COUNTIFS('Raw daily data'!$I:$I,$A12,'Raw daily data'!$F:$F,"<0")) | Q12: =IF($A12="","",SUMIFS('Raw daily data'!$F:$F,'Raw daily data'!$I:$I,$A12,'Raw daily data'!$F:$F,">0")) | R12: =IF($A12="","",ABS(SUMIFS('Raw daily data'!$F:$F,'Raw daily data'!$I:$I,$A12,'Raw daily data'!$F:$F,"<0"))) | S12: =IF(N12>0,O12/N12,"") | T12: =IF(R12>0,Q12/ABS(R12),"") | U12: =IF(F12>0,H12/F12,"") | V12: =IF(H12<0,MIN(ABS(H12)/G12,1),0) | W12: =IF($A12="","",_xlfn.MAXIFS('Raw daily data'!$J:$J,'Raw daily data'!$I:$I,$A12)) | X12: =IF(W12>=0,0,ABS(W12)/G12) | Y12: =IF($A12="","",ABS(MIN(0,_xlfn.MINIFS('Raw daily data'!$J:$J,'Raw daily data'!$I:$I,$A12)))/G12)
A13: 46044 | B13: 2 | C13: =TEXT(A13,"dddd") | E13: =E12+H12 | F13: =IF($A13="","",$E13*Summary!$B$8) | G13: =IF($A13="","",F13*Summary!$B$9) | H13: =IF($A13="","",SUMIFS('Raw daily data'!$F:$F,'Raw daily data'!$I:$I,$A13)) | I13: =I12+H13 | J13: =SUMIF($B$2:$B$41,B13,$H$2:$H$41) | K13: =Summary!$B$6 | L13: =J13-K13 | N13: =IF($A13="","",COUNTIFS('Raw daily data'!$I:$I,$A13)) | O13: =IF($A13="","",COUNTIFS('Raw daily data'!$I:$I,$A13,'Raw daily data'!$F:$F,">0")) | P13: =IF($A13="","",COUNTIFS('Raw daily data'!$I:$I,$A13,'Raw daily data'!$F:$F,"<0")) | Q13: =IF($A13="","",SUMIFS('Raw daily data'!$F:$F,'Raw daily data'!$I:$I,$A13,'Raw daily data'!$F:$F,">0")) | R13: =IF($A13="","",ABS(SUMIFS('Raw daily data'!$F:$F,'Raw daily data'!$I:$I,$A13,'Raw daily data'!$F:$F,"<0"))) | S13: =IF(N13>0,O13/N13,"") | T13: =IF(R13>0,Q13/ABS(R13),"") | U13: =IF(F13>0,H13/F13,"") | V13: =IF(H13<0,MIN(ABS(H13)/G13,1),0) | W13: =IF($A13="","",_xlfn.MAXIFS('Raw daily data'!$J:$J,'Raw daily data'!$I:$I,$A13)) | X13: =IF(W13>=0,0,ABS(W13)/G13) | Y13: =IF($A13="","",ABS(MIN(0,_xlfn.MINIFS('Raw daily data'!$J:$J,'Raw daily data'!$I:$I,$A13)))/G13)
A14: 46045 | B14: 2 | C14: =TEXT(A14,"dddd") | E14: =E13+H13 | F14: =IF($A14="","",$E14*Summary!$B$8) | G14: =IF($A14="","",F14*Summary!$B$9) | H14: =IF($A14="","",SUMIFS('Raw daily data'!$F:$F,'Raw daily data'!$I:$I,$A14)) | I14: =I13+H14 | J14: =SUMIF($B$2:$B$41,B14,$H$2:$H$41) | K14: =Summary!$B$6 | L14: =J14-K14 | N14: =IF($A14="","",COUNTIFS('Raw daily data'!$I:$I,$A14)) | O14: =IF($A14="","",COUNTIFS('Raw daily data'!$I:$I,$A14,'Raw daily data'!$F:$F,">0")) | P14: =IF($A14="","",COUNTIFS('Raw daily data'!$I:$I,$A14,'Raw daily data'!$F:$F,"<0")) | Q14: =IF($A14="","",SUMIFS('Raw daily data'!$F:$F,'Raw daily data'!$I:$I,$A14,'Raw daily data'!$F:$F,">0")) | R14: =IF($A14="","",ABS(SUMIFS('Raw daily data'!$F:$F,'Raw daily data'!$I:$I,$A14,'Raw daily data'!$F:$F,"<0"))) | S14: =IF(N14>0,O14/N14,"") | T14: =IF(R14>0,Q14/ABS(R14),"") | U14: =IF(F14>0,H14/F14,"") | V14: =IF(H14<0,MIN(ABS(H14)/G14,1),0) | W14: =IF($A14="","",_xlfn.MAXIFS('Raw daily data'!$J:$J,'Raw daily data'!$I:$I,$A14)) | X14: =IF(W14>=0,0,ABS(W14)/G14) | Y14: =IF($A14="","",ABS(MIN(0,_xlfn.MINIFS('Raw daily data'!$J:$J,'Raw daily data'!$I:$I,$A14)))/G14)
A15: 46046 | B15: 2 | C15: =TEXT(A15,"dddd") | D15: N | E15: =E14+H14 | F15: =IF($A15="","",$E15*Summary!$B$8) | G15: =IF($A15="","",F15*Summary!$B$9) | H15: =IF($A15="","",SUMIFS('Raw daily data'!$F:$F,'Raw daily data'!$I:$I,$A15)) | I15: =I14+H15 | J15: =SUMIF($B$2:$B$41,B15,$H$2:$H$41) | K15: =Summary!$B$6 | L15: =J15-K15 | N15: =IF($A15="","",COUNTIFS('Raw daily data'!$I:$I,$A15)) | O15: =IF($A15="","",COUNTIFS('Raw daily data'!$I:$I,$A15,'Raw daily data'!$F:$F,">0")) | P15: =IF($A15="","",COUNTIFS('Raw daily data'!$I:$I,$A15,'Raw daily data'!$F:$F,"<0")) | Q15: =IF($A15="","",SUMIFS('Raw daily data'!$F:$F,'Raw daily data'!$I:$I,$A15,'Raw daily data'!$F:$F,">0")) | R15: =IF($A15="","",ABS(SUMIFS('Raw daily data'!$F:$F,'Raw daily data'!$I:$I,$A15,'Raw daily data'!$F:$F,"<0"))) | S15: =IF(N15>0,O15/N15,"") | T15: =IF(R15>0,Q15/ABS(R15),"") | U15: =IF(F15>0,H15/F15,"") | V15: =IF(H15<0,MIN(ABS(H15)/G15,1),0) | W15: =IF($A15="","",_xlfn.MAXIFS('Raw daily data'!$J:$J,'Raw daily data'!$I:$I,$A15)) | X15: =IF(W15>=0,0,ABS(W15)/G15) | Y15: =IF($A15="","",ABS(MIN(0,_xlfn.MINIFS('Raw daily data'!$J:$J,'Raw daily data'!$I:$I,$A15)))/G15)
A16: 46047 | B16: 3 | C16: =TEXT(A16,"dddd") | D16: N | E16: =E15+H15 | F16: =IF($A16="","",$E16*Summary!$B$8) | G16: =IF($A16="","",F16*Summary!$B$9) | H16: =IF($A16="","",SUMIFS('Raw daily data'!$F:$F,'Raw daily data'!$I:$I,$A16)) | I16: =I15+H16 | J16: =SUMIF($B$2:$B$41,B16,$H$2:$H$41) | K16: =Summary!$B$6 | L16: =J16-K16 | N16: =IF($A16="","",COUNTIFS('Raw daily data'!$I:$I,$A16)) | O16: =IF($A16="","",COUNTIFS('Raw daily data'!$I:$I,$A16,'Raw daily data'!$F:$F,">0")) | P16: =IF($A16="","",COUNTIFS('Raw daily data'!$I:$I,$A16,'Raw daily data'!$F:$F,"<0")) | Q16: =IF($A16="","",SUMIFS('Raw daily data'!$F:$F,'Raw daily data'!$I:$I,$A16,'Raw daily data'!$F:$F,">0")) | R16: =IF($A16="","",ABS(SUMIFS('Raw daily data'!$F:$F,'Raw daily data'!$I:$I,$A16,'Raw daily data'!$F:$F,"<0"))) | S16: =IF(N16>0,O16/N16,"") | T16: =IF(R16>0,Q16/ABS(R16),"") | U16: =IF(F16>0,H16/F16,"") | V16: =IF(H16<0,MIN(ABS(H16)/G16,1),0) | W16: =IF($A16="","",_xlfn.MAXIFS('Raw daily data'!$J:$J,'Raw daily data'!$I:$I,$A16)) | X16: =IF(W16>=0,0,ABS(W16)/G16) | Y16: =IF($A16="","",ABS(MIN(0,_xlfn.MINIFS('Raw daily data'!$J:$J,'Raw daily data'!$I:$I,$A16)))/G16)
A17: 46048 | B17: 3 | C17: =TEXT(A17,"dddd") | E17: =E16+H16 | F17: =IF($A17="","",$E17*Summary!$B$8) | G17: =IF($A17="","",F17*Summary!$B$9) | H17: =IF($A17="","",SUMIFS('Raw daily data'!$F:$F,'Raw daily data'!$I:$I,$A17)) | I17: =I16+H17 | J17: =SUMIF($B$2:$B$41,B17,$H$2:$H$41) | K17: =Summary!$B$6 | L17: =J17-K17 | N17: =IF($A17="","",COUNTIFS('Raw daily data'!$I:$I,$A17)) | O17: =IF($A17="","",COUNTIFS('Raw daily data'!$I:$I,$A17,'Raw daily data'!$F:$F,">0")) | P17: =IF($A17="","",COUNTIFS('Raw daily data'!$I:$I,$A17,'Raw daily data'!$F:$F,"<0")) | Q17: =IF($A17="","",SUMIFS('Raw daily data'!$F:$F,'Raw daily data'!$I:$I,$A17,'Raw daily data'!$F:$F,">0")) | R17: =IF($A17="","",ABS(SUMIFS('Raw daily data'!$F:$F,'Raw daily data'!$I:$I,$A17,'Raw daily data'!$F:$F,"<0"))) | S17: =IF(N17>0,O17/N17,"") | T17: =IF(R17>0,Q17/ABS(R17),"") | U17: =IF(F17>0,H17/F17,"") | V17: =IF(H17<0,MIN(ABS(H17)/G17,1),0) | W17: =IF($A17="","",_xlfn.MAXIFS('Raw daily data'!$J:$J,'Raw daily data'!$I:$I,$A17)) | X17: =IF(W17>=0,0,ABS(W17)/G17) | Y17: =IF($A17="","",ABS(MIN(0,_xlfn.MINIFS('Raw daily data'!$J:$J,'Raw daily data'!$I:$I,$A17)))/G17)
A18: 46049 | B18: 3 | C18: =TEXT(A18,"dddd") | E18: =E17+H17 | F18: =IF($A18="","",$E18*Summary!$B$8) | G18: =IF($A18="","",F18*Summary!$B$9) | H18: =IF($A18="","",SUMIFS('Raw daily data'!$F:$F,'Raw daily data'!$I:$I,$A18)) | I18: =I17+H18 | J18: =SUMIF($B$2:$B$41,B18,$H$2:$H$41) | K18: =Summary!$B$6 | L18: =J18-K18 | N18: =IF($A18="","",COUNTIFS('Raw daily data'!$I:$I,$A18)) | O18: =IF($A18="","",COUNTIFS('Raw daily data'!$I:$I,$A18,'Raw daily data'!$F:$F,">0")) | P18: =IF($A18="","",COUNTIFS('Raw daily data'!$I:$I,$A18,'Raw daily data'!$F:$F,"<0")) | Q18: =IF($A18="","",SUMIFS('Raw daily data'!$F:$F,'Raw daily data'!$I:$I,$A18,'Raw daily data'!$F:$F,">0")) | R18: =IF($A18="","",ABS(SUMIFS('Raw daily data'!$F:$F,'Raw daily data'!$I:$I,$A18,'Raw daily data'!$F:$F,"<0"))) | S18: =IF(N18>0,O18/N18,"") | T18: =IF(R18>0,Q18/ABS(R18),"") | U18: =IF(F18>0,H18/F18,"") | V18: =IF(H18<0,MIN(ABS(H18)/G18,1),0) | W18: =IF($A18="","",_xlfn.MAXIFS('Raw daily data'!$J:$J,'Raw daily data'!$I:$I,$A18)) | X18: =IF(W18>=0,0,ABS(W18)/G18) | Y18: =IF($A18="","",ABS(MIN(0,_xlfn.MINIFS('Raw daily data'!$J:$J,'Raw daily data'!$I:$I,$A18)))/G18)
A19: 46050 | B19: 3 | C19: =TEXT(A19,"dddd") | E19: =E18+H18 | F19: =IF($A19="","",$E19*Summary!$B$8) | G19: =IF($A19="","",F19*Summary!$B$9) | H19: =IF($A19="","",SUMIFS('Raw daily data'!$F:$F,'Raw daily data'!$I:$I,$A19)) | I19: =I18+H19 | J19: =SUMIF($B$2:$B$41,B19,$H$2:$H$41) | K19: =Summary!$B$6 | L19: =J19-K19 | N19: =IF($A19="","",COUNTIFS('Raw daily data'!$I:$I,$A19)) | O19: =IF($A19="","",COUNTIFS('Raw daily data'!$I:$I,$A19,'Raw daily data'!$F:$F,">0")) | P19: =IF($A19="","",COUNTIFS('Raw daily data'!$I:$I,$A19,'Raw daily data'!$F:$F,"<0")) | Q19: =IF($A19="","",SUMIFS('Raw daily data'!$F:$F,'Raw daily data'!$I:$I,$A19,'Raw daily data'!$F:$F,">0")) | R19: =IF($A19="","",ABS(SUMIFS('Raw daily data'!$F:$F,'Raw daily data'!$I:$I,$A19,'Raw daily data'!$F:$F,"<0"))) | S19: =IF(N19>0,O19/N19,"") | T19: =IF(R19>0,Q19/ABS(R19),"") | U19: =IF(F19>0,H19/F19,"") | V19: =IF(H19<0,MIN(ABS(H19)/G19,1),0) | W19: =IF($A19="","",_xlfn.MAXIFS('Raw daily data'!$J:$J,'Raw daily data'!$I:$I,$A19)) | X19: =IF(W19>=0,0,ABS(W19)/G19) | Y19: =IF($A19="","",ABS(MIN(0,_xlfn.MINIFS('Raw daily data'!$J:$J,'Raw daily data'!$I:$I,$A19)))/G19)
A20: 46051 | B20: 3 | C20: =TEXT(A20,"dddd") | E20: =E19+H19 | F20: =IF($A20="","",$E20*Summary!$B$8) | G20: =IF($A20="","",F20*Summary!$B$9) | H20: =IF($A20="","",SUMIFS('Raw daily data'!$F:$F,'Raw daily data'!$I:$I,$A20)) | I20: =I19+H20 | J20: =SUMIF($B$2:$B$41,B20,$H$2:$H$41) | K20: =Summary!$B$6 | L20: =J20-K20 | N20: =IF($A20="","",COUNTIFS('Raw daily data'!$I:$I,$A20)) | O20: =IF($A20="","",COUNTIFS('Raw daily data'!$I:$I,$A20,'Raw daily data'!$F:$F,">0")) | P20: =IF($A20="","",COUNTIFS('Raw daily data'!$I:$I,$A20,'Raw daily data'!$F:$F,"<0")) | Q20: =IF($A20="","",SUMIFS('Raw daily data'!$F:$F,'Raw daily data'!$I:$I,$A20,'Raw daily data'!$F:$F,">0")) | R20: =IF($A20="","",ABS(SUMIFS('Raw daily data'!$F:$F,'Raw daily data'!$I:$I,$A20,'Raw daily data'!$F:$F,"<0"))) | S20: =IF(N20>0,O20/N20,"") | T20: =IF(R20>0,Q20/ABS(R20),"") | U20: =IF(F20>0,H20/F20,"") | V20: =IF(H20<0,MIN(ABS(H20)/G20,1),0) | W20: =IF($A20="","",_xlfn.MAXIFS('Raw daily data'!$J:$J,'Raw daily data'!$I:$I,$A20)) | X20: =IF(W20>=0,0,ABS(W20)/G20) | Y20: =IF($A20="","",ABS(MIN(0,_xlfn.MINIFS('Raw daily data'!$J:$J,'Raw daily data'!$I:$I,$A20)))/G20)
A21: 46052 | B21: 3 | C21: =TEXT(A21,"dddd") | E21: =E20+H20 | F21: =IF($A21="","",$E21*Summary!$B$8) | G21: =IF($A21="","",F21*Summary!$B$9) | H21: =IF($A21="","",SUMIFS('Raw daily data'!$F:$F,'Raw daily data'!$I:$I,$A21)) | I21: =I20+H21 | J21: =SUMIF($B$2:$B$41,B21,$H$2:$H$41) | K21: =Summary!$B$6 | L21: =J21-K21 | N21: =IF($A21="","",COUNTIFS('Raw daily data'!$I:$I,$A21)) | O21: =IF($A21="","",COUNTIFS('Raw daily data'!$I:$I,$A21,'Raw daily data'!$F:$F,">0")) | P21: =IF($A21="","",COUNTIFS('Raw daily data'!$I:$I,$A21,'Raw daily data'!$F:$F,"<0")) | Q21: =IF($A21="","",SUMIFS('Raw daily data'!$F:$F,'Raw daily data'!$I:$I,$A21,'Raw daily data'!$F:$F,">0")) | R21: =IF($A21="","",ABS(SUMIFS('Raw daily data'!$F:$F,'Raw daily data'!$I:$I,$A21,'Raw daily data'!$F:$F,"<0"))) | S21: =IF(N21>0,O21/N21,"") | T21: =IF(R21>0,Q21/ABS(R21),"") | U21: =IF(F21>0,H21/F21,"") | V21: =IF(H21<0,MIN(ABS(H21)/G21,1),0) | W21: =IF($A21="","",_xlfn.MAXIFS('Raw daily data'!$J:$J,'Raw daily data'!$I:$I,$A21)) | X21: =IF(W21>=0,0,ABS(W21)/G21) | Y21: =IF($A21="","",ABS(MIN(0,_xlfn.MINIFS('Raw daily data'!$J:$J,'Raw daily data'!$I:$I,$A21)))/G21)
A22: 46053 | B22: 3 | C22: =TEXT(A22,"dddd") | D22: N | E22: =E21+H21 | F22: =IF($A22="","",$E22*Summary!$B$8) | G22: =IF($A22="","",F22*Summary!$B$9) | H22: =IF($A22="","",SUMIFS('Raw daily data'!$F:$F,'Raw daily data'!$I:$I,$A22)) | I22: =I21+H22 | J22: =SUMIF($B$2:$B$41,B22,$H$2:$H$41) | K22: =Summary!$B$6 | L22: =J22-K22 | N22: =IF($A22="","",COUNTIFS('Raw daily data'!$I:$I,$A22)) | O22: =IF($A22="","",COUNTIFS('Raw daily data'!$I:$I,$A22,'Raw daily data'!$F:$F,">0")) | P22: =IF($A22="","",COUNTIFS('Raw daily data'!$I:$I,$A22,'Raw daily data'!$F:$F,"<0")) | Q22: =IF($A22="","",SUMIFS('Raw daily data'!$F:$F,'Raw daily data'!$I:$I,$A22,'Raw daily data'!$F:$F,">0")) | R22: =IF($A22="","",ABS(SUMIFS('Raw daily data'!$F:$F,'Raw daily data'!$I:$I,$A22,'Raw daily data'!$F:$F,"<0"))) | S22: =IF(N22>0,O22/N22,"") | T22: =IF(R22>0,Q22/ABS(R22),"") | U22: =IF(F22>0,H22/F22,"") | V22: =IF(H22<0,MIN(ABS(H22)/G22,1),0) | W22: =IF($A22="","",_xlfn.MAXIFS('Raw daily data'!$J:$J,'Raw daily data'!$I:$I,$A22)) | X22: =IF(W22>=0,0,ABS(W22)/G22) | Y22: =IF($A22="","",ABS(MIN(0,_xlfn.MINIFS('Raw daily data'!$J:$J,'Raw daily data'!$I:$I,$A22)))/G22)
A23: 46054 | B23: 4 | C23: =TEXT(A23,"dddd") | D23: N | E23: =E22+H22 | F23: =IF($A23="","",$E23*Summary!$B$8) | G23: =IF($A23="","",F23*Summary!$B$9) | H23: =IF($A23="","",SUMIFS('Raw daily data'!$F:$F,'Raw daily data'!$I:$I,$A23)) | I23: =I22+H23 | J23: =SUMIF($B$2:$B$41,B23,$H$2:$H$41) | K23: =Summary!$B$6 | L23: =J23-K23 | N23: =IF($A23="","",COUNTIFS('Raw daily data'!$I:$I,$A23)) | O23: =IF($A23="","",COUNTIFS('Raw daily data'!$I:$I,$A23,'Raw daily data'!$F:$F,">0")) | P23: =IF($A23="","",COUNTIFS('Raw daily data'!$I:$I,$A23,'Raw daily data'!$F:$F,"<0")) | Q23: =IF($A23="","",SUMIFS('Raw daily data'!$F:$F,'Raw daily data'!$I:$I,$A23,'Raw daily data'!$F:$F,">0")) | R23: =IF($A23="","",ABS(SUMIFS('Raw daily data'!$F:$F,'Raw daily data'!$I:$I,$A23,'Raw daily data'!$F:$F,"<0"))) | S23: =IF(N23>0,O23/N23,"") | T23: =IF(R23>0,Q23/ABS(R23),"") | U23: =IF(F23>0,H23/F23,"") | V23: =IF(H23<0,MIN(ABS(H23)/G23,1),0) | W23: =IF($A23="","",_xlfn.MAXIFS('Raw daily data'!$J:$J,'Raw daily data'!$I:$I,$A23)) | X23: =IF(W23>=0,0,ABS(W23)/G23) | Y23: =IF($A23="","",ABS(MIN(0,_xlfn.MINIFS('Raw daily data'!$J:$J,'Raw daily data'!$I:$I,$A23)))/G23)
A24: 46055 | B24: 4 | C24: =TEXT(A24,"dddd") | F24: =IF($A24="","",$E24*Summary!$B$8) | G24: =IF($A24="","",F24*Summary!$B$9) | H24: =IF($A24="","",SUMIFS('Raw daily data'!$F:$F,'Raw daily data'!$I:$I,$A24)) | I24: =I23+H24 | J24: =SUMIF($B$2:$B$41,B24,$H$2:$H$41) | K24: =Summary!$B$6 | L24: =J24-K24 | N24: =IF($A24="","",COUNTIFS('Raw daily data'!$I:$I,$A24)) | O24: =IF($A24="","",COUNTIFS('Raw daily data'!$I:$I,$A24,'Raw daily data'!$F:$F,">0")) | P24: =IF($A24="","",COUNTIFS('Raw daily data'!$I:$I,$A24,'Raw daily data'!$F:$F,"<0")) | Q24: =IF($A24="","",SUMIFS('Raw daily data'!$F:$F,'Raw daily data'!$I:$I,$A24,'Raw daily data'!$F:$F,">0")) | R24: =IF($A24="","",ABS(SUMIFS('Raw daily data'!$F:$F,'Raw daily data'!$I:$I,$A24,'Raw daily data'!$F:$F,"<0"))) | S24: =IF(N24>0,O24/N24,"") | T24: =IF(R24>0,Q24/ABS(R24),"") | U24: =IF(F24>0,H24/F24,"") | V24: =IF(H24<0,MIN(ABS(H24)/G24,1),0) | W24: =IF($A24="","",_xlfn.MAXIFS('Raw daily data'!$J:$J,'Raw daily data'!$I:$I,$A24)) | X24: =IF(W24>=0,0,ABS(W24)/G24) | Y24: =IFERROR(IF($A24="","",ABS(MIN(0,_xlfn.MINIFS('Raw daily data'!$J:$J,'Raw daily data'!$I:$I,$A24)))/G24),"")
A25: 46056 | B25: 4 | C25: =TEXT(A25,"dddd") | F25: =IF($A25="","",$E25*Summary!$B$8) | G25: =IF($A25="","",F25*Summary!$B$9) | H25: =IF($A25="","",SUMIFS('Raw daily data'!$F:$F,'Raw daily data'!$I:$I,$A25)) | I25: =I24+H25 | J25: =SUMIF($B$2:$B$41,B25,$H$2:$H$41) | K25: =Summary!$B$6 | L25: =J25-K25 | N25: =IF($A25="","",COUNTIFS('Raw daily data'!$I:$I,$A25)) | O25: =IF($A25="","",COUNTIFS('Raw daily data'!$I:$I,$A25,'Raw daily data'!$F:$F,">0")) | P25: =IF($A25="","",COUNTIFS('Raw daily data'!$I:$I,$A25,'Raw daily data'!$F:$F,"<0")) | Q25: =IF($A25="","",SUMIFS('Raw daily data'!$F:$F,'Raw daily data'!$I:$I,$A25,'Raw daily data'!$F:$F,">0")) | R25: =IF($A25="","",ABS(SUMIFS('Raw daily data'!$F:$F,'Raw daily data'!$I:$I,$A25,'Raw daily data'!$F:$F,"<0"))) | S25: =IF(N25>0,O25/N25,"") | T25: =IF(R25>0,Q25/ABS(R25),"") | U25: =IF(F25>0,H25/F25,"") | V25: =IF(H25<0,MIN(ABS(H25)/G25,1),0) | W25: =IF($A25="","",_xlfn.MAXIFS('Raw daily data'!$J:$J,'Raw daily data'!$I:$I,$A25)) | X25: =IF(W25>=0,0,ABS(W25)/G25) | Y25: =IFERROR(IF($A25="","",ABS(MIN(0,_xlfn.MINIFS('Raw daily data'!$J:$J,'Raw daily data'!$I:$I,$A25)))/G25),"")
A26: 46057 | B26: 4 | C26: =TEXT(A26,"dddd") | F26: =IF($A26="","",$E26*Summary!$B$8) | G26: =IF($A26="","",F26*Summary!$B$9) | H26: =IF($A26="","",SUMIFS('Raw daily data'!$F:$F,'Raw daily data'!$I:$I,$A26)) | I26: =I25+H26 | J26: =SUMIF($B$2:$B$41,B26,$H$2:$H$41) | K26: =Summary!$B$6 | L26: =J26-K26 | N26: =IF($A26="","",COUNTIFS('Raw daily data'!$I:$I,$A26)) | O26: =IF($A26="","",COUNTIFS('Raw daily data'!$I:$I,$A26,'Raw daily data'!$F:$F,">0")) | P26: =IF($A26="","",COUNTIFS('Raw daily data'!$I:$I,$A26,'Raw daily data'!$F:$F,"<0")) | Q26: =IF($A26="","",SUMIFS('Raw daily data'!$F:$F,'Raw daily data'!$I:$I,$A26,'Raw daily data'!$F:$F,">0")) | R26: =IF($A26="","",ABS(SUMIFS('Raw daily data'!$F:$F,'Raw daily data'!$I:$I,$A26,'Raw daily data'!$F:$F,"<0"))) | S26: =IF(N26>0,O26/N26,"") | T26: =IF(R26>0,Q26/ABS(R26),"") | U26: =IF(F26>0,H26/F26,"") | V26: =IF(H26<0,MIN(ABS(H26)/G26,1),0) | W26: =IF($A26="","",_xlfn.MAXIFS('Raw daily data'!$J:$J,'Raw daily data'!$I:$I,$A26)) | X26: =IF(W26>=0,0,ABS(W26)/G26) | Y26: =IFERROR(IF($A26="","",ABS(MIN(0,_xlfn.MINIFS('Raw daily data'!$J:$J,'Raw daily data'!$I:$I,$A26)))/G26),"")
A27: 46058 | B27: 4 | C27: =TEXT(A27,"dddd") | F27: =IF($A27="","",$E27*Summary!$B$8) | G27: =IF($A27="","",F27*Summary!$B$9) | H27: =IF($A27="","",SUMIFS('Raw daily data'!$F:$F,'Raw daily data'!$I:$I,$A27)) | I27: =I26+H27 | J27: =SUMIF($B$2:$B$41,B27,$H$2:$H$41) | K27: =Summary!$B$6 | L27: =J27-K27 | N27: =IF($A27="","",COUNTIFS('Raw daily data'!$I:$I,$A27)) | O27: =IF($A27="","",COUNTIFS('Raw daily data'!$I:$I,$A27,'Raw daily data'!$F:$F,">0")) | P27: =IF($A27="","",COUNTIFS('Raw daily data'!$I:$I,$A27,'Raw daily data'!$F:$F,"<0")) | Q27: =IF($A27="","",SUMIFS('Raw daily data'!$F:$F,'Raw daily data'!$I:$I,$A27,'Raw daily data'!$F:$F,">0")) | R27: =IF($A27="","",ABS(SUMIFS('Raw daily data'!$F:$F,'Raw daily data'!$I:$I,$A27,'Raw daily data'!$F:$F,"<0"))) | S27: =IF(N27>0,O27/N27,"") | T27: =IF(R27>0,Q27/ABS(R27),"") | U27: =IF(F27>0,H27/F27,"") | V27: =IF(H27<0,MIN(ABS(H27)/G27,1),0) | W27: =IF($A27="","",_xlfn.MAXIFS('Raw daily data'!$J:$J,'Raw daily data'!$I:$I,$A27)) | X27: =IF(W27>=0,0,ABS(W27)/G27) | Y27: =IFERROR(IF($A27="","",ABS(MIN(0,_xlfn.MINIFS('Raw daily data'!$J:$J,'Raw daily data'!$I:$I,$A27)))/G27),"")
A28: 46059 | B28: 4 | C28: =TEXT(A28,"dddd") | F28: =IF($A28="","",$E28*Summary!$B$8) | G28: =IF($A28="","",F28*Summary!$B$9) | H28: =IF($A28="","",SUMIFS('Raw daily data'!$F:$F,'Raw daily data'!$I:$I,$A28)) | I28: =I27+H28 | J28: =SUMIF($B$2:$B$41,B28,$H$2:$H$41) | K28: =Summary!$B$6 | L28: =J28-K28 | N28: =IF($A28="","",COUNTIFS('Raw daily data'!$I:$I,$A28)) | O28: =IF($A28="","",COUNTIFS('Raw daily data'!$I:$I,$A28,'Raw daily data'!$F:$F,">0")) | P28: =IF($A28="","",COUNTIFS('Raw daily data'!$I:$I,$A28,'Raw daily data'!$F:$F,"<0")) | Q28: =IF($A28="","",SUMIFS('Raw daily data'!$F:$F,'Raw daily data'!$I:$I,$A28,'Raw daily data'!$F:$F,">0")) | R28: =IF($A28="","",ABS(SUMIFS('Raw daily data'!$F:$F,'Raw daily data'!$I:$I,$A28,'Raw daily data'!$F:$F,"<0"))) | S28: =IF(N28>0,O28/N28,"") | T28: =IF(R28>0,Q28/ABS(R28),"") | U28: =IF(F28>0,H28/F28,"") | V28: =IF(H28<0,MIN(ABS(H28)/G28,1),0) | W28: =IF($A28="","",_xlfn.MAXIFS('Raw daily data'!$J:$J,'Raw daily data'!$I:$I,$A28)) | X28: =IF(W28>=0,0,ABS(W28)/G28) | Y28: =IFERROR(IF($A28="","",ABS(MIN(0,_xlfn.MINIFS('Raw daily data'!$J:$J,'Raw daily data'!$I:$I,$A28)))/G28),"")
A29: 46060 | B29: 4 | C29: =TEXT(A29,"dddd") | D29: N | F29: =IF($A29="","",$E29*Summary!$B$8) | G29: =IF($A29="","",F29*Summary!$B$9) | H29: =IF($A29="","",SUMIFS('Raw daily data'!$F:$F,'Raw daily data'!$I:$I,$A29)) | I29: =I28+H29 | J29: =SUMIF($B$2:$B$41,B29,$H$2:$H$41) | K29: =Summary!$B$6 | L29: =J29-K29 | N29: =IF($A29="","",COUNTIFS('Raw daily data'!$I:$I,$A29)) | O29: =IF($A29="","",COUNTIFS('Raw daily data'!$I:$I,$A29,'Raw daily data'!$F:$F,">0")) | P29: =IF($A29="","",COUNTIFS('Raw daily data'!$I:$I,$A29,'Raw daily data'!$F:$F,"<0")) | Q29: =IF($A29="","",SUMIFS('Raw daily data'!$F:$F,'Raw daily data'!$I:$I,$A29,'Raw daily data'!$F:$F,">0")) | R29: =IF($A29="","",ABS(SUMIFS('Raw daily data'!$F:$F,'Raw daily data'!$I:$I,$A29,'Raw daily data'!$F:$F,"<0"))) | S29: =IF(N29>0,O29/N29,"") | T29: =IF(R29>0,Q29/ABS(R29),"") | U29: =IF(F29>0,H29/F29,"") | V29: =IF(H29<0,MIN(ABS(H29)/G29,1),0) | W29: =IF($A29="","",_xlfn.MAXIFS('Raw daily data'!$J:$J,'Raw daily data'!$I:$I,$A29)) | X29: =IF(W29>=0,0,ABS(W29)/G29) | Y29: =IFERROR(IF($A29="","",ABS(MIN(0,_xlfn.MINIFS('Raw daily data'!$J:$J,'Raw daily data'!$I:$I,$A29)))/G29),"")
A30: 46061 | B30: 4 | C30: =TEXT(A30,"dddd") | D30: N | F30: =IF($A30="","",$E30*Summary!$B$8) | G30: =IF($A30="","",F30*Summary!$B$9) | H30: =IF($A30="","",SUMIFS('Raw daily data'!$F:$F,'Raw daily data'!$I:$I,$A30)) | I30: =I29+H30 | J30: =SUMIF($B$2:$B$41,B30,$H$2:$H$41) | K30: =Summary!$B$6 | L30: =J30-K30 | N30: =IF($A30="","",COUNTIFS('Raw daily data'!$I:$I,$A30)) | O30: =IF($A30="","",COUNTIFS('Raw daily data'!$I:$I,$A30,'Raw daily data'!$F:$F,">0")) | P30: =IF($A30="","",COUNTIFS('Raw daily data'!$I:$I,$A30,'Raw daily data'!$F:$F,"<0")) | Q30: =IF($A30="","",SUMIFS('Raw daily data'!$F:$F,'Raw daily data'!$I:$I,$A30,'Raw daily data'!$F:$F,">0")) | R30: =IF($A30="","",ABS(SUMIFS('Raw daily data'!$F:$F,'Raw daily data'!$I:$I,$A30,'Raw daily data'!$F:$F,"<0"))) | S30: =IF(N30>0,O30/N30,"") | T30: =IF(R30>0,Q30/ABS(R30),"") | U30: =IF(F30>0,H30/F30,"") | V30: =IF(H30<0,MIN(ABS(H30)/G30,1),0) | W30: =IF($A30="","",_xlfn.MAXIFS('Raw daily data'!$J:$J,'Raw daily data'!$I:$I,$A30)) | X30: =IF(W30>=0,0,ABS(W30)/G30) | Y30: =IFERROR(IF($A30="","",ABS(MIN(0,_xlfn.MINIFS('Raw daily data'!$J:$J,'Raw daily data'!$I:$I,$A30)))/G30),"")
A31: 46062 | C31: =TEXT(A31,"dddd") | F31: =IF($A31="","",$E31*Summary!$B$8) | G31: =IF($A31="","",F31*Summary!$B$9) | H31: =IF($A31="","",SUMIFS('Raw daily data'!$F:$F,'Raw daily data'!$I:$I,$A31)) | I31: =I30+H31 | J31: =SUMIF($B$2:$B$41,B31,$H$2:$H$41) | K31: =Summary!$B$6 | L31: =J31-K31 | N31: =IF($A31="","",COUNTIFS('Raw daily data'!$I:$I,$A31)) | O31: =IF($A31="","",COUNTIFS('Raw daily data'!$I:$I,$A31,'Raw daily data'!$F:$F,">0")) | P31: =IF($A31="","",COUNTIFS('Raw daily data'!$I:$I,$A31,'Raw daily data'!$F:$F,"<0")) | Q31: =IF($A31="","",SUMIFS('Raw daily data'!$F:$F,'Raw daily data'!$I:$I,$A31,'Raw daily data'!$F:$F,">0")) | R31: =IF($A31="","",ABS(SUMIFS('Raw daily data'!$F:$F,'Raw daily data'!$I:$I,$A31,'Raw daily data'!$F:$F,"<0"))) | S31: =IF(N31>0,O31/N31,"") | T31: =IF(R31>0,Q31/ABS(R31),"") | U31: =IF(F31>0,H31/F31,"") | V31: =IF(H31<0,MIN(ABS(H31)/G31,1),0) | W31: =IF($A31="","",_xlfn.MAXIFS('Raw daily data'!$J:$J,'Raw daily data'!$I:$I,$A31)) | X31: =IF(W31>=0,0,ABS(W31)/G31) | Y31: =IFERROR(IF($A31="","",ABS(MIN(0,_xlfn.MINIFS('Raw daily data'!$J:$J,'Raw daily data'!$I:$I,$A31)))/G31),"")
A32: 46063 | C32: =TEXT(A32,"dddd") | F32: =IF($A32="","",$E32*Summary!$B$8) | G32: =IF($A32="","",F32*Summary!$B$9) | H32: =IF($A32="","",SUMIFS('Raw daily data'!$F:$F,'Raw daily data'!$I:$I,$A32)) | I32: =I31+H32 | J32: =SUMIF($B$2:$B$41,B32,$H$2:$H$41) | K32: =Summary!$B$6 | L32: =J32-K32 | N32: =IF($A32="","",COUNTIFS('Raw daily data'!$I:$I,$A32)) | O32: =IF($A32="","",COUNTIFS('Raw daily data'!$I:$I,$A32,'Raw daily data'!$F:$F,">0")) | P32: =IF($A32="","",COUNTIFS('Raw daily data'!$I:$I,$A32,'Raw daily data'!$F:$F,"<0")) | Q32: =IF($A32="","",SUMIFS('Raw daily data'!$F:$F,'Raw daily data'!$I:$I,$A32,'Raw daily data'!$F:$F,">0")) | R32: =IF($A32="","",ABS(SUMIFS('Raw daily data'!$F:$F,'Raw daily data'!$I:$I,$A32,'Raw daily data'!$F:$F,"<0"))) | S32: =IF(N32>0,O32/N32,"") | T32: =IF(R32>0,Q32/ABS(R32),"") | U32: =IF(F32>0,H32/F32,"") | V32: =IF(H32<0,MIN(ABS(H32)/G32,1),0) | W32: =IF($A32="","",_xlfn.MAXIFS('Raw daily data'!$J:$J,'Raw daily data'!$I:$I,$A32)) | X32: =IF(W32>=0,0,ABS(W32)/G32) | Y32: =IFERROR(IF($A32="","",ABS(MIN(0,_xlfn.MINIFS('Raw daily data'!$J:$J,'Raw daily data'!$I:$I,$A32)))/G32),"")
A33: 46064 | C33: =TEXT(A33,"dddd") | F33: =IF($A33="","",$E33*Summary!$B$8) | G33: =IF($A33="","",F33*Summary!$B$9) | H33: =IF($A33="","",SUMIFS('Raw daily data'!$F:$F,'Raw daily data'!$I:$I,$A33)) | I33: =I32+H33 | J33: =SUMIF($B$2:$B$41,B33,$H$2:$H$41) | K33: =Summary!$B$6 | L33: =J33-K33 | N33: =IF($A33="","",COUNTIFS('Raw daily data'!$I:$I,$A33)) | O33: =IF($A33="","",COUNTIFS('Raw daily data'!$I:$I,$A33,'Raw daily data'!$F:$F,">0")) | P33: =IF($A33="","",COUNTIFS('Raw daily data'!$I:$I,$A33,'Raw daily data'!$F:$F,"<0")) | Q33: =IF($A33="","",SUMIFS('Raw daily data'!$F:$F,'Raw daily data'!$I:$I,$A33,'Raw daily data'!$F:$F,">0")) | R33: =IF($A33="","",ABS(SUMIFS('Raw daily data'!$F:$F,'Raw daily data'!$I:$I,$A33,'Raw daily data'!$F:$F,"<0"))) | S33: =IF(N33>0,O33/N33,"") | T33: =IF(R33>0,Q33/ABS(R33),"") | U33: =IF(F33>0,H33/F33,"") | V33: =IF(H33<0,MIN(ABS(H33)/G33,1),0) | W33: =IF($A33="","",_xlfn.MAXIFS('Raw daily data'!$J:$J,'Raw daily data'!$I:$I,$A33)) | X33: =IF(W33>=0,0,ABS(W33)/G33) | Y33: =IFERROR(IF($A33="","",ABS(MIN(0,_xlfn.MINIFS('Raw daily data'!$J:$J,'Raw daily data'!$I:$I,$A33)))/G33),"")
A34: 46065 | C34: =TEXT(A34,"dddd") | F34: =IF($A34="","",$E34*Summary!$B$8) | G34: =IF($A34="","",F34*Summary!$B$9) | H34: =IF($A34="","",SUMIFS('Raw daily data'!$F:$F,'Raw daily data'!$I:$I,$A34)) | I34: =I33+H34 | J34: =SUMIF($B$2:$B$41,B34,$H$2:$H$41) | K34: =Summary!$B$6 | L34: =J34-K34 | N34: =IF($A34="","",COUNTIFS('Raw daily data'!$I:$I,$A34)) | O34: =IF($A34="","",COUNTIFS('Raw daily data'!$I:$I,$A34,'Raw daily data'!$F:$F,">0")) | P34: =IF($A34="","",COUNTIFS('Raw daily data'!$I:$I,$A34,'Raw daily data'!$F:$F,"<0")) | Q34: =IF($A34="","",SUMIFS('Raw daily data'!$F:$F,'Raw daily data'!$I:$I,$A34,'Raw daily data'!$F:$F,">0")) | R34: =IF($A34="","",ABS(SUMIFS('Raw daily data'!$F:$F,'Raw daily data'!$I:$I,$A34,'Raw daily data'!$F:$F,"<0"))) | S34: =IF(N34>0,O34/N34,"") | T34: =IF(R34>0,Q34/ABS(R34),"") | U34: =IF(F34>0,H34/F34,"") | V34: =IF(H34<0,MIN(ABS(H34)/G34,1),0) | W34: =IF($A34="","",_xlfn.MAXIFS('Raw daily data'!$J:$J,'Raw daily data'!$I:$I,$A34)) | X34: =IF(W34>=0,0,ABS(W34)/G34) | Y34: =IFERROR(IF($A34="","",ABS(MIN(0,_xlfn.MINIFS('Raw daily data'!$J:$J,'Raw daily data'!$I:$I,$A34)))/G34),"")
A35: 46066 | C35: =TEXT(A35,"dddd") | F35: =IF($A35="","",$E35*Summary!$B$8) | G35: =IF($A35="","",F35*Summary!$B$9) | H35: =IF($A35="","",SUMIFS('Raw daily data'!$F:$F,'Raw daily data'!$I:$I,$A35)) | I35: =I34+H35 | J35: =SUMIF($B$2:$B$41,B35,$H$2:$H$41) | K35: =Summary!$B$6 | L35: =J35-K35 | N35: =IF($A35="","",COUNTIFS('Raw daily data'!$I:$I,$A35)) | O35: =IF($A35="","",COUNTIFS('Raw daily data'!$I:$I,$A35,'Raw daily data'!$F:$F,">0")) | P35: =IF($A35="","",COUNTIFS('Raw daily data'!$I:$I,$A35,'Raw daily data'!$F:$F,"<0")) | Q35: =IF($A35="","",SUMIFS('Raw daily data'!$F:$F,'Raw daily data'!$I:$I,$A35,'Raw daily data'!$F:$F,">0")) | R35: =IF($A35="","",ABS(SUMIFS('Raw daily data'!$F:$F,'Raw daily data'!$I:$I,$A35,'Raw daily data'!$F:$F,"<0"))) | S35: =IF(N35>0,O35/N35,"") | T35: =IF(R35>0,Q35/ABS(R35),"") | U35: =IF(F35>0,H35/F35,"") | V35: =IF(H35<0,MIN(ABS(H35)/G35,1),0) | W35: =IF($A35="","",_xlfn.MAXIFS('Raw daily data'!$J:$J,'Raw daily data'!$I:$I,$A35)) | X35: =IF(W35>=0,0,ABS(W35)/G35) | Y35: =IFERROR(IF($A35="","",ABS(MIN(0,_xlfn.MINIFS('Raw daily data'!$J:$J,'Raw daily data'!$I:$I,$A35)))/G35),"")
A36: 46067 | C36: =TEXT(A36,"dddd") | F36: =IF($A36="","",$E36*Summary!$B$8) | G36: =IF($A36="","",F36*Summary!$B$9) | H36: =IF($A36="","",SUMIFS('Raw daily data'!$F:$F,'Raw daily data'!$I:$I,$A36)) | I36: =I35+H36 | J36: =SUMIF($B$2:$B$41,B36,$H$2:$H$41) | K36: =Summary!$B$6 | L36: =J36-K36 | N36: =IF($A36="","",COUNTIFS('Raw daily data'!$I:$I,$A36)) | O36: =IF($A36="","",COUNTIFS('Raw daily data'!$I:$I,$A36,'Raw daily data'!$F:$F,">0")) | P36: =IF($A36="","",COUNTIFS('Raw daily data'!$I:$I,$A36,'Raw daily data'!$F:$F,"<0")) | Q36: =IF($A36="","",SUMIFS('Raw daily data'!$F:$F,'Raw daily data'!$I:$I,$A36,'Raw daily data'!$F:$F,">0")) | R36: =IF($A36="","",ABS(SUMIFS('Raw daily data'!$F:$F,'Raw daily data'!$I:$I,$A36,'Raw daily data'!$F:$F,"<0"))) | S36: =IF(N36>0,O36/N36,"") | T36: =IF(R36>0,Q36/ABS(R36),"") | U36: =IF(F36>0,H36/F36,"") | V36: =IF(H36<0,MIN(ABS(H36)/G36,1),0) | W36: =IF($A36="","",_xlfn.MAXIFS('Raw daily data'!$J:$J,'Raw daily data'!$I:$I,$A36)) | X36: =IF(W36>=0,0,ABS(W36)/G36) | Y36: =IFERROR(IF($A36="","",ABS(MIN(0,_xlfn.MINIFS('Raw daily data'!$J:$J,'Raw daily data'!$I:$I,$A36)))/G36),"")
A37: 46068 | C37: =TEXT(A37,"dddd") | F37: =IF($A37="","",$E37*Summary!$B$8) | G37: =IF($A37="","",F37*Summary!$B$9) | H37: =IF($A37="","",SUMIFS('Raw daily data'!$F:$F,'Raw daily data'!$I:$I,$A37)) | I37: =I36+H37 | J37: =SUMIF($B$2:$B$41,B37,$H$2:$H$41) | K37: =Summary!$B$6 | L37: =J37-K37 | N37: =IF($A37="","",COUNTIFS('Raw daily data'!$I:$I,$A37)) | O37: =IF($A37="","",COUNTIFS('Raw daily data'!$I:$I,$A37,'Raw daily data'!$F:$F,">0")) | P37: =IF($A37="","",COUNTIFS('Raw daily data'!$I:$I,$A37,'Raw daily data'!$F:$F,"<0")) | Q37: =IF($A37="","",SUMIFS('Raw daily data'!$F:$F,'Raw daily data'!$I:$I,$A37,'Raw daily data'!$F:$F,">0")) | R37: =IF($A37="","",ABS(SUMIFS('Raw daily data'!$F:$F,'Raw daily data'!$I:$I,$A37,'Raw daily data'!$F:$F,"<0"))) | S37: =IF(N37>0,O37/N37,"") | T37: =IF(R37>0,Q37/ABS(R37),"") | U37: =IF(F37>0,H37/F37,"") | V37: =IF(H37<0,MIN(ABS(H37)/G37,1),0) | W37: =IF($A37="","",_xlfn.MAXIFS('Raw daily data'!$J:$J,'Raw daily data'!$I:$I,$A37)) | X37: =IF(W37>=0,0,ABS(W37)/G37) | Y37: =IFERROR(IF($A37="","",ABS(MIN(0,_xlfn.MINIFS('Raw daily data'!$J:$J,'Raw daily data'!$I:$I,$A37)))/G37),"")
A38: 46069 | C38: =TEXT(A38,"dddd") | F38: =IF($A38="","",$E38*Summary!$B$8) | G38: =IF($A38="","",F38*Summary!$B$9) | H38: =IF($A38="","",SUMIFS('Raw daily data'!$F:$F,'Raw daily data'!$I:$I,$A38)) | I38: =I37+H38 | J38: =SUMIF($B$2:$B$41,B38,$H$2:$H$41) | K38: =Summary!$B$6 | L38: =J38-K38 | N38: =IF($A38="","",COUNTIFS('Raw daily data'!$I:$I,$A38)) | O38: =IF($A38="","",COUNTIFS('Raw daily data'!$I:$I,$A38,'Raw daily data'!$F:$F,">0")) | P38: =IF($A38="","",COUNTIFS('Raw daily data'!$I:$I,$A38,'Raw daily data'!$F:$F,"<0")) | Q38: =IF($A38="","",SUMIFS('Raw daily data'!$F:$F,'Raw daily data'!$I:$I,$A38,'Raw daily data'!$F:$F,">0")) | R38: =IF($A38="","",ABS(SUMIFS('Raw daily data'!$F:$F,'Raw daily data'!$I:$I,$A38,'Raw daily data'!$F:$F,"<0"))) | S38: =IF(N38>0,O38/N38,"") | T38: =IF(R38>0,Q38/ABS(R38),"") | U38: =IF(F38>0,H38/F38,"") | V38: =IF(H38<0,MIN(ABS(H38)/G38,1),0) | W38: =IF($A38="","",_xlfn.MAXIFS('Raw daily data'!$J:$J,'Raw daily data'!$I:$I,$A38)) | X38: =IF(W38>=0,0,ABS(W38)/G38) | Y38: =IFERROR(IF($A38="","",ABS(MIN(0,_xlfn.MINIFS('Raw daily data'!$J:$J,'Raw daily data'!$I:$I,$A38)))/G38),"")
A39: 46070 | C39: =TEXT(A39,"dddd") | F39: =IF($A39="","",$E39*Summary!$B$8) | G39: =IF($A39="","",F39*Summary!$B$9) | H39: =IF($A39="","",SUMIFS('Raw daily data'!$F:$F,'Raw daily data'!$I:$I,$A39)) | I39: =I38+H39 | J39: =SUMIF($B$2:$B$41,B39,$H$2:$H$41) | K39: =Summary!$B$6 | L39: =J39-K39 | N39: =IF($A39="","",COUNTIFS('Raw daily data'!$I:$I,$A39)) | O39: =IF($A39="","",COUNTIFS('Raw daily data'!$I:$I,$A39,'Raw daily data'!$F:$F,">0")) | P39: =IF($A39="","",COUNTIFS('Raw daily data'!$I:$I,$A39,'Raw daily data'!$F:$F,"<0")) | Q39: =IF($A39="","",SUMIFS('Raw daily data'!$F:$F,'Raw daily data'!$I:$I,$A39,'Raw daily data'!$F:$F,">0")) | R39: =IF($A39="","",ABS(SUMIFS('Raw daily data'!$F:$F,'Raw daily data'!$I:$I,$A39,'Raw daily data'!$F:$F,"<0"))) | S39: =IF(N39>0,O39/N39,"") | T39: =IF(R39>0,Q39/ABS(R39),"") | U39: =IF(F39>0,H39/F39,"") | V39: =IF(H39<0,MIN(ABS(H39)/G39,1),0) | W39: =IF($A39="","",_xlfn.MAXIFS('Raw daily data'!$J:$J,'Raw daily data'!$I:$I,$A39)) | X39: =IF(W39>=0,0,ABS(W39)/G39) | Y39: =IFERROR(IF($A39="","",ABS(MIN(0,_xlfn.MINIFS('Raw daily data'!$J:$J,'Raw daily data'!$I:$I,$A39)))/G39),"")
A40: 46071 | C40: =TEXT(A40,"dddd") | F40: =IF($A40="","",$E40*Summary!$B$8) | G40: =IF($A40="","",F40*Summary!$B$9) | H40: =IF($A40="","",SUMIFS('Raw daily data'!$F:$F,'Raw daily data'!$I:$I,$A40)) | I40: =I39+H40 | J40: =SUMIF($B$2:$B$41,B40,$H$2:$H$41) | K40: =Summary!$B$6 | L40: =J40-K40 | N40: =IF($A40="","",COUNTIFS('Raw daily data'!$I:$I,$A40)) | O40: =IF($A40="","",COUNTIFS('Raw daily data'!$I:$I,$A40,'Raw daily data'!$F:$F,">0")) | P40: =IF($A40="","",COUNTIFS('Raw daily data'!$I:$I,$A40,'Raw daily data'!$F:$F,"<0")) | Q40: =IF($A40="","",SUMIFS('Raw daily data'!$F:$F,'Raw daily data'!$I:$I,$A40,'Raw daily data'!$F:$F,">0")) | R40: =IF($A40="","",ABS(SUMIFS('Raw daily data'!$F:$F,'Raw daily data'!$I:$I,$A40,'Raw daily data'!$F:$F,"<0"))) | S40: =IF(N40>0,O40/N40,"") | T40: =IF(R40>0,Q40/ABS(R40),"") | U40: =IF(F40>0,H40/F40,"") | V40: =IF(H40<0,MIN(ABS(H40)/G40,1),0) | W40: =IF($A40="","",_xlfn.MAXIFS('Raw daily data'!$J:$J,'Raw daily data'!$I:$I,$A40)) | X40: =IF(W40>=0,0,ABS(W40)/G40) | Y40: =IFERROR(IF($A40="","",ABS(MIN(0,_xlfn.MINIFS('Raw daily data'!$J:$J,'Raw daily data'!$I:$I,$A40)))/G40),"")
A41: 46072 | C41: =TEXT(A41,"dddd") | F41: =IF($A41="","",$E41*Summary!$B$8) | G41: =IF($A41="","",F41*Summary!$B$9) | H41: =IF($A41="","",SUMIFS('Raw daily data'!$F:$F,'Raw daily data'!$I:$I,$A41)) | I41: =I40+H41 | J41: =SUMIF($B$2:$B$41,B41,$H$2:$H$41) | K41: =Summary!$B$6 | L41: =J41-K41 | N41: =IF($A41="","",COUNTIFS('Raw daily data'!$I:$I,$A41)) | O41: =IF($A41="","",COUNTIFS('Raw daily data'!$I:$I,$A41,'Raw daily data'!$F:$F,">0")) | P41: =IF($A41="","",COUNTIFS('Raw daily data'!$I:$I,$A41,'Raw daily data'!$F:$F,"<0")) | Q41: =IF($A41="","",SUMIFS('Raw daily data'!$F:$F,'Raw daily data'!$I:$I,$A41,'Raw daily data'!$F:$F,">0")) | R41: =IF($A41="","",ABS(SUMIFS('Raw daily data'!$F:$F,'Raw daily data'!$I:$I,$A41,'Raw daily data'!$F:$F,"<0"))) | S41: =IF(N41>0,O41/N41,"") | T41: =IF(R41>0,Q41/ABS(R41),"") | U41: =IF(F41>0,H41/F41,"") | V41: =IF(H41<0,MIN(ABS(H41)/G41,1),0) | W41: =IF($A41="","",_xlfn.MAXIFS('Raw daily data'!$J:$J,'Raw daily data'!$I:$I,$A41)) | X41: =IF(W41>=0,0,ABS(W41)/G41) | Y41: =IFERROR(IF($A41="","",ABS(MIN(0,_xlfn.MINIFS('Raw daily data'!$J:$J,'Raw daily data'!$I:$I,$A41)))/G41),"")

Sheet Raw daily data
A1: Symbol | B1: Name | C1: Side | D1: Quantity | E1: Price | F1: Profit | G1: Deal ID | H1: Time | I1: Trade Date | J1: Cumulative P&L for the day
A2: EURUSD | B2: EUR_USD | C2: sell | D2: 200000 | E2: 1.15899 | F2: -60 | G2: 12607 | H2: Wed, 11 Jan 2026 12:06:06 GMT | I2: =IF(H2="","",DATEVALUE(MID(H2,6,11))) | J2: =IF(F2="","",F2+IF(I2=I1,J1,0))
A3: EURUSD | B3: EUR_USD | C3: sell | D3: 500002 | E3: 1.15829 | F3: 575.0023 | G3: 12594 | H3: Wed, 12 Jan 2026 12:06:06 GMT | I3: =IF(H3="","",DATEVALUE(MID(H3,6,11))) | J3: =IF(F3="","",F3+IF(I3=I2,J2,0))
I4: =IF(H4="","",DATEVALUE(MID(H4,6,11))) | J4: =IF(F4="","",F4+IF(I4=I3,J3,0))
I5: =IF(H5="","",DATEVALUE(MID(H5,6,11))) | J5: =IF(F5="","",F5+IF(I5=I4,J4,0))
I6: =IF(H6="","",DATEVALUE(MID(H6,6,11))) | J6: =IF(F6="","",F6+IF(I6=I5,J5,0))
I7: =IF(H7="","",DATEVALUE(MID(H7,6,11))) | J7: =IF(F7="","",F7+IF(I7=I6,J6,0))
I8: =IF(H8="","",DATEVALUE(MID(H8,6,11))) | J8: =IF(F8="","",F8+IF(I8=I7,J7,0))
I9: =IF(H9="","",DATEVALUE(MID(H9,6,11))) | J9: =IF(F9="","",F9+IF(I9=I8,J8,0))
I10: =IF(H10="","",DATEVALUE(MID(H10,6,11))) | J10: =IF(F10="","",F10+IF(I10=I9,J9,0))
I11: =IF(H11="","",DATEVALUE(MID(H11,6,11))) | J11: =IF(F11="","",F11+IF(I11=I10,J10,0))
I12: =IF(H12="","",DATEVALUE(MID(H12,6,11))) | J12: =IF(F12="","",F12+IF(I12=I11,J11,0))
I13: =IF(H13="","",DATEVALUE(MID(H13,6,11))) | J13: =IF(F13="","",F13+IF(I13=I12,J12,0))
I14: =IF(H14="","",DATEVALUE(MID(H14,6,11))) | J14: =IF(F14="","",F14+IF(I14=I13,J13,0))
I15: =IF(H15="","",DATEVALUE(MID(H15,6,11))) | J15: =IF(F15="","",F15+IF(I15=I14,J14,0))
... I52: =IF(H52="","",DATEVALUE(MID(H52,6,11))) | J52: =IF(F52="","",F52+IF(I52=I51,J51,0))

Sheet Advanced Setup Planner
A1: EURUSD Planner HUD (inputs → outputs) | N1: BACKEND CALC — Use Planner_HUD (inputs & ladders) | S1: Structure (SMC) – D1 / H4 / H1 / 15m | X1: Side | Y1: =IF(AND($T$8,NOT($T$9)),"LONG",IF(AND($T$9,NOT($T$8)),"SHORT","")) | AC1: PRIMARY LADDER | AD1: Entry | AE1: TP | AF1: SL | AG1: Pips to TP1 | AH1: Eff Pips to SL | AI1: Weight | AJ1: Risk $ | AK1: Reward $ | AL1: Units | AM1: R per rung | EH1: CT_Entry | EI1: =IF(SUM($AI$28:$AI$30)=0,"",SUMPRODUCT($AD$28:$AD$30,$AI$28:$AI$30)/SUM($AI$28:$AI$30))
A2: Edit BLUE cells only. Planner_v2 reads from here. | N2: Market snapshot (15m + HTF EMAs & ATR) | S2: TF | T2: Trend | U2: Last BOS | V2: Last CHOCH | X2: Risk per Trade R ($) | Y2: =Summary!B10*Summary!B8 | AC2: Entry 0.382 | AD2: =IF($Y$1="LONG",IF($ED$58,$T$19,$O$7),IF($Y$1="SHORT",$Q$23,"")) | AE2: =IF(AD2="","",$ED$40) | AF2: =IF($Y$1="LONG",IF(OR($ED$58,$O$3>=$T$19),$ED$27,$T$20-0.0002),IF($Y$1="SHORT",IF($ED$58,MAX($O$39,$O$7)+0.0002,$T$19+0.0002),"")) | AG2: =IF(OR(AD2="",AE2=""),"",ABS((AE2-AD2)*10000)) | AH2: =IF(OR(AD2="",AF2=""),"",MAX(ABS((AD2-AF2)*10000),$ED$19)) | AI2: =$Y$7 | AJ2: =IF(OR(AI2=0,$ED$11=0,AD2=""),"",$Y$2*$ED$8*AI2/$ED$11) | AK2: =IF(OR(AJ2="",AJ2=0,AG2=""),"",AJ2*AG2/MAX(AH2,$ED$19)) | AL2: =IF(OR(AD2="",AH2="",AJ2=""),"",AJ2/(MAX(AH2,$ED$19)*$ED$3)) | AM2: =IF(OR(AG2="",AH2=""),"",AG2/MAX(AH2,$ED$19)) | AN2: =IF(AH2="","",MAX(AH2,$ED$7)) | EA2: Scoring & HUD | EC2: Ladder Controls | EE2: Big Picture | EF2: =IF($EB$25,"Avoid trading this leg – system rules (R, room, macro) are not met.",IF($EB$56=1,"HTF up, shallow pullback in Tier 1 (15m 0.382–0.618). Long bias but less room; prefer buying dips closer to Tier 2/3.",IF($EB$56=2,"HTF up, intraday pullback trading in Tier 2 (4H FVG + HTF 0.382 + EMA50D). Macro bias: buy dips; this is a B-grade but tradable zone when ladder and R/room are valid.",IF($EB$56=3,"HTF up, deep discount near structural support (Tier 3). If trend remains intact, this is a high-value region.","Price is above all discount tiers (premium) near PMH/PDH/EQH. This is not a location for fresh longs; either manage existing longs or wait for a pullback into Tier 2/3 or a clearly defined CT short setup.")))) | EH2: CT_SL | EI2: =$EB$48+0.0008
N3: Current Price | O3: ='Advanced Setup Planner'!B5 | S3: 1D | T3: =IF($O$12="","",IF(AND($O$12>$O$13,$O$13>$O$14,$O$3>$O$12+0.0002),"Bull",IF(AND($O$12<$O$13,$O$13<$O$14,$O$3<$O$12-0.0002),"Bear","Range"))) | U3: ='Advanced Setup Planner'!C24 | V3: ='Advanced Setup Planner'!D24 | X3: TP1 Price | Y3: =IF($Y$1="LONG",MIN(IF($T$15>$O$3,$T$15,10^6),IF($T$17>$O$3,$T$17,10^6),IF($T$19>$O$3,$T$19,10^6),IF($T$21>$O$3,$T$21,10^6)),IF($Y$1="SHORT",MAX(IF($T$16<$O$3,$T$16,-10^6),IF($T$18<$O$3,$T$18,-10^6),IF($T$20<$O$3,$T$20,-10^6),IF($T$22<$O$3,$T$22,-10^6)),"")) | AC3: Entry 0.500 | AD3: =IF($Y$1="LONG",IF($ED$58,AVERAGE($O$39,$O$40),$O$8),IF($Y$1="SHORT",$Q$24,"")) | AE3: =IF(AD3="","",$ED$40) | AF3: =IF($Y$1="LONG",IF(OR($ED$58,$O$3>=$T$19),$ED$27,$T$20-0.0002),IF($Y$1="SHORT",IF($ED$58,MAX($O$39,$O$7)+0.0002,$T$19+0.0002),"")) | AG3: =IF(OR(AD3="",AE3=""),"",ABS((AE3-AD3)*10000)) | AH3: =IF(OR(AD3="",AF3=""),"",MAX(ABS((AD3-AF3)*10000),$ED$19)) | AI3: =$Y$8 | AJ3: =IF(OR(AI3=0,$ED$11=0,AD3=""),"",$Y$2*$ED$8*AI3/$ED$11) | AK3: =IF(OR(AJ3="",AJ3=0,AG3=""),"",AJ3*AG3/MAX(AH3,$ED$19)) | AL3: =IF(OR(AD3="",AH3="",AJ3=""),"",AJ3/(MAX(AH3,$ED$19)*$ED$3)) | AM3: =IF(OR(AG3="",AH3=""),"",AG3/MAX(AH3,$ED$19)) | AN3: =IF(AH3="","",MAX(AH3,$ED$7)) | EC3: PipSize | ED3: 0.0001 | EF3: =IFERROR(IF(EB23<>"CoreLong","",IF($EB$55=1,"Shallow long zone (Tier 1): "&TEXT(EB51,"0.00000")&" → "&TEXT(EC51,"0.00000")&" (15m fib 0.382–0.618, less room).",IF($EB$55=2,"Main long zone (Tier 2): "&TEXT(EB52,"0.00000")&" → "&TEXT(EC52,"0.00000")&" (4H FVG + HTF 0.382 + EMA50D).",IF($EB$55=3,"Deep long zone (Tier 3): "&TEXT(EB53,"0.00000")&" → "&TEXT(EC53,"0.00000")&" (EMA100D + PWL + HTF fib).","")))),"") | EH3: CT_TP1 | EI3: =$EB$32
A4: Market snapshot (update from chart) | D4: Liquidity / Session levels | G4: FVG / value blocks | J4: Options expiry + risk/weights | S4: 4H | T4: =IF($O$11="","",IF($O$3>$O$11+0.0002,"Bull",IF($O$3<$O$11-0.0002,"Bear","Range"))) | U4: ='Advanced Setup Planner'!C25 | V4: ='Advanced Setup Planner'!D25 | X4: SL Price (Auto) | Y4: =IF($Y$5<>"",$Y$5,IF($Y$1="LONG",IF($Y$22="","",$Y$22-0.0003),IF($Y$1="SHORT",IF($Y$23="","",$Y$23+0.0003),""))) | AC4: Entry 0.618 | AD4: =IF($Y$1="LONG",IF($ED$58,MIN($O$40,$O$7),$O$10),IF($Y$1="SHORT",$Q$25,"")) | AE4: =IF(AD4="","",$ED$40) | AF4: =IF($Y$1="LONG",IF(OR($ED$58,$O$3>=$T$19),$ED$27,$T$20-0.0002),IF($Y$1="SHORT",IF($ED$58,MAX($O$39,$O$7)+0.0002,$T$19+0.0002),"")) | AG4: =IF(OR(AD4="",AE4=""),"",ABS((AE4-AD4)*10000)) | AH4: =IF(OR(AD4="",AF4=""),"",MAX(ABS((AD4-AF4)*10000),$ED$19)) | AI4: =$Y$9 | AJ4: =IF(OR(AI4=0,$ED$11=0,AD4=""),"",$Y$2*$ED$8*AI4/$ED$11) | AK4: =IF(OR(AJ4="",AJ4=0,AG4=""),"",AJ4*AG4/MAX(AH4,$ED$19)) | AL4: =IF(OR(AD4="",AH4="",AJ4=""),"",AJ4/(MAX(AH4,$ED$19)*$ED$3)) | AM4: =IF(OR(AG4="",AH4=""),"",AG4/MAX(AH4,$ED$19)) | AN4: =IF(AH4="","",MAX(AH4,$ED$7)) | EA4: PipTol_Value | EB4: =ROUND($O$18*10000*0.8,0) | EC4: MinStopPips | ED4: 8 | EE4: Long Zone (A+) | EF4: ="Deep A+ long pocket candidate (Tier 3): "&TEXT($EB$53,"0.00000")&" → "&TEXT($EC$53,"0.00000")&". Ladder (upper/mid/deep): "&TEXT($AD$15,"0.00000")&"/"&TEXT($AD$16,"0.00000")&"/"&TEXT($AD$17,"0.00000")&", SL "&TEXT($AF$15,"0.00000")&", TP1 "&TEXT($AE$15,"0.00000")&". Use this only if price flushes into Tier 3 with HTF trend intact and R/room are satisfied." | EH4: CT_TP2 | EI4: =IF($Y$1="SHORT",$Y$3,"")
A5: Current Price | B5: 1.165 | D5: PMH | E5: 1.1808 | G5: 4H FVG high | H5: 1.16139 | J5: Strike 1 | K5: 1.185 | N5: EMA9 15m | O5: ='Advanced Setup Planner'!B6 | S5: 1H | T5: =IF($O$10="","",IF($O$3>$O$10+0.0002,"Bull",IF($O$3<$O$10-0.0002,"Bear","Range"))) | U5: ='Advanced Setup Planner'!C26 | V5: ='Advanced Setup Planner'!D26 | X5: Manual SL override? | EA5: PipTol_Fib | EB5: =ROUND($O$18*10000*0.5,0) | EC5: ATR_StopMult | ED5: 1.5 | EE5: Trend Long Plan | EF5: =IFERROR(IF(AND($EB$23="CoreLong",NOT($EB$25)),"Trend long plan (current tier "&$EB$56&"): ladder at "&TEXT($AD$2,"0.00000")&"/"&TEXT($AD$3,"0.00000")&"/"&TEXT($AD$4,"0.00000")&", SL "&TEXT($AF$2,"0.00000")&", TP1 "&TEXT($AE$2,"0.00000")&". Confirm 15m/1H CHOCH up in this tier, then manage toward TP1 (and potentially PDH/PWH) using the ladder.",""),"") | EH5: CT_Risk$ | EI5: =$Y$2*0.5 | EJ5: =IFERROR(IF(EI9=0,"",(EI1-EI3)*EI9),"")
A6: EMA9 15m | B6: 1.1645 | D6: PML | E6: 1.15889 | G6: 4H FVG low | H6: 1.1605 | J6: Size 1 (bn) | K6: 1.46 | N6: EMA21 15m | O6: ='Advanced Setup Planner'!B7 | S6: 15M | T6: =IF($O$5="","",IF(AND($O$5>$O$6,$O$6>$O$7,$O$7>$O$8),"Bull",IF(AND($O$5<$O$6,$O$6<$O$7,$O$7<$O$8),"Bear","Range"))) | U6: ='Advanced Setup Planner'!C27 | V6: ='Advanced Setup Planner'!D27 | AC6: Avg Pips to SL | AD6: =IF(SUM(AL2:AL4)=0,0,SUMPRODUCT(AN2:AN4,AL2:AL4)/SUM(AL2:AL4)) | EA6: PipTol_Mid | EB6: =ROUND($O$18*10000*1,0) | EC6: ATR15m_pips | ED6: =ROUND($O$18*10000,1) | EH6: CT_PipsSL | EI6: =IF(OR(EI1="",EI2=""),"",ABS((EI1-EI2)*10000))
A7: EMA21 15m | B7: 1.164 | D7: PWH | E7: 1.1789 | G7: Daily FVG high | H7: 1.16734 | J7: Strike 2 | K7: 1.18 | N7: EMA50 15m | O7: ='Advanced Setup Planner'!B8 | X7: Weight 0.382 | Y7: ='Advanced Setup Planner'!K16 | AC7: Total Units | AD7: =SUM(AL2:AL4) | EA7: Long_EMAScore | EB7: =0.25*COUNTIF($O$10:$O$16,"<"&$O$3) | EC7: StopFloorPips | ED7: =MAX(ED4,ROUNDUP(ED6*ED5,0)) | EE7: CT Zone | EF7: =IFERROR(IF(AND($EB$23="CTshort",NOT($EB$25)),"CT short zone: "&TEXT($EB$47,"0.00000")&" → "&TEXT($EB$48,"0.00000")&" (premium liquidity cluster: PMH/PDH/EQH/PWH).",""),"") | EH7: CT_PipsTP | EI7: =IF(OR(EI3="",EI1=""),"",ABS((EI3-EI1)*10000))
A8: EMA50 15m | B8: 1.1635 | D8: PWL | E8: 1.17132 | G8: Daily FVG low | H8: 1.16627 | J8: Size 2 (bn) | K8: 1.136 | N8: SMA200 15m | O8: ='Advanced Setup Planner'!B9 | S8: HTF_Long_OK | T8: =AND(T3="Bull",T4="Bull") | X8: Weight 0.500 | Y8: ='Advanced Setup Planner'!K17 | AC8: Avg Entry | AD8: =IF(AD7=0,"",SUMPRODUCT(AD2:AD4,AL2:AL4)/AD7) | EA8: Short_EMAScore | EB8: =0.25*COUNTIF($O$10:$O$16,">"&$O$3) | EC8: PrimaryRiskMult | ED8: 1 | EE8: CT Short Plan | EF8: =IFERROR(IF(AND($EB$23="CTshort",NOT($EB$25)),"CT short plan: ladder shorts at "&TEXT($EB$48,"0.00000")&"/"&TEXT($EB$49,"0.00000")&"/"&TEXT($EB$47,"0.00000")&", SL "&TEXT($EB$48+0.0008,"0.00000")&", TP1 "&TEXT($EB$35,"0.00000")&IF($EB$32<>""," (golden mid)."," (Tier1 top; no golden overlap).")&" Size small; countertrend — only take on clear exhaustion near PDH/EQH.",""),"") | EH8: CT_Rmult | EI8: =IF(OR(EI6="",EI7="",EI6=0),"",EI7/EI6)
A9: SMA200 15m | B9: 1.16 | D9: PDH | E9: 1.16829 | G9: 1H FVG high | H9: 1.1682 | J9: Strike 3 | K9: 1.165 | S9: HTF_Short_OK | T9: =AND(T3="Bear",T4="Bear") | X9: Weight 0.618 | Y9: ='Advanced Setup Planner'!K18 | AC9: Pips to TP1 | AD9: =IF(OR(AD8="",$Y$3=""),"",ABS(($Y$3-AD8)*10000)) | EA9: Long_RSIScore | EB9: =IF($O$20<45,0.5,0)+IF($O$21<45,0.25,0)+IF($O$17<45,0.25,0) | EC9: APlusRiskMult | ED9: 1 | EH9: CT_Units | EI9: =IF(OR(EI5="",EI6="",EI6=0),"",EI5/(EI6*0.0001))
A10: EMA50 1H | B10: 1.163 | D10: PDL | E10: 1.16427 | G10: 1H FVG low | H10: 1.16779 | J10: Size 3 (bn) | K10: 1.12 | N10: EMA50 1H | O10: ='Advanced Setup Planner'!B10 | S10: LTF_Long_OK | T10: =AND(OR(T5="Bull",T5="Range"),NOT(T6="Bear")) | AC10: Reward at TP1 $ | AD10: =IF(OR(AD7=0,AD8="",$Y$3=""),"",ABS(($Y$3-AD8)*AD7)) | EA10: Short_RSIScore | EB10: =IF($O$20>55,0.5,0)+IF($O$21>55,0.25,0)+IF($O$17>55,0.25,0) | EC10: CTRiskMult | ED10: 0.6 | EE10: Avoid | EF10: =IFERROR(IF($EB$25,"Avoid new trades – R multiple, room, or macro gate not satisfied. Wait for conditions to improve and reassess.",""),"") | EH10: CT_NoTradeFlag | EI10: =NOT($T$11)
A11: EMA50 4H | B11: 1.162 | D11: EQH_above | E11: 1.17025 | J11: Strike 4 | N11: EMA50 4H | O11: ='Advanced Setup Planner'!B11 | S11: LTF_Short_OK | T11: =AND(OR(T5="Bear",T5="Range"),NOT(T6="Bull")) | X11: Ticket Size | Y11: ='Advanced Setup Planner'!K19 | AC11: R multiple at TP1 | AD11: =IF(SUM($AJ$2:$AJ$4)=0,"",SUM($AK$2:$AK$4)/SUM($AJ$2:$AJ$4)) | EA11: Long_StructScore | EB11: =0.25*COUNTIF($T$3:$T$6,"Bull") | EC11: PrimaryWgtSum | ED11: =SUM($AI$2:$AI$4)
A12: EMA50 1D | B12: 1.161 | D12: EQL_below | E12: 1.15919 | J12: Size 4 (bn) | N12: EMA50 1D | O12: ='Advanced Setup Planner'!B12 | X12: Min R (R multiple) | Y12: ='Advanced Setup Planner'!K20 | AC12: Avg Eff Pips to SL | AD12: =IF(SUM(AL2:AL4)=0,"",(AL2*MAX(AH2,$ED$19)+AL3*MAX(AH3,$ED$19)+AL4*MAX(AH4,$ED$19))/SUM(AL2:AL4)) | EA12: Short_StructScore | EB12: =0.25*COUNTIF($T$3:$T$6,"Bear") | EC12: APlusWgtSum | ED12: =SUM($AI$15:$AI$17)
A13: EMA100 1D | B13: 1.159 | D13: LTF Leg Low (15m | E13: 1.16151 | J13: Magnet Range (pips) | K13: 20 | N13: EMA100 1D | O13: ='Advanced Setup Planner'!B13 | EA13: Long_FVGScore | EB13: =MIN(1,IF(ABS(($O$3-$O$36)*10000)<=EB4,1,0)+IF(ABS(($O$3-$O$38)*10000)<=EB4,1,0)+IF(ABS(($O$3-$O$40)*10000)<=EB4,1,0)) | EC13: CTWgtSum | ED13: =SUM($AI$28:$AI$30)
A14: EMA200 1D | B14: 1.145 | D14: LTF Leg High (15m) | E14: 1.18042 | J14: Options Clamp % | K14: 0.3 | N14: EMA200 1D | O14: ='Advanced Setup Planner'!B14 | S14: Liquidity levels | X14: Active Zone | Y14: =IF(AND($O$3>=Z17-$X$20,$O$3<=AA17+$X$20),1,IF(AND($O$3>=Z18-$X$20,$O$3<=AA18+$X$20),2,IF(AND($O$3>=Z19-$X$20,$O$3<=AA19+$X$20),3,""))) | AC14: A+ LADDER | AD14: Entry | AE14: TP | AF14: SL | AG14: Pips to TP1 | AH14: Eff Pips to SL | AI14: Weight | AJ14: Risk $ | AK14: Reward $ | AL14: Units | AM14: R per rung | AN14: =IF(AH15="","",MAX(AH15,$ED$7)) | EA14: Short_FVGScore | EB14: =MIN(1,IF(ABS(($O$3-$O$35)*10000)<=EB4,1,0)+IF(ABS(($O$3-$O$37)*10000)<=EB4,1,0)+IF(ABS(($O$3-$O$39)*10000)<=EB4,1,0)) | EC14: Primary_MinStopPips | ED14: 12
A15: EMA50 1W | B15: 1.14 | D15: Session Low | E15: 1.16182 | J15: Zone tolerance | K15: 0.0002 | N15: EMA50 1W | O15: ='Advanced Setup Planner'!B15 | S15: PMH | T15: ='Advanced Setup Planner'!E5 | X15: =IF(AND($O$3>=Z17-$X$20,$O$3<=AA17+$X$20),1,IF(AND($O$3>=Z18-$X$20,$O$3<=AA18+$X$20),2,IF(AND($O$3>=Z19-$X$20,$O$3<=AA19+$X$20),3,0))) | AC15: upper rung | AD15: =IF($Y$1<>"LONG","",$O$35) | AE15: =IF(AD15="","",$ED$41) | AF15: =IF(AD15="","",$ED$30) | AG15: =IF(OR(AD15="",AE15=""),"",ABS((AE15-AD15)*10000)) | AH15: =IF(OR(AD15="",AF15=""),"",MAX(ABS((AD15-AF15)*10000),$ED$20)) | AI15: 0.4 | AJ15: =IF(OR(AI15=0,$ED$12=0,AD15=""),"",$Y$2*$ED$9*AI15/$ED$12) | AK15: =IF(OR(AJ15="",AJ15=0,AG15=""),"",AJ15*AG15/MAX(AH15,$ED$20)) | AL15: =IF(OR(AD15="",AH15="",AJ15=""),"",AJ15/(MAX(AH15,$ED$20)*$ED$3)) | AM15: =IF(OR(AG15="",AH15=""),"",AG15/MAX(AH15,$ED$20)) | AN15: =IF(AH16="","",MAX(AH16,$ED$7)) | EA15: LongScore | EB15: =IFERROR((1-$T$37*$T$36)*(EB7+EB9+EB11+EB13+EB42),"") | EC15: APlus_MinStopPips | ED15: 8
A16: EMA20 1M | B16: 1.166 | D16: Session High | E16: 1.1682 | J16: Weight 0.382 | K16: 0.2 | N16: EMA20 1M | O16: ='Advanced Setup Planner'!B16 | S16: PML | T16: ='Advanced Setup Planner'!E6 | X16: Zone | Y16: Role | Z16: Low | AA16: High | AC16: middle rung | AD16: =IF($Y$1<>"LONG","",$O$36) | AE16: =IF(AD16="","",$ED$41) | AF16: =IF(AD16="","",$ED$30) | AG16: =IF(OR(AD16="",AE16=""),"",ABS((AE16-AD16)*10000)) | AH16: =IF(OR(AD16="",AF16=""),"",MAX(ABS((AD16-AF16)*10000),$ED$20)) | AI16: 0.5 | AJ16: =IF(OR(AI16=0,$ED$12=0,AD16=""),"",$Y$2*$ED$9*AI16/$ED$12) | AK16: =IF(OR(AJ16="",AJ16=0,AG16=""),"",AJ16*AG16/MAX(AH16,$ED$20)) | AL16: =IF(OR(AD16="",AH16="",AJ16=""),"",AJ16/(MAX(AH16,$ED$20)*$ED$3)) | AM16: =IF(OR(AG16="",AH16=""),"",AG16/MAX(AH16,$ED$20)) | AN16: =IF(AH17="","",MAX(AH17,$ED$7)) | EA16: ShortScore | EB16: =IFERROR((1-$T$37*$T$36)*(EB8+EB10+EB12+EB14+EB42),"") | EC16: CT_MinStopPips | ED16: 8
A17: RSI 15M | B17: 58 | D17: HTF Swing Low (4H) | E17: 1.14931 | J17: Weight 0.500 | K17: 0.35 | N17: RSI 4HR | O17: ='Advanced Setup Planner'!B19 | S17: PWH | T17: ='Advanced Setup Planner'!E7 | X17: 1 | Y17: Shallow | Z17: =MIN($Q$24,$Q$23) | AA17: =MAX($Q$24,$Q$23) | AC17: deep rung | AD17: =IF($Y$1<>"LONG","",$O$38+$ED$29) | AE17: =IF(AD17="","",$ED$41) | AF17: =IF(AD17="","",$ED$30) | AG17: =IF(OR(AD16="",AE16=""),"",ABS((AE16-AD16)*10000)) | AH17: =IF(OR(AD17="",AF17=""),"",MAX(ABS((AD17-AF17)*10000),$ED$20)) | AI17: 0.6 | AJ17: =IF(OR(AI17=0,$ED$12=0,AD17=""),"",$Y$2*$ED$9*AI17/$ED$12) | AK17: =IF(OR(AJ17="",AJ17=0,AG17=""),"",AJ17*AG17/MAX(AH17,$ED$20)) | AL17: =IF(OR(AD17="",AH17="",AJ17=""),"",AJ17/(MAX(AH17,$ED$20)*$ED$3)) | AM17: =IF(OR(AG17="",AH17=""),"",AG17/MAX(AH17,$ED$20)) | EA17: MaxScore | EB17: =0.25*COUNTA($O$10:$O$16)+3.5 | EC17: WinProb | ED17: Expected_R | EE17: Expected_$
A18: RSI 1H | B18: 0.00047 | D18: HTF Swing High (4H) | E18: 1.18042 | J18: Weight 0.618 | K18: 0.45 | N18: ATR(14) 15m | O18: ='Advanced Setup Planner'!B20 | S18: PWL | T18: ='Advanced Setup Planner'!E8 | X18: 2 | Y18: Main | Z18: =MIN(Q25,Q24) | AA18: =MAX(Q25,Q24) | EA18: LongScore_pct | EB18: =IFERROR(IF(EB17=0,"",EB15/EB17),"") | EC18: =IF($Y$1<>"LONG","",MIN(0.8,0.4+0.4*IFERROR(EB18,0)+0.1*IFERROR(EB42,0))) | ED18: =IF($Y$1="","",IF($Y$1="LONG",IF(OR(EC18="",EB20=""),"",EC18*EB20-(1-EC18)*1),IF(OR(EC19="",EB20=""),"",EC19*EB20-(1-EC19)*1))) | EE18: =IF(ED18="","",ED18*$Y$2)
A19: RSI 4HR | B19: 0.00088 | J19: Ticket Size | K19: 0 | N19: ADR(14) | O19: ='Advanced Setup Planner'!B21 | S19: PDH | T19: ='Advanced Setup Planner'!E9 | X19: 3 | Y19: HTF | Z19: =MIN(Q31,Q29) | AA19: =MAX(Q31,Q29) | AC19: Avg Pips to SL | AD19: =IF(SUM(AL15:AL17)=0,0,SUMPRODUCT(AN14:AN16,AL15:AL17)/SUM(AL15:AL17)) | EA19: ShortScore_pct | EB19: =IFERROR(IF(EB17=0,"",EB16/EB17),"") | EC19: Primary_StopFloorPips | ED19: =MAX(ED14,ROUNDUP(ED6*ED5,0))
A20: ATR(14) 15m | B20: 55 | J20: Min R (R multiple) | K20: 3 | N20: RSI 15M | O20: ='Advanced Setup Planner'!B17 | S20: PDL | T20: ='Advanced Setup Planner'!E10 | W20: Zone tolerance | X20: ='Advanced Setup Planner'!K15 | AC20: Total Units | AD20: =SUM(AL15:AL17) | EB20: =IF(OR($EB$55=0,$AD$7<=0,$AD$12=""),"",$AD$12) | EC20: APlus_StopFloorPips | ED20: =MAX(ED15,ROUNDUP(ED6*ED5,0))
A21: ADR(14) | B21: 52 | N21: RSI 1H | O21: ='Advanced Setup Planner'!B18 | S21: EQH_above | T21: ='Advanced Setup Planner'!E11 | X21: zone-specific fibs for SL/entries | AC21: Avg Entry | AD21: =IF(AD20=0,"",SUMPRODUCT(AD15:AD17,AL15:AL17)/AD20) | EA21: Trend Mode | EB21: =IF($Y$1="","No bias",IF($Y$1="LONG",IF($T$8,"Trend-aligned","Counter-trend"),IF($Y$1="SHORT",IF($T$9,"Trend-aligned","Counter-trend"),"No bias"))) | EC21: CT_StopFloorPips | ED21: =MAX(ED16,ROUNDUP(ED6*ED5,0))
A22: Structure (SMC) – D1 / 4H / 1H / 15m | N22: Legs (Intraday / Session / HTF) | Q22: Fib outputs | S22: EQL_below | T22: ='Advanced Setup Planner'!E12 | X22: Zone_618 | Y22: =IF($Y$1="LONG",$EB$30,"") | AC22: Pips to TP1 | AD22: =IF(OR(AD21="",$Y$3=""),"",ABS(($Y$3-AD21)*10000)) | EA22: Setup Type | EB22: =IF(AND(T3="Bull",T4="Bull",T5="Bear",T6="Bear"),"Trend Pullback","Mixed") | EC22: CT_ActiveWgtSum | ED22: =SUMPRODUCT(($AD$28:$AD$30<>"")*($AI$28:$AI$30))
A23: TF | B23: Trend (auto) | C23: Last BOS (manual) | D23: Last CHOCH (manual) | N23: LTF Leg Low (15m | O23: ='Advanced Setup Planner'!E13 | P23: L1 0.382 | Q23: =IF($Y$1="SHORT",$O$23+($O$24-$O$23)*0.382,$O$24-($O$24-$O$23)*0.382) | S23: Distances to nearest liquidity | X23: Zone_500 | Y23: =IF($Y$1="SHORT",$EB$31,"") | AC23: Reward at TP1 $ | AD23: =IF(OR(AD20=0,AD21="",$Y$3=""),"",ABS(($Y$3-AD21)*AD20)) | EA23: TradeMode | EB23: =IFERROR(IF(EE52,"CoreLong",IF(EE53,"CTshort","Avoid")),"") | EC23: CT_ATRMult | ED23: 1.5
A24: 1D | B24: ='Advanced Setup Planner'!T3 | C24: Down | D24: Down | N24: LTF Leg High (15m) | O24: ='Advanced Setup Planner'!E14 | P24: L1 0.500 | Q24: =IF($Y$1="SHORT",$O$23+($O$24-$O$23)*0.5,$O$24-($O$24-$O$23)*0.5) | S24: Dist_Above (pips) | T24: =MIN(IF(T15>$O$3,ABS((T15-$O$3)*10000),1000000000),IF(T17>$O$3,ABS((T17-$O$3)*10000),1000000000),IF(T19>$O$3,ABS((T19-$O$3)*10000),1000000000),IF(T21>$O$3,ABS((T21-$O$3)*10000),1000000000)) | AC24: R multiple at TP1 | AD24: =IF(SUM($AJ$15:$AJ$17)=0,"",SUM($AK$15:$AK$17)/SUM($AJ$15:$AJ$17)) | EA24: Grade | EB24: =IF($Y$1="","N/A",IF($EB$25,"B",IF(EB34<0.4,"B",IF(EB18>=0.7,"A+",IF(EB18>=0.4,"B","C"))))) | EC24: CT_RangePips | ED24: =MAX(6,ROUND($O$18*10000*$ED$23,0))
A25: 4H | B25: ='Advanced Setup Planner'!T4 | C25: Down | D25: Down | P25: L1 0.618 | Q25: =IF($Y$1="SHORT",$O$23+($O$24-$O$23)*0.618,$O$24-($O$24-$O$23)*0.618) | S25: Dist_Below (pips) | T25: =MIN(IF(T16<$O$3,ABS((T16-$O$3)*10000),1000000000),IF(T18<$O$3,ABS((T18-$O$3)*10000),1000000000),IF(T20<$O$3,ABS((T20-$O$3)*10000),1000000000),IF(T22<$O$3,ABS((T22-$O$3)*10000),1000000000)) | AC25: Avg Eff Pips to SL | AD25: =IF(SUM(AL15:AL17)=0,"",(AL15*MAX(AH15,$ED$20)+AL16*MAX(AH16,$ED$20)+AL17*MAX(AH17,$ED$20))/SUM(AL15:AL17)) | EA25: NoTradeFlag | EB25: =IFERROR(OR($Y$1="",AND(EB23="CoreLong",OR(EE48=FALSE,$AD$12="",$AD$12<$Y$12)),AND(EB23="CTshort",OR(EE49=FALSE,$O$21<=65)),FALSE),"") | ED25: =IF($Y$1="LONG",IF(OR($ED$58,$O$3>$T$19),MAX($O$27,$O$24),$T$19),IF($Y$1="SHORT",IF(OR($ED$58,$O$3<$T$20),MIN($O$26,$O$23),$T$20),""))
A26: 1H | B26: ='Advanced Setup Planner'!T5 | C26: Down | D26: Down | N26: Session Low | O26: ='Advanced Setup Planner'!E15 | P26: L2 0.382 | Q26: =IF($Y$1="SHORT",$O$26+($O$27-$O$26)*0.382,$O$27-($O$27-$O$26)*0.382) | AN26: =IF(AH28="","",MAX(AH28,$ED$7)) | EA26: MasterSignal | EB26: =IF($Y$1="","NO SIDE – neither core long nor CT short setup is active.",IF(EB23="CoreLong",IF(EB25,"AVOID CORE LONG – not in discount or 3R not available.","CORE LONG SETUP – buy dip in active tier. Ladder entries "&TEXT($AD$2,"0.00000")&"/"&TEXT($AD$3,"0.00000")&"/"&TEXT($AD$4,"0.00000")&", SL "&TEXT($AF$2,"0.00000")&", TP1 "&TEXT($Y$3,"0.00000")&"."),IF(EB23="CTshort",IF(EB25,"AVOID CT SHORT – conditions for scalp fade not met.","OPTIONAL CT SHORT – scalp fade only. Short zone near PDH/CT highs; see CT ladder for entries, SL and TPs."),"AVOID – nothing to do here. Stand aside and wait for either discount buy or CT fade zone."))) | ED26: =IF($Y$1="LONG",IF(MAX($O$27,$O$24)>0,MAX($O$27,$O$24),$T$19),IF($Y$1="SHORT",IF(MIN($O$26,$O$23)>0,MIN($O$26,$O$23),$T$20),""))
A27: 15M | B27: ='Advanced Setup Planner'!T6 | C27: Down | D27: Down | N27: Session High | O27: ='Advanced Setup Planner'!E16 | P27: L2 0.500 | Q27: =IF($Y$1="SHORT",$O$26+($O$27-$O$26)*0.5,$O$27-($O$27-$O$26)*0.5) | S27: Long_RoomOK | T27: =IF($AD$6="",FALSE,$T$24>=3*$AD$6) | AC27: CT LADDER | AD27: Entry | AE27: TP | AF27: SL | AG27: Pips to TP1 | AH27: Eff Pips to SL | AI27: Weight | AJ27: Risk $ | AK27: Reward $ | AL27: Units | AM27: R per rung | AN27: =IF(AH29="","",MAX(AH29,$ED$7)) | EA27: Setup Summary | EB27: =IFERROR(IF(EB23="CoreLong",IF(EB25,"NO CORE LONG – wait for proper discount and 3R.","CORE LONG OK – follow MasterSignal & Trade Plan."),IF(EB23="CTshort",IF(EB25,"NO CT SHORT – CT scalp conditions incomplete.","CT SHORT OK – scalp only, log as counter-trend."),"NO TRADE – neither core nor CT setup active.")),"") | EC27: Primary_SL_Cont | ED27: =$O$40-$ED$28
P28: L2 0.618 | Q28: =IF($Y$1="SHORT",$O$26+($O$27-$O$26)*0.618,$O$27-($O$27-$O$26)*0.618) | S28: Short_RoomOK | T28: =IF(AD6="",FALSE,T25>=3*AD6) | AC28: deep rung | AD28: =IF(EB48="","",EB48) | AE28: =IF(AD28="","",IFERROR(_xlfn.AGGREGATE(14,6,CHOOSE({1,2,3,4},'Advanced Setup Planner'!$E$12,'Advanced Setup Planner'!$E$10,'Advanced Setup Planner'!$E$15,'Advanced Setup Planner'!$H$10)/(CHOOSE({1,2,3,4},'Advanced Setup Planner'!$E$12,'Advanced Setup Planner'!$E$10,'Advanced Setup Planner'!$E$15,'Advanced Setup Planner'!$H$10)<AD28),1)-$ED$3,AD28-($ED$24*$ED$3))) | AF28: =IF(AD30="","",AD30+0.0008) | AG28: =IF(OR(AD28="",AE28=""),"",ABS((AE28-AD28)*10000)) | AH28: =IF(OR(AD28="",AF28=""),"",MAX(ABS((AD28-AF28)*10000),$ED$21)) | AI28: 0.45 | AJ28: =IF(OR(AI28=0,$ED$22=0,AD28=""),"",$Y$2*$ED$10*AI28/$ED$22) | AK28: =IF(OR(AJ28="",AJ28=0,AG28=""),"",AJ28*AG28/MAX(AH28,$ED$21)) | AL28: =IF(OR(AD28="",AH28="",AJ28=""),"",AJ28/(MAX(AH28,$ED$21)*$ED$3)) | AM28: =IF(OR(AG28="",AH28=""),"",AG28/MAX(AH28,$ED$21)) | AN28: =IF(AH30="","",MAX(AH30,$ED$7)) | EA28: Trade Plan | EB28: =IFERROR(IF(EB25,"Stand aside or observation-only. Location: "&EE54&".",IF(EB23="CoreLong","CORE LONG EXECUTION – Mode: "&EB21&", Grade: "&EB24&". Bias: LONG (trend/macro). Buy active tier with ladder "&TEXT($AD$2,"0.00000")&"/"&TEXT($AD$3,"0.00000")&"/"&TEXT($AD$4,"0.00000")&". SL "&TEXT($AF$2,"0.00000")&". TP1 "&TEXT($Y$3,"0.00000")&".","CT SHORT EXECUTION – Counter-trend scalp. Short near PDH/CT zone. Use CT ladder for entries with reduced risk (0.25–0.5R). Stop above 1.1725–1.1730; TP1 back into 1.1670–1.1660, TP2 into 1.1645–1.1635.")),"") | EC28: Primary_SL_Buffer | ED28: =MAX(0.00025,$O$18*0.5)
N29: HTF Swing Low (4H) | O29: ='Advanced Setup Planner'!E17 | P29: L3 0.382 | Q29: =IF($Y$1="SHORT",$O$29+($O$30-$O$29)*0.382,$O$30-($O$30-$O$29)*0.382) | S29: Strike 1 | T29: ='Advanced Setup Planner'!K5 | U29: Size 1 (bn) | V29: ='Advanced Setup Planner'!K6 | W29: =IF(T29="","",ABS(T29-$O$3)) | AC29: middle rung | AD29: =IF(EB49="","",EB49) | AE29: =IF(AD29="","",IFERROR(_xlfn.AGGREGATE(14,6,CHOOSE({1,2,3,4},'Advanced Setup Planner'!$E$12,'Advanced Setup Planner'!$E$10,'Advanced Setup Planner'!$E$15,'Advanced Setup Planner'!$H$10)/(CHOOSE({1,2,3,4},'Advanced Setup Planner'!$E$12,'Advanced Setup Planner'!$E$10,'Advanced Setup Planner'!$E$15,'Advanced Setup Planner'!$H$10)<AD29),1)-$ED$3,AD29-($ED$24*$ED$3))) | AF29: =AF28 | AG29: =IF(OR(AD29="",AE29=""),"",ABS((AE29-AD29)*10000)) | AH29: =IF(OR(AD29="",AF29=""),"",MAX(ABS((AD29-AF29)*10000),$ED$21)) | AI29: 0.35 | AJ29: =IF(OR(AI29=0,$ED$22=0,AD29=""),"",$Y$2*$ED$10*AI29/$ED$22) | AK29: =IF(OR(AJ29="",AJ29=0,AG29=""),"",AJ29*AG29/MAX(AH29,$ED$21)) | AL29: =IF(OR(AD29="",AH29="",AJ29=""),"",AJ29/(MAX(AH29,$ED$21)*$ED$3)) | AM29: =IF(OR(AG29="",AH29=""),"",AG29/MAX(AH29,$ED$21)) | EA29: Go/No-Go | EB29: =IF($Y$1="","NO SETUP",IF(EB25,"NO TRADE – "&EE54,IF(EB23="CoreLong","GO (CORE LONG) – trend/macro aligned.","GO (CT SCALP) – small risk only."))) | EC29: Aplus_SL_Buffer | ED29: =MAX(0.00025,$O$18*0.5)
A30: Outputs (auto) | N30: HTF Swing High (4H) | O30: ='Advanced Setup Planner'!E18 | P30: L3 0.500 | Q30: =IF($Y$1="SHORT",$O$29+($O$30-$O$29)*0.5,$O$30-($O$30-$O$29)*0.5) | S30: Strike 2 | T30: ='Advanced Setup Planner'!K7 | U30: Size 2 (bn) | V30: ='Advanced Setup Planner'!K8 | W30: =IF(T30="","",ABS(T30-$O$3)) | AC30: shallow rung | AD30: =IF(EB47="","",EB47) | AE30: =IF(AD30="","",IFERROR(_xlfn.AGGREGATE(14,6,CHOOSE({1,2,3,4},'Advanced Setup Planner'!$E$12,'Advanced Setup Planner'!$E$10,'Advanced Setup Planner'!$E$15,'Advanced Setup Planner'!$H$10)/(CHOOSE({1,2,3,4},'Advanced Setup Planner'!$E$12,'Advanced Setup Planner'!$E$10,'Advanced Setup Planner'!$E$15,'Advanced Setup Planner'!$H$10)<AD30),1)-$ED$3,AD30-($ED$24*$ED$3))) | AF30: =AF28 | AG30: =IF(OR(AD30="",AE30=""),"",ABS((AE30-AD30)*10000)) | AH30: =IF(OR(AD30="",AF30=""),"",MAX(ABS((AD30-AF30)*10000),$ED$21)) | AI30: 0.2 | AJ30: =IF(OR(AI30=0,$ED$22=0,AD30=""),"",$Y$2*$ED$10*AI30/$ED$22) | AK30: =IF(OR(AJ30="",AJ30=0,AG30=""),"",AJ30*AG30/MAX(AH30,$ED$21)) | AL30: =IF(OR(AD30="",AH30="",AJ30=""),"",AJ30/(MAX(AH30,$ED$21)*$ED$3)) | AM30: =IF(OR(AG30="",AH30=""),"",AG30/MAX(AH30,$ED$21)) | EA30: Golden_Low (Overlap L1/L3) | EB30: =IF(OR($Q$23="",$Q$25="",$Q$29="",$Q$31=""),"",MAX(MIN($Q$23,$Q$25),MIN($Q$29,$Q$31))) | EC30: Aplus_SL | ED30: =$O$38-$ED$29
A31: Side (LONG/SHORT) | B31: ='Advanced Setup Planner'!Y1 | P31: L3 0.618 | Q31: =IF($Y$1="SHORT",$O$29+($O$30-$O$29)*0.618,$O$30-($O$30-$O$29)*0.618) | S31: Strike 3 | T31: ='Advanced Setup Planner'!K9 | U31: Size 3 (bn) | V31: ='Advanced Setup Planner'!K10 | W31: =IF(T31="","",ABS(T31-$O$3)) | EA31: Golden_High (Overlap L1/L3) | EB31: =IF(OR($Q$23="",$Q$25="",$Q$29="",$Q$31=""),"",MIN(MAX($Q$23,$Q$25),MAX($Q$29,$Q$31))) | EC31: (Pips_to_Entry_500) | ED31: =IF(AD3="","",($O$3-AD3)*10000)
A32: Setup Summary | B32: =IFERROR(IF('Advanced Setup Planner'!EB18="","",TEXT('Advanced Setup Planner'!EB18,"0%")&" ("&Backend!B83&") — "&Backend!B84),"") | S32: Strike 4 | U32: Size 4 (bn) | W32: =IF(T32="","",ABS(T32-$O$3)) | AC32: Avg Pips to SL | AD32: =IF(SUM(AL28:AL30)=0,0,SUMPRODUCT(AN26:AN28,AL28:AL30)/SUM(AL28:AL30)) | EA32: Golden_Mid | EB32: =IF(OR(EB30="",EB31="",EB30>EB31),"",(EB30+EB31)/2) | EC32: (Pips_to_Entry_618) | ED32: =IF(AD4="","",($O$3-AD4)*10000) | EE32: =IF($Y$1<>"LONG","","Dist to entries (pips): 0.382="&TEXT(ED30,"0.0")&", 0.5="&TEXT(ED31,"0.0")&", 0.618="&TEXT(ED32,"0.0"))
A33: Trade Mode | B33: ='Advanced Setup Planner'!EB23 | S33: Magnet Strike | T33: =IF(COUNTA(T29:T32)=0,"",INDEX(T29:T32,MATCH(MIN(W29:W32),W29:W32,0))) | AC33: Total Units | AD33: =SUM(AL28:AL30) | EA33: In_GoldenPocket_Flag | EB33: =IF(OR(EB30="",EB31="",EB30>EB31),FALSE,AND($O$3>=EB30,$O$3<=EB31)) | EC33: ValueRiskMult | ED33: 1
A34: Macro Bias (EURUSD) | B34: =IFERROR(Backend!B338,"") | N34: FVGs (4H / Daily / 1H) | S34: Magnet Range (pips) | T34: ='Advanced Setup Planner'!K13 | AC34: Avg Entry | AD34: =IF(AD33=0,"",SUMPRODUCT(AD28:AD30,AL28:AL30)/AD33) | EA34: GoldenProx_Score | EB34: =IF(OR(EB30="",EB31="",EB30>EB31),0,IF(OR($O$3<EB30,$O$3>EB31),0,MAX(0,1-(ABS($O$3-EB32)/((EB31-EB30)/2))))) | EC34: Value_MinStopPips | ED34: 10
A35: Rate diff (NOW) | B35: =IF(Backend!B86="","",TEXT(Backend!B86,"0.00")&" ("&Backend!B90&")") | N35: 4H FVG high | O35: ='Advanced Setup Planner'!H5 | S35: Distance to Magnet (pips) | T35: =IF(T33="","",ABS((T33-$O$3)*10000)) | AC35: Pips to TP1 | AD35: =IF(OR(AD34="",$AE$28=""),"",ABS(($AE$28-AD34)*10000)) | EA35: CT_TP1 (magnet below entry) | EB35: =IF($Y$1<>"SHORT","",IF(COUNT($AD$28:$AD$30)=0,"",IF(MAX(IF('Advanced Setup Planner'!$E$12<$EB$46,'Advanced Setup Planner'!$E$12,0),IF('Advanced Setup Planner'!$E$10<$EB$46,'Advanced Setup Planner'!$E$10,0),IF('Advanced Setup Planner'!$H$10<$EB$46,'Advanced Setup Planner'!$H$10,0))=0,$EB$46-MAX($X$20,$ED$24*$ED$3),MAX(IF('Advanced Setup Planner'!$E$12<$EB$46,'Advanced Setup Planner'!$E$12,0),IF('Advanced Setup Planner'!$E$10<$EB$46,'Advanced Setup Planner'!$E$10,0),IF('Advanced Setup Planner'!$H$10<$EB$46,'Advanced Setup Planner'!$H$10,0))))) | EC35: Value_StopFloorPips | ED35: =MAX($ED$34,ROUNDUP($ED$6*$ED$5,0))
A36: Rate diff change (6M vs NOW) | B36: =IF(Backend!B88="","",TEXT(Backend!B88,"0")&" steps (~"&TEXT(Backend!B89,"0")&"bp) — "&Backend!B91) | N36: 4H FVG low | O36: ='Advanced Setup Planner'!H6 | S36: Within Magnet? 0/1 | T36: =IF(AND(T33<>"",T35<=T34),1,0) | AC36: Reward at TP1 $ | AD36: =IF(OR(AD33=0,AD34="",$AE$28=""),"",ABS(($AE$28-AD34)*AD33)) | EC36: Value_SL_Buffer | ED36: =MAX(0.00025,$O$18*0.5,$ED$34*$ED$3)
A37: Yield Narrative | B37: =Backend!B356 | N37: Daily FVG high | O37: ='Advanced Setup Planner'!H7 | S37: Options Clamp % | T37: ='Advanced Setup Planner'!K14 | AC37: R multiple at TP1 | AD37: =IF(SUM($AJ$28:$AJ$30)=0,"",SUM($AK$28:$AK$30)/SUM($AJ$28:$AJ$30)) | EA37: MacroBiasScore | EB37: =IFERROR(Backend!$B$338,"") | EC37: Value_SL | ED37: =$O$40-$ED$36
A38: Narrative (plain English) | B38: =IFERROR(Backend!B110,"") | N38: Daily FVG low | O38: ='Advanced Setup Planner'!H8 | AC38: Avg Eff Pips to SL | AD38: =IF(SUM(AL28:AL30)=0,"",(AL28*MAX(AH28,$ED$21)+AL29*MAX(AH29,$ED$21)+AL30*MAX(AH30,$ED$21))/SUM(AL28:AL30)) | EA38: MacroBias_Direction | EB38: =IFERROR(IF(EB37="Buy dips",1,IF(EB37="Sell rallies",-1,0)),"") | EC38: ValueWgtSum | ED38: =SUM($AI$42:$AI$44)
A39: Action (what to do) | B39: =Backend!B112 | N39: 1H FVG high | O39: ='Advanced Setup Planner'!H9 | EA39: MacroToneAdj | EB39: =IF(Backend!$B$350>0.3,-0.5,IF(Backend!$B$350<-0.3,0.5,0)) | ED39: 8
A40: Notes | B40: =Backend!B114 | N40: 1H FVG low | O40: ='Advanced Setup Planner'!H10 | EA40: MacroPolicyAdj | EB40: =IF(Backend!$B$347<=-2,0.5,IF(Backend!$B$347>=2,-0.5,0)) | ED40: =MAX($O$27,$T$19,$T$17)+$ED$39*$ED$3
A41: Definitions | B41: =IF(B40="","",IF(B40="Aligned","Trade direction matches macro bias.","Macro bias disagrees — reduce size or demand stronger technical confirmation.")) | AC41: VALUE LADDER | AD41: Entry | AE41: TP | AF41: SL | AG41: Pips to TP1 | AH41: Eff Pips to SL | AI41: Weight | AJ41: Risk $ | AK41: Reward $ | AL41: Units | AM41: R per rung | AN41: =IF(AH42="","",MAX(AH42,$ED$7)) | EA41: Macro_TotalBias | EB41: =MAX(-1,MIN(1,EB38+EB39+EB40)) | ED41: =IF($Y$1<>"LONG","",MIN(IF($T$17>$O$3,$T$17,10^6),IF($T$19>$O$3,$T$19,10^6),IF($O$27>$O$3,$O$27,10^6)))
A42: Execution ladders (auto from Planner_v2) | AC42: Entry SMA200 | AD42: =IF($Y$1<>"LONG","",IF($O$8<=$O$3,$O$8,"")) | AE42: =IF(AD42="","",$ED$41) | AF42: =IF(AD42="","",$ED$37) | AG42: =IF(OR(AD42="",AE42=""),"",ABS((AE42-AD42)*10000)) | AH42: =IF(OR(AD42="",AF42=""),"",MAX(ABS((AD42-AF42)*10000),$ED$35)) | AI42: 0.35 | AJ42: =IF(OR(AI42=0,$ED$38=0,AD42=""),"",$Y$2*$ED$33*AI42/$ED$38) | AK42: =IF(OR(AJ42="",AJ42=0,AG42=""),"",AJ42*AG42/MAX(AH42,$ED$35)) | AL42: =IF(OR(AD42="",AH42="",AJ42=""),"",AJ42/(MAX(AH42,$ED$35)*$ED$3)) | AM42: =IF(OR(AG42="",AH42=""),"",AG42/MAX(AH42,$ED$35)) | AN42: =IF(AH43="","",MAX(AH43,$ED$7)) | EA42: MacroBiasScore | EB42: =0.5*EB41
A43: Primary Ladder (Shallow / Continuation) | AC43: Entry EMA50_1H | AD43: =IF($Y$1<>"LONG","",IF($O$10<=$O$3,$O$10,"")) | AE43: =IF(AD43="","",$ED$41) | AF43: =IF(AD43="","",$ED$37) | AG43: =IF(OR(AD43="",AE43=""),"",ABS((AE43-AD43)*10000)) | AH43: =IF(OR(AD43="",AF43=""),"",MAX(ABS((AD43-AF43)*10000),$ED$35)) | AI43: 0.4 | AJ43: =IF(OR(AI43=0,$ED$38=0,AD43=""),"",$Y$2*$ED$33*AI43/$ED$38) | AK43: =IF(OR(AJ43="",AJ43=0,AG43=""),"",AJ43*AG43/MAX(AH43,$ED$35)) | AL43: =IF(OR(AD43="",AH43="",AJ43=""),"",AJ43/(MAX(AH43,$ED$35)*$ED$3)) | AM43: =IF(OR(AG43="",AH43=""),"",AG43/MAX(AH43,$ED$35)) | AN43: =IF(AH44="","",MAX(AH44,$ED$7))
A44: Rung | B44: Entry | C44: TP | D44: SL | E44: Pips→TP | F44: EffPips→SL | G44: Units | H44: Risk $ | I44: Reward $ | J44: R | K44: R2 | AC44: Entry 1H_FVG_L | AD44: =IF($Y$1<>"LONG","",IF($O$40<=$O$3,$O$40,"")) | AE44: =IF(AD44="","",$ED$41) | AF44: =IF(AD44="","",$ED$37) | AG44: =IF(OR(AD44="",AE44=""),"",ABS((AE44-AD44)*10000)) | AH44: =IF(OR(AD44="",AF44=""),"",MAX(ABS((AD44-AF44)*10000),$ED$35)) | AI44: 0.25 | AJ44: =IF(OR(AI44=0,$ED$38=0,AD44=""),"",$Y$2*$ED$33*AI44/$ED$38) | AK44: =IF(OR(AJ44="",AJ44=0,AG44=""),"",AJ44*AG44/MAX(AH44,$ED$35)) | AL44: =IF(OR(AD44="",AH44="",AJ44=""),"",AJ44/(MAX(AH44,$ED$35)*$ED$3)) | AM44: =IF(OR(AG44="",AH44=""),"",AG44/MAX(AH44,$ED$35))
A45: Shallow | B45: ='Advanced Setup Planner'!AD2 | C45: ='Advanced Setup Planner'!AE2 | D45: ='Advanced Setup Planner'!AF2 | E45: ='Advanced Setup Planner'!AG2 | F45: ='Advanced Setup Planner'!AH2 | G45: ='Advanced Setup Planner'!AL2 | H45: ='Advanced Setup Planner'!AJ2 | I45: ='Advanced Setup Planner'!AK2 | J45: ='Advanced Setup Planner'!AM2 | K45: ='Advanced Setup Planner'!AM2 | ED45: In_Tier1 | EE45: =AND($O$3>=EB51,$O$3<=EC51)
A46: Mid | B46: ='Advanced Setup Planner'!AD3 | C46: ='Advanced Setup Planner'!AE3 | D46: ='Advanced Setup Planner'!AF3 | E46: ='Advanced Setup Planner'!AG3 | F46: ='Advanced Setup Planner'!AH3 | G46: ='Advanced Setup Planner'!AL3 | H46: ='Advanced Setup Planner'!AJ3 | I46: ='Advanced Setup Planner'!AK3 | J46: ='Advanced Setup Planner'!AM3 | K46: ='Advanced Setup Planner'!AM3 | AC46: Avg Pips to SL | AD46: =IF(SUM(AL42:AL44)=0,0,SUMPRODUCT(AN41:AN43,AL42:AL44)/SUM(AL42:AL44)) | EA46: CT_MinEntry | EB46: =MIN(IF($AD$28="",1000000000,$AD$28),IF($AD$29="",1000000000,$AD$29),IF($AD$30="",1000000000,$AD$30)) | ED46: In_Tier2 | EE46: =AND($O$3>=EB52,$O$3<=EC52)
A47: Deep | B47: ='Advanced Setup Planner'!AD4 | C47: ='Advanced Setup Planner'!AE4 | D47: ='Advanced Setup Planner'!AF4 | E47: ='Advanced Setup Planner'!AG4 | F47: ='Advanced Setup Planner'!AH4 | G47: ='Advanced Setup Planner'!AL4 | H47: ='Advanced Setup Planner'!AJ4 | I47: ='Advanced Setup Planner'!AK4 | J47: ='Advanced Setup Planner'!AM4 | K47: ='Advanced Setup Planner'!AM4 | AC47: Total Units | AD47: =SUM(AL42:AL44) | EA47: CT_Low | EB47: =IF(EB48="","",EB48+($ED$24*$ED$3)) | ED47: In_Tier3 | EE47: =IF('Advanced Setup Planner'!$E$7>$O$3,'Advanced Setup Planner'!$E$7,"")
A48: Total | B48: =IFERROR(SUBTOTAL(101,Table16[Entry]),"") | C48: =IFERROR(SUBTOTAL(101,Table16[TP]),"") | D48: =IFERROR(SUBTOTAL(101,Table16[SL]),"") | E48: =IFERROR(SUBTOTAL(101,Table16[Pips→TP]),"") | F48: =IFERROR(SUBTOTAL(101,Table16[EffPips→SL]),"") | G48: =SUBTOTAL(109,Table16[Units]) | H48: =SUBTOTAL(109,Table16[Risk $]) | I48: =SUBTOTAL(109,Table16[Reward $]) | J48: =IFERROR(Table16[[#Totals],[Reward $]]/Table16[[#Totals],[Risk $]],"") | AC48: Avg Entry | AD48: =IF(AD47=0,"",SUMPRODUCT(AD42:AD44,AL42:AL44)/AD47) | EA48: CT_High | EB48: =IF(EE51="","",EE51+$X$20) | ED48: In_Discount | EE48: =IF('Advanced Setup Planner'!$E$9>$O$3,'Advanced Setup Planner'!$E$9,"")
AC49: Pips to TP1 | AD49: =IF(OR(AD48="",$Y$3=""),"",ABS(($Y$3-AD48)*10000)) | EA49: CT_Mid | EB49: =IF(EB48="","",EB48+((($ED$24/2)*$ED$3))) | ED49: In_CT_Zone | EE49: =IF('Advanced Setup Planner'!$E$16>$O$3,'Advanced Setup Planner'!$E$16,"")
A50: Value Ladder (Mid-depth supports) | AC50: Reward at TP1 $ | AD50: =IF(OR(AD47=0,AD48="",$Y$3=""),"",ABS(($Y$3-AD48)*AD47)) | AN50: =O3 | EA50: Tier | EB50: =IF($Y$1<>"LONG","",MAX($O$3,IF(AND($T$21<>"",ABS($T$21-IF($O$27<>"",$O$27,$T$17))<=0.0025),$T$21,IF($O$27<>"",$O$27,$T$17)))) | EC50: High | ED50: In_Premium | EE50: =IF(AND('Advanced Setup Planner'!$E$11>$O$3,('Advanced Setup Planner'!$E$11-$O$3)*10000<=40),'Advanced Setup Planner'!$E$11,"")
A51: Rung | B51: Entry | C51: TP | D51: SL | E51: Pips→TP | F51: EffPips→SL | G51: Units | H51: Risk $ | I51: Reward $ | J51: R | K51: R2 | AC51: R multiple at TP1 | AD51: =IF(SUM($AJ$42:$AJ$44)=0,"",SUM($AK$42:$AK$44)/SUM($AJ$42:$AJ$44)) | AN51: L1_0.618-L1_0.382 | EA51: Tier1 Low | EB51: =MIN($Q$23,$Q$25) | EC51: =MAX($Q$23,$Q$25) | EE51: =IFERROR(_xlfn.AGGREGATE(15,6,EE47:EE50/(EE47:EE50<>""),1),$O$3+($ED$24*$ED$3))
A52: Shallow | B52: ='Advanced Setup Planner'!AD42 | C52: ='Advanced Setup Planner'!AE42 | D52: ='Advanced Setup Planner'!AF42 | E52: ='Advanced Setup Planner'!AG42 | F52: ='Advanced Setup Planner'!AH42 | G52: ='Advanced Setup Planner'!AL42 | H52: ='Advanced Setup Planner'!AJ42 | I52: ='Advanced Setup Planner'!AK42 | J52: ='Advanced Setup Planner'!AM42 | K52: ='Advanced Setup Planner'!AM42 | AC52: Avg Eff Pips to SL | AD52: =IF(SUM(AL42:AL44)=0,"",(AL42*MAX(AH42,$ED$35)+AL43*MAX(AH43,$ED$35)+AL44*MAX(AH44,$ED$35))/SUM(AL42:AL44)) | AN52: 4H_FVG_low-4H_FVG_high | EA52: 2 | EB52: =O36 | EC52: =O35 | ED52: CoreLong_Flag | EE52: =AND($EB$38>=0,T8=TRUE,NOT(T9),EE48)
A53: Mid | B53: ='Advanced Setup Planner'!AD43 | C53: ='Advanced Setup Planner'!AE43 | D53: ='Advanced Setup Planner'!AF43 | E53: ='Advanced Setup Planner'!AG43 | F53: ='Advanced Setup Planner'!AH43 | G53: ='Advanced Setup Planner'!AL43 | H53: ='Advanced Setup Planner'!AJ43 | I53: ='Advanced Setup Planner'!AK43 | J53: ='Advanced Setup Planner'!AM43 | K53: ='Advanced Setup Planner'!AM43 | AN53: DeepLow-High | EA53: 3 | EB53: =O13 | EC53: =O12 | ED53: CTShort_Flag | EE53: =AND(N($EB$38)<=0,T8=TRUE,T11=TRUE,EE49=TRUE,$O$21>70,$O$20>65)
A54: Deep | B54: ='Advanced Setup Planner'!AD44 | C54: ='Advanced Setup Planner'!AE44 | D54: ='Advanced Setup Planner'!AF44 | E54: ='Advanced Setup Planner'!AG44 | F54: ='Advanced Setup Planner'!AH44 | G54: ='Advanced Setup Planner'!AL44 | H54: ='Advanced Setup Planner'!AJ44 | I54: ='Advanced Setup Planner'!AK44 | J54: ='Advanced Setup Planner'!AM44 | K54: ='Advanced Setup Planner'!AM44 | ED54: LocationLabel | EE54: =IF(EE48,"DISCOUNT",IF(EE49,"CT_ZONE",IF(EE50,"PREMIUM","MID")))
A55: Total | B55: =IFERROR(SUBTOTAL(101,Table17[Entry]),"") | C55: =IFERROR(SUBTOTAL(101,Table17[TP]),"") | D55: =IFERROR(SUBTOTAL(101,Table17[SL]),"") | E55: =IFERROR(SUBTOTAL(101,Table17[Pips→TP]),"") | F55: =IFERROR(SUBTOTAL(101,Table17[EffPips→SL]),"") | G55: =SUBTOTAL(109,Table17[Units]) | H55: =SUBTOTAL(109,Table17[Risk $]) | I55: =SUBTOTAL(109,Table17[Reward $]) | J55: =IFERROR(Table17[[#Totals],[Reward $]]/Table17[[#Totals],[Risk $]],"") | EA55: ActiveTier | EB55: =IF(AND($O$3>=EB51,$O$3<=EC51),1,IF(AND($O$3>=EB52,$O$3<=EC52),2,IF(AND($O$3>=EB53,$O$3<=EC53),3,0)))
EB56: =EB55
A57: A+ Ladder (Deep value block) | EA57: Primary_ViewTier (1/2/3, blank=auto) | EC57: Resolved_PrimaryTier | ED57: =IF($EB$57<>"",$EB$57,IF($EB$55=0,1,$EB$55))
A58: Rung | B58: Entry | C58: TP | D58: SL | E58: Pips→TP | F58: EffPips→SL | G58: Units | H58: Risk $ | I58: Reward $ | J58: R | K58: R2
A59: Shallow | B59: ='Advanced Setup Planner'!AD15 | C59: ='Advanced Setup Planner'!AE15 | D59: ='Advanced Setup Planner'!AF15 | E59: ='Advanced Setup Planner'!AG15 | F59: ='Advanced Setup Planner'!AH15 | G59: ='Advanced Setup Planner'!AL15 | H59: ='Advanced Setup Planner'!AJ15 | I59: ='Advanced Setup Planner'!AK15 | J59: ='Advanced Setup Planner'!AM15 | K59: ='Advanced Setup Planner'!AM15
A60: Mid | B60: ='Advanced Setup Planner'!AD16 | C60: ='Advanced Setup Planner'!AE16 | D60: ='Advanced Setup Planner'!AF16 | E60: ='Advanced Setup Planner'!AG16 | F60: ='Advanced Setup Planner'!AH16 | G60: ='Advanced Setup Planner'!AL16 | H60: ='Advanced Setup Planner'!AJ16 | I60: ='Advanced Setup Planner'!AK16 | J60: ='Advanced Setup Planner'!AM16 | K60: ='Advanced Setup Planner'!AM16
A61: Deep | B61: ='Advanced Setup Planner'!AD17 | C61: ='Advanced Setup Planner'!AE17 | D61: ='Advanced Setup Planner'!AF17 | E61: ='Advanced Setup Planner'!AG17 | F61: ='Advanced Setup Planner'!AH17 | G61: ='Advanced Setup Planner'!AL17 | H61: ='Advanced Setup Planner'!AJ17 | I61: ='Advanced Setup Planner'!AK17 | J61: ='Advanced Setup Planner'!AM17 | K61: ='Advanced Setup Planner'!AM17
A62: Total | B62: =IFERROR(SUBTOTAL(101,Table18[Entry]),"") | C62: =IFERROR(SUBTOTAL(101,Table18[TP]),"") | D62: =IFERROR(SUBTOTAL(101,Table18[SL]),"") | E62: =IFERROR(SUBTOTAL(101,Table18[Pips→TP]),"") | F62: =IFERROR(SUBTOTAL(101,Table18[EffPips→SL]),"") | G62: =SUBTOTAL(109,Table18[Units]) | H62: =SUBTOTAL(109,Table18[Risk $]) | I62: =SUBTOTAL(109,Table18[Reward $]) | J62: =IFERROR(Table18[[#Totals],[Reward $]]/Table18[[#Totals],[Risk $]],"")
A64: CT Ladder (Fade ceiling; only on rejection) | L64: =IF('Advanced Setup Planner'!Y1<>"SHORT","CT inactive (Side is "&'Advanced Setup Planner'!Y1&"). Switch Side to SHORT to use CT.","")
A65: Rung | B65: Entry | C65: TP | D65: SL | E65: Pips→TP | F65: EffPips→SL | G65: Units | H65: Risk $ | I65: Reward $ | J65: R | K65: Column1
A66: Shallow | B66: ='Advanced Setup Planner'!AD28 | C66: ='Advanced Setup Planner'!AE28 | D66: ='Advanced Setup Planner'!AF28 | E66: ='Advanced Setup Planner'!AG28 | F66: ='Advanced Setup Planner'!AH28 | G66: ='Advanced Setup Planner'!AL28 | H66: ='Advanced Setup Planner'!AJ28 | I66: ='Advanced Setup Planner'!AK28 | J66: ='Advanced Setup Planner'!AM28
A67: Mid | B67: ='Advanced Setup Planner'!AD29 | C67: ='Advanced Setup Planner'!AE29 | D67: ='Advanced Setup Planner'!AF29 | E67: ='Advanced Setup Planner'!AG29 | F67: ='Advanced Setup Planner'!AH29 | G67: ='Advanced Setup Planner'!AL29 | H67: ='Advanced Setup Planner'!AJ29 | I67: ='Advanced Setup Planner'!AK29 | J67: ='Advanced Setup Planner'!AM29
A68: Deep | B68: ='Advanced Setup Planner'!AD30 | C68: ='Advanced Setup Planner'!AE30 | D68: ='Advanced Setup Planner'!AF30 | E68: ='Advanced Setup Planner'!AG30 | F68: ='Advanced Setup Planner'!AH30 | G68: ='Advanced Setup Planner'!AL30 | H68: ='Advanced Setup Planner'!AJ30 | I68: ='Advanced Setup Planner'!AK30 | J68: ='Advanced Setup Planner'!AM30
A69: Total | B69: =IFERROR(SUBTOTAL(101,Table19[Entry]),"") | C69: =IFERROR(SUBTOTAL(101,Table19[TP]),"") | D69: =IFERROR(SUBTOTAL(101,Table19[SL]),"") | E69: =IFERROR(SUBTOTAL(101,Table19[Pips→TP]),"") | F69: =IFERROR(SUBTOTAL(101,Table19[EffPips→SL]),"") | G69: =SUBTOTAL(109,Table19[Units]) | H69: =SUBTOTAL(109,Table19[Risk $]) | I69: =SUBTOTAL(109,Table19[Reward $]) | J69: =IFERROR(Table19[[#Totals],[Reward $]]/Table19[[#Totals],[Risk $]],"")

Sheet Backend
A1: List
A2: Bull
A3: Bear
A4: Range
A5: Up
A6: Down
A7: None
A8: 1
A9: 2
A10: 3
A11: Falling
A12: Neutral
A13: Rising
A14: Softening
A15: Mixed
A16: Tight
A17: Slowing
A18: Stable
A19: Accelerating
A20: More cuts
A21: Hold/uncertain
A22: Fewer cuts
... A80: Narrative Engine (do not edit)
A82: SetupScore | B82: =IFERROR('Advanced Setup Planner'!EB18,"")
A83: SetupGrade | B83: =IFERROR(IF(B82="","",IF(B82>=0.8,"A",IF(B82>=0.65,"B",IF(B82>=0.5,"C","D")))),"")
A84: SetupMeaning | B84: =IFERROR(IF(B83="","",IF(B83="A","High quality: ok to execute if plan rules are met.",IF(B83="B","Tradable but selective: wait for confirmation / smaller size.",IF(B83="C","Weak: wait for better location or stronger confirmation.","Avoid: observation only.")))),"")
A86: RateDiff_Now | B86: =IF(OR(Backend!Z211="",Backend!Z212=""),"",Backend!Z211-Backend!Z212)
A87: RateDiff_6M | B87: =IF(Backend!B346="","",Backend!B346)
A88: RateDiff_ChangeSteps | B88: =IF(Backend!B347="","",Backend!B347)
A89: RateDiff_ChangeBP | B89: =IF(B88="","",B88*25)
A90: RateDiff_NowLabel | B90: =IF(B86="","",IF(B86>0,"USD advantage now","EUR advantage now"))
A91: RateDiff_ChangeLabel | B91: =IF(B88="","",IF(B88<0,"USD advantage shrinking over ~6M","USD advantage widening over ~6M"))
A93: FedTone | B93: =IF(Backend!B349="","",IF(Backend!B349>=0.25,"hawkish",IF(Backend!B349<=-0.25,"dovish","neutral"))&" (daily "&TEXT(Backend!B349,"0.00")&")")
A94: ECBTone | B94: =IF(Backend!B351="","",IF(Backend!B351>=0.25,"hawkish",IF(Backend!B351<=-0.25,"dovish","neutral"))&" (daily "&TEXT(Backend!B351,"0.00")&")")
B95: =IF(Backend!B350="","",IF(Backend!B350>=0.25,"hawkish",IF(Backend!B350<=-0.25,"dovish","neutral"))&" (30d "&TEXT(Backend!B350,"0.00")&")")
B96: =IF(Backend!B352="","",IF(Backend!B352>=0.25,"hawkish",IF(Backend!B352<=-0.25,"dovish","neutral"))&" (30d "&TEXT(Backend!B352,"0.00")&")")
B97: =IFERROR(IF(Backend!B338="Buy dips","LONG",IF(Backend!B338="Sell rallies","SHORT","NEUTRAL")),"")
A98: Price | B98: ='Advanced Setup Planner'!B5
B99: =IFERROR(IF(OR(B97="NEUTRAL",B98=""),"",IF(B97=B98,"Aligned: macro "&Backend!B338&" matches technical "&B98,"Misaligned: macro "&Backend!B338&" vs technical "&B98)),"")
A100: Strike1 | B100: =IF('Advanced Setup Planner'!K5="","",'Advanced Setup Planner'!K5) | C100: =IFERROR(IF(B100="",1E+99,ABS(B100-B98)),"") | D100: =IF('Advanced Setup Planner'!K6="","",'Advanced Setup Planner'!K6)
A101: Strike2 | B101: =IF('Advanced Setup Planner'!K7="","",'Advanced Setup Planner'!K7) | C101: =IFERROR(IF(B101="",1E+99,ABS(B101-B98)),"") | D101: =IF('Advanced Setup Planner'!K8="","",'Advanced Setup Planner'!K8)
A102: Strike3 | B102: =IF('Advanced Setup Planner'!K9="","",'Advanced Setup Planner'!K9) | C102: =IFERROR(IF(B102="",1E+99,ABS(B102-B98)),"") | D102: =IF('Advanced Setup Planner'!K10="","",'Advanced Setup Planner'!K10)
A103: Strike4 | B103: =IF('Advanced Setup Planner'!K11="","",'Advanced Setup Planner'!K11) | C103: =IFERROR(IF(B103="",1E+99,ABS(B103-B98)),"") | D103: =IF('Advanced Setup Planner'!K12="","",'Advanced Setup Planner'!K12)
A105: NearestStrike | B105: =IFERROR(INDEX(B100:B103,MATCH(MIN(C100:C103),C100:C103,0)),"")
A106: NearestSize | B106: =IF(B105="","",INDEX(D100:D103,MATCH(B105,B100:B103,0)))
A107: NearestPips | B107: =IF(B105="","",ABS(B105-B98)*10000)
A108: StrikeNote | B108: =IF(B105="","",IF(B107<=15,"Options magnet nearby: strike "&TEXT(B105,"0.0000")&" (~"&TEXT(B107,"0")&" pips, size "&TEXT(B106,"0.00")&"bn).","Options strikes not near price (nearest "&TEXT(B105,"0.0000")&", ~"&TEXT(B107,"0")&" pips)."))
A110: Narrative | B110: =IFERROR(IF('Advanced Setup Planner'!B5="","","1) Macro bias: "&Backend!B338&". "&IF(B86="","","Rate gap NOW "&TEXT(B86,"0.00")&" ("&B90&"). ")&IF(B88="","","Expected 6M change "&TEXT(B88,"0")&" steps ("&TEXT(B89,"0")&"bp) — "&B91&". ")&"2) Yields: "&Backend!B356&". "&"3) Speakers: Fed "&IF(B93<>"",B93&", ","")&IF(B95<>"",B95,"")&"; ECB "&IF(B94<>"",B94&", ","")&IF(B96<>"",B96,"")&". "&IF(B108="","",B108)),"")
A112: Action | B112: =IFERROR(IF('Advanced Setup Planner'!B5="","",IF(B99="","",B99&" — ")&IF(Backend!B338="Buy dips","Action: prefer LONG pullbacks into support (Primary/Value). Avoid chasing highs. ",IF(Backend!B338="Sell rallies","Action: prefer SHORT rallies into resistance (CT/Primary-short). Avoid selling lows. ","Action: macro neutral — lean on structure/levels, trade smaller."))&IF(OR(B97="NEUTRAL",B98=""),"",IF(B97<>B98," Reduce size; demand stronger confirmation (e.g., BOS/CHOCH + rejection/acceptance).",""))),"")
A114: Glossary | B114: ="Steps = 25bp moves (quarter‑point). Example: -4 steps ≈ -100bp of USD-vs-EUR advantage compressing over ~6 months."
A130: Date | B130: CentralBank | C130: Person | D130: Role | E130: Event | F130: Topic | G130: Tone | H130: Tone_Score | I130: Notes | J130: Link/Source | L130: Hawkish | M130: 1 | P130: FED
A131: 45959 | B131: FED | C131: Powell | G131: Neutral | H131: =IF(G131="","",VLOOKUP(G131,$L$130:$M$132,2,FALSE)) | L131: Neutral | M131: 0 | P131: BOJ
A132: 45967 | B132: FED | C132: Goolsbee | G132: Hawkish | H132: =IF(G132="","",VLOOKUP(G132,$L$130:$M$132,2,FALSE)) | L132: Dovish | M132: -1 | P132: ECB
A133: 45967 | B133: FED | C133: Hammack | G133: Hawkish | H133: =IF(G133="","",VLOOKUP(G133,$L$130:$M$132,2,FALSE))
A134: 45971 | B134: FED | C134: Musalem | G134: Hawkish | H134: =IF(G134="","",VLOOKUP(G134,$L$130:$M$132,2,FALSE))
A135: 45971 | B135: FED | C135: Miran | G135: Dovish | H135: =IF(G135="","",VLOOKUP(G135,$L$130:$M$132,2,FALSE))
A136: 45974 | B136: FED | C136: Kashkari | G136: Neutral | H136: =IF(G136="","",VLOOKUP(G136,$L$130:$M$132,2,FALSE))
A137: 45979 | B137: FED | C137: Barkin | G137: Neutral | H137: =IF(G137="","",VLOOKUP(G137,$L$130:$M$132,2,FALSE))
A138: 45982 | B138: FED | C138: Logan | G138: Hawkish | H138: =IF(G138="","",VLOOKUP(G138,$L$130:$M$132,2,FALSE))
A139: 45982 | B139: FED | C139: Collins | G139: Hawkish | H139: =IF(G139="","",VLOOKUP(G139,$L$130:$M$132,2,FALSE))
A140: 45982 | B140: FED | C140: Daly | G140: Dovish | H140: =IF(G140="","",VLOOKUP(G140,$L$130:$M$132,2,FALSE))
A141: 45982 | B141: FED | C141: Williams | G141: Dovish | H141: =IF(G141="","",VLOOKUP(G141,$L$130:$M$132,2,FALSE))
A142: 45985 | B142: FED | C142: Waller | G142: Dovish | H142: =IF(G142="","",VLOOKUP(G142,$L$130:$M$132,2,FALSE))
A143: 45999 | B143: ECB | C143: Schnabel | G143: Hawkish | H143: =IF(G143="","",VLOOKUP(G143,$L$130:$M$132,2,FALSE))
A144: 45999 | B144: ECB | C144: Rehn | G144: Dovish | H144: =IF(G144="","",VLOOKUP(G144,$L$130:$M$132,2,FALSE))
... A163: 46008 | B163: BOJ | C163: Takashi | G163: Hawkish | H163: =IF(G163="","",VLOOKUP(G163,$L$130:$M$132,2,FALSE))
A180: Date | B180: Currency | C180: Rate1_mid 350-375) | D180: Prob1 | E180: Rate2_mid (375-400) | F180: Prob2 | G180: Rate3_mid (325-350) | H180: Prob3 | I180: ExpRate | J180: CutsVsToday
A181: 46050 | B181: US | C181: 3.625 | D181: 0.756 | E181: 3.875 | F181: 0 | G181: 3.375 | H181: 0.244 | I181: =IF(B181="","",IF(SUM(D181,F181,H181)=0,"",(C181*D181+E181*F181+G181*H181)/SUM(D181,F181,H181))) | J181: =IF(I181="","",ROUND((IF(B181="US",Backend!$Z$211,IF(B181="ECB",Backend!$Z$212,""))-I181)/0.25,0))
A182: 46082 | B182: US | C182: 3.625 | D182: 0.505 | E182: 3.875 | F182: 0 | G182: 3.375 | H182: 0.414 | I182: =IF(B182="","",IF(SUM(D182,F182,H182)=0,"",(C182*D182+E182*F182+G182*H182)/SUM(D182,F182,H182))) | J182: =IF(I182="","",ROUND((IF(B182="US",Backend!$Z$211,IF(B182="ECB",Backend!$Z$212,""))-I182)/0.25,0))
A183: 46141 | B183: US | C183: 3.625 | D183: 0.39 | E183: 3.875 | F183: 0 | G183: 3.375 | H183: 0.157 | I183: =IF(B183="","",IF(SUM(D183,F183,H183)=0,"",(C183*D183+E183*F183+G183*H183)/SUM(D183,F183,H183))) | J183: =IF(I183="","",ROUND((IF(B183="US",Backend!$Z$211,IF(B183="ECB",Backend!$Z$212,""))-I183)/0.25,0))
A184: 46190 | B184: US | C184: 3.625 | D184: 0.186 | E184: 3.875 | F184: 0 | G184: 3.375 | H184: 0.39 | I184: =IF(B184="","",IF(SUM(D184,F184,H184)=0,"",(C184*D184+E184*F184+G184*H184)/SUM(D184,F184,H184))) | J184: =IF(I184="","",ROUND((IF(B184="US",Backend!$Z$211,IF(B184="ECB",Backend!$Z$212,""))-I184)/0.25,0))
A185: 46232 | B185: US | C185: 3.625 | D185: 0.135 | E185: 3.875 | F185: 0 | G185: 3.375 | H185: 0.355 | I185: =IF(B185="","",IF(SUM(D185,F185,H185)=0,"",(C185*D185+E185*F185+G185*H185)/SUM(D185,F185,H185))) | J185: =IF(I185="","",ROUND((IF(B185="US",Backend!$Z$211,IF(B185="ECB",Backend!$Z$212,""))-I185)/0.25,0))
A186: 46056 | B186: ECB | C186: 1.75 | D186: 0 | E186: 2 | F186: 0.847 | G186: 2.25 | H186: 0.018 | I186: =IF(B186="","",IF(SUM(D186,F186,H186)=0,"",(C186*D186+E186*F186+G186*H186)/SUM(D186,F186,H186))) | J186: =IF(I186="","",ROUND((IF(B186="US",Backend!$Z$211,IF(B186="ECB",Backend!$Z$212,""))-I186)/0.25,0))
A187: 46098 | B187: ECB | C187: 1.75 | D187: 0.243 | E187: 2 | F187: 0.721 | G187: 2.25 | H187: 0.016 | I187: =IF(B187="","",IF(SUM(D187,F187,H187)=0,"",(C187*D187+E187*F187+G187*H187)/SUM(D187,F187,H187))) | J187: =IF(I187="","",ROUND((IF(B187="US",Backend!$Z$211,IF(B187="ECB",Backend!$Z$212,""))-I187)/0.25,0))
A188: 46140 | B188: ECB | C188: 1.75 | D188: 0.288 | E188: 2 | F188: 0.655 | G188: 2.25 | H188: 0.014 | I188: =IF(B188="","",IF(SUM(D188,F188,H188)=0,"",(C188*D188+E188*F188+G188*H188)/SUM(D188,F188,H188))) | J188: =IF(I188="","",ROUND((IF(B188="US",Backend!$Z$211,IF(B188="ECB",Backend!$Z$212,""))-I188)/0.25,0))
A189: 46182 | B189: ECB | C189: 1.75 | D189: 0.304 | E189: 2 | F189: 0.627 | G189: 2.25 | H189: 0.014 | I189: =IF(B189="","",IF(SUM(D189,F189,H189)=0,"",(C189*D189+E189*F189+G189*H189)/SUM(D189,F189,H189))) | J189: =IF(I189="","",ROUND((IF(B189="US",Backend!$Z$211,IF(B189="ECB",Backend!$Z$212,""))-I189)/0.25,0))
A190: 46224 | B190: ECB | C190: 1.75 | D190: 0.31 | E190: 2 | F190: 0.614 | G190: 2.25 | H190: 0.013 | I190: =IF(B190="","",IF(SUM(D190,F190,H190)=0,"",(C190*D190+E190*F190+G190*H190)/SUM(D190,F190,H190))) | J190: =IF(I190="","",ROUND((IF(B190="US",Backend!$Z$211,IF(B190="ECB",Backend!$Z$212,""))-I190)/0.25,0))
A191: 46274 | B191: ECB | C191: 1.75 | D191: 0.312 | E191: 2 | F191: 0.612 | G191: 2.25 | H191: 0.013 | I191: =IF(B191="","",IF(SUM(D191,F191,H191)=0,"",(C191*D191+E191*F191+G191*H191)/SUM(D191,F191,H191))) | J191: =IF(I191="","",ROUND((IF(B191="US",Backend!$Z$211,IF(B191="ECB",Backend!$Z$212,""))-I191)/0.25,0))
A210: Date | B210: Category | C210: Event | D210: Actual | E210: Forecast | F210: Previous | G210: Surprise vs Forecast | H210: Change vs Prev | I210: Qualitative | J210: EffectDirection | K210: Adj_Surprise | L210: Adj_ChangeAdj_ChangeAdj_ChangeAdj_ChangeAdj_ChangeAdj_ChangeAdj_ChangeAdj_ChangeAdj_Change | N210: Date | O210: Tenor | T210: Δd (1d) | U210: Δ5d
A211: 45985 | B211: Growth - EUR | C211: German ifo Business Climate | D211: 88.1 | E211: 88.6 | F211: 88.4 | G211: =IF(NOT(ISNUMBER(D211)),"",IF(NOT(ISNUMBER(E211)),"",D211-E211)) | H211: =IF(NOT(ISNUMBER(D211)),"",IF(NOT(ISNUMBER(F211)),"",D211-F211)) | I211: =IF(AND(K211="",L211=""),"N/A",IF(AND(ABS(N(K211))<0.0005,ABS(N(L211))<0.0005),"Stable",IF(AND(L211="",ABS(N(K211))>=0.0005),IF(N(K211)>0,"Accelerating","Slowing"),IF(AND(K211="",ABS(N(L211))>=0.0005),IF(N(L211)>0,"Accelerating","Slowing"),IF(AND(N(K211)>0,N(L211)>=0),"Accelerating",IF(AND(N(K211)<0,N(L211)<=0),"Slowing","Mixed")))))) | J211: =IF(OR(ISNUMBER(SEARCH("Unemployment",C211)),ISNUMBER(SEARCH("Claims",C211)),ISNUMBER(SEARCH("Jobless",C211)),ISNUMBER(SEARCH("Inventories",C211)),ISNUMBER(SEARCH("Wholesale Inventories",C211)),ISNUMBER(SEARCH("JOLTS Job Openings",C211)),ISNUMBER(SEARCH("Inflation Expectations",C211))),-1,1) | K211: =IF(OR(G211="",G211="(NA)"),"",J211*G211) | L211: =IF(OR(H211="",H211="(NA)"),"",J211*H211) | N211: 46006 | O211: US 2y | P211: 3.497 | Q211: 3.519 | R211: 3.61 | S211: 3.612 | T211: =IF(OR(P211="",Q211=""),"",P211-Q211) | U211: =IF(OR(P211="",R211=""),"",P211-R211) | V211: =IF(OR(P211="",S211=""),"",P211-S211) | W211: =IF(P211="","",IF(AND(U211>0.03,V211>0),"Rising",IF(AND(U211<-0.03,V211<0),"Falling","Flat"))) | X211: =IF(W211="","",IFERROR(VLOOKUP(W211,Backend!$D$324:$E$337,2,FALSE)*1,0)) | Z211: =(3.75+4.99)/2 | AA211: Fed_CurrentRate
A212: 45986 | B212: Growth - US | C212: ADP Weekly Employment Change | D212: -13000 | E212: -2500 | G212: =IF(NOT(ISNUMBER(D212)),"",IF(NOT(ISNUMBER(E212)),"",D212-E212)) | H212: =IF(NOT(ISNUMBER(D212)),"",IF(NOT(ISNUMBER(F212)),"",D212-F212)) | I212: =IF(AND(K212="",L212=""),"N/A",IF(AND(ABS(N(K212))<0.0005,ABS(N(L212))<0.0005),"Stable",IF(AND(L212="",ABS(N(K212))>=0.0005),IF(N(K212)>0,"Accelerating","Slowing"),IF(AND(K212="",ABS(N(L212))>=0.0005),IF(N(L212)>0,"Accelerating","Slowing"),IF(AND(N(K212)>0,N(L212)>=0),"Accelerating",IF(AND(N(K212)<0,N(L212)<=0),"Slowing","Mixed")))))) | J212: =IF(OR(ISNUMBER(SEARCH("Unemployment",C212)),ISNUMBER(SEARCH("Claims",C212)),ISNUMBER(SEARCH("Jobless",C212)),ISNUMBER(SEARCH("Inventories",C212)),ISNUMBER(SEARCH("Wholesale Inventories",C212)),ISNUMBER(SEARCH("JOLTS Job Openings",C212)),ISNUMBER(SEARCH("Inflation Expectations",C212))),-1,1) | K212: =IF(OR(G212="",G212="(NA)"),"",J212*G212) | L212: =IF(OR(H212="",H212="(NA)"),"",J212*H212) | N212: 46006 | O212: US 5y | P212: 3.719 | Q212: 3.741 | R212: 3.783 | S212: 3.704 | T212: =IF(OR(P212="",Q212=""),"",P212-Q212) | U212: =IF(OR(P212="",R212=""),"",P212-R212) | V212: =IF(OR(P212="",S212=""),"",P212-S212) | W212: =IF(P212="","",IF(AND(U212>0.03,V212>0),"Rising",IF(AND(U212<-0.03,V212<0),"Falling","Flat"))) | X212: =IF(W212="","",IFERROR(VLOOKUP(W212,Backend!$D$324:$E$337,2,FALSE)*1,0)) | Z212: 2 | AA212: ECB_CurrentRate
A213: 45986 | B213: Growth - US | C213: Core Retail Sales m/m | D213: 0.003 | E213: 0.003 | F213: 0.006 | G213: =IF(NOT(ISNUMBER(D213)),"",IF(NOT(ISNUMBER(E213)),"",D213-E213)) | H213: =IF(NOT(ISNUMBER(D213)),"",IF(NOT(ISNUMBER(F213)),"",D213-F213)) | I213: =IF(AND(K213="",L213=""),"N/A",IF(AND(ABS(N(K213))<0.0005,ABS(N(L213))<0.0005),"Stable",IF(AND(L213="",ABS(N(K213))>=0.0005),IF(N(K213)>0,"Accelerating","Slowing"),IF(AND(K213="",ABS(N(L213))>=0.0005),IF(N(L213)>0,"Accelerating","Slowing"),IF(AND(N(K213)>0,N(L213)>=0),"Accelerating",IF(AND(N(K213)<0,N(L213)<=0),"Slowing","Mixed")))))) | J213: =IF(OR(ISNUMBER(SEARCH("Unemployment",C213)),ISNUMBER(SEARCH("Claims",C213)),ISNUMBER(SEARCH("Jobless",C213)),ISNUMBER(SEARCH("Inventories",C213)),ISNUMBER(SEARCH("Wholesale Inventories",C213)),ISNUMBER(SEARCH("JOLTS Job Openings",C213)),ISNUMBER(SEARCH("Inflation Expectations",C213))),-1,1) | K213: =IF(OR(G213="",G213="(NA)"),"",J213*G213) | L213: =IF(OR(H213="",H213="(NA)"),"",J213*H213) | N213: 46006 | O213: US 10y | P213: 4.168 | Q213: 4.183 | R213: 4.188 | S213: 4.116 | T213: =IF(OR(P213="",Q213=""),"",P213-Q213) | U213: =IF(OR(P213="",R213=""),"",P213-R213) | V213: =IF(OR(P213="",S213=""),"",P213-S213) | W213: =IF(P213="","",IF(AND(U213>0.03,V213>0),"Rising",IF(AND(U213<-0.03,V213<0),"Falling","Flat"))) | X213: =IF(W213="","",IFERROR(VLOOKUP(W213,Backend!$D$324:$E$337,2,FALSE)*1,0)) | Z213: 0 | AA213: JPY_CurrentRate
A214: 45986 | B214: Growth - US | C214: Retail Sales m/m | D214: 0.002 | E214: 0.004 | F214: -0.001 | G214: =IF(NOT(ISNUMBER(D214)),"",IF(NOT(ISNUMBER(E214)),"",D214-E214)) | H214: =IF(NOT(ISNUMBER(D214)),"",IF(NOT(ISNUMBER(F214)),"",D214-F214)) | I214: =IF(AND(K214="",L214=""),"N/A",IF(AND(ABS(N(K214))<0.0005,ABS(N(L214))<0.0005),"Stable",IF(AND(L214="",ABS(N(K214))>=0.0005),IF(N(K214)>0,"Accelerating","Slowing"),IF(AND(K214="",ABS(N(L214))>=0.0005),IF(N(L214)>0,"Accelerating","Slowing"),IF(AND(N(K214)>0,N(L214)>=0),"Accelerating",IF(AND(N(K214)<0,N(L214)<=0),"Slowing","Mixed")))))) | J214: =IF(OR(ISNUMBER(SEARCH("Unemployment",C214)),ISNUMBER(SEARCH("Claims",C214)),ISNUMBER(SEARCH("Jobless",C214)),ISNUMBER(SEARCH("Inventories",C214)),ISNUMBER(SEARCH("Wholesale Inventories",C214)),ISNUMBER(SEARCH("JOLTS Job Openings",C214)),ISNUMBER(SEARCH("Inflation Expectations",C214))),-1,1) | K214: =IF(OR(G214="",G214="(NA)"),"",J214*G214) | L214: =IF(OR(H214="",H214="(NA)"),"",J214*H214) | N214: 46006 | O214: US 30y | P214: 4.844 | Q214: 4.58 | R214: 4.808 | S214: 4.753 | T214: =IF(OR(P214="",Q214=""),"",P214-Q214) | U214: =IF(OR(P214="",R214=""),"",P214-R214) | V214: =IF(OR(P214="",S214=""),"",P214-S214) | W214: =IF(P214="","",IF(AND(U214>0.03,V214>0),"Rising",IF(AND(U214<-0.03,V214<0),"Falling","Flat"))) | X214: =IF(W214="","",IFERROR(VLOOKUP(W214,Backend!$D$324:$E$337,2,FALSE)*1,0))
A215: 45986 | B215: Growth - US | C215: CB Consumer Confidence | D215: 88.7 | E215: 93.4 | F215: 95.5 | G215: =IF(NOT(ISNUMBER(D215)),"",IF(NOT(ISNUMBER(E215)),"",D215-E215)) | H215: =IF(NOT(ISNUMBER(D215)),"",IF(NOT(ISNUMBER(F215)),"",D215-F215)) | I215: =IF(AND(K215="",L215=""),"N/A",IF(AND(ABS(N(K215))<0.0005,ABS(N(L215))<0.0005),"Stable",IF(AND(L215="",ABS(N(K215))>=0.0005),IF(N(K215)>0,"Accelerating","Slowing"),IF(AND(K215="",ABS(N(L215))>=0.0005),IF(N(L215)>0,"Accelerating","Slowing"),IF(AND(N(K215)>0,N(L215)>=0),"Accelerating",IF(AND(N(K215)<0,N(L215)<=0),"Slowing","Mixed")))))) | J215: =IF(OR(ISNUMBER(SEARCH("Unemployment",C215)),ISNUMBER(SEARCH("Claims",C215)),ISNUMBER(SEARCH("Jobless",C215)),ISNUMBER(SEARCH("Inventories",C215)),ISNUMBER(SEARCH("Wholesale Inventories",C215)),ISNUMBER(SEARCH("JOLTS Job Openings",C215)),ISNUMBER(SEARCH("Inflation Expectations",C215))),-1,1) | K215: =IF(OR(G215="",G215="(NA)"),"",J215*G215) | L215: =IF(OR(H215="",H215="(NA)"),"",J215*H215) | N215: Date | O215: Tenor | T215: Δd (1d) | U215: Δ5d
A216: 45986 | B216: Inflation – US | C216: Core PPI m/m | D216: 0.001 | E216: 0.002 | F216: -0.001 | G216: =IF(NOT(ISNUMBER(D216)),"",IF(NOT(ISNUMBER(E216)),"",D216-E216)) | H216: =IF(NOT(ISNUMBER(D216)),"",IF(NOT(ISNUMBER(F216)),"",D216-F216)) | I216: =IF(AND(K216="",L216=""),"N/A",IF(AND(ABS(N(K216))<0.0005,ABS(N(L216))<0.0005),"Stable",IF(AND(L216="",ABS(N(K216))>=0.0005),IF(N(K216)>0,"Accelerating","Slowing"),IF(AND(K216="",ABS(N(L216))>=0.0005),IF(N(L216)>0,"Accelerating","Slowing"),IF(AND(N(K216)>0,N(L216)>=0),"Accelerating",IF(AND(N(K216)<0,N(L216)<=0),"Slowing","Mixed")))))) | J216: =IF(OR(ISNUMBER(SEARCH("Unemployment",C216)),ISNUMBER(SEARCH("Claims",C216)),ISNUMBER(SEARCH("Jobless",C216)),ISNUMBER(SEARCH("Inventories",C216)),ISNUMBER(SEARCH("Wholesale Inventories",C216)),ISNUMBER(SEARCH("JOLTS Job Openings",C216)),ISNUMBER(SEARCH("Inflation Expectations",C216))),-1,1) | K216: =IF(OR(G216="",G216="(NA)"),"",J216*G216) | L216: =IF(OR(H216="",H216="(NA)"),"",J216*H216) | N216: 46006 | O216: US 2s10s | P216: =IF(OR(P211="",P213=""),"",P213-P211) | Q216: =IF(OR(Q211="",Q213=""),"",Q213-Q211) | R216: =IF(OR(R211="",R213=""),"",R213-R211) | S216: =IF(OR(S211="",S213=""),"",S213-S211) | T216: =IF(OR(P216="",Q216=""),"",P216-Q216) | U216: =IF(OR(P216="",R216=""),"",P216-R216) | V216: =IF(OR(P216="",S216=""),"",P216-S216) | W216: =IF(P216="","",IF(AND(U216>0.03,V216>0),"Rising",IF(AND(U216<-0.03,V216<0),"Falling","Flat"))) | X216: =IF(W216="","",IFERROR(VLOOKUP(W216,Backend!$D$324:$E$337,2,FALSE)*1,0))
A217: 45987 | B217: Growth - US | C217: Core Durable Goods Orders m/m | D217: 0.006 | E217: 0.002 | F217: 0.003 | G217: =IF(NOT(ISNUMBER(D217)),"",IF(NOT(ISNUMBER(E217)),"",D217-E217)) | H217: =IF(NOT(ISNUMBER(D217)),"",IF(NOT(ISNUMBER(F217)),"",D217-F217)) | I217: =IF(AND(K217="",L217=""),"N/A",IF(AND(ABS(N(K217))<0.0005,ABS(N(L217))<0.0005),"Stable",IF(AND(L217="",ABS(N(K217))>=0.0005),IF(N(K217)>0,"Accelerating","Slowing"),IF(AND(K217="",ABS(N(L217))>=0.0005),IF(N(L217)>0,"Accelerating","Slowing"),IF(AND(N(K217)>0,N(L217)>=0),"Accelerating",IF(AND(N(K217)<0,N(L217)<=0),"Slowing","Mixed")))))) | J217: =IF(OR(ISNUMBER(SEARCH("Unemployment",C217)),ISNUMBER(SEARCH("Claims",C217)),ISNUMBER(SEARCH("Jobless",C217)),ISNUMBER(SEARCH("Inventories",C217)),ISNUMBER(SEARCH("Wholesale Inventories",C217)),ISNUMBER(SEARCH("JOLTS Job Openings",C217)),ISNUMBER(SEARCH("Inflation Expectations",C217))),-1,1) | K217: =IF(OR(G217="",G217="(NA)"),"",J217*G217) | L217: =IF(OR(H217="",H217="(NA)"),"",J217*H217) | N217: 46006 | O217: US 5s30s | P217: =IF(OR(P212="",P214=""),"",P214-P212) | Q217: =IF(OR(Q212="",Q214=""),"",Q214-Q212) | R217: =IF(OR(R212="",R214=""),"",R214-R212) | S217: =IF(OR(S212="",S214=""),"",S214-S212) | T217: =IF(OR(P217="",Q217=""),"",P217-Q217) | U217: =IF(OR(P217="",R217=""),"",P217-R217) | V217: =IF(OR(P217="",S217=""),"",P217-S217) | W217: =IF(P217="","",IF(AND(U217>0.03,V217>0),"Rising",IF(AND(U217<-0.03,V217<0),"Falling","Flat"))) | X217: =IF(W217="","",IFERROR(VLOOKUP(W217,Backend!$D$324:$E$337,2,FALSE)*1,0))
A218: 45987 | B218: Growth - US | C218: Durable Goods Orders m/m | D218: 0.005 | E218: 0.005 | F218: 0.03 | G218: =IF(NOT(ISNUMBER(D218)),"",IF(NOT(ISNUMBER(E218)),"",D218-E218)) | H218: =IF(NOT(ISNUMBER(D218)),"",IF(NOT(ISNUMBER(F218)),"",D218-F218)) | I218: =IF(AND(K218="",L218=""),"N/A",IF(AND(ABS(N(K218))<0.0005,ABS(N(L218))<0.0005),"Stable",IF(AND(L218="",ABS(N(K218))>=0.0005),IF(N(K218)>0,"Accelerating","Slowing"),IF(AND(K218="",ABS(N(L218))>=0.0005),IF(N(L218)>0,"Accelerating","Slowing"),IF(AND(N(K218)>0,N(L218)>=0),"Accelerating",IF(AND(N(K218)<0,N(L218)<=0),"Slowing","Mixed")))))) | J218: =IF(OR(ISNUMBER(SEARCH("Unemployment",C218)),ISNUMBER(SEARCH("Claims",C218)),ISNUMBER(SEARCH("Jobless",C218)),ISNUMBER(SEARCH("Inventories",C218)),ISNUMBER(SEARCH("Wholesale Inventories",C218)),ISNUMBER(SEARCH("JOLTS Job Openings",C218)),ISNUMBER(SEARCH("Inflation Expectations",C218))),-1,1) | K218: =IF(OR(G218="",G218="(NA)"),"",J218*G218) | L218: =IF(OR(H218="",H218="(NA)"),"",J218*H218)
A219: 45987 | B219: Labour – US | C219: Unemployment Claims | D219: 216000 | E219: 226000 | F219: 222000 | G219: =IF(NOT(ISNUMBER(D219)),"",IF(NOT(ISNUMBER(E219)),"",D219-E219)) | H219: =IF(NOT(ISNUMBER(D219)),"",IF(NOT(ISNUMBER(F219)),"",D219-F219)) | I219: =IF(AND(K219="",L219=""),"N/A",IF(AND(ABS(N(K219))<0.0005,ABS(N(L219))<0.0005),"Stable",IF(AND(L219="",ABS(N(K219))>=0.0005),IF(N(K219)>0,"Accelerating","Slowing"),IF(AND(K219="",ABS(N(L219))>=0.0005),IF(N(L219)>0,"Accelerating","Slowing"),IF(AND(N(K219)>0,N(L219)>=0),"Accelerating",IF(AND(N(K219)<0,N(L219)<=0),"Slowing","Mixed")))))) | J219: =IF(OR(ISNUMBER(SEARCH("Unemployment",C219)),ISNUMBER(SEARCH("Claims",C219)),ISNUMBER(SEARCH("Jobless",C219)),ISNUMBER(SEARCH("Inventories",C219)),ISNUMBER(SEARCH("Wholesale Inventories",C219)),ISNUMBER(SEARCH("JOLTS Job Openings",C219)),ISNUMBER(SEARCH("Inflation Expectations",C219))),-1,1) | K219: =IF(OR(G219="",G219="(NA)"),"",J219*G219) | L219: =IF(OR(H219="",H219="(NA)"),"",J219*H219) | N219: Date | O219: Tenor | T219: Δd (1d) | U219: Δ5d
A220: 45988 | B220: Growth - EUR | C220: German GfK Consumer Climate | D220: -23.2 | E220: -23.6 | F220: -24.1 | G220: =IF(NOT(ISNUMBER(D220)),"",IF(NOT(ISNUMBER(E220)),"",D220-E220)) | H220: =IF(NOT(ISNUMBER(D220)),"",IF(NOT(ISNUMBER(F220)),"",D220-F220)) | I220: =IF(AND(K220="",L220=""),"N/A",IF(AND(ABS(N(K220))<0.0005,ABS(N(L220))<0.0005),"Stable",IF(AND(L220="",ABS(N(K220))>=0.0005),IF(N(K220)>0,"Accelerating","Slowing"),IF(AND(K220="",ABS(N(L220))>=0.0005),IF(N(L220)>0,"Accelerating","Slowing"),IF(AND(N(K220)>0,N(L220)>=0),"Accelerating",IF(AND(N(K220)<0,N(L220)<=0),"Slowing","Mixed")))))) | J220: =IF(OR(ISNUMBER(SEARCH("Unemployment",C220)),ISNUMBER(SEARCH("Claims",C220)),ISNUMBER(SEARCH("Jobless",C220)),ISNUMBER(SEARCH("Inventories",C220)),ISNUMBER(SEARCH("Wholesale Inventories",C220)),ISNUMBER(SEARCH("JOLTS Job Openings",C220)),ISNUMBER(SEARCH("Inflation Expectations",C220))),-1,1) | K220: =IF(OR(G220="",G220="(NA)"),"",J220*G220) | L220: =IF(OR(H220="",H220="(NA)"),"",J220*H220) | N220: 46006 | O220: DE 2y | T220: =IF(OR(P220="",Q220=""),"",P220-Q220) | U220: =IF(OR(P220="",R220=""),"",P220-R220) | V220: =IF(OR(P220="",S220=""),"",P220-S220) | W220: =IF(P220="","",IF(AND(U220>0.03,V220>0),"Rising",IF(AND(U220<-0.03,V220<0),"Falling","Flat")))
A221: 45989 | B221: Inflation – EUR | C221: German Prelim CPI m/m | D221: 0.002 | E221: 0 | F221: 0.003 | G221: =IF(NOT(ISNUMBER(D221)),"",IF(NOT(ISNUMBER(E221)),"",D221-E221)) | H221: =IF(NOT(ISNUMBER(D221)),"",IF(NOT(ISNUMBER(F221)),"",D221-F221)) | I221: =IF(AND(K221="",L221=""),"N/A",IF(AND(ABS(N(K221))<0.0005,ABS(N(L221))<0.0005),"Stable",IF(AND(L221="",ABS(N(K221))>=0.0005),IF(N(K221)>0,"Accelerating","Slowing"),IF(AND(K221="",ABS(N(L221))>=0.0005),IF(N(L221)>0,"Accelerating","Slowing"),IF(AND(N(K221)>0,N(L221)>=0),"Accelerating",IF(AND(N(K221)<0,N(L221)<=0),"Slowing","Mixed")))))) | J221: =IF(OR(ISNUMBER(SEARCH("Unemployment",C221)),ISNUMBER(SEARCH("Claims",C221)),ISNUMBER(SEARCH("Jobless",C221)),ISNUMBER(SEARCH("Inventories",C221)),ISNUMBER(SEARCH("Wholesale Inventories",C221)),ISNUMBER(SEARCH("JOLTS Job Openings",C221)),ISNUMBER(SEARCH("Inflation Expectations",C221))),-1,1) | K221: =IF(OR(G221="",G221="(NA)"),"",J221*G221) | L221: =IF(OR(H221="",H221="(NA)"),"",J221*H221) | N221: 46006 | O221: DE 5y | T221: =IF(OR(P221="",Q221=""),"",P221-Q221) | U221: =IF(OR(P221="",R221=""),"",P221-R221) | V221: =IF(OR(P221="",S221=""),"",P221-S221) | W221: =IF(P221="","",IF(AND(U221>0.03,V221>0),"Rising",IF(AND(U221<-0.03,V221<0),"Falling","Flat")))
A222: 45989 | B222: Labour – EUR | C222: German Unemployment Change | D222: 1000 | E222: 4000 | F222: -2000 | G222: =IF(NOT(ISNUMBER(D222)),"",IF(NOT(ISNUMBER(E222)),"",D222-E222)) | H222: =IF(NOT(ISNUMBER(D222)),"",IF(NOT(ISNUMBER(F222)),"",D222-F222)) | I222: =IF(AND(K222="",L222=""),"N/A",IF(AND(ABS(N(K222))<0.0005,ABS(N(L222))<0.0005),"Stable",IF(AND(L222="",ABS(N(K222))>=0.0005),IF(N(K222)>0,"Accelerating","Slowing"),IF(AND(K222="",ABS(N(L222))>=0.0005),IF(N(L222)>0,"Accelerating","Slowing"),IF(AND(N(K222)>0,N(L222)>=0),"Accelerating",IF(AND(N(K222)<0,N(L222)<=0),"Slowing","Mixed")))))) | J222: =IF(OR(ISNUMBER(SEARCH("Unemployment",C222)),ISNUMBER(SEARCH("Claims",C222)),ISNUMBER(SEARCH("Jobless",C222)),ISNUMBER(SEARCH("Inventories",C222)),ISNUMBER(SEARCH("Wholesale Inventories",C222)),ISNUMBER(SEARCH("JOLTS Job Openings",C222)),ISNUMBER(SEARCH("Inflation Expectations",C222))),-1,1) | K222: =IF(OR(G222="",G222="(NA)"),"",J222*G222) | L222: =IF(OR(H222="",H222="(NA)"),"",J222*H222) | N222: 46006 | O222: DE 10y | T222: =IF(OR(P222="",Q222=""),"",P222-Q222) | U222: =IF(OR(P222="",R222=""),"",P222-R222) | V222: =IF(OR(P222="",S222=""),"",P222-S222) | W222: =IF(P222="","",IF(AND(U222>0.03,V222>0),"Rising",IF(AND(U222<-0.03,V222<0),"Falling","Flat")))
A223: 45992 | B223: Growth - US | C223: Final Manufacturing PMI | D223: 52.2 | E223: 51.9 | F223: 51.9 | G223: =IF(NOT(ISNUMBER(D223)),"",IF(NOT(ISNUMBER(E223)),"",D223-E223)) | H223: =IF(NOT(ISNUMBER(D223)),"",IF(NOT(ISNUMBER(F223)),"",D223-F223)) | I223: =IF(AND(K223="",L223=""),"N/A",IF(AND(ABS(N(K223))<0.0005,ABS(N(L223))<0.0005),"Stable",IF(AND(L223="",ABS(N(K223))>=0.0005),IF(N(K223)>0,"Accelerating","Slowing"),IF(AND(K223="",ABS(N(L223))>=0.0005),IF(N(L223)>0,"Accelerating","Slowing"),IF(AND(N(K223)>0,N(L223)>=0),"Accelerating",IF(AND(N(K223)<0,N(L223)<=0),"Slowing","Mixed")))))) | J223: =IF(OR(ISNUMBER(SEARCH("Unemployment",C223)),ISNUMBER(SEARCH("Claims",C223)),ISNUMBER(SEARCH("Jobless",C223)),ISNUMBER(SEARCH("Inventories",C223)),ISNUMBER(SEARCH("Wholesale Inventories",C223)),ISNUMBER(SEARCH("JOLTS Job Openings",C223)),ISNUMBER(SEARCH("Inflation Expectations",C223))),-1,1) | K223: =IF(OR(G223="",G223="(NA)"),"",J223*G223) | L223: =IF(OR(H223="",H223="(NA)"),"",J223*H223) | N223: 46006 | O223: DE 30y | T223: =IF(OR(P223="",Q223=""),"",P223-Q223) | U223: =IF(OR(P223="",R223=""),"",P223-R223) | V223: =IF(OR(P223="",S223=""),"",P223-S223) | W223: =IF(P223="","",IF(AND(U223>0.03,V223>0),"Rising",IF(AND(U223<-0.03,V223<0),"Falling","Flat")))
A224: 45992 | B224: Growth - US | C224: ISM Manufacturing Prices | D224: 58.5 | E224: 59.5 | F224: 58 | G224: =IF(NOT(ISNUMBER(D224)),"",IF(NOT(ISNUMBER(E224)),"",D224-E224)) | H224: =IF(NOT(ISNUMBER(D224)),"",IF(NOT(ISNUMBER(F224)),"",D224-F224)) | I224: =IF(AND(K224="",L224=""),"N/A",IF(AND(ABS(N(K224))<0.0005,ABS(N(L224))<0.0005),"Stable",IF(AND(L224="",ABS(N(K224))>=0.0005),IF(N(K224)>0,"Accelerating","Slowing"),IF(AND(K224="",ABS(N(L224))>=0.0005),IF(N(L224)>0,"Accelerating","Slowing"),IF(AND(N(K224)>0,N(L224)>=0),"Accelerating",IF(AND(N(K224)<0,N(L224)<=0),"Slowing","Mixed")))))) | J224: =IF(OR(ISNUMBER(SEARCH("Unemployment",C224)),ISNUMBER(SEARCH("Claims",C224)),ISNUMBER(SEARCH("Jobless",C224)),ISNUMBER(SEARCH("Inventories",C224)),ISNUMBER(SEARCH("Wholesale Inventories",C224)),ISNUMBER(SEARCH("JOLTS Job Openings",C224)),ISNUMBER(SEARCH("Inflation Expectations",C224))),-1,1) | K224: =IF(OR(G224="",G224="(NA)"),"",J224*G224) | L224: =IF(OR(H224="",H224="(NA)"),"",J224*H224) | N224: Date | O224: Tenor | T224: Δd (1d) | U224: Δ5d
A225: 45992 | B225: Growth - US | C225: ISM Manufacturing PMI | D225: 48.2 | E225: 49 | F225: 48.7 | G225: =IF(NOT(ISNUMBER(D225)),"",IF(NOT(ISNUMBER(E225)),"",D225-E225)) | H225: =IF(NOT(ISNUMBER(D225)),"",IF(NOT(ISNUMBER(F225)),"",D225-F225)) | I225: =IF(AND(K225="",L225=""),"N/A",IF(AND(ABS(N(K225))<0.0005,ABS(N(L225))<0.0005),"Stable",IF(AND(L225="",ABS(N(K225))>=0.0005),IF(N(K225)>0,"Accelerating","Slowing"),IF(AND(K225="",ABS(N(L225))>=0.0005),IF(N(L225)>0,"Accelerating","Slowing"),IF(AND(N(K225)>0,N(L225)>=0),"Accelerating",IF(AND(N(K225)<0,N(L225)<=0),"Slowing","Mixed")))))) | J225: =IF(OR(ISNUMBER(SEARCH("Unemployment",C225)),ISNUMBER(SEARCH("Claims",C225)),ISNUMBER(SEARCH("Jobless",C225)),ISNUMBER(SEARCH("Inventories",C225)),ISNUMBER(SEARCH("Wholesale Inventories",C225)),ISNUMBER(SEARCH("JOLTS Job Openings",C225)),ISNUMBER(SEARCH("Inflation Expectations",C225))),-1,1) | K225: =IF(OR(G225="",G225="(NA)"),"",J225*G225) | L225: =IF(OR(H225="",H225="(NA)"),"",J225*H225) | N225: 46006 | O225: DE 2s10s | P225: =IF(OR(P220="",P222=""),"",(P222-P220)*100) | Q225: =IF(OR(Q220="",Q222=""),"",(Q222-Q220)*100) | R225: =IF(OR(R220="",R222=""),"",(R222-R220)*100) | S225: =IF(OR(S220="",S222=""),"",(S222-S220)*100) | T225: =IF(OR(P225="",Q225=""),"",P225-Q225) | U225: =IF(OR(P225="",R225=""),"",P225-R225) | V225: =IF(OR(P225="",S225=""),"",P225-S225) | W225: =IF(P225="","",IF(AND(U225>3,V225>0),"Rising",IF(AND(U225<-3,V225<0),"Falling","Flat")))
A226: 45992 | B226: Growth - US | C226: Final Manufacturing PMI | D226: 52.2 | E226: 51.9 | F226: 51.9 | G226: =IF(NOT(ISNUMBER(D226)),"",IF(NOT(ISNUMBER(E226)),"",D226-E226)) | H226: =IF(NOT(ISNUMBER(D226)),"",IF(NOT(ISNUMBER(F226)),"",D226-F226)) | I226: =IF(AND(K226="",L226=""),"N/A",IF(AND(ABS(N(K226))<0.0005,ABS(N(L226))<0.0005),"Stable",IF(AND(L226="",ABS(N(K226))>=0.0005),IF(N(K226)>0,"Accelerating","Slowing"),IF(AND(K226="",ABS(N(L226))>=0.0005),IF(N(L226)>0,"Accelerating","Slowing"),IF(AND(N(K226)>0,N(L226)>=0),"Accelerating",IF(AND(N(K226)<0,N(L226)<=0),"Slowing","Mixed")))))) | J226: =IF(OR(ISNUMBER(SEARCH("Unemployment",C226)),ISNUMBER(SEARCH("Claims",C226)),ISNUMBER(SEARCH("Jobless",C226)),ISNUMBER(SEARCH("Inventories",C226)),ISNUMBER(SEARCH("Wholesale Inventories",C226)),ISNUMBER(SEARCH("JOLTS Job Openings",C226)),ISNUMBER(SEARCH("Inflation Expectations",C226))),-1,1) | K226: =IF(OR(G226="",G226="(NA)"),"",J226*G226) | L226: =IF(OR(H226="",H226="(NA)"),"",J226*H226) | N226: 46006 | O226: DE 5s30s | P226: =IF(OR(P221="",P223=""),"",(P223-P221)*100) | Q226: =IF(OR(Q221="",Q223=""),"",(Q223-Q221)*100) | R226: =IF(OR(R221="",R223=""),"",(R223-R221)*100) | S226: =IF(OR(S221="",S223=""),"",(S223-S221)*100) | T226: =IF(OR(P226="",Q226=""),"",P226-Q226) | U226: =IF(OR(P226="",R226=""),"",P226-R226) | V226: =IF(OR(P226="",S226=""),"",P226-S226) | W226: =IF(P226="","",IF(AND(U226>3,V226>0),"Rising",IF(AND(U226<-3,V226<0),"Falling","Flat")))
A227: 45992 | B227: Growth - US | C227: ISM Manufacturing Prices | D227: 58.5 | E227: 59.5 | F227: 58 | G227: =IF(NOT(ISNUMBER(D227)),"",IF(NOT(ISNUMBER(E227)),"",D227-E227)) | H227: =IF(NOT(ISNUMBER(D227)),"",IF(NOT(ISNUMBER(F227)),"",D227-F227)) | I227: =IF(AND(K227="",L227=""),"N/A",IF(AND(ABS(N(K227))<0.0005,ABS(N(L227))<0.0005),"Stable",IF(AND(L227="",ABS(N(K227))>=0.0005),IF(N(K227)>0,"Accelerating","Slowing"),IF(AND(K227="",ABS(N(L227))>=0.0005),IF(N(L227)>0,"Accelerating","Slowing"),IF(AND(N(K227)>0,N(L227)>=0),"Accelerating",IF(AND(N(K227)<0,N(L227)<=0),"Slowing","Mixed")))))) | J227: =IF(OR(ISNUMBER(SEARCH("Unemployment",C227)),ISNUMBER(SEARCH("Claims",C227)),ISNUMBER(SEARCH("Jobless",C227)),ISNUMBER(SEARCH("Inventories",C227)),ISNUMBER(SEARCH("Wholesale Inventories",C227)),ISNUMBER(SEARCH("JOLTS Job Openings",C227)),ISNUMBER(SEARCH("Inflation Expectations",C227))),-1,1) | K227: =IF(OR(G227="",G227="(NA)"),"",J227*G227) | L227: =IF(OR(H227="",H227="(NA)"),"",J227*H227)
A228: 45992 | B228: Growth - US | C228: ISM Manufacturing PMI | D228: 48.2 | E228: 49 | F228: 48.7 | G228: =IF(NOT(ISNUMBER(D228)),"",IF(NOT(ISNUMBER(E228)),"",D228-E228)) | H228: =IF(NOT(ISNUMBER(D228)),"",IF(NOT(ISNUMBER(F228)),"",D228-F228)) | I228: =IF(AND(K228="",L228=""),"N/A",IF(AND(ABS(N(K228))<0.0005,ABS(N(L228))<0.0005),"Stable",IF(AND(L228="",ABS(N(K228))>=0.0005),IF(N(K228)>0,"Accelerating","Slowing"),IF(AND(K228="",ABS(N(L228))>=0.0005),IF(N(L228)>0,"Accelerating","Slowing"),IF(AND(N(K228)>0,N(L228)>=0),"Accelerating",IF(AND(N(K228)<0,N(L228)<=0),"Slowing","Mixed")))))) | J228: =IF(OR(ISNUMBER(SEARCH("Unemployment",C228)),ISNUMBER(SEARCH("Claims",C228)),ISNUMBER(SEARCH("Jobless",C228)),ISNUMBER(SEARCH("Inventories",C228)),ISNUMBER(SEARCH("Wholesale Inventories",C228)),ISNUMBER(SEARCH("JOLTS Job Openings",C228)),ISNUMBER(SEARCH("Inflation Expectations",C228))),-1,1) | K228: =IF(OR(G228="",G228="(NA)"),"",J228*G228) | L228: =IF(OR(H228="",H228="(NA)"),"",J228*H228) | N228: Date | O228: Tenor | T228: Δd (1d) | U228: Δ5d
A229: 45993 | B229: Growth - US | C229: FOMC Member Bowman Speaks | D229: (NA) | E229: (NA) | F229: (NA) | G229: =IF(NOT(ISNUMBER(D229)),"",IF(NOT(ISNUMBER(E229)),"",D229-E229)) | H229: =IF(NOT(ISNUMBER(D229)),"",IF(NOT(ISNUMBER(F229)),"",D229-F229)) | I229: =IF(AND(K229="",L229=""),"N/A",IF(AND(ABS(N(K229))<0.0005,ABS(N(L229))<0.0005),"Stable",IF(AND(L229="",ABS(N(K229))>=0.0005),IF(N(K229)>0,"Accelerating","Slowing"),IF(AND(K229="",ABS(N(L229))>=0.0005),IF(N(L229)>0,"Accelerating","Slowing"),IF(AND(N(K229)>0,N(L229)>=0),"Accelerating",IF(AND(N(K229)<0,N(L229)<=0),"Slowing","Mixed")))))) | J229: =IF(OR(ISNUMBER(SEARCH("Unemployment",C229)),ISNUMBER(SEARCH("Claims",C229)),ISNUMBER(SEARCH("Jobless",C229)),ISNUMBER(SEARCH("Inventories",C229)),ISNUMBER(SEARCH("Wholesale Inventories",C229)),ISNUMBER(SEARCH("JOLTS Job Openings",C229)),ISNUMBER(SEARCH("Inflation Expectations",C229))),-1,1) | K229: =IF(OR(G229="",G229="(NA)"),"",J229*G229) | L229: =IF(OR(H229="",H229="(NA)"),"",J229*H229) | N229: 46006 | O229: JP 2y | T229: =IF(OR(P229="",Q229=""),"",P229-Q229) | U229: =IF(OR(P229="",R229=""),"",P229-R229) | V229: =IF(OR(P229="",S229=""),"",P229-S229) | W229: =IF(P229="","",IF(AND(U229>0.03,V229>0),"Rising",IF(AND(U229<-0.03,V229<0),"Falling","Flat")))
A230: 45993 | B230: Growth - US | C230: Import Prices m/m | D230: 0 | E230: 0.001 | F230: 0.001 | G230: =IF(NOT(ISNUMBER(D230)),"",IF(NOT(ISNUMBER(E230)),"",D230-E230)) | H230: =IF(NOT(ISNUMBER(D230)),"",IF(NOT(ISNUMBER(F230)),"",D230-F230)) | I230: =IF(AND(K230="",L230=""),"N/A",IF(AND(ABS(N(K230))<0.0005,ABS(N(L230))<0.0005),"Stable",IF(AND(L230="",ABS(N(K230))>=0.0005),IF(N(K230)>0,"Accelerating","Slowing"),IF(AND(K230="",ABS(N(L230))>=0.0005),IF(N(L230)>0,"Accelerating","Slowing"),IF(AND(N(K230)>0,N(L230)>=0),"Accelerating",IF(AND(N(K230)<0,N(L230)<=0),"Slowing","Mixed")))))) | J230: =IF(OR(ISNUMBER(SEARCH("Unemployment",C230)),ISNUMBER(SEARCH("Claims",C230)),ISNUMBER(SEARCH("Jobless",C230)),ISNUMBER(SEARCH("Inventories",C230)),ISNUMBER(SEARCH("Wholesale Inventories",C230)),ISNUMBER(SEARCH("JOLTS Job Openings",C230)),ISNUMBER(SEARCH("Inflation Expectations",C230))),-1,1) | K230: =IF(OR(G230="",G230="(NA)"),"",J230*G230) | L230: =IF(OR(H230="",H230="(NA)"),"",J230*H230) | N230: 46006 | O230: JP 5y | T230: =IF(OR(P230="",Q230=""),"",P230-Q230) | U230: =IF(OR(P230="",R230=""),"",P230-R230) | V230: =IF(OR(P230="",S230=""),"",P230-S230) | W230: =IF(P230="","",IF(AND(U230>0.03,V230>0),"Rising",IF(AND(U230<-0.03,V230<0),"Falling","Flat")))
A231: 45993 | B231: Growth - US | C231: Capacity Utilization Rate | D231: 0.759 | E231: 0.769 | F231: 0.759 | G231: =IF(NOT(ISNUMBER(D231)),"",IF(NOT(ISNUMBER(E231)),"",D231-E231)) | H231: =IF(NOT(ISNUMBER(D231)),"",IF(NOT(ISNUMBER(F231)),"",D231-F231)) | I231: =IF(AND(K231="",L231=""),"N/A",IF(AND(ABS(N(K231))<0.0005,ABS(N(L231))<0.0005),"Stable",IF(AND(L231="",ABS(N(K231))>=0.0005),IF(N(K231)>0,"Accelerating","Slowing"),IF(AND(K231="",ABS(N(L231))>=0.0005),IF(N(L231)>0,"Accelerating","Slowing"),IF(AND(N(K231)>0,N(L231)>=0),"Accelerating",IF(AND(N(K231)<0,N(L231)<=0),"Slowing","Mixed")))))) | J231: =IF(OR(ISNUMBER(SEARCH("Unemployment",C231)),ISNUMBER(SEARCH("Claims",C231)),ISNUMBER(SEARCH("Jobless",C231)),ISNUMBER(SEARCH("Inventories",C231)),ISNUMBER(SEARCH("Wholesale Inventories",C231)),ISNUMBER(SEARCH("JOLTS Job Openings",C231)),ISNUMBER(SEARCH("Inflation Expectations",C231))),-1,1) | K231: =IF(OR(G231="",G231="(NA)"),"",J231*G231) | L231: =IF(OR(H231="",H231="(NA)"),"",J231*H231) | N231: 46006 | O231: JP 10y | T231: =IF(OR(P231="",Q231=""),"",P231-Q231) | U231: =IF(OR(P231="",R231=""),"",P231-R231) | V231: =IF(OR(P231="",S231=""),"",P231-S231) | W231: =IF(P231="","",IF(AND(U231>0.03,V231>0),"Rising",IF(AND(U231<-0.03,V231<0),"Falling","Flat")))
...
