Workbook
Name Macro_Data: Table9[[#All],[Category]:[Qualitative]]
Name tblMacroUS: Table9[[#All],[Category]:[Qualitative]]
Name tblPolicy: #REF!

Sheet Summary
A1: Label | B1: Value
A2: Monthly Target ($) | B2: 20000
A3: Planned Active Trading Days | B3: 17
A4: Average Target per Trading Day ($) | B4: =B2/B3 -> 1176.4706
A5: Weeks in Cycle | B5: 4
A6: Average Target per Week ($) | B6: =B2/B5 -> 5000
A7: Required R per week | B7: =B6/B17 -> 9.0226504
A8: Risk % of NAV per trade | B8: 0.07
A9: Max Daily Loss (R multiples) | B9: 2
A10: Current NAV ($) | B10: 7175.38
A11: Cumulative P&L Month ($) | B11: =IFERROR(LOOKUP(2,1/('Daily Log'!$I:$I<>""),'Daily Log'!$I:$I),"") -> 515.0023
A12: Remaining Target ($) | B12: =B2-B11 -> 19484.998
A13: Trading Days Used | B13: =COUNTIFS('Daily Log'!D:D,"Y") -> 2
A14: Trading Days Remaining | B14: =B3-B13 -> 15
A15: Required P&L per Remaining Day | B15: =IF(B14>0,B12/B14,"") -> 1298.9998
A16: Target R per Day (approx) | B16: =IF(AND(B14>0,B18>0),B15/B18,"") -> 2.610573
A17: Projected Month P&L ($) | B17: =B11+(B14*B16) -> 554.1609
A18: Average R value ($) | B18: =IF(K22>0,B11/K22,"") -> 497.59185
A19: Today’s expected plan P&L ($) | B19: =Planner_v2!AF18
A21: Week # | B21: Active Days | C21: Total Trades | D21: Total Wins | E21: Total Losses | F21: Week Net P&L | G21: Weekly Target | H21: Week Variance ($) | I21: Avg Win Rate % | J21: Avg Reward:Risk | K21: Total R | L21: Avg R per Day
A22: 1 | B22: =COUNTIFS('Daily Log'!$B:$B,$A22,'Daily Log'!$D:$D,"Y") -> 2 | C22: =SUMIFS('Daily Log'!$N:$N,'Daily Log'!$B:$B,$A22) -> 2 | D22: =SUMIFS('Daily Log'!$O:$O,'Daily Log'!$B:$B,$A22) -> 1 | E22: =SUMIFS('Daily Log'!$P:$P,'Daily Log'!$B:$B,$A22) -> 1 | F22: =SUMIFS('Daily Log'!$H:$H,'Daily Log'!$B:$B,$A22) -> 515.0023 | G22: =$B$6 -> 5000 | H22: =F22-G22 -> -4484.9977 | I22: =IF(B22>0,AVERAGEIFS('Daily Log'!$S:$S,'Daily Log'!$B:$B,$A22,'Daily Log'!$D:$D,"Y"),"") -> 0.5 | J22: =IF(B22>0,IFERROR(AVERAGEIFS('Daily Log'!$T:$T,'Daily Log'!$B:$B,$A22,'Daily Log'!$D:$D,"Y",'Daily Log'!$T:$T,">0"),""),"") | K22: =SUMIFS('Daily Log'!$U:$U,'Daily Log'!$B:$B,$A22,'Daily Log'!$D:$D,"Y") -> 1.0349894 | L22: =IF(B22>0,K22/B22,"") -> 0.51749471
A23: 2 | B23: =COUNTIFS('Daily Log'!$B:$B,$A23,'Daily Log'!$D:$D,"Y") -> 0 | C23: =SUMIFS('Daily Log'!$N:$N,'Daily Log'!$B:$B,$A23) -> 0 | D23: =SUMIFS('Daily Log'!$O:$O,'Daily Log'!$B:$B,$A23) -> 0 | E23: =SUMIFS('Daily Log'!$P:$P,'Daily Log'!$B:$B,$A23) -> 0 | F23: =SUMIFS('Daily Log'!$H:$H,'Daily Log'!$B:$B,$A23) -> 0 | G23: =$B$6 -> 5000 | H23: =F23-G23 -> -5000 | I23: =IF(B23>0,AVERAGEIFS('Daily Log'!$S:$S,'Daily Log'!$B:$B,$A23,'Daily Log'!$D:$D,"Y"),"") | J23: =IF(B23>0,AVERAGEIFS('Daily Log'!$T:$T,'Daily Log'!$B:$B,$A23,'Daily Log'!$D:$D,"Y",'Daily Log'!$T:$T,">0"),"") | K23: =SUMIFS('Daily Log'!$U:$U,'Daily Log'!$B:$B,$A23,'Daily Log'!$D:$D,"Y") -> 0 | L23: =IF(B23>0,K23/B23,"")
A24: 3 | B24: =COUNTIFS('Daily Log'!$B:$B,$A24,'Daily Log'!$D:$D,"Y") -> 0 | C24: =SUMIFS('Daily Log'!$N:$N,'Daily Log'!$B:$B,$A24) -> 0 | D24: =SUMIFS('Daily Log'!$O:$O,'Daily Log'!$B:$B,$A24) -> 0 | E24: =SUMIFS('Daily Log'!$P:$P,'Daily Log'!$B:$B,$A24) -> 0 | F24: =SUMIFS('Daily Log'!$H:$H,'Daily Log'!$B:$B,$A24) -> 0 | G24: =$B$6 -> 5000 | H24: =F24-G24 -> -5000 | I24: =IF(B24>0,AVERAGEIFS('Daily Log'!$S:$S,'Daily Log'!$B:$B,$A24,'Daily Log'!$D:$D,"Y"),"") | J24: =IF(B24>0,AVERAGEIFS('Daily Log'!$T:$T,'Daily Log'!$B:$B,$A24,'Daily Log'!$D:$D,"Y",'Daily Log'!$T:$T,">0"),"") | K24: =SUMIFS('Daily Log'!$U:$U,'Daily Log'!$B:$B,$A24,'Daily Log'!$D:$D,"Y") -> 0 | L24: =IF(B24>0,K24/B24,"")
A25: 4 | B25: =COUNTIFS('Daily Log'!$B:$B,$A25,'Daily Log'!$D:$D,"Y") -> 0 | C25: =SUMIFS('Daily Log'!$N:$N,'Daily Log'!$B:$B,$A25) -> 0 | D25: =SUMIFS('Daily Log'!$O:$O,'Daily Log'!$B:$B,$A25) -> 0 | E25: =SUMIFS('Daily Log'!$P:$P,'Daily Log'!$B:$B,$A25) -> 0 | F25: =SUMIFS('Daily Log'!$H:$H,'Daily Log'!$B:$B,$A25) -> 0 | G25: =$B$6 -> 5000 | H25: =F25-G25 -> -5000 | I25: =IF(B25>0,AVERAGEIFS('Daily Log'!$S:$S,'Daily Log'!$B:$B,$A25,'Daily Log'!$D:$D,"Y"),"") | J25: =IF(B25>0,AVERAGEIFS('Daily Log'!$T:$T,'Daily Log'!$B:$B,$A25,'Daily Log'!$D:$D,"Y",'Daily Log'!$T:$T,">0"),"") | K25: =SUMIFS('Daily Log'!$U:$U,'Daily Log'!$B:$B,$A25,'Daily Log'!$D:$D,"Y") -> 0 | L25: =IF(B25>0,K25/B25,"")

Sheet Daily Log
A1: Date | B1: Week # | C1: Day of Week | D1: Active Trading Day? (Y/N) | E1: Start NAV ($) | F1: Risk per Trade R ($) | G1: Max Daily Loss Cap ($) | H1: Net P&L ($) | I1: Cumulative P&L Month ($) | J1: Week P&L ($) | K1: Weekly Target ($) | L1: Week Variance vs Target ($) | M1: Notes | N1: # Trades | O1: # Wins | P1: # Losses | Q1: Total Wins ($) | R1: Total Losses ($) | S1: Win Rate (%) | T1: Reward:Risk | U1: Daily R-multiple | V1: Losses vs Cap | W1: Intraday Net P&L (so far) | X1: % of Cap Used (Net) | Y1: Worst Intraday DD % of Cap
A2: 46033 | B2: 1 | C2: =TEXT(A2,"dddd") -> Sunday | D2: Y | E2: 7175.38 | F2: =IF($A2="","",$E2*Summary!$B$8) -> 502.2766 | G2: =IF($A2="","",F2*Summary!$B$9) -> 1004.5532 | H2: =IF($A2="","",SUMIFS('Raw daily data'!$F:$F,'Raw daily data'!$I:$I,$A2)) -> -60 | I2: =H2 -> -60 | J2: =SUMIF($B$2:$B$41,B2,$H$2:$H$41) -> 515.0023 | K2: =Summary!$B$6 -> 5000 | L2: =J2-K2 -> -4484.9977 | N2: =IF($A2="","",COUNTIFS('Raw daily data'!$I:$I,$A2)) -> 1 | O2: =IF($A2="","",COUNTIFS('Raw daily data'!$I:$I,$A2,'Raw daily data'!$F:$F,">0")) -> 0 | P2: =IF($A2="","",COUNTIFS('Raw daily data'!$I:$I,$A2,'Raw daily data'!$F:$F,"<0")) -> 1 | Q2: =IF($A2="","",SUMIFS('Raw daily data'!$F:$F,'Raw daily data'!$I:$I,$A2,'Raw daily data'!$F:$F,">0")) -> 0 | R2: =IF($A2="","",ABS(SUMIFS('Raw daily data'!$F:$F,'Raw daily data'!$I:$I,$A2,'Raw daily data'!$F:$F,"<0"))) -> 60 | S2: =IF(N2>0,O2/N2,"") -> 0 | T2: =IF(R2>0,Q2/ABS(R2),"") -> 0 | U2: =IF(F2>0,H2/F2,"") -> -0.11945609 | V2: =IF(H2<0,MIN(ABS(H2)/G2,1),0) -> 0.059728046 | W2: =IF($A2="","",_xlfn.MAXIFS('Raw daily data'!$J:$J,'Raw daily data'!$I:$I,$A2)) -> -60 | X2: =IF(W2>=0,0,ABS(W2)/G2) -> 0.059728046 | Y2: =IF($A2="","",ABS(MIN(0,_xlfn.MINIFS('Raw daily data'!$J:$J,'Raw daily data'!$I:$I,$A2)))/G2) -> 0.059728046
A3: 46034 | B3: 1 | C3: =TEXT(A3,"dddd") -> Monday | D3: Y | E3: =E2+H2 -> 7115.38 | F3: =IF($A3="","",$E3*Summary!$B$8) -> 498.0766 | G3: =IF($A3="","",F3*Summary!$B$9) -> 996.1532 | H3: =IF($A3="","",SUMIFS('Raw daily data'!$F:$F,'Raw daily data'!$I:$I,$A3)) -> 575.0023 | I3: =I2+H3 -> 515.0023 | J3: =SUMIF($B$2:$B$41,B3,$H$2:$H$41) -> 515.0023 | K3: =Summary!$B$6 -> 5000 | L3: =J3-K3 -> -4484.9977 | N3: =IF($A3="","",COUNTIFS('Raw daily data'!$I:$I,$A3)) -> 1 | O3: =IF($A3="","",COUNTIFS('Raw daily data'!$I:$I,$A3,'Raw daily data'!$F:$F,">0")) -> 1 | P3: =IF($A3="","",COUNTIFS('Raw daily data'!$I:$I,$A3,'Raw daily data'!$F:$F,"<0")) -> 0 | Q3: =IF($A3="","",SUMIFS('Raw daily data'!$F:$F,'Raw daily data'!$I:$I,$A3,'Raw daily data'!$F:$F,">0")) -> 575.0023 | R3: =IF($A3="","",ABS(SUMIFS('Raw daily data'!$F:$F,'Raw daily data'!$I:$I,$A3,'Raw daily data'!$F:$F,"<0"))) -> 0 | S3: =IF(N3>0,O3/N3,"") -> 1 | T3: =IF(R3>0,Q3/ABS(R3),"") | U3: =IF(F3>0,H3/F3,"") -> 1.1544455 | V3: =IF(H3<0,MIN(ABS(H3)/G3,1),0) -> 0 | W3: =IF($A3="","",_xlfn.MAXIFS('Raw daily data'!$J:$J,'Raw daily data'!$I:$I,$A3)) -> 575.0023 | X3: =IF(W3>=0,0,ABS(W3)/G3) -> 0 | Y3: =IF($A3="","",ABS(MIN(0,_xlfn.MINIFS('Raw daily data'!$J:$J,'Raw daily data'!$I:$I,$A3)))/G3) -> 0
A4: 46035 | B4: 1 | C4: =TEXT(A4,"dddd") -> Tuesday | D4: N | E4: =E3+H3 -> 7690.3823 | F4: =IF($A4="","",$E4*Summary!$B$8) -> 538.32676 | G4: =IF($A4="","",F4*Summary!$B$9) -> 1076.6535 | H4: =IF($A4="","",SUMIFS('Raw daily data'!$F:$F,'Raw daily data'!$I:$I,$A4)) -> 0 | I4: =I3+H4 -> 515.0023 | J4: =SUMIF($B$2:$B$41,B4,$H$2:$H$41) -> 515.0023 | K4: =Summary!$B$6 -> 5000 | L4: =J4-K4 -> -4484.9977 | N4: =IF($A4="","",COUNTIFS('Raw daily data'!$I:$I,$A4)) -> 0 | O4: =IF($A4="","",COUNTIFS('Raw daily data'!$I:$I,$A4,'Raw daily data'!$F:$F,">0")) -> 0 | P4: =IF($A4="","",COUNTIFS('Raw daily data'!$I:$I,$A4,'Raw daily data'!$F:$F,"<0")) -> 0 | Q4: =IF($A4="","",SUMIFS('Raw daily data'!$F:$F,'Raw daily data'!$I:$I,$A4,'Raw daily data'!$F:$F,">0")) -> 0 | R4: =IF($A4="","",ABS(SUMIFS('Raw daily data'!$F:$F,'Raw daily data'!$I:$I,$A4,'Raw daily data'!$F:$F,"<0"))) -> 0 | S4: =IF(N4>0,O4/N4,"") | T4: =IF(R4>0,Q4/ABS(R4),"") | U4: =IF(F4>0,H4/F4,"") -> 0 | V4: =IF(H4<0,MIN(ABS(H4)/G4,1),0) -> 0 | W4: =IF($A4="","",_xlfn.MAXIFS('Raw daily data'!$J:$J,'Raw daily data'!$I:$I,$A4)) -> 0 | X4: =IF(W4>=0,0,ABS(W4)/G4) -> 0 | Y4: =IF($A4="","",ABS(MIN(0,_xlfn.MINIFS('Raw daily data'!$J:$J,'Raw daily data'!$I:$I,$A4)))/G4) -> 0
A5: 46036 | B5: 1 | C5: =TEXT(A5,"dddd") -> Wednesday | D5: N | E5: =E4+H4 -> 7690.3823 | F5: =IF($A5="","",$E5*Summary!$B$8) -> 538.32676 | G5: =IF($A5="","",F5*Summary!$B$9) -> 1076.6535 | H5: =IF($A5="","",SUMIFS('Raw daily data'!$F:$F,'Raw daily data'!$I:$I,$A5)) -> 0 | I5: =I4+H5 -> 515.0023 | J5: =SUMIF($B$2:$B$41,B5,$H$2:$H$41) -> 515.0023 | K5: =Summary!$B$6 -> 5000 | L5: =J5-K5 -> -4484.9977 | N5: =IF($A5="","",COUNTIFS('Raw daily data'!$I:$I,$A5)) -> 0 | O5: =IF($A5="","",COUNTIFS('Raw daily data'!$I:$I,$A5,'Raw daily data'!$F:$F,">0")) -> 0 | P5: =IF($A5="","",COUNTIFS('Raw daily data'!$I:$I,$A5,'Raw daily data'!$F:$F,"<0")) -> 0 | Q5: =IF($A5="","",SUMIFS('Raw daily data'!$F:$F,'Raw daily data'!$I:$I,$A5,'Raw daily data'!$F:$F,">0")) -> 0 | R5: =IF($A5="","",ABS(SUMIFS('Raw daily data'!$F:$F,'Raw daily data'!$I:$I,$A5,'Raw daily data'!$F:$F,"<0"))) -> 0 | S5: =IF(N5>0,O5/N5,"") | T5: =IF(R5>0,Q5/ABS(R5),"") | U5: =IF(F5>0,H5/F5,"") -> 0 | V5: =IF(H5<0,MIN(ABS(H5)/G5,1),0) -> 0 | W5: =IF($A5="","",_xlfn.MAXIFS('Raw daily data'!$J:$J,'Raw daily data'!$I:$I,$A5)) -> 0 | X5: =IF(W5>=0,0,ABS(W5)/G5) -> 0 | Y5: =IF($A5="","",ABS(MIN(0,_xlfn.MINIFS('Raw daily data'!$J:$J,'Raw daily data'!$I:$I,$A5)))/G5) -> 0
A6: 46037 | B6: 1 | C6: =TEXT(A6,"dddd") -> Thursday | D6: N | E6: =E5+H5 -> 7690.3823 | F6: =IF($A6="","",$E6*Summary!$B$8) -> 538.32676 | G6: =IF($A6="","",F6*Summary!$B$9) -> 1076.6535 | H6: =IF($A6="","",SUMIFS('Raw daily data'!$F:$F,'Raw daily data'!$I:$I,$A6)) -> 0 | I6: =I5+H6 -> 515.0023 | J6: =SUMIF($B$2:$B$41,B6,$H$2:$H$41) -> 515.0023 | K6: =Summary!$B$6 -> 5000 | L6: =J6-K6 -> -4484.9977 | N6: =IF($A6="","",COUNTIFS('Raw daily data'!$I:$I,$A6)) -> 0 | O6: =IF($A6="","",COUNTIFS('Raw daily data'!$I:$I,$A6,'Raw daily data'!$F:$F,">0")) -> 0 | P6: =IF($A6="","",COUNTIFS('Raw daily data'!$I:$I,$A6,'Raw daily data'!$F:$F,"<0")) -> 0 | Q6: =IF($A6="","",SUMIFS('Raw daily data'!$F:$F,'Raw daily data'!$I:$I,$A6,'Raw daily data'!$F:$F,">0")) -> 0 | R6: =IF($A6="","",ABS(SUMIFS('Raw daily data'!$F:$F,'Raw daily data'!$I:$I,$A6,'Raw daily data'!$F:$F,"<0"))) -> 0 | S6: =IF(N6>0,O6/N6,"") | T6: =IF(R6>0,Q6/ABS(R6),"") | U6: =IF(F6>0,H6/F6,"") -> 0 | V6: =IF(H6<0,MIN(ABS(H6)/G6,1),0) -> 0 | W6: =IF($A6="","",_xlfn.MAXIFS('Raw daily data'!$J:$J,'Raw daily data'!$I:$I,$A6)) -> 0 | X6: =IF(W6>=0,0,ABS(W6)/G6) -> 0 | Y6: =IF($A6="","",ABS(MIN(0,_xlfn.MINIFS('Raw daily data'!$J:$J,'Raw daily data'!$I:$I,$A6)))/G6) -> 0
A7: 46038 | B7: 1 | C7: =TEXT(A7,"dddd") -> Friday | D7: N | E7: =E6+H6 -> 7690.3823 | F7: =IF($A7="","",$E7*Summary!$B$8) -> 538.32676 | G7: =IF($A7="","",F7*Summary!$B$9) -> 1076.6535 | H7: =IF($A7="","",SUMIFS('Raw daily data'!$F:$F,'Raw daily data'!$I:$I,$A7)) -> 0 | I7: =I6+H7 -> 515.0023 | J7: =SUMIF($B$2:$B$41,B7,$H$2:$H$41) -> 515.0023 | K7: =Summary!$B$6 -> 5000 | L7: =J7-K7 -> -4484.9977 | N7: =IF($A7="","",COUNTIFS('Raw daily data'!$I:$I,$A7)) -> 0 | O7: =IF($A7="","",COUNTIFS('Raw daily data'!$I:$I,$A7,'Raw daily data'!$F:$F,">0")) -> 0 | P7: =IF($A7="","",COUNTIFS('Raw daily data'!$I:$I,$A7,'Raw daily data'!$F:$F,"<0")) -> 0 | Q7: =IF($A7="","",SUMIFS('Raw daily data'!$F:$F,'Raw daily data'!$I:$I,$A7,'Raw daily data'!$F:$F,">0")) -> 0 | R7: =IF($A7="","",ABS(SUMIFS('Raw daily data'!$F:$F,'Raw daily data'!$I:$I,$A7,'Raw daily data'!$F:$F,"<0"))) -> 0 | S7: =IF(N7>0,O7/N7,"") | T7: =IF(R7>0,Q7/ABS(R7),"") | U7: =IF(F7>0,H7/F7,"") -> 0 | V7: =IF(H7<0,MIN(ABS(H7)/G7,1),0) -> 0 | W7: =IF($A7="","",_xlfn.MAXIFS('Raw daily data'!$J:$J,'Raw daily data'!$I:$I,$A7)) -> 0 | X7: =IF(W7>=0,0,ABS(W7)/G7) -> 0 | Y7: =IF($A7="","",ABS(MIN(0,_xlfn.MINIFS('Raw daily data'!$J:$J,'Raw daily data'!$I:$I,$A7)))/G7) -> 0
A8: 46039 | B8: 1 | C8: =TEXT(A8,"dddd") -> Saturday | D8: N | E8: =E7+H7 -> 7690.3823 | F8: =IF($A8="","",$E8*Summary!$B$8) -> 538.32676 | G8: =IF($A8="","",F8*Summary!$B$9) -> 1076.6535 | H8: =IF($A8="","",SUMIFS('Raw daily data'!$F:$F,'Raw daily data'!$I:$I,$A8)) -> 0 | I8: =I7+H8 -> 515.0023 | J8: =SUMIF($B$2:$B$41,B8,$H$2:$H$41) -> 515.0023 | K8: =Summary!$B$6 -> 5000 | L8: =J8-K8 -> -4484.9977 | N8: =IF($A8="","",COUNTIFS('Raw daily data'!$I:$I,$A8)) -> 0 | O8: =IF($A8="","",COUNTIFS('Raw daily data'!$I:$I,$A8,'Raw daily data'!$F:$F,">0")) -> 0 | P8: =IF($A8="","",COUNTIFS('Raw daily data'!$I:$I,$A8,'Raw daily data'!$F:$F,"<0")) -> 0 | Q8: =IF($A8="","",SUMIFS('Raw daily data'!$F:$F,'Raw daily data'!$I:$I,$A8,'Raw daily data'!$F:$F,">0")) -> 0 | R8: =IF($A8="","",ABS(SUMIFS('Raw daily data'!$F:$F,'Raw daily data'!$I:$I,$A8,'Raw daily data'!$F:$F,"<0"))) -> 0 | S8: =IF(N8>0,O8/N8,"") | T8: =IF(R8>0,Q8/ABS(R8),"") | U8: =IF(F8>0,H8/F8,"") -> 0 | V8: =IF(H8<0,MIN(ABS(H8)/G8,1),0) -> 0 | W8: =IF($A8="","",_xlfn.MAXIFS('Raw daily data'!$J:$J,'Raw daily data'!$I:$I,$A8)) -> 0 | X8: =IF(W8>=0,0,ABS(W8)/G8) -> 0 | Y8: =IF($A8="","",ABS(MIN(0,_xlfn.MINIFS('Raw daily data'!$J:$J,'Raw daily data'!$I:$I,$A8)))/G8) -> 0
A9: 46040 | B9: 2 | C9: =TEXT(A9,"dddd") -> Sunday | D9: N | E9: =E8+H8 -> 7690.3823 | F9: =IF($A9="","",$E9*Summary!$B$8) -> 538.32676 | G9: =IF($A9="","",F9*Summary!$B$9) -> 1076.6535 | H9: =IF($A9="","",SUMIFS('Raw daily data'!$F:$F,'Raw daily data'!$I:$I,$A9)) -> 0 | I9: =I8+H9 -> 515.0023 | J9: =SUMIF($B$2:$B$41,B9,$H$2:$H$41) -> 0 | K9: =Summary!$B$6 -> 5000 | L9: =J9-K9 -> -5000 | N9: =IF($A9="","",COUNTIFS('Raw daily data'!$I:$I,$A9)) -> 0 | O9: =IF($A9="","",COUNTIFS('Raw daily data'!$I:$I,$A9,'Raw daily data'!$F:$F,">0")) -> 0 | P9: =IF($A9="","",COUNTIFS('Raw daily data'!$I:$I,$A9,'Raw daily data'!$F:$F,"<0")) -> 0 | Q9: =IF($A9="","",SUMIFS('Raw daily data'!$F:$F,'Raw daily data'!$I:$I,$A9,'Raw daily data'!$F:$F,">0")) -> 0 | R9: =IF($A9="","",ABS(SUMIFS('Raw daily data'!$F:$F,'Raw daily data'!$I:$I,$A9,'Raw daily data'!$F:$F,"<0"))) -> 0 | S9: =IF(N9>0,O9/N9,"") | T9: =IF(R9>0,Q9/ABS(R9),"") | U9: =IF(F9>0,H9/F9,"") -> 0 | V9: =IF(H9<0,MIN(ABS(H9)/G9,1),0) -> 0 | W9: =IF($A9="","",_xlfn.MAXIFS('Raw daily data'!$J:$J,'Raw daily data'!$I:$I,$A9)) -> 0 | X9: =IF(W9>=0,0,ABS(W9)/G9) -> 0 | Y9: =IF($A9="","",ABS(MIN(0,_xlfn.MINIFS('Raw daily data'!$J:$J,'Raw daily data'!$I:$I,$A9)))/G9) -> 0
A10: 46041 | B10: 2 | C10: =TEXT(A10,"dddd") -> Monday | E10: =E9+H9 -> 7690.3823 | F10: =IF($A10="","",$E10*Summary!$B$8) -> 538.32676 | G10: =IF($A10="","",F10*Summary!$B$9) -> 1076.6535 | H10: =IF($A10="","",SUMIFS('Raw daily data'!$F:$F,'Raw daily data'!$I:$I,$A10)) -> 0 | I10: =I9+H10 -> 515.0023 | J10: =SUMIF($B$2:$B$41,B10,$H$2:$H$41) -> 0 | K10: =Summary!$B$6 -> 5000 | L10: =J10-K10 -> -5000 | N10: =IF($A10="","",COUNTIFS('Raw daily data'!$I:$I,$A10)) -> 0 | O10: =IF($A10="","",COUNTIFS('Raw daily data'!$I:$I,$A10,'Raw daily data'!$F:$F,">0")) -> 0 | P10: =IF($A10="","",COUNTIFS('Raw daily data'!$I:$I,$A10,'Raw daily data'!$F:$F,"<0")) -> 0 | Q10: =IF($A10="","",SUMIFS('Raw daily data'!$F:$F,'Raw daily data'!$I:$I,$A10,'Raw daily data'!$F:$F,">0")) -> 0 | R10: =IF($A10="","",ABS(SUMIFS('Raw daily data'!$F:$F,'Raw daily data'!$I:$I,$A10,'Raw daily data'!$F:$F,"<0"))) -> 0 | S10: =IF(N10>0,O10/N10,"") | T10: =IF(R10>0,Q10/ABS(R10),"") | U10: =IF(F10>0,H10/F10,"") -> 0 | V10: =IF(H10<0,MIN(ABS(H10)/G10,1),0) -> 0 | W10: =IF($A10="","",_xlfn.MAXIFS('Raw daily data'!$J:$J,'Raw daily data'!$I:$I,$A10)) -> 0 | X10: =IF(W10>=0,0,ABS(W10)/G10) -> 0 | Y10: =IF($A10="","",ABS(MIN(0,_xlfn.MINIFS('Raw daily data'!$J:$J,'Raw daily data'!$I:$I,$A10)))/G10) -> 0
A11: 46042 | B11: 2 | C11: =TEXT(A11,"dddd") -> Tuesday | E11: =E10+H10 -> 7690.3823 | F11: =IF($A11="","",$E11*Summary!$B$8) -> 538.32676 | G11: =IF($A11="","",F11*Summary!$B$9) -> 1076.6535 | H11: =IF($A11="","",SUMIFS('Raw daily data'!$F:$F,'Raw daily data'!$I:$I,$A11)) -> 0 | I11: =I10+H11 -> 515.0023 | J11: =SUMIF($B$2:$B$41,B11,$H$2:$H$41) -> 0 | K11: =Summary!$B$6 -> 5000 | L11: =J11-K11 -> -5000 | N11: =IF($A11="","",COUNTIFS('Raw daily data'!$I:$I,$A11)) -> 0 | O11: =IF($A11="","",COUNTIFS('Raw daily data'!$I:$I,$A11,'Raw daily data'!$F:$F,">0")) -> 0 | P11: =IF($A11="","",COUNTIFS('Raw daily data'!$I:$I,$A11,'Raw daily data'!$F:$F,"<0")) -> 0 | Q11: =IF($A11="","",SUMIFS('Raw daily data'!$F:$F,'Raw daily data'!$I:$I,$A11,'Raw daily data'!$F:$F,">0")) -> 0 | R11: =IF($A11="","",ABS(SUMIFS('Raw daily data'!$F:$F,'Raw daily data'!$I:$I,$A11,'Raw daily data'!$F:$F,"<0"))) -> 0 | S11: =IF(N11>0,O11/N11,"") | T11: =IF(R11>0,Q11/ABS(R11),"") | U11: =IF(F11>0,H11/F11,"") -> 0 | V11: =IF(H11<0,MIN(ABS(H11)/G11,1),0) -> 0 | W11: =IF($A11="","",_xlfn.MAXIFS('Raw daily data'!$J:$J,'Raw daily data'!$I:$I,$A11)) -> 0 | X11: =IF(W11>=0,0,ABS(W11)/G11) -> 0 | Y11: =IF($A11="","",ABS(MIN(0,_xlfn.MINIFS('Raw daily data'!$J:$J,'Raw daily data'!$I:$I,$A11)))/G11) -> 0
A12: 46043 | B12: 2 | C12: =TEXT(A12,"dddd") -> Wednesday | E12: =E11+H11 -> 7690.3823 | F12: =IF($A12="","",$E12*Summary!$B$8) -> 538.32676 | G12: =IF($A12="","",F12*Summary!$B$9) -> 1076.6535 | H12: =IF($A12="","",SUMIFS('Raw daily data'!$F:$F,'Raw daily data'!$I:$I,$A12)) -> 0 | I12: =I11+H12 -> 515.0023 | J12: =SUMIF($B$2:$B$41,B12,$H$2:$H$41) -> 0 | K12: =Summary!$B$6 -> 5000 | L12: =J12-K12 -> -5000 | N12: =IF($A12="","",COUNTIFS('Raw daily data'!$I:$I,$A12)) -> 0 | O12: =IF($A12="","",COUNTIFS('Raw daily data'!$I:$I,$A12,'Raw daily data'!$F:$F,">0")) -> 0 | P12: =IF($A12="","",COUNTIFS('Raw daily data'!$I:$I,$A12,'Raw daily data'!$F:$F,"<0")) -> 0 | Q12: =IF($A12="","",SUMIFS('Raw daily data'!$F:$F,'Raw daily data'!$I:$I,$A12,'Raw daily data'!$F:$F,">0")) -> 0 | R12: =IF($A12="","",ABS(SUMIFS('Raw daily data'!$F:$F,'Raw daily data'!$I:$I,$A12,'Raw daily data'!$F:$F,"<0"))) -> 0 | S12: =IF(N12>0,O12/N12,"") | T12: =IF(R12>0,Q12/ABS(R12),"") | U12: =IF(F12>0,H12/F12,"") -> 0 | V12: =IF(H12<0,MIN(ABS(H12)/G12,1),0) -> 0 | W12: =IF($A12="","",_xlfn.MAXIFS('Raw daily data'!$J:$J,'Raw daily data'!$I:$I,$A12)) -> 0 | X12: =IF(W12>=0,0,ABS(W12)/G12) -> 0 | Y12: =IF($A12="","",ABS(MIN(0,_xlfn.MINIFS('Raw daily data'!$J:$J,'Raw daily data'!$I:$I,$A12)))/G12) -> 0
A13: 46044 | B13: 2 | C13: =TEXT(A13,"dddd") -> Thursday | E13: =E12+H12 -> 7690.3823 | F13: =IF($A13="","",$E13*Summary!$B$8) -> 538.32676 | G13: =IF($A13="","",F13*Summary!$B$9) -> 1076.6535 | H13: =IF($A13="","",SUMIFS('Raw daily data'!$F:$F,'Raw daily data'!$I:$I,$A13)) -> 0 | I13: =I12+H13 -> 515.0023 | J13: =SUMIF($B$2:$B$41,B13,$H$2:$H$41) -> 0 | K13: =Summary!$B$6 -> 5000 | L13: =J13-K13 -> -5000 | N13: =IF($A13="","",COUNTIFS('Raw daily data'!$I:$I,$A13)) -> 0 | O13: =IF($A13="","",COUNTIFS('Raw daily data'!$I:$I,$A13,'Raw daily data'!$F:$F,">0")) -> 0 | P13: =IF($A13="","",COUNTIFS('Raw daily data'!$I:$I,$A13,'Raw daily data'!$F:$F,"<0")) -> 0 | Q13: =IF($A13="","",SUMIFS('Raw daily data'!$F:$F,'Raw daily data'!$I:$I,$A13,'Raw daily data'!$F:$F,">0")) -> 0 | R13: =IF($A13="","",ABS(SUMIFS('Raw daily data'!$F:$F,'Raw daily data'!$I:$I,$A13,'Raw daily data'!$F:$F,"<0"))) -> 0 | S13: =IF(N13>0,O13/N13,"") | T13: =IF(R13>0,Q13/ABS(R13),"") | U13: =IF(F13>0,H13/F13,"") -> 0 | V13: =IF(H13<0,MIN(ABS(H13)/G13,1),0) -> 0 | W13: =IF($A13="","",_xlfn.MAXIFS('Raw daily data'!$J:$J,'Raw daily data'!$I:$I,$A13)) -> 0 | X13: =IF(W13>=0,0,ABS(W13)/G13) -> 0 | Y13: =IF($A13="","",ABS(MIN(0,_xlfn.MINIFS('Raw daily data'!$J:$J,'Raw daily data'!$I:$I,$A13)))/G13) -> 0
A14: 46045 | B14: 2 | C14: =TEXT(A14,"dddd") -> Friday | E14: =E13+H13 -> 7690.3823 | F14: =IF($A14="","",$E14*Summary!$B$8) -> 538.32676 | G14: =IF($A14="","",F14*Summary!$B$9) -> 1076.6535 | H14: =IF($A14="","",SUMIFS('Raw daily data'!$F:$F,'Raw daily data'!$I:$I,$A14)) -> 0 | I14: =I13+H14 -> 515.0023 | J14: =SUMIF($B$2:$B$41,B14,$H$2:$H$41) -> 0 | K14: =Summary!$B$6 -> 5000 | L14: =J14-K14 -> -5000 | N14: =IF($A14="","",COUNTIFS('Raw daily data'!$I:$I,$A14)) -> 0 | O14: =IF($A14="","",COUNTIFS('Raw daily data'!$I:$I,$A14,'Raw daily data'!$F:$F,">0")) -> 0 | P14: =IF($A14="","",COUNTIFS('Raw daily data'!$I:$I,$A14,'Raw daily data'!$F:$F,"<0")) -> 0 | Q14: =IF($A14="","",SUMIFS('Raw daily data'!$F:$F,'Raw daily data'!$I:$I,$A14,'Raw daily data'!$F:$F,">0")) -> 0 | R14: =IF($A14="","",ABS(SUMIFS('Raw daily data'!$F:$F,'Raw daily data'!$I:$I,$A14,'Raw daily data'!$F:$F,"<0"))) -> 0 | S14: =IF(N14>0,O14/N14,"") | T14: =IF(R14>0,Q14/ABS(R14),"") | U14: =IF(F14>0,H14/F14,"") -> 0 | V14: =IF(H14<0,MIN(ABS(H14)/G14,1),0) -> 0 | W14: =IF($A14="","",_xlfn.MAXIFS('Raw daily data'!$J:$J,'Raw daily data'!$I:$I,$A14)) -> 0 | X14: =IF(W14>=0,0,ABS(W14)/G14) -> 0 | Y14: =IF($A14="","",ABS(MIN(0,_xlfn.MINIFS('Raw daily data'!$J:$J,'Raw daily data'!$I:$I,$A14)))/G14) -> 0
A15: 46046 | B15: 2 | C15: =TEXT(A15,"dddd") -> Saturday | D15: N | E15: =E14+H14 -> 7690.3823 | F15: =IF($A15="","",$E15*Summary!$B$8) -> 538.32676 | G15: =IF($A15="","",F15*Summary!$B$9) -> 1076.6535 | H15: =IF($A15="","",SUMIFS('Raw daily data'!$F:$F,'Raw daily data'!$I:$I,$A15)) -> 0 | I15: =I14+H15 -> 515.0023 | J15: =SUMIF($B$2:$B$41,B15,$H$2:$H$41) -> 0 | K15: =Summary!$B$6 -> 5000 | L15: =J15-K15 -> -5000 | N15: =IF($A15="","",COUNTIFS('Raw daily data'!$I:$I,$A15)) -> 0 | O15: =IF($A15="","",COUNTIFS('Raw daily data'!$I:$I,$A15,'Raw daily data'!$F:$F,">0")) -> 0 | P15: =IF($A15="","",COUNTIFS('Raw daily data'!$I:$I,$A15,'Raw daily data'!$F:$F,"<0")) -> 0 | Q15: =IF($A15="","",SUMIFS('Raw daily data'!$F:$F,'Raw daily data'!$I:$I,$A15,'Raw daily data'!$F:$F,">0")) -> 0 | R15: =IF($A15="","",ABS(SUMIFS('Raw daily data'!$F:$F,'Raw daily data'!$I:$I,$A15,'Raw daily data'!$F:$F,"<0"))) -> 0 | S15: =IF(N15>0,O15/N15,"") | T15: =IF(R15>0,Q15/ABS(R15),"") | U15: =IF(F15>0,H15/F15,"") -> 0 | V15: =IF(H15<0,MIN(ABS(H15)/G15,1),0) -> 0 | W15: =IF($A15="","",_xlfn.MAXIFS('Raw daily data'!$J:$J,'Raw daily data'!$I:$I,$A15)) -> 0 | X15: =IF(W15>=0,0,ABS(W15)/G15) -> 0 | Y15: =IF($A15="","",ABS(MIN(0,_xlfn.MINIFS('Raw daily data'!$J:$J,'Raw daily data'!$I:$I,$A15)))/G15) -> 0
A16: 46047 | B16: 3 | C16: =TEXT(A16,"dddd") -> Sunday | D16: N | E16: =E15+H15 -> 7690.3823 | F16: =IF($A16="","",$E16*Summary!$B$8) -> 538.32676 | G16: =IF($A16="","",F16*Summary!$B$9) -> 1076.6535 | H16: =IF($A16="","",SUMIFS('Raw daily data'!$F:$F,'Raw daily data'!$I:$I,$A16)) -> 0 | I16: =I15+H16 -> 515.0023 | J16: =SUMIF($B$2:$B$41,B16,$H$2:$H$41) -> 0 | K16: =Summary!$B$6 -> 5000 | L16: =J16-K16 -> -5000 | N16: =IF($A16="","",COUNTIFS('Raw daily data'!$I:$I,$A16)) -> 0 | O16: =IF($A16="","",COUNTIFS('Raw daily data'!$I:$I,$A16,'Raw daily data'!$F:$F,">0")) -> 0 | P16: =IF($A16="","",COUNTIFS('Raw daily data'!$I:$I,$A16,'Raw daily data'!$F:$F,"<0")) -> 0 | Q16: =IF($A16="","",SUMIFS('Raw daily data'!$F:$F,'Raw daily data'!$I:$I,$A16,'Raw daily data'!$F:$F,">0")) -> 0 | R16: =IF($A16="","",ABS(SUMIFS('Raw daily data'!$F:$F,'Raw daily data'!$I:$I,$A16,'Raw daily data'!$F:$F,"<0"))) -> 0 | S16: =IF(N16>0,O16/N16,"") | T16: =IF(R16>0,Q16/ABS(R16),"") | U16: =IF(F16>0,H16/F16,"") -> 0 | V16: =IF(H16<0,MIN(ABS(H16)/G16,1),0) -> 0 | W16: =IF($A16="","",_xlfn.MAXIFS('Raw daily data'!$J:$J,'Raw daily data'!$I:$I,$A16)) -> 0 | X16: =IF(W16>=0,0,ABS(W16)/G16) -> 0 | Y16: =IF($A16="","",ABS(MIN(0,_xlfn.MINIFS('Raw daily data'!$J:$J,'Raw daily data'!$I:$I,$A16)))/G16) -> 0
A17: 46048 | B17: 3 | C17: =TEXT(A17,"dddd") -> Monday | E17: =E16+H16 -> 7690.3823 | F17: =IF($A17="","",$E17*Summary!$B$8) -> 538.32676 | G17: =IF($A17="","",F17*Summary!$B$9) -> 1076.6535 | H17: =IF($A17="","",SUMIFS('Raw daily data'!$F:$F,'Raw daily data'!$I:$I,$A17)) -> 0 | I17: =I16+H17 -> 515.0023 | J17: =SUMIF($B$2:$B$41,B17,$H$2:$H$41) -> 0 | K17: =Summary!$B$6 -> 5000 | L17: =J17-K17 -> -5000 | N17: =IF($A17="","",COUNTIFS('Raw daily data'!$I:$I,$A17)) -> 0 | O17: =IF($A17="","",COUNTIFS('Raw daily data'!$I:$I,$A17,'Raw daily data'!$F:$F,">0")) -> 0 | P17: =IF($A17="","",COUNTIFS('Raw daily data'!$I:$I,$A17,'Raw daily data'!$F:$F,"<0")) -> 0 | Q17: =IF($A17="","",SUMIFS('Raw daily data'!$F:$F,'Raw daily data'!$I:$I,$A17,'Raw daily data'!$F:$F,">0")) -> 0 | R17: =IF($A17="","",ABS(SUMIFS('Raw daily data'!$F:$F,'Raw daily data'!$I:$I,$A17,'Raw daily data'!$F:$F,"<0"))) -> 0 | S17: =IF(N17>0,O17/N17,"") | T17: =IF(R17>0,Q17/ABS(R17),"") | U17: =IF(F17>0,H17/F17,"") -> 0 | V17: =IF(H17<0,MIN(ABS(H17)/G17,1),0) -> 0 | W17: =IF($A17="","",_xlfn.MAXIFS('Raw daily data'!$J:$J,'Raw daily data'!$I:$I,$A17)) -> 0 | X17: =IF(W17>=0,0,ABS(W17)/G17) -> 0 | Y17: =IF($A17="","",ABS(MIN(0,_xlfn.MINIFS('Raw daily data'!$J:$J,'Raw daily data'!$I:$I,$A17)))/G17) -> 0
A18: 46049 | B18: 3 | C18: =TEXT(A18,"dddd") -> Tuesday | E18: =E17+H17 -> 7690.3823 | F18: =IF($A18="","",$E18*Summary!$B$8) -> 538.32676 | G18: =IF($A18="","",F18*Summary!$B$9) -> 1076.6535 | H18: =IF($A18="","",SUMIFS('Raw daily data'!$F:$F,'Raw daily data'!$I:$I,$A18)) -> 0 | I18: =I17+H18 -> 515.0023 | J18: =SUMIF($B$2:$B$41,B18,$H$2:$H$41) -> 0 | K18: =Summary!$B$6 -> 5000 | L18: =J18-K18 -> -5000 | N18: =IF($A18="","",COUNTIFS('Raw daily data'!$I:$I,$A18)) -> 0 | O18: =IF($A18="","",COUNTIFS('Raw daily data'!$I:$I,$A18,'Raw daily data'!$F:$F,">0")) -> 0 | P18: =IF($A18="","",COUNTIFS('Raw daily data'!$I:$I,$A18,'Raw daily data'!$F:$F,"<0")) -> 0 | Q18: =IF($A18="","",SUMIFS('Raw daily data'!$F:$F,'Raw daily data'!$I:$I,$A18,'Raw daily data'!$F:$F,">0")) -> 0 | R18: =IF($A18="","",ABS(SUMIFS('Raw daily data'!$F:$F,'Raw daily data'!$I:$I,$A18,'Raw daily data'!$F:$F,"<0"))) -> 0 | S18: =IF(N18>0,O18/N18,"") | T18: =IF(R18>0,Q18/ABS(R18),"") | U18: =IF(F18>0,H18/F18,"") -> 0 | V18: =IF(H18<0,MIN(ABS(H18)/G18,1),0) -> 0 | W18: =IF($A18="","",_xlfn.MAXIFS('Raw daily data'!$J:$J,'Raw daily data'!$I:$I,$A18)) -> 0 | X18: =IF(W18>=0,0,ABS(W18)/G18) -> 0 | Y18: =IF($A18="","",ABS(MIN(0,_xlfn.MINIFS('Raw daily data'!$J:$J,'Raw daily data'!$I:$I,$A18)))/G18) -> 0
A19: 46050 | B19: 3 | C19: =TEXT(A19,"dddd") -> Wednesday | E19: =E18+H18 -> 7690.3823 | F19: =IF($A19="","",$E19*Summary!$B$8) -> 538.32676 | G19: =IF($A19="","",F19*Summary!$B$9) -> 1076.6535 | H19: =IF($A19="","",SUMIFS('Raw daily data'!$F:$F,'Raw daily data'!$I:$I,$A19)) -> 0 | I19: =I18+H19 -> 515.0023 | J19: =SUMIF($B$2:$B$41,B19,$H$2:$H$41) -> 0 | K19: =Summary!$B$6 -> 5000 | L19: =J19-K19 -> -5000 | N19: =IF($A19="","",COUNTIFS('Raw daily data'!$I:$I,$A19)) -> 0 | O19: =IF($A19="","",COUNTIFS('Raw daily data'!$I:$I,$A19,'Raw daily data'!$F:$F,">0")) -> 0 | P19: =IF($A19="","",COUNTIFS('Raw daily data'!$I:$I,$A19,'Raw daily data'!$F:$F,"<0")) -> 0 | Q19: =IF($A19="","",SUMIFS('Raw daily data'!$F:$F,'Raw daily data'!$I:$I,$A19,'Raw daily data'!$F:$F,">0")) -> 0 | R19: =IF($A19="","",ABS(SUMIFS('Raw daily data'!$F:$F,'Raw daily data'!$I:$I,$A19,'Raw daily data'!$F:$F,"<0"))) -> 0 | S19: =IF(N19>0,O19/N19,"") | T19: =IF(R19>0,Q19/ABS(R19),"") | U19: =IF(F19>0,H19/F19,"") -> 0 | V19: =IF(H19<0,MIN(ABS(H19)/G19,1),0) -> 0 | W19: =IF($A19="","",_xlfn.MAXIFS('Raw daily data'!$J:$J,'Raw daily data'!$I:$I,$A19)) -> 0 | X19: =IF(W19>=0,0,ABS(W19)/G19) -> 0 | Y19: =IF($A19="","",ABS(MIN(0,_xlfn.MINIFS('Raw daily data'!$J:$J,'Raw daily data'!$I:$I,$A19)))/G19) -> 0
A20: 46051 | B20: 3 | C20: =TEXT(A20,"dddd") -> Thursday | E20: =E19+H19 -> 7690.3823 | F20: =IF($A20="","",$E20*Summary!$B$8) -> 538.32676 | G20: =IF($A20="","",F20*Summary!$B$9) -> 1076.6535 | H20: =IF($A20="","",SUMIFS('Raw daily data'!$F:$F,'Raw daily data'!$I:$I,$A20)) -> 0 | I20: =I19+H20 -> 515.0023 | J20: =SUMIF($B$2:$B$41,B20,$H$2:$H$41) -> 0 | K20: =Summary!$B$6 -> 5000 | L20: =J20-K20 -> -5000 | N20: =IF($A20="","",COUNTIFS('Raw daily data'!$I:$I,$A20)) -> 0 | O20: =IF($A20="","",COUNTIFS('Raw daily data'!$I:$I,$A20,'Raw daily data'!$F:$F,">0")) -> 0 | P20: =IF($A20="","",COUNTIFS('Raw daily data'!$I:$I,$A20,'Raw daily data'!$F:$F,"<0")) -> 0 | Q20: =IF($A20="","",SUMIFS('Raw daily data'!$F:$F,'Raw daily data'!$I:$I,$A20,'Raw daily data'!$F:$F,">0")) -> 0 | R20: =IF($A20="","",ABS(SUMIFS('Raw daily data'!$F:$F,'Raw daily data'!$I:$I,$A20,'Raw daily data'!$F:$F,"<0"))) -> 0 | S20: =IF(N20>0,O20/N20,"") | T20: =IF(R20>0,Q20/ABS(R20),"") | U20: =IF(F20>0,H20/F20,"") -> 0 | V20: =IF(H20<0,MIN(ABS(H20)/G20,1),0) -> 0 | W20: =IF($A20="","",_xlfn.MAXIFS('Raw daily data'!$J:$J,'Raw daily data'!$I:$I,$A20)) -> 0 | X20: =IF(W20>=0,0,ABS(W20)/G20) -> 0 | Y20: =IF($A20="","",ABS(MIN(0,_xlfn.MINIFS('Raw daily data'!$J:$J,'Raw daily data'!$I:$I,$A20)))/G20) -> 0
A21: 46052 | B21: 3 | C21: =TEXT(A21,"dddd") -> Friday | E21: =E20+H20 -> 7690.3823 | F21: =IF($A21="","",$E21*Summary!$B$8) -> 538.32676 | G21: =IF($A21="","",F21*Summary!$B$9) -> 1076.6535 | H21: =IF($A21="","",SUMIFS('Raw daily data'!$F:$F,'Raw daily data'!$I:$I,$A21)) -> 0 | I21: =I20+H21 -> 515.0023 | J21: =SUMIF($B$2:$B$41,B21,$H$2:$H$41) -> 0 | K21: =Summary!$B$6 -> 5000 | L21: =J21-K21 -> -5000 | N21: =IF($A21="","",COUNTIFS('Raw daily data'!$I:$I,$A21)) -> 0 | O21: =IF($A21="","",COUNTIFS('Raw daily data'!$I:$I,$A21,'Raw daily data'!$F:$F,">0")) -> 0 | P21: =IF($A21="","",COUNTIFS('Raw daily data'!$I:$I,$A21,'Raw daily data'!$F:$F,"<0")) -> 0 | Q21: =IF($A21="","",SUMIFS('Raw daily data'!$F:$F,'Raw daily data'!$I:$I,$A21,'Raw daily data'!$F:$F,">0")) -> 0 | R21: =IF($A21="","",ABS(SUMIFS('Raw daily data'!$F:$F,'Raw daily data'!$I:$I,$A21,'Raw daily data'!$F:$F,"<0"))) -> 0 | S21: =IF(N21>0,O21/N21,"") | T21: =IF(R21>0,Q21/ABS(R21),"") | U21: =IF(F21>0,H21/F21,"") -> 0 | V21: =IF(H21<0,MIN(ABS(H21)/G21,1),0) -> 0 | W21: =IF($A21="","",_xlfn.MAXIFS('Raw daily data'!$J:$J,'Raw daily data'!$I:$I,$A21)) -> 0 | X21: =IF(W21>=0,0,ABS(W21)/G21) -> 0 | Y21: =IF($A21="","",ABS(MIN(0,_xlfn.MINIFS('Raw daily data'!$J:$J,'Raw daily data'!$I:$I,$A21)))/G21) -> 0
A22: 46053 | B22: 3 | C22: =TEXT(A22,"dddd") -> Saturday | D22: N | E22: =E21+H21 -> 7690.3823 | F22: =IF($A22="","",$E22*Summary!$B$8) -> 538.32676 | G22: =IF($A22="","",F22*Summary!$B$9) -> 1076.6535 | H22: =IF($A22="","",SUMIFS('Raw daily data'!$F:$F,'Raw daily data'!$I:$I,$A22)) -> 0 | I22: =I21+H22 -> 515.0023 | J22: =SUMIF($B$2:$B$41,B22,$H$2:$H$41) -> 0 | K22: =Summary!$B$6 -> 5000 | L22: =J22-K22 -> -5000 | N22: =IF($A22="","",COUNTIFS('Raw daily data'!$I:$I,$A22)) -> 0 | O22: =IF($A22="","",COUNTIFS('Raw daily data'!$I:$I,$A22,'Raw daily data'!$F:$F,">0")) -> 0 | P22: =IF($A22="","",COUNTIFS('Raw daily data'!$I:$I,$A22,'Raw daily data'!$F:$F,"<0")) -> 0 | Q22: =IF($A22="","",SUMIFS('Raw daily data'!$F:$F,'Raw daily data'!$I:$I,$A22,'Raw daily data'!$F:$F,">0")) -> 0 | R22: =IF($A22="","",ABS(SUMIFS('Raw daily data'!$F:$F,'Raw daily data'!$I:$I,$A22,'Raw daily data'!$F:$F,"<0"))) -> 0 | S22: =IF(N22>0,O22/N22,"") | T22: =IF(R22>0,Q22/ABS(R22),"") | U22: =IF(F22>0,H22/F22,"") -> 0 | V22: =IF(H22<0,MIN(ABS(H22)/G22,1),0) -> 0 | W22: =IF($A22="","",_xlfn.MAXIFS('Raw daily data'!$J:$J,'Raw daily data'!$I:$I,$A22)) -> 0 | X22: =IF(W22>=0,0,ABS(W22)/G22) -> 0 | Y22: =IF($A22="","",ABS(MIN(0,_xlfn.MINIFS('Raw daily data'!$J:$J,'Raw daily data'!$I:$I,$A22)))/G22) -> 0
A23: 46054 | B23: 4 | C23: =TEXT(A23,"dddd") -> Sunday | D23: N | E23: =E22+H22 -> 7690.3823 | F23: =IF($A23="","",$E23*Summary!$B$8) -> 538.32676 | G23: =IF($A23="","",F23*Summary!$B$9) -> 1076.6535 | H23: =IF($A23="","",SUMIFS('Raw daily data'!$F:$F,'Raw daily data'!$I:$I,$A23)) -> 0 | I23: =I22+H23 -> 515.0023 | J23: =SUMIF($B$2:$B$41,B23,$H$2:$H$41) -> 0 | K23: =Summary!$B$6 -> 5000 | L23: =J23-K23 -> -5000 | N23: =IF($A23="","",COUNTIFS('Raw daily data'!$I:$I,$A23)) -> 0 | O23: =IF($A23="","",COUNTIFS('Raw daily data'!$I:$I,$A23,'Raw daily data'!$F:$F,">0")) -> 0 | P23: =IF($A23="","",COUNTIFS('Raw daily data'!$I:$I,$A23,'Raw daily data'!$F:$F,"<0")) -> 0 | Q23: =IF($A23="","",SUMIFS('Raw daily data'!$F:$F,'Raw daily data'!$I:$I,$A23,'Raw daily data'!$F:$F,">0")) -> 0 | R23: =IF($A23="","",ABS(SUMIFS('Raw daily data'!$F:$F,'Raw daily data'!$I:$I,$A23,'Raw daily data'!$F:$F,"<0"))) -> 0 | S23: =IF(N23>0,O23/N23,"") | T23: =IF(R23>0,Q23/ABS(R23),"") | U23: =IF(F23>0,H23/F23,"") -> 0 | V23: =IF(H23<0,MIN(ABS(H23)/G23,1),0) -> 0 | W23: =IF($A23="","",_xlfn.MAXIFS('Raw daily data'!$J:$J,'Raw daily data'!$I:$I,$A23)) -> 0 | X23: =IF(W23>=0,0,ABS(W23)/G23) -> 0 | Y23: =IF($A23="","",ABS(MIN(0,_xlfn.MINIFS('Raw daily data'!$J:$J,'Raw daily data'!$I:$I,$A23)))/G23) -> 0
A24: 46055 | B24: 4 | C24: =TEXT(A24,"dddd") -> Monday | F24: =IF($A24="","",$E24*Summary!$B$8) -> 0 | G24: =IF($A24="","",F24*Summary!$B$9) -> 0 | H24: =IF($A24="","",SUMIFS('Raw daily data'!$F:$F,'Raw daily data'!$I:$I,$A24)) -> 0 | I24: =I23+H24 -> 515.0023 | J24: =SUMIF($B$2:$B$41,B24,$H$2:$H$41) -> 0 | K24: =Summary!$B$6 -> 5000 | L24: =J24-K24 -> -5000 | N24: =IF($A24="","",COUNTIFS('Raw daily data'!$I:$I,$A24)) -> 0 | O24: =IF($A24="","",COUNTIFS('Raw daily data'!$I:$I,$A24,'Raw daily data'!$F:$F,">0")) -> 0 | P24: =IF($A24="","",COUNTIFS('Raw daily data'!$I:$I,$A24,'Raw daily data'!$F:$F,"<0")) -> 0 | Q24: =IF($A24="","",SUMIFS('Raw daily data'!$F:$F,'Raw daily data'!$I:$I,$A24,'Raw daily data'!$F:$F,">0")) -> 0 | R24: =IF($A24="","",ABS(SUMIFS('Raw daily data'!$F:$F,'Raw daily data'!$I:$I,$A24,'Raw daily data'!$F:$F,"<0"))) -> 0 | S24: =IF(N24>0,O24/N24,"") | T24: =IF(R24>0,Q24/ABS(R24),"") | U24: =IF(F24>0,H24/F24,"") | V24: =IF(H24<0,MIN(ABS(H24)/G24,1),0) -> 0 | W24: =IF($A24="","",_xlfn.MAXIFS('Raw daily data'!$J:$J,'Raw daily data'!$I:$I,$A24)) -> 0 | X24: =IF(W24>=0,0,ABS(W24)/G24) -> 0 | Y24: =IFERROR(IF($A24="","",ABS(MIN(0,_xlfn.MINIFS('Raw daily data'!$J:$J,'Raw daily data'!$I:$I,$A24)))/G24),"")
A25: 46056 | B25: 4 | C25: =TEXT(A25,"dddd") -> Tuesday | F25: =IF($A25="","",$E25*Summary!$B$8) -> 0 | G25: =IF($A25="","",F25*Summary!$B$9) -> 0 | H25: =IF($A25="","",SUMIFS('Raw daily data'!$F:$F,'Raw daily data'!$I:$I,$A25)) -> 0 | I25: =I24+H25 -> 515.0023 | J25: =SUMIF($B$2:$B$41,B25,$H$2:$H$41) -> 0 | K25: =Summary!$B$6 -> 5000 | L25: =J25-K25 -> -5000 | N25: =IF($A25="","",COUNTIFS('Raw daily data'!$I:$I,$A25)) -> 0 | O25: =IF($A25="","",COUNTIFS('Raw daily data'!$I:$I,$A25,'Raw daily data'!$F:$F,">0")) -> 0 | P25: =IF($A25="","",COUNTIFS('Raw daily data'!$I:$I,$A25,'Raw daily data'!$F:$F,"<0")) -> 0 | Q25: =IF($A25="","",SUMIFS('Raw daily data'!$F:$F,'Raw daily data'!$I:$I,$A25,'Raw daily data'!$F:$F,">0")) -> 0 | R25: =IF($A25="","",ABS(SUMIFS('Raw daily data'!$F:$F,'Raw daily data'!$I:$I,$A25,'Raw daily data'!$F:$F,"<0"))) -> 0 | S25: =IF(N25>0,O25/N25,"") | T25: =IF(R25>0,Q25/ABS(R25),"") | U25: =IF(F25>0,H25/F25,"") | V25: =IF(H25<0,MIN(ABS(H25)/G25,1),0) -> 0 | W25: =IF($A25="","",_xlfn.MAXIFS('Raw daily data'!$J:$J,'Raw daily data'!$I:$I,$A25)) -> 0 | X25: =IF(W25>=0,0,ABS(W25)/G25) -> 0 | Y25: =IFERROR(IF($A25="","",ABS(MIN(0,_xlfn.MINIFS('Raw daily data'!$J:$J,'Raw daily data'!$I:$I,$A25)))/G25),"")
A26: 46057 | B26: 4 | C26: =TEXT(A26,"dddd") -> Wednesday | F26: =IF($A26="","",$E26*Summary!$B$8) -> 0 | G26: =IF($A26="","",F26*Summary!$B$9) -> 0 | H26: =IF($A26="","",SUMIFS('Raw daily data'!$F:$F,'Raw daily data'!$I:$I,$A26)) -> 0 | I26: =I25+H26 -> 515.0023 | J26: =SUMIF($B$2:$B$41,B26,$H$2:$H$41) -> 0 | K26: =Summary!$B$6 -> 5000 | L26: =J26-K26 -> -5000 | N26: =IF($A26="","",COUNTIFS('Raw daily data'!$I:$I,$A26)) -> 0 | O26: =IF($A26="","",COUNTIFS('Raw daily data'!$I:$I,$A26,'Raw daily data'!$F:$F,">0")) -> 0 | P26: =IF($A26="","",COUNTIFS('Raw daily data'!$I:$I,$A26,'Raw daily data'!$F:$F,"<0")) -> 0 | Q26: =IF($A26="","",SUMIFS('Raw daily data'!$F:$F,'Raw daily data'!$I:$I,$A26,'Raw daily data'!$F:$F,">0")) -> 0 | R26: =IF($A26="","",ABS(SUMIFS('Raw daily data'!$F:$F,'Raw daily data'!$I:$I,$A26,'Raw daily data'!$F:$F,"<0"))) -> 0 | S26: =IF(N26>0,O26/N26,"") | T26: =IF(R26>0,Q26/ABS(R26),"") | U26: =IF(F26>0,H26/F26,"") | V26: =IF(H26<0,MIN(ABS(H26)/G26,1),0) -> 0 | W26: =IF($A26="","",_xlfn.MAXIFS('Raw daily data'!$J:$J,'Raw daily data'!$I:$I,$A26)) -> 0 | X26: =IF(W26>=0,0,ABS(W26)/G26) -> 0 | Y26: =IFERROR(IF($A26="","",ABS(MIN(0,_xlfn.MINIFS('Raw daily data'!$J:$J,'Raw daily data'!$I:$I,$A26)))/G26),"")
A27: 46058 | B27: 4 | C27: =TEXT(A27,"dddd") -> Thursday | F27: =IF($A27="","",$E27*Summary!$B$8) -> 0 | G27: =IF($A27="","",F27*Summary!$B$9) -> 0 | H27: =IF($A27="","",SUMIFS('Raw daily data'!$F:$F,'Raw daily data'!$I:$I,$A27)) -> 0 | I27: =I26+H27 -> 515.0023 | J27: =SUMIF($B$2:$B$41,B27,$H$2:$H$41) -> 0 | K27: =Summary!$B$6 -> 5000 | L27: =J27-K27 -> -5000 | N27: =IF($A27="","",COUNTIFS('Raw daily data'!$I:$I,$A27)) -> 0 | O27: =IF($A27="","",COUNTIFS('Raw daily data'!$I:$I,$A27,'Raw daily data'!$F:$F,">0")) -> 0 | P27: =IF($A27="","",COUNTIFS('Raw daily data'!$I:$I,$A27,'Raw daily data'!$F:$F,"<0")) -> 0 | Q27: =IF($A27="","",SUMIFS('Raw daily data'!$F:$F,'Raw daily data'!$I:$I,$A27,'Raw daily data'!$F:$F,">0")) -> 0 | R27: =IF($A27="","",ABS(SUMIFS('Raw daily data'!$F:$F,'Raw daily data'!$I:$I,$A27,'Raw daily data'!$F:$F,"<0"))) -> 0 | S27: =IF(N27>0,O27/N27,"") | T27: =IF(R27>0,Q27/ABS(R27),"") | U27: =IF(F27>0,H27/F27,"") | V27: =IF(H27<0,MIN(ABS(H27)/G27,1),0) -> 0 | W27: =IF($A27="","",_xlfn.MAXIFS('Raw daily data'!$J:$J,'Raw daily data'!$I:$I,$A27)) -> 0 | X27: =IF(W27>=0,0,ABS(W27)/G27) -> 0 | Y27: =IFERROR(IF($A27="","",ABS(MIN(0,_xlfn.MINIFS('Raw daily data'!$J:$J,'Raw daily data'!$I:$I,$A27)))/G27),"")
A28: 46059 | B28: 4 | C28: =TEXT(A28,"dddd") -> Friday | F28: =IF($A28="","",$E28*Summary!$B$8) -> 0 | G28: =IF($A28="","",F28*Summary!$B$9) -> 0 | H28: =IF($A28="","",SUMIFS('Raw daily data'!$F:$F,'Raw daily data'!$I:$I,$A28)) -> 0 | I28: =I27+H28 -> 515.0023 | J28: =SUMIF($B$2:$B$41,B28,$H$2:$H$41) -> 0 | K28: =Summary!$B$6 -> 5000 | L28: =J28-K28 -> -5000 | N28: =IF($A28="","",COUNTIFS('Raw daily data'!$I:$I,$A28)) -> 0 | O28: =IF($A28="","",COUNTIFS('Raw daily data'!$I:$I,$A28,'Raw daily data'!$F:$F,">0")) -> 0 | P28: =IF($A28="","",COUNTIFS('Raw daily data'!$I:$I,$A28,'Raw daily data'!$F:$F,"<0")) -> 0 | Q28: =IF($A28="","",SUMIFS('Raw daily data'!$F:$F,'Raw daily data'!$I:$I,$A28,'Raw daily data'!$F:$F,">0")) -> 0 | R28: =IF($A28="","",ABS(SUMIFS('Raw daily data'!$F:$F,'Raw daily data'!$I:$I,$A28,'Raw daily data'!$F:$F,"<0"))) -> 0 | S28: =IF(N28>0,O28/N28,"") | T28: =IF(R28>0,Q28/ABS(R28),"") | U28: =IF(F28>0,H28/F28,"") | V28: =IF(H28<0,MIN(ABS(H28)/G28,1),0) -> 0 | W28: =IF($A28="","",_xlfn.MAXIFS('Raw daily data'!$J:$J,'Raw daily data'!$I:$I,$A28)) -> 0 | X28: =IF(W28>=0,0,ABS(W28)/G28) -> 0 | Y28: =IFERROR(IF($A28="","",ABS(MIN(0,_xlfn.MINIFS('Raw daily data'!$J:$J,'Raw daily data'!$I:$I,$A28)))/G28),"")
A29: 46060 | B29: 4 | C29: =TEXT(A29,"dddd") -> Saturday | D29: N | F29: =IF($A29="","",$E29*Summary!$B$8) -> 0 | G29: =IF($A29="","",F29*Summary!$B$9) -> 0 | H29: =IF($A29="","",SUMIFS('Raw daily data'!$F:$F,'Raw daily data'!$I:$I,$A29)) -> 0 | I29: =I28+H29 -> 515.0023 | J29: =SUMIF($B$2:$B$41,B29,$H$2:$H$41) -> 0 | K29: =Summary!$B$6 -> 5000 | L29: =J29-K29 -> -5000 | N29: =IF($A29="","",COUNTIFS('Raw daily data'!$I:$I,$A29)) -> 0 | O29: =IF($A29="","",COUNTIFS('Raw daily data'!$I:$I,$A29,'Raw daily data'!$F:$F,">0")) -> 0 | P29: =IF($A29="","",COUNTIFS('Raw daily data'!$I:$I,$A29,'Raw daily data'!$F:$F,"<0")) -> 0 | Q29: =IF($A29="","",SUMIFS('Raw daily data'!$F:$F,'Raw daily data'!$I:$I,$A29,'Raw daily data'!$F:$F,">0")) -> 0 | R29: =IF($A29="","",ABS(SUMIFS('Raw daily data'!$F:$F,'Raw daily data'!$I:$I,$A29,'Raw daily data'!$F:$F,"<0"))) -> 0 | S29: =IF(N29>0,O29/N29,"") | T29: =IF(R29>0,Q29/ABS(R29),"") | U29: =IF(F29>0,H29/F29,"") | V29: =IF(H29<0,MIN(ABS(H29)/G29,1),0) -> 0 | W29: =IF($A29="","",_xlfn.MAXIFS('Raw daily data'!$J:$J,'Raw daily data'!$I:$I,$A29)) -> 0 | X29: =IF(W29>=0,0,ABS(W29)/G29) -> 0 | Y29: =IFERROR(IF($A29="","",ABS(MIN(0,_xlfn.MINIFS('Raw daily data'!$J:$J,'Raw daily data'!$I:$I,$A29)))/G29),"")
A30: 46061 | B30: 4 | C30: =TEXT(A30,"dddd") -> Sunday | D30: N | F30: =IF($A30="","",$E30*Summary!$B$8) -> 0 | G30: =IF($A30="","",F30*Summary!$B$9) -> 0 | H30: =IF($A30="","",SUMIFS('Raw daily data'!$F:$F,'Raw daily data'!$I:$I,$A30)) -> 0 | I30: =I29+H30 -> 515.0023 | J30: =SUMIF($B$2:$B$41,B30,$H$2:$H$41) -> 0 | K30: =Summary!$B$6 -> 5000 | L30: =J30-K30 -> -5000 | N30: =IF($A30="","",COUNTIFS('Raw daily data'!$I:$I,$A30)) -> 0 | O30: =IF($A30="","",COUNTIFS('Raw daily data'!$I:$I,$A30,'Raw daily data'!$F:$F,">0")) -> 0 | P30: =IF($A30="","",COUNTIFS('Raw daily data'!$I:$I,$A30,'Raw daily data'!$F:$F,"<0")) -> 0 | Q30: =IF($A30="","",SUMIFS('Raw daily data'!$F:$F,'Raw daily data'!$I:$I,$A30,'Raw daily data'!$F:$F,">0")) -> 0 | R30: =IF($A30="","",ABS(SUMIFS('Raw daily data'!$F:$F,'Raw daily data'!$I:$I,$A30,'Raw daily data'!$F:$F,"<0"))) -> 0 | S30: =IF(N30>0,O30/N30,"") | T30: =IF(R30>0,Q30/ABS(R30),"") | U30: =IF(F30>0,H30/F30,"") | V30: =IF(H30<0,MIN(ABS(H30)/G30,1),0) -> 0 | W30: =IF($A30="","",_xlfn.MAXIFS('Raw daily data'!$J:$J,'Raw daily data'!$I:$I,$A30)) -> 0 | X30: =IF(W30>=0,0,ABS(W30)/G30) -> 0 | Y30: =IFERROR(IF($A30="","",ABS(MIN(0,_xlfn.MINIFS('Raw daily data'!$J:$J,'Raw daily data'!$I:$I,$A30)))/G30),"")
A31: 46062 | C31: =TEXT(A31,"dddd") -> Monday | F31: =IF($A31="","",$E31*Summary!$B$8) -> 0 | G31: =IF($A31="","",F31*Summary!$B$9) -> 0 | H31: =IF($A31="","",SUMIFS('Raw daily data'!$F:$F,'Raw daily data'!$I:$I,$A31)) -> 0 | I31: =I30+H31 -> 515.0023 | J31: =SUMIF($B$2:$B$41,B31,$H$2:$H$41) -> 0 | K31: =Summary!$B$6 -> 5000 | L31: =J31-K31 -> -5000 | N31: =IF($A31="","",COUNTIFS('Raw daily data'!$I:$I,$A31)) -> 0 | O31: =IF($A31="","",COUNTIFS('Raw daily data'!$I:$I,$A31,'Raw daily data'!$F:$F,">0")) -> 0 | P31: =IF($A31="","",COUNTIFS('Raw daily data'!$I:$I,$A31,'Raw daily data'!$F:$F,"<0")) -> 0 | Q31: =IF($A31="","",SUMIFS('Raw daily data'!$F:$F,'Raw daily data'!$I:$I,$A31,'Raw daily data'!$F:$F,">0")) -> 0 | R31: =IF($A31="","",ABS(SUMIFS('Raw daily data'!$F:$F,'Raw daily data'!$I:$I,$A31,'Raw daily data'!$F:$F,"<0"))) -> 0 | S31: =IF(N31>0,O31/N31,"") | T31: =IF(R31>0,Q31/ABS(R31),"") | U31: =IF(F31>0,H31/F31,"") | V31: =IF(H31<0,MIN(ABS(H31)/G31,1),0) -> 0 | W31: =IF($A31="","",_xlfn.MAXIFS('Raw daily data'!$J:$J,'Raw daily data'!$I:$I,$A31)) -> 0 | X31: =IF(W31>=0,0,ABS(W31)/G31) -> 0 | Y31: =IFERROR(IF($A31="","",ABS(MIN(0,_xlfn.MINIFS('Raw daily data'!$J:$J,'Raw daily data'!$I:$I,$A31)))/G31),"")
A32: 46063 | C32: =TEXT(A32,"dddd") -> Tuesday | F32: =IF($A32="","",$E32*Summary!$B$8) -> 0 | G32: =IF($A32="","",F32*Summary!$B$9) -> 0 | H32: =IF($A32="","",SUMIFS('Raw daily data'!$F:$F,'Raw daily data'!$I:$I,$A32)) -> 0 | I32: =I31+H32 -> 515.0023 | J32: =SUMIF($B$2:$B$41,B32,$H$2:$H$41) -> 0 | K32: =Summary!$B$6 -> 5000 | L32: =J32-K32 -> -5000 | N32: =IF($A32="","",COUNTIFS('Raw daily data'!$I:$I,$A32)) -> 0 | O32: =IF($A32="","",COUNTIFS('Raw daily data'!$I:$I,$A32,'Raw daily data'!$F:$F,">0")) -> 0 | P32: =IF($A32="","",COUNTIFS('Raw daily data'!$I:$I,$A32,'Raw daily data'!$F:$F,"<0")) -> 0 | Q32: =IF($A32="","",SUMIFS('Raw daily data'!$F:$F,'Raw daily data'!$I:$I,$A32,'Raw daily data'!$F:$F,">0")) -> 0 | R32: =IF($A32="","",ABS(SUMIFS('Raw daily data'!$F:$F,'Raw daily data'!$I:$I,$A32,'Raw daily data'!$F:$F,"<0"))) -> 0 | S32: =IF(N32>0,O32/N32,"") | T32: =IF(R32>0,Q32/ABS(R32),"") | U32: =IF(F32>0,H32/F32,"") | V32: =IF(H32<0,MIN(ABS(H32)/G32,1),0) -> 0 | W32: =IF($A32="","",_xlfn.MAXIFS('Raw daily data'!$J:$J,'Raw daily data'!$I:$I,$A32)) -> 0 | X32: =IF(W32>=0,0,ABS(W32)/G32) -> 0 | Y32: =IFERROR(IF($A32="","",ABS(MIN(0,_xlfn.MINIFS('Raw daily data'!$J:$J,'Raw daily data'!$I:$I,$A32)))/G32),"")
A33: 46064 | C33: =TEXT(A33,"dddd") -> Wednesday | F33: =IF($A33="","",$E33*Summary!$B$8) -> 0 | G33: =IF($A33="","",F33*Summary!$B$9) -> 0 | H33: =IF($A33="","",SUMIFS('Raw daily data'!$F:$F,'Raw daily data'!$I:$I,$A33)) -> 0 | I33: =I32+H33 -> 515.0023 | J33: =SUMIF($B$2:$B$41,B33,$H$2:$H$41) -> 0 | K33: =Summary!$B$6 -> 5000 | L33: =J33-K33 -> -5000 | N33: =IF($A33="","",COUNTIFS('Raw daily data'!$I:$I,$A33)) -> 0 | O33: =IF($A33="","",COUNTIFS('Raw daily data'!$I:$I,$A33,'Raw daily data'!$F:$F,">0")) -> 0 | P33: =IF($A33="","",COUNTIFS('Raw daily data'!$I:$I,$A33,'Raw daily data'!$F:$F,"<0")) -> 0 | Q33: =IF($A33="","",SUMIFS('Raw daily data'!$F:$F,'Raw daily data'!$I:$I,$A33,'Raw daily data'!$F:$F,">0")) -> 0 | R33: =IF($A33="","",ABS(SUMIFS('Raw daily data'!$F:$F,'Raw daily data'!$I:$I,$A33,'Raw daily data'!$F:$F,"<0"))) -> 0 | S33: =IF(N33>0,O33/N33,"") | T33: =IF(R33>0,Q33/ABS(R33),"") | U33: =IF(F33>0,H33/F33,"") | V33: =IF(H33<0,MIN(ABS(H33)/G33,1),0) -> 0 | W33: =IF($A33="","",_xlfn.MAXIFS('Raw daily data'!$J:$J,'Raw daily data'!$I:$I,$A33)) -> 0 | X33: =IF(W33>=0,0,ABS(W33)/G33) -> 0 | Y33: =IFERROR(IF($A33="","",ABS(MIN(0,_xlfn.MINIFS('Raw daily data'!$J:$J,'Raw daily data'!$I:$I,$A33)))/G33),"")
A34: 46065 | C34: =TEXT(A34,"dddd") -> Thursday | F34: =IF($A34="","",$E34*Summary!$B$8) -> 0 | G34: =IF($A34="","",F34*Summary!$B$9) -> 0 | H34: =IF($A34="","",SUMIFS('Raw daily data'!$F:$F,'Raw daily data'!$I:$I,$A34)) -> 0 | I34: =I33+H34 -> 515.0023 | J34: =SUMIF($B$2:$B$41,B34,$H$2:$H$41) -> 0 | K34: =Summary!$B$6 -> 5000 | L34: =J34-K34 -> -5000 | N34: =IF($A34="","",COUNTIFS('Raw daily data'!$I:$I,$A34)) -> 0 | O34: =IF($A34="","",COUNTIFS('Raw daily data'!$I:$I,$A34,'Raw daily data'!$F:$F,">0")) -> 0 | P34: =IF($A34="","",COUNTIFS('Raw daily data'!$I:$I,$A34,'Raw daily data'!$F:$F,"<0")) -> 0 | Q34: =IF($A34="","",SUMIFS('Raw daily data'!$F:$F,'Raw daily data'!$I:$I,$A34,'Raw daily data'!$F:$F,">0")) -> 0 | R34: =IF($A34="","",ABS(SUMIFS('Raw daily data'!$F:$F,'Raw daily data'!$I:$I,$A34,'Raw daily data'!$F:$F,"<0"))) -> 0 | S34: =IF(N34>0,O34/N34,"") | T34: =IF(R34>0,Q34/ABS(R34),"") | U34: =IF(F34>0,H34/F34,"") | V34: =IF(H34<0,MIN(ABS(H34)/G34,1),0) -> 0 | W34: =IF($A34="","",_xlfn.MAXIFS('Raw daily data'!$J:$J,'Raw daily data'!$I:$I,$A34)) -> 0 | X34: =IF(W34>=0,0,ABS(W34)/G34) -> 0 | Y34: =IFERROR(IF($A34="","",ABS(MIN(0,_xlfn.MINIFS('Raw daily data'!$J:$J,'Raw daily data'!$I:$I,$A34)))/G34),"")
A35: 46066 | C35: =TEXT(A35,"dddd") -> Friday | F35: =IF($A35="","",$E35*Summary!$B$8) -> 0 | G35: =IF($A35="","",F35*Summary!$B$9) -> 0 | H35: =IF($A35="","",SUMIFS('Raw daily data'!$F:$F,'Raw daily data'!$I:$I,$A35)) -> 0 | I35: =I34+H35 -> 515.0023 | J35: =SUMIF($B$2:$B$41,B35,$H$2:$H$41) -> 0 | K35: =Summary!$B$6 -> 5000 | L35: =J35-K35 -> -5000 | N35: =IF($A35="","",COUNTIFS('Raw daily data'!$I:$I,$A35)) -> 0 | O35: =IF($A35="","",COUNTIFS('Raw daily data'!$I:$I,$A35,'Raw daily data'!$F:$F,">0")) -> 0 | P35: =IF($A35="","",COUNTIFS('Raw daily data'!$I:$I,$A35,'Raw daily data'!$F:$F,"<0")) -> 0 | Q35: =IF($A35="","",SUMIFS('Raw daily data'!$F:$F,'Raw daily data'!$I:$I,$A35,'Raw daily data'!$F:$F,">0")) -> 0 | R35: =IF($A35="","",ABS(SUMIFS('Raw daily data'!$F:$F,'Raw daily data'!$I:$I,$A35,'Raw daily data'!$F:$F,"<0"))) -> 0 | S35: =IF(N35>0,O35/N35,"") | T35: =IF(R35>0,Q35/ABS(R35),"") | U35: =IF(F35>0,H35/F35,"") | V35: =IF(H35<0,MIN(ABS(H35)/G35,1),0) -> 0 | W35: =IF($A35="","",_xlfn.MAXIFS('Raw daily data'!$J:$J,'Raw daily data'!$I:$I,$A35)) -> 0 | X35: =IF(W35>=0,0,ABS(W35)/G35) -> 0 | Y35: =IFERROR(IF($A35="","",ABS(MIN(0,_xlfn.MINIFS('Raw daily data'!$J:$J,'Raw daily data'!$I:$I,$A35)))/G35),"")
A36: 46067 | C36: =TEXT(A36,"dddd") -> Saturday | F36: =IF($A36="","",$E36*Summary!$B$8) -> 0 | G36: =IF($A36="","",F36*Summary!$B$9) -> 0 | H36: =IF($A36="","",SUMIFS('Raw daily data'!$F:$F,'Raw daily data'!$I:$I,$A36)) -> 0 | I36: =I35+H36 -> 515.0023 | J36: =SUMIF($B$2:$B$41,B36,$H$2:$H$41) -> 0 | K36: =Summary!$B$6 -> 5000 | L36: =J36-K36 -> -5000 | N36: =IF($A36="","",COUNTIFS('Raw daily data'!$I:$I,$A36)) -> 0 | O36: =IF($A36="","",COUNTIFS('Raw daily data'!$I:$I,$A36,'Raw daily data'!$F:$F,">0")) -> 0 | P36: =IF($A36="","",COUNTIFS('Raw daily data'!$I:$I,$A36,'Raw daily data'!$F:$F,"<0")) -> 0 | Q36: =IF($A36="","",SUMIFS('Raw daily data'!$F:$F,'Raw daily data'!$I:$I,$A36,'Raw daily data'!$F:$F,">0")) -> 0 | R36: =IF($A36="","",ABS(SUMIFS('Raw daily data'!$F:$F,'Raw daily data'!$I:$I,$A36,'Raw daily data'!$F:$F,"<0"))) -> 0 | S36: =IF(N36>0,O36/N36,"") | T36: =IF(R36>0,Q36/ABS(R36),"") | U36: =IF(F36>0,H36/F36,"") | V36: =IF(H36<0,MIN(ABS(H36)/G36,1),0) -> 0 | W36: =IF($A36="","",_xlfn.MAXIFS('Raw daily data'!$J:$J,'Raw daily data'!$I:$I,$A36)) -> 0 | X36: =IF(W36>=0,0,ABS(W36)/G36) -> 0 | Y36: =IFERROR(IF($A36="","",ABS(MIN(0,_xlfn.MINIFS('Raw daily data'!$J:$J,'Raw daily data'!$I:$I,$A36)))/G36),"")
A37: 46068 | C37: =TEXT(A37,"dddd") -> Sunday | F37: =IF($A37="","",$E37*Summary!$B$8) -> 0 | G37: =IF($A37="","",F37*Summary!$B$9) -> 0 | H37: =IF($A37="","",SUMIFS('Raw daily data'!$F:$F,'Raw daily data'!$I:$I,$A37)) -> 0 | I37: =I36+H37 -> 515.0023 | J37: =SUMIF($B$2:$B$41,B37,$H$2:$H$41) -> 0 | K37: =Summary!$B$6 -> 5000 | L37: =J37-K37 -> -5000 | N37: =IF($A37="","",COUNTIFS('Raw daily data'!$I:$I,$A37)) -> 0 | O37: =IF($A37="","",COUNTIFS('Raw daily data'!$I:$I,$A37,'Raw daily data'!$F:$F,">0")) -> 0 | P37: =IF($A37="","",COUNTIFS('Raw daily data'!$I:$I,$A37,'Raw daily data'!$F:$F,"<0")) -> 0 | Q37: =IF($A37="","",SUMIFS('Raw daily data'!$F:$F,'Raw daily data'!$I:$I,$A37,'Raw daily data'!$F:$F,">0")) -> 0 | R37: =IF($A37="","",ABS(SUMIFS('Raw daily data'!$F:$F,'Raw daily data'!$I:$I,$A37,'Raw daily data'!$F:$F,"<0"))) -> 0 | S37: =IF(N37>0,O37/N37,"") | T37: =IF(R37>0,Q37/ABS(R37),"") | U37: =IF(F37>0,H37/F37,"") | V37: =IF(H37<0,MIN(ABS(H37)/G37,1),0) -> 0 | W37: =IF($A37="","",_xlfn.MAXIFS('Raw daily data'!$J:$J,'Raw daily data'!$I:$I,$A37)) -> 0 | X37: =IF(W37>=0,0,ABS(W37)/G37) -> 0 | Y37: =IFERROR(IF($A37="","",ABS(MIN(0,_xlfn.MINIFS('Raw daily data'!$J:$J,'Raw daily data'!$I:$I,$A37)))/G37),"")
A38: 46069 | C38: =TEXT(A38,"dddd") -> Monday | F38: =IF($A38="","",$E38*Summary!$B$8) -> 0 | G38: =IF($A38="","",F38*Summary!$B$9) -> 0 | H38: =IF($A38="","",SUMIFS('Raw daily data'!$F:$F,'Raw daily data'!$I:$I,$A38)) -> 0 | I38: =I37+H38 -> 515.0023 | J38: =SUMIF($B$2:$B$41,B38,$H$2:$H$41) -> 0 | K38: =Summary!$B$6 -> 5000 | L38: =J38-K38 -> -5000 | N38: =IF($A38="","",COUNTIFS('Raw daily data'!$I:$I,$A38)) -> 0 | O38: =IF($A38="","",COUNTIFS('Raw daily data'!$I:$I,$A38,'Raw daily data'!$F:$F,">0")) -> 0 | P38: =IF($A38="","",COUNTIFS('Raw daily data'!$I:$I,$A38,'Raw daily data'!$F:$F,"<0")) -> 0 | Q38: =IF($A38="","",SUMIFS('Raw daily data'!$F:$F,'Raw daily data'!$I:$I,$A38,'Raw daily data'!$F:$F,">0")) -> 0 | R38: =IF($A38="","",ABS(SUMIFS('Raw daily data'!$F:$F,'Raw daily data'!$I:$I,$A38,'Raw daily data'!$F:$F,"<0"))) -> 0 | S38: =IF(N38>0,O38/N38,"") | T38: =IF(R38>0,Q38/ABS(R38),"") | U38: =IF(F38>0,H38/F38,"") | V38: =IF(H38<0,MIN(ABS(H38)/G38,1),0) -> 0 | W38: =IF($A38="","",_xlfn.MAXIFS('Raw daily data'!$J:$J,'Raw daily data'!$I:$I,$A38)) -> 0 | X38: =IF(W38>=0,0,ABS(W38)/G38) -> 0 | Y38: =IFERROR(IF($A38="","",ABS(MIN(0,_xlfn.MINIFS('Raw daily data'!$J:$J,'Raw daily data'!$I:$I,$A38)))/G38),"")
A39: 46070 | C39: =TEXT(A39,"dddd") -> Tuesday | F39: =IF($A39="","",$E39*Summary!$B$8) -> 0 | G39: =IF($A39="","",F39*Summary!$B$9) -> 0 | H39: =IF($A39="","",SUMIFS('Raw daily data'!$F:$F,'Raw daily data'!$I:$I,$A39)) -> 0 | I39: =I38+H39 -> 515.0023 | J39: =SUMIF($B$2:$B$41,B39,$H$2:$H$41) -> 0 | K39: =Summary!$B$6 -> 5000 | L39: =J39-K39 -> -5000 | N39: =IF($A39="","",COUNTIFS('Raw daily data'!$I:$I,$A39)) -> 0 | O39: =IF($A39="","",COUNTIFS('Raw daily data'!$I:$I,$A39,'Raw daily data'!$F:$F,">0")) -> 0 | P39: =IF($A39="","",COUNTIFS('Raw daily data'!$I:$I,$A39,'Raw daily data'!$F:$F,"<0")) -> 0 | Q39: =IF($A39="","",SUMIFS('Raw daily data'!$F:$F,'Raw daily data'!$I:$I,$A39,'Raw daily data'!$F:$F,">0")) -> 0 | R39: =IF($A39="","",ABS(SUMIFS('Raw daily data'!$F:$F,'Raw daily data'!$I:$I,$A39,'Raw daily data'!$F:$F,"<0"))) -> 0 | S39: =IF(N39>0,O39/N39,"") | T39: =IF(R39>0,Q39/ABS(R39),"") | U39: =IF(F39>0,H39/F39,"") | V39: =IF(H39<0,MIN(ABS(H39)/G39,1),0) -> 0 | W39: =IF($A39="","",_xlfn.MAXIFS('Raw daily data'!$J:$J,'Raw daily data'!$I:$I,$A39)) -> 0 | X39: =IF(W39>=0,0,ABS(W39)/G39) -> 0 | Y39: =IFERROR(IF($A39="","",ABS(MIN(0,_xlfn.MINIFS('Raw daily data'!$J:$J,'Raw daily data'!$I:$I,$A39)))/G39),"")
A40: 46071 | C40: =TEXT(A40,"dddd") -> Wednesday | F40: =IF($A40="","",$E40*Summary!$B$8) -> 0 | G40: =IF($A40="","",F40*Summary!$B$9) -> 0 | H40: =IF($A40="","",SUMIFS('Raw daily data'!$F:$F,'Raw daily data'!$I:$I,$A40)) -> 0 | I40: =I39+H40 -> 515.0023 | J40: =SUMIF($B$2:$B$41,B40,$H$2:$H$41) -> 0 | K40: =Summary!$B$6 -> 5000 | L40: =J40-K40 -> -5000 | N40: =IF($A40="","",COUNTIFS('Raw daily data'!$I:$I,$A40)) -> 0 | O40: =IF($A40="","",COUNTIFS('Raw daily data'!$I:$I,$A40,'Raw daily data'!$F:$F,">0")) -> 0 | P40: =IF($A40="","",COUNTIFS('Raw daily data'!$I:$I,$A40,'Raw daily data'!$F:$F,"<0")) -> 0 | Q40: =IF($A40="","",SUMIFS('Raw daily data'!$F:$F,'Raw daily data'!$I:$I,$A40,'Raw daily data'!$F:$F,">0")) -> 0 | R40: =IF($A40="","",ABS(SUMIFS('Raw daily data'!$F:$F,'Raw daily data'!$I:$I,$A40,'Raw daily data'!$F:$F,"<0"))) -> 0 | S40: =IF(N40>0,O40/N40,"") | T40: =IF(R40>0,Q40/ABS(R40),"") | U40: =IF(F40>0,H40/F40,"") | V40: =IF(H40<0,MIN(ABS(H40)/G40,1),0) -> 0 | W40: =IF($A40="","",_xlfn.MAXIFS('Raw daily data'!$J:$J,'Raw daily data'!$I:$I,$A40)) -> 0 | X40: =IF(W40>=0,0,ABS(W40)/G40) -> 0 | Y40: =IFERROR(IF($A40="","",ABS(MIN(0,_xlfn.MINIFS('Raw daily data'!$J:$J,'Raw daily data'!$I:$I,$A40)))/G40),"")
A41: 46072 | C41: =TEXT(A41,"dddd") -> Thursday | F41: =IF($A41="","",$E41*Summary!$B$8) -> 0 | G41: =IF($A41="","",F41*Summary!$B$9) -> 0 | H41: =IF($A41="","",SUMIFS('Raw daily data'!$F:$F,'Raw daily data'!$I:$I,$A41)) -> 0 | I41: =I40+H41 -> 515.0023 | J41: =SUMIF($B$2:$B$41,B41,$H$2:$H$41) -> 0 | K41: =Summary!$B$6 -> 5000 | L41: =J41-K41 -> -5000 | N41: =IF($A41="","",COUNTIFS('Raw daily data'!$I:$I,$A41)) -> 0 | O41: =IF($A41="","",COUNTIFS('Raw daily data'!$I:$I,$A41,'Raw daily data'!$F:$F,">0")) -> 0 | P41: =IF($A41="","",COUNTIFS('Raw daily data'!$I:$I,$A41,'Raw daily data'!$F:$F,"<0")) -> 0 | Q41: =IF($A41="","",SUMIFS('Raw daily data'!$F:$F,'Raw daily data'!$I:$I,$A41,'Raw daily data'!$F:$F,">0")) -> 0 | R41: =IF($A41="","",ABS(SUMIFS('Raw daily data'!$F:$F,'Raw daily data'!$I:$I,$A41,'Raw daily data'!$F:$F,"<0"))) -> 0 | S41: =IF(N41>0,O41/N41,"") | T41: =IF(R41>0,Q41/ABS(R41),"") | U41: =IF(F41>0,H41/F41,"") | V41: =IF(H41<0,MIN(ABS(H41)/G41,1),0) -> 0 | W41: =IF($A41="","",_xlfn.MAXIFS('Raw daily data'!$J:$J,'Raw daily data'!$I:$I,$A41)) -> 0 | X41: =IF(W41>=0,0,ABS(W41)/G41) -> 0 | Y41: =IFERROR(IF($A41="","",ABS(MIN(0,_xlfn.MINIFS('Raw daily data'!$J:$J,'Raw daily data'!$I:$I,$A41)))/G41),"")

Sheet Raw daily data
A1: Symbol | B1: Name | C1: Side | D1: Quantity | E1: Price | F1: Profit | G1: Deal ID | H1: Time | I1: Trade Date | J1: Cumulative P&L for the day
A2: EURUSD | B2: EUR_USD | C2: sell | D2: 200000 | E2: 1.15899 | F2: -60 | G2: 12607 | H2: Wed, 11 Jan 2026 12:06:06 GMT | I2: =IF(H2="","",DATEVALUE(MID(H2,6,11))) -> 46033 | J2: =IF(F2="","",F2+IF(I2=I1,J1,0)) -> -60
A3: EURUSD | B3: EUR_USD | C3: sell | D3: 500002 | E3: 1.15829 | F3: 575.0023 | G3: 12594 | H3: Wed, 12 Jan 2026 12:06:06 GMT | I3: =IF(H3="","",DATEVALUE(MID(H3,6,11))) -> 46034 | J3: =IF(F3="","",F3+IF(I3=I2,J2,0)) -> 575.0023
I4: =IF(H4="","",DATEVALUE(MID(H4,6,11))) | J4: =IF(F4="","",F4+IF(I4=I3,J3,0))
I5: =IF(H5="","",DATEVALUE(MID(H5,6,11))) | J5: =IF(F5="","",F5+IF(I5=I4,J4,0))
I6: =IF(H6="","",DATEVALUE(MID(H6,6,11))) | J6: =IF(F6="","",F6+IF(I6=I5,J5,0))
I7: =IF(H7="","",DATEVALUE(MID(H7,6,11))) | J7: =IF(F7="","",F7+IF(I7=I6,J6,0))
I8: =IF(H8="","",DATEVALUE(MID(H8,6,11))) | J8: =IF(F8="","",F8+IF(I8=I7,J7,0))
I9: =IF(H9="","",DATEVALUE(MID(H9,6,11))) | J9: =IF(F9="","",F9+IF(I9=I8,J8,0))
I10: =IF(H10="","",DATEVALUE(MID(H10,6,11))) | J10: =IF(F10="","",F10+IF(I10=I9,J9,0))
I11: =IF(H11="","",DATEVALUE(MID(H11,6,11))) | J11: =IF(F11="","",F11+IF(I11=I10,J10,0))
I12: =IF(H12="","",DATEVALUE(MID(H12,6,11))) | J12: =IF(F12="","",F12+IF(I12=I11,J11,0))
I13: =IF(H13="","",DATEVALUE(MID(H13,6,11))) | J13: =IF(F13="","",F13+IF(I13=I12,J12,0))
I14: =IF(H14="","",DATEVALUE(MID(H14,6,11))) | J14: =IF(F14="","",F14+IF(I14=I13,J13,0))
I15: =IF(H15="","",DATEVALUE(MID(H15,6,11))) | J15: =IF(F15="","",F15+IF(I15=I14,J14,0))
... I52: =IF(H52="","",DATEVALUE(MID(H52,6,11))) | J52: =IF(F52="","",F52+IF(I52=I51,J51,0))

Sheet Setup Planner (old)
A1: Price/EMA's | B1: Value | D1: Monthly/weekly/daily TPO | E1: Value | G1: HTF & LTF fib anchors | H1: Value | J1: RSI | K1: Value | M1: PipTol | N1: Value | S1: Column1 | T1: Entry | U1: TP | V1: SL | W1: Pips to TP1 | X1: Reward at TP1 ($) | Y1: Pips to SL | Z1: Risk at SL ($) | AA1: R multiple at TP1 | AB1: Units | AC1: TF | AD1: Trend | AE1: Last BOS | AF1: Last CHOCH | AG1: Notes
A2: Current Price | B2: 1.16438 | D2: Monthly VAH | E2: 1.16562 | G2: HTF Swing Low (4H) | H2: 1.14931 | J2: RSI 15m | K2: 49.98 | M2: PipTol Value (for VAH/VAL/FVG) | N2: =ROUND($B$15*10000*0.5,0) -> 2 | P2: LongScore | Q2: =(1-0.5*$N$23)*(1-$B$34*$B$33)*($N$5+$N$7+$N$10+$N$13+$N$15+$N$26+$N$28) -> 1.225 | S2: Entry 0.382 | T2: =IF($N$30=1,$H$25,$B$2) -> 1.1615164 | U2: =K6 -> 1.1656 | V2: =K7 -> 1.162 | W2: =IF(OR(T2="",$U$2=""),"",ABS($U$2-T2)*10000) -> 40.836 | X2: =IF(W2="","",W2*T14*0.0001) -> 156.66845 | Y2: =IF($V$2="","",ABS(T2-$V$2)*10000) -> 4.836 | Z2: =IF(Y2="","",Y2*T14*0.0001) -> 18.553448 | AA2: =IF(OR($K$5=0,X2=""),"",X2/$K$5) -> 0.42336841 | AB2: =T14 -> 38365.278 | AC2: 1D | AD2: Bull | AE2: Down | AF2: Up
A3: EMA9 15m | B3: 1.16429 | D3: Monthly POC | E3: 1.16095 | G3: HTF Swing High (4H) | H3: 1.1682 | J3: RSI 1H | K3: 42.88 | M3: PipTol Fib (for fibs) | N3: =ROUND($B$15*10000*0.3,0) -> 1 | P3: ShortScore | Q3: =(1-0.5*$N$23)*(1-$B$34*$B$33)*($N$6+$N$8+$N$11+$N$14+$N$16+$N$27+$N$29) -> 0.875 | S3: Entry 0.500 | T3: =IF($N$30=1,$H$26,$B$2) -> 1.16036 | U3: =U2 -> 1.1656 | V3: =V2 -> 1.162 | W3: =IF(OR(T3="",$U$2=""),"",ABS($U$2-T3)*10000) -> 52.4 | X3: =IF(W3="","",W3*T15*0.0001) -> 351.8096 | Y3: =IF($V$2="","",ABS(T3-$V$2)*10000) -> 16.4 | Z3: =IF(Y3="","",Y3*T15*0.0001) -> 110.10835 | AA3: =IF(OR($K$5=0,X3=""),"",X3/$K$5) -> 0.9507024 | AB3: =T15 -> 67139.236 | AC3: 4H | AD3: Bull | AE3: Up | AF3: Up
A4: EMA21 15m | B4: 1.16433 | D4: Monthly VAL | E4: 1.15958 | J4: RSI 4H | K4: 51.66 | M4: PipTol Mid | N4: =ROUND($B$15*10000*0.6,0) -> 3 | S4: Entry 0.618 | T4: =IF($N$30=1,$H$27,$B$2) -> 1.1592036 | U4: =U3 -> 1.1656 | V4: =V3 -> 1.162 | W4: =IF(OR(T4="",$U$2=""),"",ABS($U$2-T4)*10000) -> 63.964 | X4: =IF(W4="","",W4*T16*0.0001) -> 552.14924 | Y4: =IF($V$2="","",ABS(T4-$V$2)*10000) -> 27.964 | Z4: =IF(Y4="","",Y4*T16*0.0001) -> 241.39049 | AA4: =IF(OR($K$5=0,X4=""),"",X4/$K$5) -> 1.4920844 | AB4: =T16 -> 86321.875 | AC4: 1H | AD4: Bear | AE4: Down | AF4: Down
A5: EMA50 15m | B5: 1.16458 | D5: Monthly MID | E5: 1.16385 | G5: HTF Fib 0.382 | H5: =H3-(H3-H2)*0.382 -> 1.160984 | J5: Risk per Trade R ($) | K5: =Summary!B8*Summary!B10*(0.7+0.3*MAX($Q$8,$Q$9)) -> 370.05229 | M5: Long_ValScore | N5: =IF(AND($B$2>$B$6,ABS(($B$2-$E$4)*10000)<=$N$2),1,0)+IF(AND($B$2>$B$6,ABS(($B$2-$E$8)*10000)<=$N$2),1,0)+IF(AND($B$2>$B$6,ABS(($B$2-$E$12)*10000)<=$N$2),1,0)+IF(AND($N$22=1,$B$2>$B$6,ABS(($B$2-$E$17)*10000)<=$N$2),1,0) -> 0 | P5: Bias | Q5: =IF(AND($Q$8>=0.7,$Q$9<=0.3),"A+ LONG ZONE",IF(AND($Q$9>=0.7,$Q$8<=0.3),"A+ SHORT ZONE","MID / WAIT")) -> MID / WAIT | R5: =IF($N$23=1,"⚠ In MID / BALANCE zone – expect chop","") | W5: =SUBTOTAL(109,Table5[Pips to TP1]) -> 0 | X5: =SUBTOTAL(109,Table5[Reward at TP1 ($)]) -> 0 | Y5: =SUBTOTAL(109,Table5[Pips to SL]) -> 0 | Z5: =SUBTOTAL(109,Table5[Risk at SL ($)]) -> 0 | AA5: =SUBTOTAL(109,Table5[R multiple at TP1]) -> 0 | AB5: =SUBTOTAL(109,Table5[Units]) -> 0 | AC5: 15M | AD5: Bear | AE5: Down | AF5: Down
A6: SMA200 15m | B6: 1.16565 | D6: Weekly VAH | E6: 1.1656 | G6: HTF Fib 0.500 | H6: =H3-(H3-H2)*0.5 -> 1.158755 | J6: TP1 Price | K6: =IF($K$11="LONG",MIN(IF($E$2>$B$2,$E$2,10^6),IF($E$6>$B$2,$E$6,10^6),IF($E$10>$B$2,$E$10,10^6),IF($H$3>$B$2,$H$3,10^6)),MAX(IF($E$4<$B$2,$E$4,-10^6),IF($E$8<$B$2,$E$8,-10^6),IF($E$12<$B$2,$E$12,-10^6),IF($H$2<$B$2,$H$2,-10^6))) -> 1.1656 | L6: =MIN(IF($E$2>$B$2,$E$2),IF($E$6>$B$2,$E$6),IF($E$10>$B$2,$E$10),IF($H$2>$B$2,$H$2)) -> 0 | M6: Short_ValScore | N6: =IF(AND($B$2<$B$6,ABS(($B$2-$E$2)*10000)<=$N$2),1,0)+IF(AND($B$2<$B$6,ABS(($B$2-$E$6)*10000)<=$N$2),1,0)+IF(AND($B$2<$B$6,ABS(($B$2-$E$10)*10000)<=$N$2),1,0)+IF(AND($N$22=1,$B$2<$B$6,ABS(($B$2-$E$14)*10000)<=$N$2),1,0) -> 0 | P6: MaxScorePossible | Q6: 10 | AC6: HTF_Long_OK | AD6: =AND(AD2="Bull",AD3="Bull") -> TRUE
D7: Weekly POC | E7: 1.16095 | G7: HTF Fib 0.618 | H7: =H3-(H3-H2)*0.618 -> 1.156526 | J7: SL Price | K7: 1.162 | M7: Long_EMAScore | N7: =IF(AND($B$2>$B$3,$B$3>$B$4,$B$4>$B$5,$B$5>$B$6),1,0)+0.25*COUNTIF($B$8:$B$14,"<"&$B$2) -> 1.5 | S7: Pips to SL 0.382 | T7: =IF($K$7="","",ABS(T2-$K$7)*10000) -> 4.836 | AC7: HTF_Short_OK | AD7: =AND(AD2="Bear",AD3="Bear") -> FALSE
A8: EMA50 1H | B8: 1.16502 | D8: Weekly VAL | E8: 1.15932 | J8: Weight 0.382 | K8: =IF(MAX($Q$8,$Q$9)>=0.7,0.15,0.2) -> 0.2 | M8: Short_EMAScore | N8: =IF(AND($B$2<$B$3,$B$3<$B$4,$B$4<$B$5,$B$5<$B$6),1,0)+0.25*COUNTIF($B$8:$B$14,">"&$B$2) -> 0.25 | P8: LongScore% | Q8: =MIN(1,$Q$2/$Q$6) -> 0.1225 | S8: Pips to SL 0.500 | T8: =IF($K$7="","",ABS(T3-$K$7)*10000) -> 16.4 | AC8: LTF_Long_OK | AD8: =AND(OR(AD4="Bull",AD4="Range"),OR(AD5<>"Bear"),OR(AF4="Up",AF4="None")) -> FALSE
A9: EMA50 4H | B9: 1.16223 | D9: Weekly MID | E9: 1.16356 | G9: LTF Leg Low (15m | H9: 1.15894 | J9: Weight 0.500 | K9: =IF(MAX($Q$8,$Q$9)>=0.7,0.3,0.35) -> 0.35 | P9: ShortScore% | Q9: =MIN(1,$Q$3/$Q$6) -> 0.0875 | S9: Pips to SL 0.618 | T9: =IF($K$7="","",ABS(T4-$K$7)*10000) -> 27.964 | AC9: LTF_Short_OK | AD9: =AND(OR(AD4="Bear",AD4="Range"),OR(AD5<>"Bull"),OR(AF4="Down",AF4="None")) -> TRUE
A10: EMA50 1D | B10: 1.16099 | D10: Prev Daily VAH | E10: 1.16741 | G10: LTF Leg High (15m) | H10: 1.16526 | J10: Weight 0.618 | K10: =IF(MAX($Q$8,$Q$9)>=0.7,0.55,0.45) -> 0.45 | M10: Long_FibScore | N10: =IF(AND($B$2<$H$22,ABS(($B$2-$H$5)*10000)<=$N$3),0.5,0)+IF(AND($B$2<$H$22,ABS(($B$2-$H$6)*10000)<=$N$3),0.5,0)+IF(AND($B$2<$H$22,ABS(($B$2-$H$7)*10000)<=$N$3),0.5,0) -> 0 | P10: Setup Type | Q10: =IF($K$11="NONE","No Setup",IF($N$31="Trend-aligned","Trend Pullback","Counter-trend Fade")) -> Trend Pullback
A11: EMA100 1D | B11: 1.15845 | D11: Prev Daily POC | E11: 1.16595 | J11: Long vs Short domination | K11: =IF($Q$2>$Q$3,"LONG",IF($Q$3>$Q$2,"SHORT","NONE")) -> LONG | M11: Short_FibScore | N11: =IF(AND($B$2>$H$22,ABS(($B$2-$H$5)*10000)<=$N$3),0.5,0)+IF(AND($B$2>$H$22,ABS(($B$2-$H$6)*10000)<=$N$3),0.5,0)+IF(AND($B$2>$H$22,ABS(($B$2-$H$7)*10000)<=$N$3),0.5,0) -> 0 | P11: Trend Mode | Q11: =IF($K$11="NONE","No bias",$N$31) -> Trend-aligned | S11: Avg Pips to SL | T11: =IF(OR(T7="",T8="",T9=""),"",$K$8*T7+$K$9*T8+$K$10*T9) -> 19.291
A12: EMA200 1D | B12: 1.14382 | D12: Prev Daily VAL | E12: 1.16551 | G12: LTF Fib 0.382 | H12: =H10-(H10-H9)*0.382 -> 1.1628458 | P12: Grade | Q12: =IF(OR($K$11="NONE",$T$21=""),"N/A",IF(OR($T$21<$Q$24,AND($K$11="LONG",NOT($AD$27)),AND($K$11="SHORT",NOT($AD$28))),"C",IF($Q$8>=0.7,"A+",IF($Q$8>=0.4,"B","C")))) -> C | S12: Total Units | T12: =IF(T11="","",$K$5/(T11*0.0001)) -> 191826.39
A13: EMA50 1W | B13: 1.13782 | D13: Prev Daily MID | E13: 1.16616 | G13: LTF Fib 0.500 | H13: =H10-(H10-H9)*0.5 -> 1.1621 | M13: Long_RSIScore | N13: =IF($K$2<45,0.5,0)+IF($K$3<45,0.25,0)+IF($K$4<45,0.25,0) -> 0.25
A14: EMA20 1M | B14: 1.11879 | D14: Current Daily VAH | E14: 1.16572 | G14: LTF Fib 0.618 | H14: =H10-(H10-H9)*0.618 -> 1.1613542 | M14: Short_RSIScore | N14: =IF($K$2>55,0.5,0)+IF($K$3>55,0.25,0)+IF($K$4>55,0.25,0) -> 0 | P14: NoTradeFlag | Q14: =OR($K$11="NONE",$T$21<$Q$24,AND($K$11="LONG",NOT($AD$27)),AND($K$11="SHORT",NOT($AD$28)),AND($Q$11="Counter-trend",$Q$12="C")) -> TRUE | S14: Units @0.382 | T14: =IF(T12="","",T12*$K$8) -> 38365.278 | AC14: Liquidity
A15: ATR(14) 15m | B15: 0.00044 | D15: Current Daily POC | E15: 1.16516 | M15: Long_FVGScore | N15: =IF(ABS(($B$2-$H$17)*10000)<=$N$2,1,0)+IF(ABS(($B$2-$H$19)*10000)<=$N$2,1,0)+IF(ABS(($B$2-$H$21)*10000)<=$N$2,1,0) -> 0 | S15: Units @0.500 | T15: =IF(T12="","",T12*$K$9) -> 67139.236 | AC15: PMH | AD15: 1.16561
D16: Curr Daily MID | E16: 1.16506 | G16: 4H FVG high | H16: 1.16411 | M16: Short_FVGScore | N16: =IF(ABS(($B$2-$H$16)*10000)<=$N$2,1,0)+IF(ABS(($B$2-$H$18)*10000)<=$N$2,1,0)+IF(ABS(($B$2-$H$20)*10000)<=$N$2,1,0) -> 0 | S16: Units @0.618 | T16: =IF(T12="","",T12*$K$10) -> 86321.875 | AC16: PML | AD16: 1.14685
D17: Curr Daily VAL | E17: 1.16421 | G17: 4H FVG low | H17: 1.16253 | M17: Long_CurrentDayValScore | N17: =IF(AND($L$22,$N$20=1,$B$2>$B$6,ABS(($B$2-$E$17)*10000)<=$N$2),1,0) -> 0 | AC17: PWH | AD17: 1.16135
G18: Daily FVG high | H18: 1.164 | K18: News Window? | L18: FALSE | M18: Short_CurrentDayValScore | N18: =IF(AND($L$22,$N$20=1,$B$2<$B$6,ABS(($B$2-$E$14)*10000)<=$N$2),1,0) -> 0 | S18: Avg Entry | T18: =IF($T$12=0,0,SUMPRODUCT(T14:T16,T2:T4)/$T$12) -> 1.1600709 | AC18: PWL | AD18: 1.15016
G19: Daily FVG low | H19: 1.16249 | K19: Session Quality? | L19: FALSE | S19: Pips to TP1 | T19: =IF(OR(T18="",$K$6=""),"",ABS($K$6-T18)*10000) -> 55.291 | AC19: PDH | AD19: 1.1682
A20: Today’s High | B20: =H10 -> 1.16526 | G20: 1H FVG high | H20: 1.16198 | K20: Spread/Slippage Bad? | L20: FALSE | M20: Min Day Range Pips | N20: 20 | S20: Reward at TP1 ($) | T20: =ABS($K$6-$T$18)*$T$12 -> 1060.6273 | AC20: PDL | AD20: 1.16412
A21: Today’s Low | B21: =H9 -> 1.15894 | G21: 1H FVG low | H21: 1.16128 | M21: Curr Day Range Pips | N21: =IF(AND($E$14<>"",$E$17<>""),ABS(($E$14-$E$17)*10000),0) -> 15.1 | S21: R multiple at TP1 | T21: =IF($K$5=0,0,$T$20/$K$5) -> 2.8661552 | AB21: BOS | AC21: EQH_above | AD21: 1.16599
A22: Day Range (pips) | B22: =ABS(($B$20-$B$21)*10000) -> 63.2 | G22: mid of HTF leg | H22: =($H$2+$H$3)/2 -> 1.158755 | K22: (ContextOK) | L22: =IF(OR($L$18,$L$19,$L$20),0,1) -> 1 | M22: Curr Day Range OK? 0/1 | N22: =IF($N$21>=$N$20,1,0) -> 0 | P22: Setup Summary | Q22: =IF($N$21=0,"🚫 NO TRADE – context filter is ON (news/session/spread).",IF($T$21<$Q$25,"🚫 REJECT – R multiple at TP1 is only "&TEXT($T$21,"0.0")&"R (min "&TEXT($Q$25,"0.0")&"R).",IF($N$30=0,"⚠ Counter-trend setup. "&IF($Q$5="A+ LONG ZONE","✅ A+ LONG setup – Long "&TEXT($Q$8,"0%")&", Short "&TEXT($Q$9,"0%")&".",IF($Q$5="A+ SHORT ZONE","✅ A+ SHORT setup – Short "&TEXT($Q$9,"0%")&", Long "&TEXT($Q$8,"0%")&".","⚪ MID / WAIT – Long "&TEXT($Q$8,"0%")&", Short "&TEXT($Q$9,"0%")&".")),IF($Q$5="A+ LONG ZONE","✅ A+ LONG setup – Long "&TEXT($Q$8,"0%")&", Short "&TEXT($Q$9,"0%")&".",IF($Q$5="A+ SHORT ZONE","✅ A+ SHORT setup – Short "&TEXT($Q$9,"0%")&", Long "&TEXT($Q$8,"0%")&".","⚪ MID / WAIT – Long "&TEXT($Q$8,"0%")&", Short "&TEXT($Q$9,"0%")&"."))))) -> ⚪ MID / WAIT – Long 12%, Short 9%. | AB22: CHoCH | AC22: EQL_below | AD22: 1.16416
A23: Location in Daily Range % | B23: =IF($B$22=0,0,ABS(($B$2-$B$21)*10000)/$B$22) -> 0.86075949 | G23: Intraday Leg Low | H23: 1.15546 | M23: MidChopFlag | N23: =IF(MIN(ABS(($B$2-$E$5)*10000),ABS(($B$2-$E$9)*10000),ABS(($B$2-$E$13)*10000),ABS(($B$2-$E$16)*10000))<=$N$4,1,0) -> 0 | P23: Trade Plan | Q23: =IF($N$21=0,"No trade – stand aside.","Plan: "&IF($Q$4="MID / WAIT","WAIT / optional small "&LOWER($K$11)&" probe ","enter "&LOWER($K$11)&" ")&"@ "&TEXT($T$18,"0.0000")&", TP "&TEXT($K$6,"0.0000")&", SL "&TEXT($K$7,"0.0000")&", risk $"&TEXT($K$5,"0")&" for "&TEXT($T$21,"0.0")&"R to TP1.") -> Plan: enter long @ 1.1601, TP 1.1656, SL 1.1620, risk $370 for 2.9R to TP1.
A24: ADR(14) | B24: 0.00069 | G24: Intraday Leg High | H24: =H10 -> 1.16526 | K24: UseCurrentDayTPO | L24: TRUE | Q24: =IF($B$33=1,"🔔 Near options expiry magnet at "&TEXT($B$30,"0.0000")&". ","") -> 🔔 Near options expiry magnet at 1.1650. | AC24: Dist_Above (pips | AD24: =MIN(IF(AD15>$B$2,ABS((AD15-$B$2)*10000),1000000000),IF(AD17>$B$2,ABS((AD17-$B$2)*10000),1000000000),IF(AD19>$B$2,ABS((AD19-$B$2)*10000),1000000000),IF(AD21>$B$2,ABS((AD21-$B$2)*10000),1000000000)) -> 12.3
A25: % of ADR used | B25: =IF($B$24=0,0,$B$22/$B$24) -> 91594.203 | G25: Session Fib 0.382 | H25: =H24-(H24-H23)*0.382 -> 1.1615164 | M25: mid tolerance | N25: 8 | AC25: Dist_Below (pips) | AD25: =MIN(IF(AD16<$B$2,ABS((AD16-$B$2)*10000),1000000000),IF(AD18<$B$2,ABS((AD18-$B$2)*10000),1000000000),IF(AD20<$B$2,ABS((AD20-$B$2)*10000),1000000000),IF(AD22<$B$2,ABS((AD22-$B$2)*10000),1000000000)) -> 2.2
A26: Options Expiry | G26: Session Fib 0.500 | H26: =H24-(H24-H23)*0.5 -> 1.16036 | M26: Long_MidScore | N26: =IF(AND($B$2>$B$6,MIN(ABS(($B$2-$E$5)*10000),ABS(($B$2-$E$9)*10000))<=$N$25),1,0) -> 0
A27: Strike 1 | B27: 1.1214 | C27: Size 1 (bn) | D27: 1.18 | E27: =IF($B$27="","",ABS(($B$2-$B$27)*10000)) -> 429.8 | G27: Session Fib 0.618 | H27: =H24-(H24-H23)*0.618 -> 1.1592036 | M27: Short_MidScore | N27: =IF(AND($B$2<$B$6,MIN(ABS(($B$2-$E$5)*10000),ABS(($B$2-$E$9)*10000))<=$N$25),1,0) -> 1 | AC27: Long_RoomOK | AD27: =IF($T$11="",FALSE,AD24>=3*$T$11) -> FALSE
A28: Strike 2 | B28: 1.18 | C28: Size 2 (bn) | D28: 1.79 | E28: =IF($B$28="","",ABS(($B$2-$B$28)*10000)) -> 156.2 | H28: =IF($B$42="Zone 1",$H$14,IF($B$42="Zone 2",$H$27,IF($B$42="Zone 3",$H$7,""))) | M28: Long_StructScore | N28: =IF(AND($AD$6,$AD$8),1,0) -> 0 | AC28: Short_RoomOK | AD28: =IF($T$11="",FALSE,AD25>=3*$T$11) -> FALSE
A29: Strike 3 | B29: 1.165 | C29: Size 3 (bn) | D29: 0.856 | E29: =IF($B$29="","",ABS(($B$2-$B$29)*10000)) -> 6.2 | M29: Short_StructScore | N29: =IF(AND($AD$7,$AD$9),1,0) -> 0
A30: Magnet Strike | B30: =IF(COUNTA($B$27:$B$29)=0,"",INDEX($B$27:$B$29,MATCH(MIN($E$27:$E$29),$E$27:$E$29,0))) -> 1.165 | M30: TrendAlignFlag | N30: =IF(OR(AND($K$11="LONG",$H$2<$H$3),AND($K$11="SHORT",$H$2>$H$3)),1,0) -> 1
A31: Magnet Range (pips) | B31: 20 | M31: TrendModeText | N31: =IF($N$30=1,"Trend-aligned","Counter-trend") -> Trend-aligned
A32: Distance to Magnet (pips) | B32: =IF($B$30="","",ABS(($B$2-$B$30)*10000)) -> 6.2
A33: Within Magnet? 0/1 | B33: =IF(AND($B$30<>"",$B$32<=$B$31),1,0) -> 1
A34: Options Clamp % | B34: 0.3
N35: Zone | O35: Fib | P35: Entry | Q35: TP1 | R35: SL | S35: Pips to TP1 | T35: Pips to SL | U35: R multiple (per rung) | V35: Weight | W35: Risk $ | X35: Reward $ | Y35: Units
N36: 1 | O36: 0.382 | P36: =$H$12 -> 1.1628458 | Q36: =$K$6 -> 1.1656 | R36: =$K$7 -> 1.162 | S36: =ABS($Q36-$P36)*10000 -> 27.5424 | T36: =ABS($P36-$R36)*10000 -> 8.4576 | U36: =IF(T36=0,"",S36/T36) -> 3.2565267 | V36: =$K$8 -> 0.2 | W36: =$K$5*V36 -> 74.010457 | X36: =IF(U36="","",W36*U36) -> 241.01703 | Y36: =IF(T36=0,"",W36/(T36*0.0001)) -> 87507.635
A37: Zone | B37: Role | C37: Low | D37: High | E37: Active? | F37: Ladder Mode | G37: Notes | N37: 1 | O37: 0.5 | P37: =$H$13 -> 1.1621 | Q37: =$K$6 -> 1.1656 | R37: =$K$7 -> 1.162 | S37: =ABS($Q37-$P37)*10000 -> 35 | T37: =ABS($P37-$R37)*10000 -> 1 | U37: =IF(T37=0,"",S37/T37) -> 35 | V37: =$K$8 -> 0.2 | W37: =$K$5*V37 -> 74.010457 | X37: =IF(U37="","",W37*U37) -> 2590.366 | Y37: =IF(T37=0,"",W37/(T37*0.0001)) -> 740104.57
A38: 1 | B38: Shallow | C38: =MIN($H$14,$H$12) -> 1.1613542 | D38: =MAX($H$14,$H$12) -> 1.1628458 | E38: TRUE | F38: Half-size ladder | G38: Intraday leg fib zone | N38: 1 | O38: 0.618 | P38: =$H$14 -> 1.1613542 | Q38: =$K$6 -> 1.1656 | R38: =$K$7 -> 1.162 | S38: =ABS($Q38-$P38)*10000 -> 42.4576 | T38: =ABS($P38-$R38)*10000 -> 6.4576 | U38: =IF(T38=0,"",S38/T38) -> 6.5748266 | V38: =$K$8 -> 0.2 | W38: =$K$5*V38 -> 74.010457 | X38: =IF(U38="","",W38*U38) -> 486.60592 | Y38: =IF(T38=0,"",W38/(T38*0.0001)) -> 114609.85
A39: 2 | B39: Main A+ | C39: =MIN($H$27,$H$25) -> 1.1592036 | D39: =MAX($H$27,$H$25) -> 1.1615164 | E39: TRUE | F39: Full ladder | G39: Session fib + POC/VAH/FVG confluence | N39: Zone 1 Total R | U39: =IF($K$5=0,"",(X36+X37+X38)/$K$5) -> 8.9662706 | Y39: =IF(T39=0,"",W39/(T39*0.0001))
A40: 3 | B40: HTF backup | C40: =MIN($H$7,$H$5) -> 1.156526 | D40: =MAX($H$7,$H$5) -> 1.160984 | E40: FALSE | F40: Case-by-case | G40: HTF 0.5–0.618 region | N40: 2 | O40: 0.382 | P40: =$H$25 -> 1.1615164 | Q40: =$K$6 -> 1.1656 | R40: =$K$7 -> 1.162 | S40: =ABS($Q40-$P40)*10000 -> 40.836 | T40: =ABS($P40-$R40)*10000 -> 4.836 | U40: =IF(T40=0,"",S40/T40) -> 8.4441687 | V40: =$K$8 -> 0.2 | W40: =$K$5*V40 -> 74.010457 | X40: =IF(U40="","",W40*U40) -> 624.95679 | Y40: =IF(T40=0,"",W40/(T40*0.0001)) -> 153040.65
N41: 2 | O41: 0.5 | P41: =$H$26 -> 1.16036 | Q41: =$K$6 -> 1.1656 | R41: =$K$7 -> 1.162 | S41: =ABS($Q41-$P41)*10000 -> 52.4 | T41: =ABS($P41-$R41)*10000 -> 16.4 | U41: =IF(T41=0,"",S41/T41) -> 3.195122 | V41: =$K$9 -> 0.35 | W41: =$K$5*V41 -> 129.5183 | X41: =IF(U41="","",W41*U41) -> 413.82676 | Y41: =IF(T41=0,"",W41/(T41*0.0001)) -> 78974.573
A42: Current Zone | B42: =IF(AND($B$2>=C38,$B$2<=D38),"Zone 1",IF(AND($B$2>=C39,$B$2<=D39),"Zone 2",IF(AND($B$2>=C40,$B$2<=D40),"Zone 3","None"))) -> None | N42: 2 | O42: 0.618 | P42: =$H$27 -> 1.1592036 | Q42: =$K$6 -> 1.1656 | R42: =$K$7 -> 1.162 | S42: =ABS($Q42-$P42)*10000 -> 63.964 | T42: =ABS($P42-$R42)*10000 -> 27.964 | U42: =IF(T42=0,"",S42/T42) -> 2.2873695 | V42: =$K$10 -> 0.45 | W42: =$K$5*V42 -> 166.52353 | X42: =IF(U42="","",W42*U42) -> 380.90084 | Y42: =IF(T42=0,"",W42/(T42*0.0001)) -> 59549.252
N43: Zone 2 Total R | U43: =IF($K$5=0,"",(X40+X41+X42)/$K$5) -> 3.8364427 | Y43: =SUM(Y40:Y42) -> 291564.47
N44: 3 | O44: 0.382 | P44: =$H$5 -> 1.160984 | Q44: =$K$6 -> 1.1656 | R44: =$K$7 -> 1.162 | S44: =ABS($Q44-$P44)*10000 -> 46.1598 | T44: =ABS($P44-$R44)*10000 -> 10.1598 | U44: =IF(T44=0,"",S44/T44) -> 4.5433768 | V44: =$K$8 -> 0.2 | W44: =$K$5*V44 -> 74.010457 | X44: =IF(U44="","",W44*U44) -> 336.2574 | Y44: =IF(T44=0,"",W44/(T44*0.0001)) -> 72846.372
N45: 3 | O45: 0.5 | P45: =$H$6 -> 1.158755 | Q45: =$K$6 -> 1.1656 | R45: =$K$7 -> 1.162 | S45: =ABS($Q45-$P45)*10000 -> 68.45 | T45: =ABS($P45-$R45)*10000 -> 32.45 | U45: =IF(T45=0,"",S45/T45) -> 2.1093991 | V45: =$K$9 -> 0.35 | W45: =$K$5*V45 -> 129.5183 | X45: =IF(U45="","",W45*U45) -> 273.20578 | Y45: =IF(T45=0,"",W45/(T45*0.0001)) -> 39913.189
N46: 3 | O46: 0.618 | P46: =$H$7 -> 1.156526 | Q46: =$K$6 -> 1.1656 | R46: =$K$7 -> 1.162 | S46: =ABS($Q46-$P46)*10000 -> 90.7402 | T46: =ABS($P46-$R46)*10000 -> 54.7402 | U46: =IF(T46=0,"",S46/T46) -> 1.657652 | V46: =$K$10 -> 0.45 | W46: =$K$5*V46 -> 166.52353 | X46: =IF(U46="","",W46*U46) -> 276.03805 | Y46: =IF(T46=0,"",W46/(T46*0.0001)) -> 30420.701
N47: Zone 3 Total R | U47: =IF($K$5=0,"",(X44+X45+X46)/$K$5) -> 2.3929084 | Y47: =SUM(Y44:Y46) -> 143180.26
M50: DailyLocationScore_Long | N50: =IF($B$23<=0.4,0.5,0) -> 0
M51: DailyLocationScore_Short | N51: =IF($B$23>=0.6,0.5,0) -> 0.5
M52: TrendDayFlag | N52: =IF($B$25>=0.8,1,0) -> 1
M53: ExhaustedForNewTrendEntries | N53: =IF($B$25>=1,1,0) -> 1

Sheet Planner_v2
A1: BACKEND CALC — Use Planner_HUD (inputs & ladders) | F1: Structure (SMC) – D1 / H4 / H1 / 15m | K1: Side | L1: =IF(AND($G$8,NOT($G$9)),"LONG",IF(AND($G$9,NOT($G$8)),"SHORT","")) | P1: PRIMARY LADDER | Q1: Entry | R1: TP | S1: SL | T1: Pips to TP1 | U1: Eff Pips to SL | V1: Weight | W1: Risk $ | X1: Reward $ | Y1: Units | Z1: R per rung | AI1: CT_Entry | AJ1: =IF(SUM($V$28:$V$30)=0,"",SUMPRODUCT($Q$28:$Q$30,$V$28:$V$30)/SUM($V$28:$V$30)) -> 1.1648025
A2: Market snapshot (15m + HTF EMAs & ATR) | F2: TF | G2: Trend | H2: Last BOS | I2: Last CHOCH | K2: Risk per Trade R ($) | L2: =Summary!B10*Summary!B8 -> 502.2766 | P2: Entry 0.382 | Q2: =IF($L$1="LONG",IF($AE$58,$G$19,$B$7),IF($L$1="SHORT",$D$23,"")) | R2: =IF(Q2="","",$AE$40) | S2: =IF($L$1="LONG",IF(OR($AE$58,$B$3>=$G$19),$AE$27,$G$20-0.0002),IF($L$1="SHORT",IF($AE$58,MAX($B$39,$B$7)+0.0002,$G$19+0.0002),"")) | T2: =IF(OR(Q2="",R2=""),"",ABS((R2-Q2)*10000)) | U2: =IF(OR(Q2="",S2=""),"",MAX(ABS((Q2-S2)*10000),$AE$19)) | V2: =$L$7 -> 0.2 | W2: =IF(OR(V2=0,$AE$11=0,Q2=""),"",$L$2*$AE$8*V2/$AE$11) | X2: =IF(OR(W2="",W2=0,T2=""),"",W2*T2/MAX(U2,$AE$19)) | Y2: =IF(OR(Q2="",U2="",W2=""),"",W2/(MAX(U2,$AE$19)*$AE$3)) | Z2: =IF(OR(T2="",U2=""),"",T2/MAX(U2,$AE$19)) | AA2: =IF(U2="","",MAX(U2,$AE$7)) | AB2: Scoring & HUD | AD2: Ladder Controls | AF2: Big Picture | AG2: =IF($AC$25,"Avoid trading this leg – system rules (R, room, macro) are not met.",IF($AC$56=1,"HTF up, shallow pullback in Tier 1 (15m 0.382–0.618). Long bias but less room; prefer buying dips closer to Tier 2/3.",IF($AC$56=2,"HTF up, intraday pullback trading in Tier 2 (4H FVG + HTF 0.382 + EMA50D). Macro bias: buy dips; this is a B-grade but tradable zone when ladder and R/room are valid.",IF($AC$56=3,"HTF up, deep discount near structural support (Tier 3). If trend remains intact, this is a high-value region.","Price is above all discount tiers (premium) near PMH/PDH/EQH. This is not a location for fresh longs; either manage existing longs or wait for a pullback into Tier 2/3 or a clearly defined CT short setup.")))) -> Avoid trading this leg – system rules (R, room, macro) are not met. | AI2: CT_SL | AJ2: =$AC$48+0.0008 -> 1.16534
A3: Current Price | B3: =Planner_HUD!B5 -> 1.16364 | F3: 1D | G3: =IF($B$12="","",IF(AND($B$12>$B$13,$B$13>$B$14,$B$3>$B$12+0.0002),"Bull",IF(AND($B$12<$B$13,$B$13<$B$14,$B$3<$B$12-0.0002),"Bear","Range"))) -> Range | H3: =Planner_HUD!C24 -> Down | I3: =Planner_HUD!D24 -> Down | K3: TP1 Price | L3: =IF($L$1="LONG",MIN(IF($G$15>$B$3,$G$15,10^6),IF($G$17>$B$3,$G$17,10^6),IF($G$19>$B$3,$G$19,10^6),IF($G$21>$B$3,$G$21,10^6)),IF($L$1="SHORT",MAX(IF($G$16<$B$3,$G$16,-10^6),IF($G$18<$B$3,$G$18,-10^6),IF($G$20<$B$3,$G$20,-10^6),IF($G$22<$B$3,$G$22,-10^6)),"")) | P3: Entry 0.500 | Q3: =IF($L$1="LONG",IF($AE$58,AVERAGE($B$39,$B$40),$B$8),IF($L$1="SHORT",$D$24,"")) | R3: =IF(Q3="","",$AE$40) | S3: =IF($L$1="LONG",IF(OR($AE$58,$B$3>=$G$19),$AE$27,$G$20-0.0002),IF($L$1="SHORT",IF($AE$58,MAX($B$39,$B$7)+0.0002,$G$19+0.0002),"")) | T3: =IF(OR(Q3="",R3=""),"",ABS((R3-Q3)*10000)) | U3: =IF(OR(Q3="",S3=""),"",MAX(ABS((Q3-S3)*10000),$AE$19)) | V3: =$L$8 -> 0.35 | W3: =IF(OR(V3=0,$AE$11=0,Q3=""),"",$L$2*$AE$8*V3/$AE$11) | X3: =IF(OR(W3="",W3=0,T3=""),"",W3*T3/MAX(U3,$AE$19)) | Y3: =IF(OR(Q3="",U3="",W3=""),"",W3/(MAX(U3,$AE$19)*$AE$3)) | Z3: =IF(OR(T3="",U3=""),"",T3/MAX(U3,$AE$19)) | AA3: =IF(U3="","",MAX(U3,$AE$7)) | AD3: PipSize | AE3: 0.0001 | AG3: =IF(AC23<>"CoreLong","",IF($AC$55=1,"Shallow long zone (Tier 1): "&TEXT(AC51,"0.00000")&" → "&TEXT(AD51,"0.00000")&" (15m fib 0.382–0.618, less room).",IF($AC$55=2,"Main long zone (Tier 2): "&TEXT(AC52,"0.00000")&" → "&TEXT(AD52,"0.00000")&" (4H FVG + HTF 0.382 + EMA50D).",IF($AC$55=3,"Deep long zone (Tier 3): "&TEXT(AC53,"0.00000")&" → "&TEXT(AD53,"0.00000")&" (EMA100D + PWL + HTF fib).","")))) | AI3: CT_TP1 | AJ3: =$AC$32
F4: 4H | G4: =IF($B$11="","",IF($B$3>$B$11+0.0002,"Bull",IF($B$3<$B$11-0.0002,"Bear","Range"))) -> Bear | H4: =Planner_HUD!C25 -> Down | I4: =Planner_HUD!D25 -> Down | K4: SL Price (Auto) | L4: =IF($L$5<>"",$L$5,IF($L$1="LONG",IF($L$22="","",$L$22-0.0003),IF($L$1="SHORT",IF($L$23="","",$L$23+0.0003),""))) | P4: Entry 0.618 | Q4: =IF($L$1="LONG",IF($AE$58,MIN($B$40,$B$7),$B$10),IF($L$1="SHORT",$D$25,"")) | R4: =IF(Q4="","",$AE$40) | S4: =IF($L$1="LONG",IF(OR($AE$58,$B$3>=$G$19),$AE$27,$G$20-0.0002),IF($L$1="SHORT",IF($AE$58,MAX($B$39,$B$7)+0.0002,$G$19+0.0002),"")) | T4: =IF(OR(Q4="",R4=""),"",ABS((R4-Q4)*10000)) | U4: =IF(OR(Q4="",S4=""),"",MAX(ABS((Q4-S4)*10000),$AE$19)) | V4: =$L$9 -> 0.45 | W4: =IF(OR(V4=0,$AE$11=0,Q4=""),"",$L$2*$AE$8*V4/$AE$11) | X4: =IF(OR(W4="",W4=0,T4=""),"",W4*T4/MAX(U4,$AE$19)) | Y4: =IF(OR(Q4="",U4="",W4=""),"",W4/(MAX(U4,$AE$19)*$AE$3)) | Z4: =IF(OR(T4="",U4=""),"",T4/MAX(U4,$AE$19)) | AA4: =IF(U4="","",MAX(U4,$AE$7)) | AB4: PipTol_Value | AC4: =ROUND($B$18*10000*0.8,0) -> 4 | AD4: MinStopPips | AE4: 8 | AF4: Long Zone (A+) | AG4: ="Deep A+ long pocket candidate (Tier 3): "&TEXT($AC$53,"0.00000")&" → "&TEXT($AD$53,"0.00000")&". Ladder (upper/mid/deep): "&TEXT($Q$15,"0.00000")&"/"&TEXT($Q$16,"0.00000")&"/"&TEXT($Q$17,"0.00000")&", SL "&TEXT($S$15,"0.00000")&", TP1 "&TEXT($R$15,"0.00000")&". Use this only if price flushes into Tier 3 with HTF trend intact and R/room are satisfied." -> Deep A+ long pocket candidate (Tier 3): 1.16347 → 1.16757. Ladder (upper/mid/deep): //, SL , TP1 . Use this only if price flushes into Tier 3 with HTF trend intact and R/room are satisfied. | AI4: CT_TP2 | AJ4: =IF($L$1="SHORT",$L$3,"")
A5: EMA9 15m | B5: =Planner_HUD!B6 -> 1.16347 | F5: 1H | G5: =IF($B$10="","",IF($B$3>$B$10+0.0002,"Bull",IF($B$3<$B$10-0.0002,"Bear","Range"))) -> Bear | H5: =Planner_HUD!C26 -> Down | I5: =Planner_HUD!D26 -> Down | K5: Manual SL override? | AB5: PipTol_Fib | AC5: =ROUND($B$18*10000*0.5,0) -> 2 | AD5: ATR_StopMult | AE5: 1.5 | AF5: Trend Long Plan | AG5: =IF(AND($AC$23="CoreLong",NOT($AC$25)),"Trend long plan (current tier "&$AC$56&"): ladder at "&TEXT($Q$2,"0.00000")&"/"&TEXT($Q$3,"0.00000")&"/"&TEXT($Q$4,"0.00000")&", SL "&TEXT($S$2,"0.00000")&", TP1 "&TEXT($R$2,"0.00000")&". Confirm 15m/1H CHOCH up in this tier, then manage toward TP1 (and potentially PDH/PWH) using the ladder.","") | AI5: CT_Risk$ | AJ5: =$L$2*0.5 -> 251.1383 | AK5: =IF(AJ9=0,"",(AJ1-AJ3)*AJ9) -> #VALUE!
A6: EMA21 15m | B6: =Planner_HUD!B7 -> 1.16351 | F6: 15M | G6: =IF($B$5="","",IF(AND($B$5>$B$6,$B$6>$B$7,$B$7>$B$8),"Bull",IF(AND($B$5<$B$6,$B$6<$B$7,$B$7<$B$8),"Bear","Range"))) -> Bear | H6: =Planner_HUD!C27 -> Down | I6: =Planner_HUD!D27 -> Down | P6: Avg Pips to SL | Q6: =IF(SUM(Y2:Y4)=0,0,SUMPRODUCT(AA2:AA4,Y2:Y4)/SUM(Y2:Y4)) -> 0 | AB6: PipTol_Mid | AC6: =ROUND($B$18*10000*1,0) -> 5 | AD6: ATR15m_pips | AE6: =ROUND($B$18*10000,1) -> 4.7 | AI6: CT_PipsSL | AJ6: =IF(OR(AJ1="",AJ2=""),"",ABS((AJ1-AJ2)*10000)) -> 5.375
A7: EMA50 15m | B7: =Planner_HUD!B8 -> 1.16383 | K7: Weight 0.382 | L7: =Planner_HUD!K16 -> 0.2 | P7: Total Units | Q7: =SUM(Y2:Y4) -> 0 | AB7: Long_EMAScore | AC7: =0.25*COUNTIF($B$10:$B$16,"<"&$B$3) -> 1 | AD7: StopFloorPips | AE7: =MAX(AE4,ROUNDUP(AE6*AE5,0)) -> 8 | AF7: CT Zone | AG7: =IF(AND($AC$23="CTshort",NOT($AC$25)),"CT short zone: "&TEXT($AC$47,"0.00000")&" → "&TEXT($AC$48,"0.00000")&" (premium liquidity cluster: PMH/PDH/EQH/PWH).","") | AI7: CT_PipsTP | AJ7: =IF(OR(AJ3="",AJ1=""),"",ABS((AJ3-AJ1)*10000))
A8: SMA200 15m | B8: =Planner_HUD!B9 -> 1.1658 | F8: HTF_Long_OK | G8: =AND(G3="Bull",G4="Bull") -> FALSE | K8: Weight 0.500 | L8: =Planner_HUD!K17 -> 0.35 | P8: Avg Entry | Q8: =IF(Q7=0,"",SUMPRODUCT(Q2:Q4,Y2:Y4)/Q7) | AB8: Short_EMAScore | AC8: =0.25*COUNTIF($B$10:$B$16,">"&$B$3) -> 0.75 | AD8: PrimaryRiskMult | AE8: 1 | AF8: CT Short Plan | AG8: =IF(AND($AC$23="CTshort",NOT($AC$25)),"CT short plan: ladder shorts at "&TEXT($AC$48,"0.00000")&"/"&TEXT($AC$49,"0.00000")&"/"&TEXT($AC$47,"0.00000")&", SL "&TEXT($AC$48+0.0008,"0.00000")&", TP1 "&TEXT($AC$35,"0.00000")&IF($AC$32<>""," (golden mid)."," (Tier1 top; no golden overlap).")&" Size small; countertrend — only take on clear exhaustion near PDH/EQH.","") | AI8: CT_Rmult | AJ8: =IF(OR(AJ6="",AJ7="",AJ6=0),"",AJ7/AJ6)
F9: HTF_Short_OK | G9: =AND(G3="Bear",G4="Bear") -> FALSE | K9: Weight 0.618 | L9: =Planner_HUD!K18 -> 0.45 | P9: Pips to TP1 | Q9: =IF(OR(Q8="",$L$3=""),"",ABS(($L$3-Q8)*10000)) | AB9: Long_RSIScore | AC9: =IF($B$20<45,0.5,0)+IF($B$21<45,0.25,0)+IF($B$17<45,0.25,0) -> 0.5 | AD9: APlusRiskMult | AE9: 1 | AI9: CT_Units | AJ9: =IF(OR(AJ5="",AJ6="",AJ6=0),"",AJ5/(AJ6*0.0001)) -> 467234.05
A10: EMA50 1H | B10: =Planner_HUD!B10 -> 1.16567 | F10: LTF_Long_OK | G10: =AND(OR(G5="Bull",G5="Range"),NOT(G6="Bear")) -> FALSE | P10: Reward at TP1 $ | Q10: =IF(OR(Q7=0,Q8="",$L$3=""),"",ABS(($L$3-Q8)*Q7)) | AB10: Short_RSIScore | AC10: =IF($B$20>55,0.5,0)+IF($B$21>55,0.25,0)+IF($B$17>55,0.25,0) -> 0 | AD10: CTRiskMult | AE10: 0.6 | AF10: Avoid | AG10: =IF($AC$25,"Avoid new trades – R multiple, room, or macro gate not satisfied. Wait for conditions to improve and reassess.","") -> Avoid new trades – R multiple, room, or macro gate not satisfied. Wait for conditions to improve and reassess. | AI10: CT_NoTradeFlag | AJ10: =NOT($G$11) -> FALSE
A11: EMA50 4H | B11: =Planner_HUD!B11 -> 1.16963 | F11: LTF_Short_OK | G11: =AND(OR(G5="Bear",G5="Range"),NOT(G6="Bull")) -> TRUE | K11: Ticket Size | L11: =Planner_HUD!K19 -> 0 | P11: R multiple at TP1 | Q11: =IF(SUM($W$2:$W$4)=0,"",SUM($X$2:$X$4)/SUM($W$2:$W$4)) | AB11: Long_StructScore | AC11: =0.25*COUNTIF($G$3:$G$6,"Bull") -> 0 | AD11: PrimaryWgtSum | AE11: =SUM($V$2:$V$4) -> 1
A12: EMA50 1D | B12: =Planner_HUD!B12 -> 1.16757 | K12: Min R (R multiple) | L12: =Planner_HUD!K20 -> 3 | P12: Avg Eff Pips to SL | Q12: =IF(SUM(Y2:Y4)=0,"",(Y2*MAX(U2,$AE$19)+Y3*MAX(U3,$AE$19)+Y4*MAX(U4,$AE$19))/SUM(Y2:Y4)) | AB12: Short_StructScore | AC12: =0.25*COUNTIF($G$3:$G$6,"Bear") -> 0.75 | AD12: APlusWgtSum | AE12: =SUM($V$15:$V$17) -> 1.5
A13: EMA100 1D | B13: =Planner_HUD!B13 -> 1.16347 | AB13: Long_FVGScore | AC13: =MIN(1,IF(ABS(($B$3-$B$36)*10000)<=AC4,1,0)+IF(ABS(($B$3-$B$38)*10000)<=AC4,1,0)+IF(ABS(($B$3-$B$40)*10000)<=AC4,1,0)) -> 0 | AD13: CTWgtSum | AE13: =SUM($V$28:$V$30) -> 1
A14: EMA200 1D | B14: =Planner_HUD!B14 -> 1.14963 | F14: Liquidity levels | K14: Active Zone | L14: =IF(AND($B$3>=M17-$K$20,$B$3<=N17+$K$20),1,IF(AND($B$3>=M18-$K$20,$B$3<=N18+$K$20),2,IF(AND($B$3>=M19-$K$20,$B$3<=N19+$K$20),3,""))) -> 3 | P14: A+ LADDER | Q14: Entry | R14: TP | S14: SL | T14: Pips to TP1 | U14: Eff Pips to SL | V14: Weight | W14: Risk $ | X14: Reward $ | Y14: Units | Z14: R per rung | AA14: =IF(U15="","",MAX(U15,$AE$7)) | AB14: Short_FVGScore | AC14: =MIN(1,IF(ABS(($B$3-$B$35)*10000)<=AC4,1,0)+IF(ABS(($B$3-$B$37)*10000)<=AC4,1,0)+IF(ABS(($B$3-$B$39)*10000)<=AC4,1,0)) -> 0 | AD14: Primary_MinStopPips | AE14: 12
A15: EMA50 1W | B15: =Planner_HUD!B15 -> 1.1439 | F15: PMH | G15: =Planner_HUD!E5 -> 1.1808 | K15: =IF(AND($B$3>=M17-$K$20,$B$3<=N17+$K$20),1,IF(AND($B$3>=M18-$K$20,$B$3<=N18+$K$20),2,IF(AND($B$3>=M19-$K$20,$B$3<=N19+$K$20),3,0))) -> 3 | P15: upper rung | Q15: =IF($L$1<>"LONG","",$B$35) | R15: =IF(Q15="","",$AE$41) | S15: =IF(Q15="","",$AE$30) | T15: =IF(OR(Q15="",R15=""),"",ABS((R15-Q15)*10000)) | U15: =IF(OR(Q15="",S15=""),"",MAX(ABS((Q15-S15)*10000),$AE$20)) | V15: 0.4 | W15: =IF(OR(V15=0,$AE$12=0,Q15=""),"",$L$2*$AE$9*V15/$AE$12) | X15: =IF(OR(W15="",W15=0,T15=""),"",W15*T15/MAX(U15,$AE$20)) | Y15: =IF(OR(Q15="",U15="",W15=""),"",W15/(MAX(U15,$AE$20)*$AE$3)) | Z15: =IF(OR(T15="",U15=""),"",T15/MAX(U15,$AE$20)) | AA15: =IF(U16="","",MAX(U16,$AE$7)) | AB15: LongScore | AC15: =(1-$G$37*$G$36)*(AC7+AC9+AC11+AC13+AC42) -> 0.7 | AD15: APlus_MinStopPips | AE15: 8
A16: EMA20 1M | B16: =Planner_HUD!B16 -> 1.1241 | F16: PML | G16: =Planner_HUD!E6 -> 1.15889 | K16: Zone | L16: Role | M16: Low | N16: High | P16: middle rung | Q16: =IF($L$1<>"LONG","",$B$36) | R16: =IF(Q16="","",$AE$41) | S16: =IF(Q16="","",$AE$30) | T16: =IF(OR(Q16="",R16=""),"",ABS((R16-Q16)*10000)) | U16: =IF(OR(Q16="",S16=""),"",MAX(ABS((Q16-S16)*10000),$AE$20)) | V16: 0.5 | W16: =IF(OR(V16=0,$AE$12=0,Q16=""),"",$L$2*$AE$9*V16/$AE$12) | X16: =IF(OR(W16="",W16=0,T16=""),"",W16*T16/MAX(U16,$AE$20)) | Y16: =IF(OR(Q16="",U16="",W16=""),"",W16/(MAX(U16,$AE$20)*$AE$3)) | Z16: =IF(OR(T16="",U16=""),"",T16/MAX(U16,$AE$20)) | AA16: =IF(U17="","",MAX(U17,$AE$7)) | AB16: ShortScore | AC16: =(1-$G$37*$G$36)*(AC8+AC10+AC12+AC14+AC42) -> 0.7 | AD16: CT_MinStopPips | AE16: 8
A17: RSI 4HR | B17: =Planner_HUD!B19 -> 31.67 | F17: PWH | G17: =Planner_HUD!E7 -> 1.1789 | K17: 1 | L17: Shallow | M17: =MIN($D$24,$D$23) -> 1.170965 | N17: =MAX($D$24,$D$23) -> 1.1731964 | P17: deep rung | Q17: =IF($L$1<>"LONG","",$B$38+$AE$29) | R17: =IF(Q17="","",$AE$41) | S17: =IF(Q17="","",$AE$30) | T17: =IF(OR(Q16="",R16=""),"",ABS((R16-Q16)*10000)) | U17: =IF(OR(Q17="",S17=""),"",MAX(ABS((Q17-S17)*10000),$AE$20)) | V17: 0.6 | W17: =IF(OR(V17=0,$AE$12=0,Q17=""),"",$L$2*$AE$9*V17/$AE$12) | X17: =IF(OR(W17="",W17=0,T17=""),"",W17*T17/MAX(U17,$AE$20)) | Y17: =IF(OR(Q17="",U17="",W17=""),"",W17/(MAX(U17,$AE$20)*$AE$3)) | Z17: =IF(OR(T17="",U17=""),"",T17/MAX(U17,$AE$20)) | AB17: MaxScore | AC17: =0.25*COUNTA($B$10:$B$16)+3.5 -> 5.25 | AD17: WinProb | AE17: Expected_R | AF17: Expected_$
A18: ATR(14) 15m | B18: =Planner_HUD!B20 -> 0.00047 | F18: PWL | G18: =Planner_HUD!E8 -> 1.17132 | K18: 2 | L18: Main | M18: =MIN(D25,D24) -> 1.1687336 | N18: =MAX(D25,D24) -> 1.170965 | AB18: LongScore_pct | AC18: =IF(AC17=0,"",AC15/AC17) -> 0.13333333 | AD18: =IF($L$1<>"LONG","",MIN(0.8,0.4+0.4*IFERROR(AC18,0)+0.1*IFERROR(AC42,0))) | AE18: =IF($L$1="","",IF($L$1="LONG",IF(OR(AD18="",AC20=""),"",AD18*AC20-(1-AD18)*1),IF(OR(AD19="",AC20=""),"",AD19*AC20-(1-AD19)*1))) | AF18: =IF(AE18="","",AE18*$L$2)
A19: ADR(14) | B19: =Planner_HUD!B21 -> 0.00088 | F19: PDH | G19: =Planner_HUD!E9 -> 1.16829 | K19: 3 | L19: HTF | M19: =MIN(D31,D29) -> 1.161194 | N19: =MAX(D31,D29) -> 1.168536 | P19: Avg Pips to SL | Q19: =IF(SUM(Y15:Y17)=0,0,SUMPRODUCT(AA14:AA16,Y15:Y17)/SUM(Y15:Y17)) -> 0 | AB19: ShortScore_pct | AC19: =IF(AC17=0,"",AC16/AC17) -> 0.13333333 | AD19: Primary_StopFloorPips | AE19: =MAX(AE14,ROUNDUP(AE6*AE5,0)) -> 12
A20: RSI 15M | B20: =Planner_HUD!B17 -> 51.21 | F20: PDL | G20: =Planner_HUD!E10 -> 1.16427 | J20: Zone tolerance | K20: =Planner_HUD!K15 -> 0.0002 | P20: Total Units | Q20: =SUM(Y15:Y17) -> 0 | AC20: =IF(OR($AC$55=0,$Q$7<=0,$Q$12=""),"",$Q$12) | AD20: APlus_StopFloorPips | AE20: =MAX(AE15,ROUNDUP(AE6*AE5,0)) -> 8
A21: RSI 1H | B21: =Planner_HUD!B18 -> 38.35 | F21: EQH_above | G21: =Planner_HUD!E11 -> 1.17025 | K21: zone-specific fibs for SL/entries | P21: Avg Entry | Q21: =IF(Q20=0,"",SUMPRODUCT(Q15:Q17,Y15:Y17)/Q20) | AB21: Trend Mode | AC21: =IF($L$1="","No bias",IF($L$1="LONG",IF($G$8,"Trend-aligned","Counter-trend"),IF($L$1="SHORT",IF($G$9,"Trend-aligned","Counter-trend"),"No bias"))) -> No bias | AD21: CT_StopFloorPips | AE21: =MAX(AE16,ROUNDUP(AE6*AE5,0)) -> 8
A22: Legs (Intraday / Session / HTF) | D22: Fib outputs | F22: EQL_below | G22: =Planner_HUD!E12 -> 1.15919 | K22: Zone_618 | L22: =IF($L$1="LONG",$AC$30,"") | P22: Pips to TP1 | Q22: =IF(OR(Q21="",$L$3=""),"",ABS(($L$3-Q21)*10000)) | AB22: Setup Type | AC22: =IF(AND(G3="Bull",G4="Bull",G5="Bear",G6="Bear"),"Trend Pullback","Mixed") -> Mixed | AD22: CT_ActiveWgtSum | AE22: =SUMPRODUCT(($Q$28:$Q$30<>"")*($V$28:$V$30)) -> 1
A23: LTF Leg Low (15m | B23: =Planner_HUD!E13 -> 1.16151 | C23: L1 0.382 | D23: =IF($L$1="SHORT",$B$23+($B$24-$B$23)*0.382,$B$24-($B$24-$B$23)*0.382) -> 1.1731964 | F23: Distances to nearest liquidity | K23: Zone_500 | L23: =IF($L$1="SHORT",$AC$31,"") | P23: Reward at TP1 $ | Q23: =IF(OR(Q20=0,Q21="",$L$3=""),"",ABS(($L$3-Q21)*Q20)) | AB23: TradeMode | AC23: =IF(AF52,"CoreLong",IF(AF53,"CTshort","Avoid")) -> Avoid | AD23: CT_ATRMult | AE23: 1.5
A24: LTF Leg High (15m) | B24: =Planner_HUD!E14 -> 1.18042 | C24: L1 0.500 | D24: =IF($L$1="SHORT",$B$23+($B$24-$B$23)*0.5,$B$24-($B$24-$B$23)*0.5) -> 1.170965 | F24: Dist_Above (pips) | G24: =MIN(IF(G15>$B$3,ABS((G15-$B$3)*10000),1000000000),IF(G17>$B$3,ABS((G17-$B$3)*10000),1000000000),IF(G19>$B$3,ABS((G19-$B$3)*10000),1000000000),IF(G21>$B$3,ABS((G21-$B$3)*10000),1000000000)) -> 46.5 | P24: R multiple at TP1 | Q24: =IF(SUM($W$15:$W$17)=0,"",SUM($X$15:$X$17)/SUM($W$15:$W$17)) | AB24: Grade | AC24: =IF($L$1="","N/A",IF($AC$25,"B",IF(AC34<0.4,"B",IF(AC18>=0.7,"A+",IF(AC18>=0.4,"B","C"))))) -> N/A | AD24: CT_RangePips | AE24: =MAX(6,ROUND($B$18*10000*$AE$23,0)) -> 7
C25: L1 0.618 | D25: =IF($L$1="SHORT",$B$23+($B$24-$B$23)*0.618,$B$24-($B$24-$B$23)*0.618) -> 1.1687336 | F25: Dist_Below (pips) | G25: =MIN(IF(G16<$B$3,ABS((G16-$B$3)*10000),1000000000),IF(G18<$B$3,ABS((G18-$B$3)*10000),1000000000),IF(G20<$B$3,ABS((G20-$B$3)*10000),1000000000),IF(G22<$B$3,ABS((G22-$B$3)*10000),1000000000)) -> 44.5 | P25: Avg Eff Pips to SL | Q25: =IF(SUM(Y15:Y17)=0,"",(Y15*MAX(U15,$AE$20)+Y16*MAX(U16,$AE$20)+Y17*MAX(U17,$AE$20))/SUM(Y15:Y17)) | AB25: NoTradeFlag | AC25: =OR($L$1="",AND(AC23="CoreLong",OR(AF48=FALSE,$Q$12="",$Q$12<$L$12)),AND(AC23="CTshort",OR(AF49=FALSE,$B$21<=65)),FALSE) -> TRUE | AE25: =IF($L$1="LONG",IF(OR($AE$58,$B$3>$G$19),MAX($B$27,$B$24),$G$19),IF($L$1="SHORT",IF(OR($AE$58,$B$3<$G$20),MIN($B$26,$B$23),$G$20),""))
A26: Session Low | B26: =Planner_HUD!E15 -> 1.16182 | C26: L2 0.382 | D26: =IF($L$1="SHORT",$B$26+($B$27-$B$26)*0.382,$B$27-($B$27-$B$26)*0.382) -> 1.1657628 | AA26: =IF(U28="","",MAX(U28,$AE$7)) -> 15 | AB26: MasterSignal | AC26: =IF($L$1="","NO SIDE – neither core long nor CT short setup is active.",IF(AC23="CoreLong",IF(AC25,"AVOID CORE LONG – not in discount or 3R not available.","CORE LONG SETUP – buy dip in active tier. Ladder entries "&TEXT($Q$2,"0.00000")&"/"&TEXT($Q$3,"0.00000")&"/"&TEXT($Q$4,"0.00000")&", SL "&TEXT($S$2,"0.00000")&", TP1 "&TEXT($L$3,"0.00000")&"."),IF(AC23="CTshort",IF(AC25,"AVOID CT SHORT – conditions for scalp fade not met.","OPTIONAL CT SHORT – scalp fade only. Short zone near PDH/CT highs; see CT ladder for entries, SL and TPs."),"AVOID – nothing to do here. Stand aside and wait for either discount buy or CT fade zone."))) -> NO SIDE – neither core long nor CT short setup is active. | AE26: =IF($L$1="LONG",IF(MAX($B$27,$B$24)>0,MAX($B$27,$B$24),$G$19),IF($L$1="SHORT",IF(MIN($B$26,$B$23)>0,MIN($B$26,$B$23),$G$20),""))
A27: Session High | B27: =Planner_HUD!E16 -> 1.1682 | C27: L2 0.500 | D27: =IF($L$1="SHORT",$B$26+($B$27-$B$26)*0.5,$B$27-($B$27-$B$26)*0.5) -> 1.16501 | F27: Long_RoomOK | G27: =IF($Q$6="",FALSE,$G$24>=3*$Q$6) -> TRUE | P27: CT LADDER | Q27: Entry | R27: TP | S27: SL | T27: Pips to TP1 | U27: Eff Pips to SL | V27: Weight | W27: Risk $ | X27: Reward $ | Y27: Units | Z27: R per rung | AA27: =IF(U29="","",MAX(U29,$AE$7)) -> 11.5 | AB27: Setup Summary | AC27: =IF(AC23="CoreLong",IF(AC25,"NO CORE LONG – wait for proper discount and 3R.","CORE LONG OK – follow MasterSignal & Trade Plan."),IF(AC23="CTshort",IF(AC25,"NO CT SHORT – CT scalp conditions incomplete.","CT SHORT OK – scalp only, log as counter-trend."),"NO TRADE – neither core nor CT setup active.")) -> NO TRADE – neither core nor CT setup active. | AD27: Primary_SL_Cont | AE27: =$B$40-$AE$28 -> 1.16754
C28: L2 0.618 | D28: =IF($L$1="SHORT",$B$26+($B$27-$B$26)*0.618,$B$27-($B$27-$B$26)*0.618) -> 1.1642572 | F28: Short_RoomOK | G28: =IF(Q6="",FALSE,G25>=3*Q6) -> TRUE | P28: deep rung | Q28: =IF(AC48="","",AC48) -> 1.16454 | R28: =IF(Q28="","",IFERROR(_xlfn.AGGREGATE(14,6,CHOOSE({1,2,3,4},Planner_HUD!$E$12,Planner_HUD!$E$10,Planner_HUD!$E$15,Planner_HUD!$H$10)/(CHOOSE({1,2,3,4},Planner_HUD!$E$12,Planner_HUD!$E$10,Planner_HUD!$E$15,Planner_HUD!$H$10)<Q28),1)-$AE$3,Q28-($AE$24*$AE$3))) -> 1.15909 | S28: =IF(Q30="","",Q30+0.0008) -> 1.16604 | T28: =IF(OR(Q28="",R28=""),"",ABS((R28-Q28)*10000)) -> 54.5 | U28: =IF(OR(Q28="",S28=""),"",MAX(ABS((Q28-S28)*10000),$AE$21)) -> 15 | V28: 0.45 | W28: =IF(OR(V28=0,$AE$22=0,Q28=""),"",$L$2*$AE$10*V28/$AE$22) -> 135.61468 | X28: =IF(OR(W28="",W28=0,T28=""),"",W28*T28/MAX(U28,$AE$21)) -> 492.73334 | Y28: =IF(OR(Q28="",U28="",W28=""),"",W28/(MAX(U28,$AE$21)*$AE$3)) -> 90409.788 | Z28: =IF(OR(T28="",U28=""),"",T28/MAX(U28,$AE$21)) -> 3.6333333 | AA28: =IF(U30="","",MAX(U30,$AE$7)) -> 8 | AB28: Trade Plan | AC28: =IF(AC25,"Stand aside or observation-only. Location: "&AF54&".",IF(AC23="CoreLong","CORE LONG EXECUTION – Mode: "&AC21&", Grade: "&AC24&". Bias: LONG (trend/macro). Buy active tier with ladder "&TEXT($Q$2,"0.00000")&"/"&TEXT($Q$3,"0.00000")&"/"&TEXT($Q$4,"0.00000")&". SL "&TEXT($S$2,"0.00000")&". TP1 "&TEXT($L$3,"0.00000")&".","CT SHORT EXECUTION – Counter-trend scalp. Short near PDH/CT zone. Use CT ladder for entries with reduced risk (0.25–0.5R). Stop above 1.1725–1.1730; TP1 back into 1.1670–1.1660, TP2 into 1.1645–1.1635.")) -> Stand aside or observation-only. Location: DISCOUNT. | AD28: Primary_SL_Buffer | AE28: =MAX(0.00025,$B$18*0.5) -> 0.00025
A29: HTF Swing Low (4H) | B29: =Planner_HUD!E17 -> 1.14931 | C29: L3 0.382 | D29: =IF($L$1="SHORT",$B$29+($B$30-$B$29)*0.382,$B$30-($B$30-$B$29)*0.382) -> 1.168536 | F29: Strike 1 | G29: =Planner_HUD!K5 -> 1.13 | H29: Size 1 (bn) | I29: =Planner_HUD!K6 -> 1.46 | J29: =IF(G29="","",ABS(G29-$B$3)) -> 0.03364 | P29: middle rung | Q29: =IF(AC49="","",AC49) -> 1.16489 | R29: =IF(Q29="","",IFERROR(_xlfn.AGGREGATE(14,6,CHOOSE({1,2,3,4},Planner_HUD!$E$12,Planner_HUD!$E$10,Planner_HUD!$E$15,Planner_HUD!$H$10)/(CHOOSE({1,2,3,4},Planner_HUD!$E$12,Planner_HUD!$E$10,Planner_HUD!$E$15,Planner_HUD!$H$10)<Q29),1)-$AE$3,Q29-($AE$24*$AE$3))) -> 1.15909 | S29: =S28 -> 1.16604 | T29: =IF(OR(Q29="",R29=""),"",ABS((R29-Q29)*10000)) -> 58 | U29: =IF(OR(Q29="",S29=""),"",MAX(ABS((Q29-S29)*10000),$AE$21)) -> 11.5 | V29: 0.35 | W29: =IF(OR(V29=0,$AE$22=0,Q29=""),"",$L$2*$AE$10*V29/$AE$22) -> 105.47809 | X29: =IF(OR(W29="",W29=0,T29=""),"",W29*T29/MAX(U29,$AE$21)) -> 531.97643 | Y29: =IF(OR(Q29="",U29="",W29=""),"",W29/(MAX(U29,$AE$21)*$AE$3)) -> 91720.075 | Z29: =IF(OR(T29="",U29=""),"",T29/MAX(U29,$AE$21)) -> 5.0434783 | AB29: Go/No-Go | AC29: =IF($L$1="","NO SETUP",IF(AC25,"NO TRADE – "&AF54,IF(AC23="CoreLong","GO (CORE LONG) – trend/macro aligned.","GO (CT SCALP) – small risk only."))) -> NO SETUP | AD29: Aplus_SL_Buffer | AE29: =MAX(0.00025,$B$18*0.5) -> 0.00025
A30: HTF Swing High (4H) | B30: =Planner_HUD!E18 -> 1.18042 | C30: L3 0.500 | D30: =IF($L$1="SHORT",$B$29+($B$30-$B$29)*0.5,$B$30-($B$30-$B$29)*0.5) -> 1.164865 | F30: Strike 2 | G30: =Planner_HUD!K7 -> 1.18 | H30: Size 2 (bn) | I30: =Planner_HUD!K8 -> 1.136 | J30: =IF(G30="","",ABS(G30-$B$3)) -> 0.01636 | P30: shallow rung | Q30: =IF(AC47="","",AC47) -> 1.16524 | R30: =IF(Q30="","",IFERROR(_xlfn.AGGREGATE(14,6,CHOOSE({1,2,3,4},Planner_HUD!$E$12,Planner_HUD!$E$10,Planner_HUD!$E$15,Planner_HUD!$H$10)/(CHOOSE({1,2,3,4},Planner_HUD!$E$12,Planner_HUD!$E$10,Planner_HUD!$E$15,Planner_HUD!$H$10)<Q30),1)-$AE$3,Q30-($AE$24*$AE$3))) -> 1.15909 | S30: =S28 -> 1.16604 | T30: =IF(OR(Q30="",R30=""),"",ABS((R30-Q30)*10000)) -> 61.5 | U30: =IF(OR(Q30="",S30=""),"",MAX(ABS((Q30-S30)*10000),$AE$21)) -> 8 | V30: 0.2 | W30: =IF(OR(V30=0,$AE$22=0,Q30=""),"",$L$2*$AE$10*V30/$AE$22) -> 60.273192 | X30: =IF(OR(W30="",W30=0,T30=""),"",W30*T30/MAX(U30,$AE$21)) -> 463.35016 | Y30: =IF(OR(Q30="",U30="",W30=""),"",W30/(MAX(U30,$AE$21)*$AE$3)) -> 75341.49 | Z30: =IF(OR(T30="",U30=""),"",T30/MAX(U30,$AE$21)) -> 7.6875 | AB30: Golden_Low (Overlap L1/L3) | AC30: =IF(OR($D$23="",$D$25="",$D$29="",$D$31=""),"",MAX(MIN($D$23,$D$25),MIN($D$29,$D$31))) -> 1.1687336 | AD30: Aplus_SL | AE30: =$B$38-$AE$29 -> 1.16602
C31: L3 0.618 | D31: =IF($L$1="SHORT",$B$29+($B$30-$B$29)*0.618,$B$30-($B$30-$B$29)*0.618) -> 1.161194 | F31: Strike 3 | G31: =Planner_HUD!K9 -> 1.165 | H31: Size 3 (bn) | I31: =Planner_HUD!K10 -> 1.12 | J31: =IF(G31="","",ABS(G31-$B$3)) -> 0.00136 | AB31: Golden_High (Overlap L1/L3) | AC31: =IF(OR($D$23="",$D$25="",$D$29="",$D$31=""),"",MIN(MAX($D$23,$D$25),MAX($D$29,$D$31))) -> 1.168536 | AD31: (Pips_to_Entry_500) | AE31: =IF(Q3="","",($B$3-Q3)*10000)
F32: Strike 4 | H32: Size 4 (bn) | J32: =IF(G32="","",ABS(G32-$B$3)) | P32: Avg Pips to SL | Q32: =IF(SUM(Y28:Y30)=0,0,SUMPRODUCT(AA26:AA28,Y28:Y30)/SUM(Y28:Y30)) -> 11.704835 | AB32: Golden_Mid | AC32: =IF(OR(AC30="",AC31="",AC30>AC31),"",(AC30+AC31)/2) | AD32: (Pips_to_Entry_618) | AE32: =IF(Q4="","",($B$3-Q4)*10000) | AF32: =IF($L$1<>"LONG","","Dist to entries (pips): 0.382="&TEXT(AE30,"0.0")&", 0.5="&TEXT(AE31,"0.0")&", 0.618="&TEXT(AE32,"0.0"))
F33: Magnet Strike | G33: =IF(COUNTA(G29:G32)=0,"",INDEX(G29:G32,MATCH(MIN(J29:J32),J29:J32,0))) -> 1.165 | P33: Total Units | Q33: =SUM(Y28:Y30) -> 257471.35 | AB33: In_GoldenPocket_Flag | AC33: =IF(OR(AC30="",AC31="",AC30>AC31),FALSE,AND($B$3>=AC30,$B$3<=AC31)) -> FALSE | AD33: ValueRiskMult | AE33: 1
A34: FVGs (4H / Daily / 1H) | F34: Magnet Range (pips) | G34: =Planner_HUD!K13 -> 20 | P34: Avg Entry | Q34: =IF(Q33=0,"",SUMPRODUCT(Q28:Q30,Y28:Y30)/Q33) -> 1.1648695 | AB34: GoldenProx_Score | AC34: =IF(OR(AC30="",AC31="",AC30>AC31),0,IF(OR($B$3<AC30,$B$3>AC31),0,MAX(0,1-(ABS($B$3-AC32)/((AC31-AC30)/2))))) -> 0 | AD34: Value_MinStopPips | AE34: 10
A35: 4H FVG high | B35: =Planner_HUD!H5 -> 1.16139 | F35: Distance to Magnet (pips) | G35: =IF(G33="","",ABS((G33-$B$3)*10000)) -> 13.6 | P35: Pips to TP1 | Q35: =IF(OR(Q34="",$R$28=""),"",ABS(($R$28-Q34)*10000)) -> 57.795165 | AB35: CT_TP1 (magnet below entry) | AC35: =IF($L$1<>"SHORT","",IF(COUNT($Q$28:$Q$30)=0,"",IF(MAX(IF(Planner_HUD!$E$12<$AC$46,Planner_HUD!$E$12,0),IF(Planner_HUD!$E$10<$AC$46,Planner_HUD!$E$10,0),IF(Planner_HUD!$H$10<$AC$46,Planner_HUD!$H$10,0))=0,$AC$46-MAX($K$20,$AE$24*$AE$3),MAX(IF(Planner_HUD!$E$12<$AC$46,Planner_HUD!$E$12,0),IF(Planner_HUD!$E$10<$AC$46,Planner_HUD!$E$10,0),IF(Planner_HUD!$H$10<$AC$46,Planner_HUD!$H$10,0))))) | AD35: Value_StopFloorPips | AE35: =MAX($AE$34,ROUNDUP($AE$6*$AE$5,0)) -> 10
A36: 4H FVG low | B36: =Planner_HUD!H6 -> 1.1605 | F36: Within Magnet? 0/1 | G36: =IF(AND(G33<>"",G35<=G34),1,0) -> 1 | P36: Reward at TP1 $ | Q36: =IF(OR(Q33=0,Q34="",$R$28=""),"",ABS(($R$28-Q34)*Q33)) -> 1488.0599 | AD36: Value_SL_Buffer | AE36: =MAX(0.00025,$B$18*0.5,$AE$34*$AE$3) -> 0.001
A37: Daily FVG high | B37: =Planner_HUD!H7 -> 1.16734 | F37: Options Clamp % | G37: =Planner_HUD!K14 -> 0.3 | P37: R multiple at TP1 | Q37: =IF(SUM($W$28:$W$30)=0,"",SUM($X$28:$X$30)/SUM($W$28:$W$30)) -> 4.9377174 | AB37: MacroBiasScore | AC37: =Macro_Dashboard!$B$19 -> Neutral | AD37: Value_SL | AE37: =$B$40-$AE$36 -> 1.16679
A38: Daily FVG low | B38: =Planner_HUD!H8 -> 1.16627 | P38: Avg Eff Pips to SL | Q38: =IF(SUM(Y28:Y30)=0,"",(Y28*MAX(U28,$AE$21)+Y29*MAX(U29,$AE$21)+Y30*MAX(U30,$AE$21))/SUM(Y28:Y30)) -> 11.704835 | AB38: MacroBias_Direction | AC38: =IF(AC37="Buy dips",1,IF(AC37="Sell rallies",-1,0)) -> 0 | AD38: ValueWgtSum | AE38: =SUM($V$42:$V$44) -> 1
A39: 1H FVG high | B39: =Planner_HUD!H9 -> 1.1682 | AB39: MacroToneAdj | AC39: =IF(Macro_Dashboard!$B$31>0.3,-0.5,IF(Macro_Dashboard!$B$31<-0.3,0.5,0)) -> -0.5 | AE39: 8
A40: 1H FVG low | B40: =Planner_HUD!H10 -> 1.16779 | AB40: MacroPolicyAdj | AC40: =IF(Macro_Dashboard!$B$28<=-2,0.5,IF(Macro_Dashboard!$B$28>=2,-0.5,0)) -> -0.5 | AE40: =MAX($B$27,$G$19,$G$17)+$AE$39*$AE$3 -> 1.1797
P41: VALUE LADDER | Q41: Entry | R41: TP | S41: SL | T41: Pips to TP1 | U41: Eff Pips to SL | V41: Weight | W41: Risk $ | X41: Reward $ | Y41: Units | Z41: R per rung | AA41: =IF(U42="","",MAX(U42,$AE$7)) | AB41: Macro_TotalBias | AC41: =MAX(-1,MIN(1,AC38+AC39+AC40)) -> -1 | AE41: =IF($L$1<>"LONG","",MIN(IF($G$17>$B$3,$G$17,10^6),IF($G$19>$B$3,$G$19,10^6),IF($B$27>$B$3,$B$27,10^6)))
P42: Entry SMA200 | Q42: =IF($L$1<>"LONG","",IF($B$8<=$B$3,$B$8,"")) | R42: =IF(Q42="","",$AE$41) | S42: =IF(Q42="","",$AE$37) | T42: =IF(OR(Q42="",R42=""),"",ABS((R42-Q42)*10000)) | U42: =IF(OR(Q42="",S42=""),"",MAX(ABS((Q42-S42)*10000),$AE$35)) | V42: 0.35 | W42: =IF(OR(V42=0,$AE$38=0,Q42=""),"",$L$2*$AE$33*V42/$AE$38) | X42: =IF(OR(W42="",W42=0,T42=""),"",W42*T42/MAX(U42,$AE$35)) | Y42: =IF(OR(Q42="",U42="",W42=""),"",W42/(MAX(U42,$AE$35)*$AE$3)) | Z42: =IF(OR(T42="",U42=""),"",T42/MAX(U42,$AE$35)) | AA42: =IF(U43="","",MAX(U43,$AE$7)) | AB42: MacroBiasScore | AC42: =0.5*AC41 -> -0.5
P43: Entry EMA50_1H | Q43: =IF($L$1<>"LONG","",IF($B$10<=$B$3,$B$10,"")) | R43: =IF(Q43="","",$AE$41) | S43: =IF(Q43="","",$AE$37) | T43: =IF(OR(Q43="",R43=""),"",ABS((R43-Q43)*10000)) | U43: =IF(OR(Q43="",S43=""),"",MAX(ABS((Q43-S43)*10000),$AE$35)) | V43: 0.4 | W43: =IF(OR(V43=0,$AE$38=0,Q43=""),"",$L$2*$AE$33*V43/$AE$38) | X43: =IF(OR(W43="",W43=0,T43=""),"",W43*T43/MAX(U43,$AE$35)) | Y43: =IF(OR(Q43="",U43="",W43=""),"",W43/(MAX(U43,$AE$35)*$AE$3)) | Z43: =IF(OR(T43="",U43=""),"",T43/MAX(U43,$AE$35)) | AA43: =IF(U44="","",MAX(U44,$AE$7))
P44: Entry 1H_FVG_L | Q44: =IF($L$1<>"LONG","",IF($B$40<=$B$3,$B$40,"")) | R44: =IF(Q44="","",$AE$41) | S44: =IF(Q44="","",$AE$37) | T44: =IF(OR(Q44="",R44=""),"",ABS((R44-Q44)*10000)) | U44: =IF(OR(Q44="",S44=""),"",MAX(ABS((Q44-S44)*10000),$AE$35)) | V44: 0.25 | W44: =IF(OR(V44=0,$AE$38=0,Q44=""),"",$L$2*$AE$33*V44/$AE$38) | X44: =IF(OR(W44="",W44=0,T44=""),"",W44*T44/MAX(U44,$AE$35)) | Y44: =IF(OR(Q44="",U44="",W44=""),"",W44/(MAX(U44,$AE$35)*$AE$3)) | Z44: =IF(OR(T44="",U44=""),"",T44/MAX(U44,$AE$35))
AE45: In_Tier1 | AF45: =AND($B$3>=AC51,$B$3<=AD51) -> FALSE
P46: Avg Pips to SL | Q46: =IF(SUM(Y42:Y44)=0,0,SUMPRODUCT(AA41:AA43,Y42:Y44)/SUM(Y42:Y44)) -> 0 | AB46: CT_MinEntry | AC46: =MIN(IF($Q$28="",1000000000,$Q$28),IF($Q$29="",1000000000,$Q$29),IF($Q$30="",1000000000,$Q$30)) -> 1.16454 | AE46: In_Tier2 | AF46: =AND($B$3>=AC52,$B$3<=AD52) -> FALSE
P47: Total Units | Q47: =SUM(Y42:Y44) -> 0 | AB47: CT_Low | AC47: =IF(AC48="","",AC48+($AE$24*$AE$3)) -> 1.16524 | AE47: In_Tier3 | AF47: =IF(Planner_HUD!$E$7>$B$3,Planner_HUD!$E$7,"") -> 1.1789
P48: Avg Entry | Q48: =IF(Q47=0,"",SUMPRODUCT(Q42:Q44,Y42:Y44)/Q47) | AB48: CT_High | AC48: =IF(AF51="","",AF51+$K$20) -> 1.16454 | AE48: In_Discount | AF48: =IF(Planner_HUD!$E$9>$B$3,Planner_HUD!$E$9,"") -> 1.16829
P49: Pips to TP1 | Q49: =IF(OR(Q48="",$L$3=""),"",ABS(($L$3-Q48)*10000)) | AB49: CT_Mid | AC49: =IF(AC48="","",AC48+((($AE$24/2)*$AE$3))) -> 1.16489 | AE49: In_CT_Zone | AF49: =IF(Planner_HUD!$E$16>$B$3,Planner_HUD!$E$16,"") -> 1.1682
P50: Reward at TP1 $ | Q50: =IF(OR(Q47=0,Q48="",$L$3=""),"",ABS(($L$3-Q48)*Q47)) | AA50: =B3 -> 1.16364 | AB50: Tier | AC50: =IF($L$1<>"LONG","",MAX($B$3,IF(AND($G$21<>"",ABS($G$21-IF($B$27<>"",$B$27,$G$17))<=0.0025),$G$21,IF($B$27<>"",$B$27,$G$17)))) | AD50: High | AE50: In_Premium | AF50: =IF(AND(Planner_HUD!$E$11>$B$3,(Planner_HUD!$E$11-$B$3)*10000<=40),Planner_HUD!$E$11,"")
P51: R multiple at TP1 | Q51: =IF(SUM($W$42:$W$44)=0,"",SUM($X$42:$X$44)/SUM($W$42:$W$44)) | AA51: L1_0.618-L1_0.382 | AB51: Tier1 Low | AC51: =MIN($D$23,$D$25) -> 1.1687336 | AD51: =MAX($D$23,$D$25) -> 1.1731964 | AF51: =IFERROR(_xlfn.AGGREGATE(15,6,AF47:AF50/(AF47:AF50<>""),1),$B$3+($AE$24*$AE$3)) -> 1.16434
P52: Avg Eff Pips to SL | Q52: =IF(SUM(Y42:Y44)=0,"",(Y42*MAX(U42,$AE$35)+Y43*MAX(U43,$AE$35)+Y44*MAX(U44,$AE$35))/SUM(Y42:Y44)) | AA52: 4H_FVG_low-4H_FVG_high | AB52: 2 | AC52: =B36 -> 1.1605 | AD52: =B35 -> 1.16139 | AE52: CoreLong_Flag | AF52: =AND($AC$38>=0,G8=TRUE,NOT(G9),AF48) -> FALSE
AA53: DeepLow-High | AB53: 3 | AC53: =B13 -> 1.16347 | AD53: =B12 -> 1.16757 | AE53: CTShort_Flag | AF53: =AND(N($AC$38)<=0,G8=TRUE,G11=TRUE,AF49=TRUE,$B$21>70,$B$20>65) -> FALSE
AE54: LocationLabel | AF54: =IF(AF48,"DISCOUNT",IF(AF49,"CT_ZONE",IF(AF50,"PREMIUM","MID"))) -> DISCOUNT
AB55: ActiveTier | AC55: =IF(AND($B$3>=AC51,$B$3<=AD51),1,IF(AND($B$3>=AC52,$B$3<=AD52),2,IF(AND($B$3>=AC53,$B$3<=AD53),3,0))) -> 3
AC56: =AC55 -> 3
AB57: Primary_ViewTier (1/2/3, blank=auto) | AD57: Resolved_PrimaryTier | AE57: =IF($AC$57<>"",$AC$57,IF($AC$55=0,1,$AC$55)) -> 3

Sheet Planner_HUD
A1: EURUSD Planner HUD (inputs → outputs)
A2: Edit BLUE cells only. Planner_v2 reads from here.
A4: Market snapshot (update from chart) | D4: Liquidity / Session levels | G4: FVG / value blocks | J4: Options expiry + risk/weights
A5: Current Price | B5: 1.16364 | D5: PMH | E5: 1.1808 | G5: 4H FVG high | H5: 1.16139 | J5: Strike 1 | K5: 1.13
A6: EMA9 15m | B6: 1.16347 | D6: PML | E6: 1.15889 | G6: 4H FVG low | H6: 1.1605 | J6: Size 1 (bn) | K6: 1.46
A7: EMA21 15m | B7: 1.16351 | D7: PWH | E7: 1.1789 | G7: Daily FVG high | H7: 1.16734 | J7: Strike 2 | K7: 1.18
A8: EMA50 15m | B8: 1.16383 | D8: PWL | E8: 1.17132 | G8: Daily FVG low | H8: 1.16627 | J8: Size 2 (bn) | K8: 1.136
A9: SMA200 15m | B9: 1.1658 | D9: PDH | E9: 1.16829 | G9: 1H FVG high | H9: 1.1682 | J9: Strike 3 | K9: 1.165
A10: EMA50 1H | B10: 1.16567 | D10: PDL | E10: 1.16427 | G10: 1H FVG low | H10: 1.16779 | J10: Size 3 (bn) | K10: 1.12
A11: EMA50 4H | B11: 1.16963 | D11: EQH_above | E11: 1.17025 | J11: Strike 4
A12: EMA50 1D | B12: 1.16757 | D12: EQL_below | E12: 1.15919 | J12: Size 4 (bn)
A13: EMA100 1D | B13: 1.16347 | D13: LTF Leg Low (15m | E13: 1.16151 | J13: Magnet Range (pips) | K13: 20
A14: EMA200 1D | B14: 1.14963 | D14: LTF Leg High (15m) | E14: 1.18042 | J14: Options Clamp % | K14: 0.3
A15: EMA50 1W | B15: 1.1439 | D15: Session Low | E15: 1.16182 | J15: Zone tolerance | K15: 0.0002
A16: EMA20 1M | B16: 1.1241 | D16: Session High | E16: 1.1682 | J16: Weight 0.382 | K16: 0.2
A17: RSI 15M | B17: 51.21 | D17: HTF Swing Low (4H) | E17: 1.14931 | J17: Weight 0.500 | K17: 0.35
A18: RSI 1H | B18: 38.35 | D18: HTF Swing High (4H) | E18: 1.18042 | J18: Weight 0.618 | K18: 0.45
A19: RSI 4HR | B19: 31.67 | J19: Ticket Size | K19: 0
A20: ATR(14) 15m | B20: 0.00047 | J20: Min R (R multiple) | K20: 3
A21: ADR(14) | B21: 0.00088
A22: Structure (SMC) – D1 / 4H / 1H / 15m
A23: TF | B23: Trend (auto) | C23: Last BOS (manual) | D23: Last CHOCH (manual)
A24: 1D | B24: =Planner_v2!G3 -> Range | C24: Down | D24: Down
A25: 4H | B25: =Planner_v2!G4 -> Bear | C25: Down | D25: Down
A26: 1H | B26: =Planner_v2!G5 -> Bear | C26: Down | D26: Down
A27: 15M | B27: =Planner_v2!G6 -> Bear | C27: Down | D27: Down
A30: Outputs (auto)
A31: Side (LONG/SHORT) | B31: =Planner_v2!L1
A32: Setup Summary | B32: =IF(Planner_v2!AC18="","",TEXT(Planner_v2!AC18,"0%")&" ("&Narrative_Engine!B4&") — "&Narrative_Engine!B5) -> 13% (D) — Avoid: observation only.
A33: Trade Mode | B33: =Planner_v2!AC23 -> Avoid
A34: Macro Bias (EURUSD) | B34: =Macro_Dashboard!B19 -> Neutral
A35: Rate diff (NOW) | B35: =IF(Narrative_Engine!B7="","",TEXT(Narrative_Engine!B7,"0.00")&" ("&Narrative_Engine!B11&")") -> 2.37 (USD advantage now)
A36: Rate diff change (6M vs NOW) | B36: =IF(Narrative_Engine!B9="","",TEXT(Narrative_Engine!B9,"0")&" steps (~"&TEXT(Narrative_Engine!B10,"0")&"bp) — "&Narrative_Engine!B12)
A37: Yield Narrative | B37: =Macro_Dashboard!B37 -> US yields: 2Y 3.50% (-2bp 1d) — 2Y falling → easier Fed priced → USD headwind. Curve (2s10s): 1bp — Curve normal → growth ok
A38: Narrative (plain English) | B38: =Narrative_Engine!B31 -> 1) Macro bias: Neutral. Rate gap NOW 2.37 (USD advantage now). 2) Yields: US yields: 2Y 3.50% (-2bp 1d) — 2Y falling → easier Fed priced → USD headwind. Curve (2s10s): 1bp — Curve normal → growth ok. 3) Speakers: Fed neutral (daily -0.08), ; ECB hawkish (daily 0.25), .
A39: Action (what to do) | B39: =Narrative_Engine!B33 -> Action: macro neutral — lean on structure/levels, trade smaller.
A40: Notes | B40: =Narrative_Engine!B35 -> Steps = 25bp moves (quarter‑point). Example: -4 steps ≈ -100bp of USD-vs-EUR advantage compressing over ~6 months.
A41: Definitions | B41: =IF(B40="","",IF(B40="Aligned","Trade direction matches macro bias.","Macro bias disagrees — reduce size or demand stronger technical confirmation.")) -> Macro bias disagrees — reduce size or demand stronger technical confirmation.
A42: Execution ladders (auto from Planner_v2)
A43: Primary Ladder (Shallow / Continuation)
A44: Rung | B44: Entry | C44: TP | D44: SL | E44: Pips→TP | F44: EffPips→SL | G44: Units | H44: Risk $ | I44: Reward $ | J44: R | K44: R2
A45: Shallow | B45: =Planner_v2!Q2 | C45: =Planner_v2!R2 | D45: =Planner_v2!S2 | E45: =Planner_v2!T2 | F45: =Planner_v2!U2 | G45: =Planner_v2!Y2 | H45: =Planner_v2!W2 | I45: =Planner_v2!X2 | J45: =Planner_v2!Z2 | K45: =Planner_v2!Z2
A46: Mid | B46: =Planner_v2!Q3 | C46: =Planner_v2!R3 | D46: =Planner_v2!S3 | E46: =Planner_v2!T3 | F46: =Planner_v2!U3 | G46: =Planner_v2!Y3 | H46: =Planner_v2!W3 | I46: =Planner_v2!X3 | J46: =Planner_v2!Z3 | K46: =Planner_v2!Z3
A47: Deep | B47: =Planner_v2!Q4 | C47: =Planner_v2!R4 | D47: =Planner_v2!S4 | E47: =Planner_v2!T4 | F47: =Planner_v2!U4 | G47: =Planner_v2!Y4 | H47: =Planner_v2!W4 | I47: =Planner_v2!X4 | J47: =Planner_v2!Z4 | K47: =Planner_v2!Z4
A48: Total | B48: =IFERROR(SUBTOTAL(101,Table16[Entry]),"") | C48: =IFERROR(SUBTOTAL(101,Table16[TP]),"") | D48: =IFERROR(SUBTOTAL(101,Table16[SL]),"") | E48: =IFERROR(SUBTOTAL(101,Table16[Pips→TP]),"") | F48: =IFERROR(SUBTOTAL(101,Table16[EffPips→SL]),"") | G48: =SUBTOTAL(109,Table16[Units]) -> 0 | H48: =SUBTOTAL(109,Table16[Risk $]) -> 0 | I48: =SUBTOTAL(109,Table16[Reward $]) -> 0 | J48: =IFERROR(Table16[[#Totals],[Reward $]]/Table16[[#Totals],[Risk $]],"")
A50: Value Ladder (Mid-depth supports)
A51: Rung | B51: Entry | C51: TP | D51: SL | E51: Pips→TP | F51: EffPips→SL | G51: Units | H51: Risk $ | I51: Reward $ | J51: R | K51: R2
A52: Shallow | B52: =Planner_v2!Q42 | C52: =Planner_v2!R42 | D52: =Planner_v2!S42 | E52: =Planner_v2!T42 | F52: =Planner_v2!U42 | G52: =Planner_v2!Y42 | H52: =Planner_v2!W42 | I52: =Planner_v2!X42 | J52: =Planner_v2!Z42 | K52: =Planner_v2!Z42
A53: Mid | B53: =Planner_v2!Q43 | C53: =Planner_v2!R43 | D53: =Planner_v2!S43 | E53: =Planner_v2!T43 | F53: =Planner_v2!U43 | G53: =Planner_v2!Y43 | H53: =Planner_v2!W43 | I53: =Planner_v2!X43 | J53: =Planner_v2!Z43 | K53: =Planner_v2!Z43
A54: Deep | B54: =Planner_v2!Q44 | C54: =Planner_v2!R44 | D54: =Planner_v2!S44 | E54: =Planner_v2!T44 | F54: =Planner_v2!U44 | G54: =Planner_v2!Y44 | H54: =Planner_v2!W44 | I54: =Planner_v2!X44 | J54: =Planner_v2!Z44 | K54: =Planner_v2!Z44
A55: Total | B55: =IFERROR(SUBTOTAL(101,Table17[Entry]),"") | C55: =IFERROR(SUBTOTAL(101,Table17[TP]),"") | D55: =IFERROR(SUBTOTAL(101,Table17[SL]),"") | E55: =IFERROR(SUBTOTAL(101,Table17[Pips→TP]),"") | F55: =IFERROR(SUBTOTAL(101,Table17[EffPips→SL]),"") | G55: =SUBTOTAL(109,Table17[Units]) -> 0 | H55: =SUBTOTAL(109,Table17[Risk $]) -> 0 | I55: =SUBTOTAL(109,Table17[Reward $]) -> 0 | J55: =IFERROR(Table17[[#Totals],[Reward $]]/Table17[[#Totals],[Risk $]],"")
A57: A+ Ladder (Deep value block)
A58: Rung | B58: Entry | C58: TP | D58: SL | E58: Pips→TP | F58: EffPips→SL | G58: Units | H58: Risk $ | I58: Reward $ | J58: R | K58: R2
A59: Shallow | B59: =Planner_v2!Q15 | C59: =Planner_v2!R15 | D59: =Planner_v2!S15 | E59: =Planner_v2!T15 | F59: =Planner_v2!U15 | G59: =Planner_v2!Y15 | H59: =Planner_v2!W15 | I59: =Planner_v2!X15 | J59: =Planner_v2!Z15 | K59: =Planner_v2!Z15
A60: Mid | B60: =Planner_v2!Q16 | C60: =Planner_v2!R16 | D60: =Planner_v2!S16 | E60: =Planner_v2!T16 | F60: =Planner_v2!U16 | G60: =Planner_v2!Y16 | H60: =Planner_v2!W16 | I60: =Planner_v2!X16 | J60: =Planner_v2!Z16 | K60: =Planner_v2!Z16
A61: Deep | B61: =Planner_v2!Q17 | C61: =Planner_v2!R17 | D61: =Planner_v2!S17 | E61: =Planner_v2!T17 | F61: =Planner_v2!U17 | G61: =Planner_v2!Y17 | H61: =Planner_v2!W17 | I61: =Planner_v2!X17 | J61: =Planner_v2!Z17 | K61: =Planner_v2!Z17
A62: Total | B62: =IFERROR(SUBTOTAL(101,Table18[Entry]),"") | C62: =IFERROR(SUBTOTAL(101,Table18[TP]),"") | D62: =IFERROR(SUBTOTAL(101,Table18[SL]),"") | E62: =IFERROR(SUBTOTAL(101,Table18[Pips→TP]),"") | F62: =IFERROR(SUBTOTAL(101,Table18[EffPips→SL]),"") | G62: =SUBTOTAL(109,Table18[Units]) -> 0 | H62: =SUBTOTAL(109,Table18[Risk $]) -> 0 | I62: =SUBTOTAL(109,Table18[Reward $]) -> 0 | J62: =IFERROR(Table18[[#Totals],[Reward $]]/Table18[[#Totals],[Risk $]],"")
A64: CT Ladder (Fade ceiling; only on rejection) | L64: =IF(Planner_v2!L1<>"SHORT","CT inactive (Side is "&Planner_v2!L1&"). Switch Side to SHORT to use CT.","") -> CT inactive (Side is ). Switch Side to SHORT to use CT.
A65: Rung | B65: Entry | C65: TP | D65: SL | E65: Pips→TP | F65: EffPips→SL | G65: Units | H65: Risk $ | I65: Reward $ | J65: R | K65: Column1
A66: Shallow | B66: =Planner_v2!Q28 -> 1.16454 | C66: =Planner_v2!R28 -> 1.15909 | D66: =Planner_v2!S28 -> 1.16604 | E66: =Planner_v2!T28 -> 54.5 | F66: =Planner_v2!U28 -> 15 | G66: =Planner_v2!Y28 -> 90409.788 | H66: =Planner_v2!W28 -> 135.61468 | I66: =Planner_v2!X28 -> 492.73334 | J66: =Planner_v2!Z28 -> 3.6333333
A67: Mid | B67: =Planner_v2!Q29 -> 1.16489 | C67: =Planner_v2!R29 -> 1.15909 | D67: =Planner_v2!S29 -> 1.16604 | E67: =Planner_v2!T29 -> 58 | F67: =Planner_v2!U29 -> 11.5 | G67: =Planner_v2!Y29 -> 91720.075 | H67: =Planner_v2!W29 -> 105.47809 | I67: =Planner_v2!X29 -> 531.97643 | J67: =Planner_v2!Z29 -> 5.0434783
A68: Deep | B68: =Planner_v2!Q30 -> 1.16524 | C68: =Planner_v2!R30 -> 1.15909 | D68: =Planner_v2!S30 -> 1.16604 | E68: =Planner_v2!T30 -> 61.5 | F68: =Planner_v2!U30 -> 8 | G68: =Planner_v2!Y30 -> 75341.49 | H68: =Planner_v2!W30 -> 60.273192 | I68: =Planner_v2!X30 -> 463.35016 | J68: =Planner_v2!Z30 -> 7.6875
A69: Total | B69: =IFERROR(SUBTOTAL(101,Table19[Entry]),"") -> 1.16489 | C69: =IFERROR(SUBTOTAL(101,Table19[TP]),"") -> 1.15909 | D69: =IFERROR(SUBTOTAL(101,Table19[SL]),"") -> 1.16604 | E69: =IFERROR(SUBTOTAL(101,Table19[Pips→TP]),"") -> 58 | F69: =IFERROR(SUBTOTAL(101,Table19[EffPips→SL]),"") -> 11.5 | G69: =SUBTOTAL(109,Table19[Units]) -> 257471.35 | H69: =SUBTOTAL(109,Table19[Risk $]) -> 301.36596 | I69: =SUBTOTAL(109,Table19[Reward $]) -> 1488.0599 | J69: =IFERROR(Table19[[#Totals],[Reward $]]/Table19[[#Totals],[Risk $]],"") -> 4.9377174

Sheet Macro_Dashboard
A1: Macro Outlook – Weekly Context
A3: Daily Macro Dashboard
A4: USD | D4: Rating | F4: EUR | J4: JPY | N4: Yield Curve Translator (US Treasuries)
A5: Inflation Trend | B5: =IFERROR(LOOKUP(2,1/((Macro_Data!$B$2:$B$148="Inflation – US")*(Macro_Data!$I$2:$I$148<>"")),Macro_Data!$I$2:$I$148),"") -> Slowing | C5: =IF(B5="","",VLOOKUP(B5,$D$5:$E$19,2,FALSE)) -> -1 | D5: Falling | E5: -1 | F5: Inflation Trend | G5: =IFERROR(LOOKUP(2,1/((Macro_Data!$B$2:$B$148="Inflation – EUR")*(Macro_Data!$I$2:$I$148<>"")),Macro_Data!$I$2:$I$148),"") -> Slowing | H5: =IF(G5="","",VLOOKUP(G5,$D$5:$E$19,2,FALSE)) -> -1 | J5: Inflation Trend | K5: =IFERROR(LOOKUP(2,1/((Macro_Data!$B$2:$B$148="Inflation – EUR")*(Macro_Data!$I$2:$I$148<>"")),Macro_Data!$I$2:$I$148),"") -> Slowing | L5: =IF(K5="","",VLOOKUP(K5,$D$5:$E$19,2,FALSE)) -> -1 | N5: Tenor | O5: Level | P5: Δ1d (bp) | Q5: Δ5d (bp) | R5: Δ20d (bp) | S5: What this usually means | T5: Dynamic read (auto)
A6: Labour Trend | B6: =IFERROR(LOOKUP(2,1/((Macro_Data!$B$2:$B$148="Labour – US")*(Macro_Data!$I$2:$I$148<>"")),Macro_Data!$I$2:$I$148),"") -> Mixed | C6: =IF(B6="","",VLOOKUP(B6,$D$5:$E$19,2,FALSE)) -> 0 | D6: Neutral | E6: 0 | F6: Labour Trend | G6: =IFERROR(LOOKUP(2,1/((Macro_Data!$B$2:$B$148="Labour – EUR")*(Macro_Data!$I$2:$I$148<>"")),Macro_Data!$I$2:$I$148),"") -> Accelerating | H6: =IF(G6="","",VLOOKUP(G6,$D$5:$E$19,2,FALSE)) -> 1 | J6: Labour Trend | K6: =IFERROR(LOOKUP(2,1/((Macro_Data!$B$2:$B$148="Labour – EUR")*(Macro_Data!$I$2:$I$148<>"")),Macro_Data!$I$2:$I$148),"") -> Accelerating | L6: =IF(K6="","",VLOOKUP(K6,$D$5:$E$19,2,FALSE)) -> 1 | N6: US 2y | O6: =IFERROR(VLOOKUP(N6,Macro_Data!$O$2:$V$8,2,FALSE),"") -> 3.497 | P6: =IFERROR(VLOOKUP(N6,Macro_Data!$O$2:$V$8,6,FALSE)*100,"") -> -2.2 | Q6: =IFERROR(VLOOKUP(N6,Macro_Data!$O$2:$V$8,7,FALSE)*100,"") -> -11.3 | R6: =IFERROR(VLOOKUP(N6,Macro_Data!$O$2:$V$8,8,FALSE)*100,"") -> -11.5 | S6: Front-end: policy path / next 6–18 months expectations | T6: =IF(O6="","",IF(P6>2,"2Y rising → tighter Fed priced → USD tailwind",IF(P6<-2,"2Y falling → easier Fed priced → USD headwind","2Y stable → policy steady"))) -> 2Y falling → easier Fed priced → USD headwind
A7: Growth Trend | B7: =IFERROR(LOOKUP(2,1/((Macro_Data!$B$2:$B$148="Growth - US")*(Macro_Data!$I$2:$I$148<>"")),Macro_Data!$I$2:$I$148),"") -> Slowing | C7: =IF(B7="","",VLOOKUP(B7,$D$5:$E$19,2,FALSE)) -> -1 | D7: Rising | E7: 1 | F7: Growth Trend | G7: =IFERROR(LOOKUP(2,1/((Macro_Data!$B$2:$B$148="Growth - EUR")*(Macro_Data!$I$2:$I$148<>"")),Macro_Data!$I$2:$I$148),"") -> Stable | H7: -1 | J7: Growth Trend | K7: =IFERROR(LOOKUP(2,1/((Macro_Data!$B$2:$B$148="Growth - EUR")*(Macro_Data!$I$2:$I$148<>"")),Macro_Data!$I$2:$I$148),"") -> Stable | L7: -1 | N7: US 5y | O7: =IFERROR(VLOOKUP(N7,Macro_Data!$O$2:$V$8,2,FALSE),"") -> 3.719 | P7: =IFERROR(VLOOKUP(N7,Macro_Data!$O$2:$V$8,6,FALSE)*100,"") -> -2.2 | Q7: =IFERROR(VLOOKUP(N7,Macro_Data!$O$2:$V$8,7,FALSE)*100,"") -> -6.4 | R7: =IFERROR(VLOOKUP(N7,Macro_Data!$O$2:$V$8,8,FALSE)*100,"") -> 1.5 | S7: Medium: growth + inflation outlook (cycle) | T7: =IF(O7="","",IF(P7>2,"5Y rising → growth/inflation repriced up (USD supportive)",IF(P7<-2,"5Y falling → growth scare/easing priced (USD headwind)","5Y stable"))) -> 5Y falling → growth scare/easing priced (USD headwind)
A8: Fed Policy Direction | B8: =IF(B40="","",IF(B40>=2,"More cuts",IF(B40<=-2,"Less cuts","Hold"))) | C8: =IF(B8="","",VLOOKUP(B8,$D$5:$E$19,2,FALSE)) | D8: Softening | E8: -1 | F8: Fed Policy Direction | G8: =IF(B41="","",IF(B41>=2,"More cuts",IF(B41<=-2,"Less cuts","Hold"))) | H8: =IF(G8="","",VLOOKUP(G8,$D$5:$E$19,2,FALSE)) | J8: Fed Policy Direction | K8: =IF(F41="","",IF(F41>=2,"More cuts",IF(F41<=-2,"Less cuts","Hold"))) | L8: =IF(K8="","",VLOOKUP(K8,$D$5:$E$19,2,FALSE)) | N8: US 10y | O8: =IFERROR(VLOOKUP(N8,Macro_Data!$O$2:$V$8,2,FALSE),"") -> 4.168 | P8: =IFERROR(VLOOKUP(N8,Macro_Data!$O$2:$V$8,6,FALSE)*100,"") -> -1.5 | Q8: =IFERROR(VLOOKUP(N8,Macro_Data!$O$2:$V$8,7,FALSE)*100,"") -> -2 | R8: =IFERROR(VLOOKUP(N8,Macro_Data!$O$2:$V$8,8,FALSE)*100,"") -> 5.2 | S8: Long: long-run growth + inflation + term premium | T8: =IF(O8="","",IF(P8>2,"10Y rising → term premium/growth up (USD supportive)",IF(P8<-2,"10Y falling → duration bid/risk-off (USD mixed)","10Y stable"))) -> 10Y stable
A9: Global Risk Environment | B9: Mixed | C9: =IF(B9="","",VLOOKUP(B9,$D$5:$E$19,2,FALSE)) -> 0 | D9: Mixed | E9: 0 | F9: Global Risk Environment | G9: Mixed | H9: =IF(G9="","",VLOOKUP(G9,$D$5:$E$19,2,FALSE)) -> 0 | J9: Global Risk Environment | K9: Mixed | L9: =IF(K9="","",VLOOKUP(K9,$D$5:$E$19,2,FALSE)) -> 0 | N9: US 30y | O9: =IFERROR(VLOOKUP(N9,Macro_Data!$O$2:$V$8,2,FALSE),"") -> 4.844 | P9: =IFERROR(VLOOKUP(N9,Macro_Data!$O$2:$V$8,6,FALSE)*100,"") -> 26.4 | Q9: =IFERROR(VLOOKUP(N9,Macro_Data!$O$2:$V$8,7,FALSE)*100,"") -> 3.6 | R9: =IFERROR(VLOOKUP(N9,Macro_Data!$O$2:$V$8,8,FALSE)*100,"") -> 9.1 | S9: Long-end: term premium + supply/duration + inflation tail risk | T9: =IF(O9="","",IF(P9>2,"30Y rising → term premium/supply pressure (USD mixed)",IF(P9<-2,"30Y falling → long-end bid (risk-off)","30Y stable"))) -> 30Y rising → term premium/supply pressure (USD mixed)
A10: US Yield Trend | B10: =IF(C10="","",IF(C10>=0.5,"Rising",IF(C10<=-0.5,"Falling","Flat"))) -> Rising | C10: =IF(COUNTA(Macro_Data!$X$2:$X$8)=0,"",AVERAGE(Macro_Data!$X$2:$X$5)+0.5*AVERAGE(Macro_Data!$X$7:$X$8)) -> 0.5 | D10: Tight | E10: 1 | F10: EUR Yield Trend | G10: =IF(H10="","",IF(H10>=0.5,"Rising",IF(H10<=-0.5,"Falling","Flat"))) -> Rising | H10: =IF(COUNTA(Macro_Data!$X$2:$X$7)=0,"",AVERAGE(Macro_Data!$X$2:$X$5)+0.5*Macro_Data!$X$7) -> 0.5 | J10: JPY Yield Trend | K10: =IF(L10="","",IF(L10>=0.5,"Rising",IF(L10<=-0.5,"Falling","Flat"))) -> Rising | L10: =IF(COUNTA(Macro_Data!$X$2:$X$7)=0,"",AVERAGE(Macro_Data!$X$2:$X$5)+0.5*Macro_Data!$X$7) -> 0.5 | N10: US 2s10s | O10: =IFERROR(VLOOKUP(N10,Macro_Data!$O$2:$V$8,2,FALSE),"") -> 0.671 | P10: =IFERROR(VLOOKUP(N10,Macro_Data!$O$2:$V$8,6,FALSE)*100,"") -> 0.7 | Q10: =IFERROR(VLOOKUP(N10,Macro_Data!$O$2:$V$8,7,FALSE)*100,"") -> 9.3 | R10: =IFERROR(VLOOKUP(N10,Macro_Data!$O$2:$V$8,8,FALSE)*100,"") -> 16.7 | S10: Curve slope: 10Y−2Y. Negative = inversion (easing/recession risk priced) | T10: =IF(O10="","",IF(O10<0,IF(P10>2,"Inversion easing (steepening) → easing cycle risk","Inversion persists → caution growth"),IF(O10>0,IF(P10<-2,"Curve flattening → late-cycle risk","Curve normal → growth ok"),"Curve flat"))) -> Curve normal → growth ok
D11: Slowing | E11: -1 | N11: US 5s30s | O11: =IFERROR(VLOOKUP(N11,Macro_Data!$O$2:$V$8,2,FALSE),"") -> 1.125 | P11: =IFERROR(VLOOKUP(N11,Macro_Data!$O$2:$V$8,6,FALSE)*100,"") -> 28.6 | Q11: =IFERROR(VLOOKUP(N11,Macro_Data!$O$2:$V$8,7,FALSE)*100,"") -> 10 | R11: =IFERROR(VLOOKUP(N11,Macro_Data!$O$2:$V$8,8,FALSE)*100,"") -> 7.6 | S11: Long-end steepness: 30Y−5Y. Rising = higher term premium / supply pressure | T11: =IF(O11="","",IF(P11>2,"5s30 steepening → term premium/supply up (USD mixed)",IF(P11<-2,"5s30 flattening → long-end bid","5s30 stable"))) -> 5s30 steepening → term premium/supply up (USD mixed)
D12: Stable | E12: 0 | N12: Rule of thumb for FX (USD):
A13: Macro_USD_Score | B13: =IF(COUNTA($C$5:$C$10)=0,"",SUM($C$5:$C$10)) -> -1.5 | D13: Accelerating | E13: 1 | N13: • Rising 2Y = tighter Fed priced → tends to support USD. • Falling 2Y = easier Fed priced → tends to weigh USD. • Curve steepening driven by falling 2Y often = easing cycle / risk-on.
A14: Macro_EUR_Score | B14: =IF(COUNTA($H$5:$H$10)=0,"",SUM($H$5:$H$10)) -> -0.5 | D14: More cuts | E14: -1
A15: Macro_JPY_Score | B15: =0 -> 0 | D15: Hold | E15: 0
A16: Macro_USD_Strength | B16: =IF(B13="","",IF(B13>=2,"Strong USD",IF(B13<=-2,"Weak USD","Neutral USD"))) -> Neutral USD | D16: Less cuts | E16: 1
A17: Macro_EUR_Strength | B17: =IF(B14="","",IF(B14>=2,"Strong EUR",IF(B14<=-2,"Weak EUR","Neutral EUR"))) -> Neutral EUR | D17: Risk-on | E17: -1
D18: Risk-off | E18: 1
A19: EURUSD Macro Bias | B19: =IF(OR(B13="",B14=""),"",IF(B14-B13>=2,"Buy dips",IF(B14-B13<=-2,"Sell rallies","Neutral"))) -> Neutral | D19: Flat | E19: 0
A20: USDJPY Macro Bias | B20: =IF(B13="","Neutral",IF(B13-B15>=2,"Buy USD / Sell JPY",IF(B13-B15<=-2,"Sell USD / Buy JPY","Neutral"))) -> Neutral
A21: Risk Asset Bias | B21: =IF(B13="","Mixed",IF(AND(C9=1,C10=1,C5<=0),"Risk-on",IF(AND(C9=-1,C10=-1,C5>0),"Risk-off","Mixed"))) -> Mixed
A22: US_YieldTrend_Score (-1..+1) | B22: =C10 -> 0.5
A23: Fed_Ease_Score | B23: =IF(B40="","",IF(B40>=2,1,IF(B40<=-2,-1,0)))
A24: ECB_Ease_Score | B24: =IF(B41="","",IF(B41>=2,1,IF(B41<=-2,-1,0)))
A25: BoJ_Ease_Score | B25: 0
A27: Rate_Diff_Level | B27: =IF(OR(Macro_Data!$Z$2="",Macro_Data!$Z$3="",$B$40="",$B$41=""),"",(Macro_Data!$Z$2-0.25*$B$40)-(Macro_Data!$Z$3-0.25*$B$41)) | C27: =IF(B27="","",IF(B27>1.5,"Strong USD carry tailwind",IF(B27>0.5,"Mild USD carry tailwind",IF(B27<-1.5,"Strong EUR carry tailwind",IF(B27<-0.5,"Mild EUR carry tailwind","Carry roughly neutral")))))
A28: Rate_Diff_Score | B28: =IF(OR(Macro_Data!Z2="",Macro_Data!Z3="",$B$40="",$B$41=""),"",ROUND((((Macro_Data!Z2-0.25*$B$40)-(Macro_Data!Z3-0.25*$B$41))-(Macro_Data!Z2-Macro_Data!Z3))/0.25,0)) | C28: =IF(B28="","",IF(B28<=-2,"Spread narrowing in favour of EUR",IF(B28>=2,"Spread widening in favour of USD","Spread roughly unchanged"))) | G28: =Macro_Data!Z2 -> 4.37
A29: Last FOMC date | B29: 46001
A30: Fed_DailyTone | B30: =IF($B$29="","",IFERROR(AVERAGEIFS(Macro_Speakers!$H:$H,Macro_Speakers!$B:$B,"FED",Macro_Speakers!$A:$A,">="&$B$29),"")) -> -0.083333333 | C30: =IF(B30="","",IF(B30>0.3,"Hawkish",IF(B30<-0.3,"Dovish","Mixed"))) -> Mixed
A31: Fed_WeeklyTone | B31: =IFERROR(AVERAGEIFS(Macro_Speakers!$H:$H,Macro_Speakers!$B:$B,"FED",Macro_Speakers!$A:$A,">="&TODAY()-30),"") | C31: =IF(B31="","",IF(B31>0.3,"Hawkish",IF(B31<-0.3,"Dovish","Mixed")))
A32: ECB_DailyTone | B32: =IF($B$29="","",IFERROR(AVERAGEIFS(Macro_Speakers!$H:$H,Macro_Speakers!$B:$B,"ECB",Macro_Speakers!$A:$A,">="&$B$29),"")) -> 0.25 | C32: =IF(B32="","",IF(B32>0.3,"Hawkish",IF(B32<-0.3,"Dovish","Mixed"))) -> Mixed
A33: ECB_WeeklyTone | B33: =IFERROR(AVERAGEIFS(Macro_Speakers!$H:$H,Macro_Speakers!$B:$B,"ECB",Macro_Speakers!$A:$A,">="&TODAY()-30),"") | C33: =IF(B33="","",IF(B33>0.3,"Hawkish",IF(B33<-0.3,"Dovish","Mixed")))
A34: JPY_DailyTone | B34: =IF($B$29="","",IFERROR(AVERAGEIFS(Macro_Speakers!$H:$H,Macro_Speakers!$B:$B,"ECB",Macro_Speakers!$A:$A,">="&$B$29),"")) -> 0.25 | C34: =IF(B34="","",IF(B34>0.3,"Hawkish",IF(B34<-0.3,"Dovish","Mixed"))) -> Mixed
A35: JPY_WeeklyTone | B35: =IFERROR(AVERAGEIFS(Macro_Speakers!$H:$H,Macro_Speakers!$B:$B,"ECB",Macro_Speakers!$A:$A,">="&TODAY()-30),"") | C35: =IF(B35="","",IF(B35>0.3,"Hawkish",IF(B35<-0.3,"Dovish","Mixed")))
A37: Yield Narrative | B37: =IF(O6="","","US yields: 2Y "&TEXT(O6,"0.00")&"% ("&IF(P6="","",IF(P6>0,"+"&TEXT(P6,"0"),TEXT(P6,"0")))&"bp 1d) — "&T6&". "&"Curve (2s10s): "&TEXT(O10,"0")&"bp — "&T10) -> US yields: 2Y 3.50% (-2bp 1d) — 2Y falling → easier Fed priced → USD headwind. Curve (2s10s): 1bp — Curve normal → growth ok
B38: =IF($B$19="","",IF($B$19="Buy dips","Macro backdrop leans EUR support.","Macro backdrop leans USD support.")&" (Rate diff: "&TEXT($B$28,"0")&" steps; Yields: "&$B$10&"; Fed tone: "&$B$31&"; ECB tone: "&$B$33&")") -> Macro backdrop leans USD support. (Rate diff: steps; Yields: Rising; Fed tone: ; ECB tone: )
A40: Fed_ForwardCuts_6m | B40: =IFERROR(INDEX(Macro_Rates!$J$2:$J$92,MATCH(_xlfn.AGGREGATE(15,6,Macro_Rates!$A$2:$A$92/((Macro_Rates!$B$2:$B$92="US")*(Macro_Rates!$A$2:$A$92>=TODAY()+180)),1),Macro_Rates!$A$2:$A$92,0)),"")
A41: ECB_ForwardCuts_6m | B41: =IFERROR(INDEX(Macro_Rates!$J$2:$J$92,MATCH(_xlfn.AGGREGATE(15,6,Macro_Rates!$A$2:$A$92/((Macro_Rates!$B$2:$B$92="ECB")*(Macro_Rates!$A$2:$A$92>=TODAY()+180)),1),Macro_Rates!$A$2:$A$92,0)),"")
A42: JPY_ForwardCuts_6m

Sheet Macro_Data
A1: Date | B1: Category | C1: Event | D1: Actual | E1: Forecast | F1: Previous | G1: Surprise vs Forecast | H1: Change vs Prev | I1: Qualitative | J1: EffectDirection | K1: Adj_Surprise | L1: Adj_ChangeAdj_ChangeAdj_ChangeAdj_ChangeAdj_ChangeAdj_ChangeAdj_ChangeAdj_ChangeAdj_Change | N1: Date | O1: Tenor | P1: today's yield | Q1: yield 1 trading day ago | R1: yield 5 trading day ago | S1: yield 20 trading day ago | T1: Δd (1d) | U1: Δ5d | V1: Δ20d | W1: Trend | X1: TrendScore
A2: 45985 | B2: Growth - EUR | C2: German ifo Business Climate | D2: 88.1 | E2: 88.6 | F2: 88.4 | G2: =IF(NOT(ISNUMBER(Table9[[#This Row],[Actual]])),"",IF(NOT(ISNUMBER(Table9[[#This Row],[Forecast]])),"",Table9[[#This Row],[Actual]]-Table9[[#This Row],[Forecast]])) -> -0.5 | H2: =IF(NOT(ISNUMBER(Table9[[#This Row],[Actual]])),"",IF(NOT(ISNUMBER(Table9[[#This Row],[Previous]])),"",Table9[[#This Row],[Actual]]-Table9[[#This Row],[Previous]])) -> -0.3 | I2: =IF(AND(K2="",L2=""),"N/A",IF(AND(ABS(N(K2))<0.0005,ABS(N(L2))<0.0005),"Stable",IF(AND(L2="",ABS(N(K2))>=0.0005),IF(N(K2)>0,"Accelerating","Slowing"),IF(AND(K2="",ABS(N(L2))>=0.0005),IF(N(L2)>0,"Accelerating","Slowing"),IF(AND(N(K2)>0,N(L2)>=0),"Accelerating",IF(AND(N(K2)<0,N(L2)<=0),"Slowing","Mixed")))))) -> Slowing | J2: =IF(OR(ISNUMBER(SEARCH("Unemployment",C2)),ISNUMBER(SEARCH("Claims",C2)),ISNUMBER(SEARCH("Jobless",C2)),ISNUMBER(SEARCH("Inventories",C2)),ISNUMBER(SEARCH("Wholesale Inventories",C2)),ISNUMBER(SEARCH("JOLTS Job Openings",C2)),ISNUMBER(SEARCH("Inflation Expectations",C2))),-1,1) -> 1 | K2: =IF(OR(G2="",G2="(NA)"),"",J2*G2) -> -0.5 | L2: =IF(OR(H2="",H2="(NA)"),"",J2*H2) -> -0.3 | N2: 46006 | O2: US 2y | P2: 3.497 | Q2: 3.519 | R2: 3.61 | S2: 3.612 | T2: =IF(OR(P2="",Q2=""),"",P2-Q2) -> -0.022 | U2: =IF(OR(P2="",R2=""),"",P2-R2) -> -0.113 | V2: =IF(OR(P2="",S2=""),"",P2-S2) -> -0.115 | W2: =IF(P2="","",IF(AND(U2>0.03,V2>0),"Rising",IF(AND(U2<-0.03,V2<0),"Falling","Flat"))) -> Falling | X2: =IF(W2="","",IFERROR(VLOOKUP(W2,Macro_Dashboard!$D$5:$E$18,2,FALSE)*1,0)) -> -1 | Z2: =(3.75+4.99)/2 -> 4.37 | AA2: Fed_CurrentRate
A3: 45986 | B3: Growth - US | C3: ADP Weekly Employment Change | D3: -13000 | E3: -2500 | G3: =IF(NOT(ISNUMBER(Table9[[#This Row],[Actual]])),"",IF(NOT(ISNUMBER(Table9[[#This Row],[Forecast]])),"",Table9[[#This Row],[Actual]]-Table9[[#This Row],[Forecast]])) -> -10500 | H3: =IF(NOT(ISNUMBER(Table9[[#This Row],[Actual]])),"",IF(NOT(ISNUMBER(Table9[[#This Row],[Previous]])),"",Table9[[#This Row],[Actual]]-Table9[[#This Row],[Previous]])) | I3: =IF(AND(K3="",L3=""),"N/A",IF(AND(ABS(N(K3))<0.0005,ABS(N(L3))<0.0005),"Stable",IF(AND(L3="",ABS(N(K3))>=0.0005),IF(N(K3)>0,"Accelerating","Slowing"),IF(AND(K3="",ABS(N(L3))>=0.0005),IF(N(L3)>0,"Accelerating","Slowing"),IF(AND(N(K3)>0,N(L3)>=0),"Accelerating",IF(AND(N(K3)<0,N(L3)<=0),"Slowing","Mixed")))))) -> Slowing | J3: =IF(OR(ISNUMBER(SEARCH("Unemployment",C3)),ISNUMBER(SEARCH("Claims",C3)),ISNUMBER(SEARCH("Jobless",C3)),ISNUMBER(SEARCH("Inventories",C3)),ISNUMBER(SEARCH("Wholesale Inventories",C3)),ISNUMBER(SEARCH("JOLTS Job Openings",C3)),ISNUMBER(SEARCH("Inflation Expectations",C3))),-1,1) -> 1 | K3: =IF(OR(G3="",G3="(NA)"),"",J3*G3) -> -10500 | L3: =IF(OR(H3="",H3="(NA)"),"",J3*H3) | N3: 46006 | O3: US 5y | P3: 3.719 | Q3: 3.741 | R3: 3.783 | S3: 3.704 | T3: =IF(OR(P3="",Q3=""),"",P3-Q3) -> -0.022 | U3: =IF(OR(P3="",R3=""),"",P3-R3) -> -0.064 | V3: =IF(OR(P3="",S3=""),"",P3-S3) -> 0.015 | W3: =IF(P3="","",IF(AND(U3>0.03,V3>0),"Rising",IF(AND(U3<-0.03,V3<0),"Falling","Flat"))) -> Flat | X3: =IF(W3="","",IFERROR(VLOOKUP(W3,Macro_Dashboard!$D$5:$E$18,2,FALSE)*1,0)) -> 0 | Z3: 2 | AA3: ECB_CurrentRate
A4: 45986 | B4: Growth - US | C4: Core Retail Sales m/m | D4: 0.003 | E4: 0.003 | F4: 0.006 | G4: =IF(NOT(ISNUMBER(Table9[[#This Row],[Actual]])),"",IF(NOT(ISNUMBER(Table9[[#This Row],[Forecast]])),"",Table9[[#This Row],[Actual]]-Table9[[#This Row],[Forecast]])) -> 0 | H4: =IF(NOT(ISNUMBER(Table9[[#This Row],[Actual]])),"",IF(NOT(ISNUMBER(Table9[[#This Row],[Previous]])),"",Table9[[#This Row],[Actual]]-Table9[[#This Row],[Previous]])) -> -0.003 | I4: =IF(AND(K4="",L4=""),"N/A",IF(AND(ABS(N(K4))<0.0005,ABS(N(L4))<0.0005),"Stable",IF(AND(L4="",ABS(N(K4))>=0.0005),IF(N(K4)>0,"Accelerating","Slowing"),IF(AND(K4="",ABS(N(L4))>=0.0005),IF(N(L4)>0,"Accelerating","Slowing"),IF(AND(N(K4)>0,N(L4)>=0),"Accelerating",IF(AND(N(K4)<0,N(L4)<=0),"Slowing","Mixed")))))) -> Mixed | J4: =IF(OR(ISNUMBER(SEARCH("Unemployment",C4)),ISNUMBER(SEARCH("Claims",C4)),ISNUMBER(SEARCH("Jobless",C4)),ISNUMBER(SEARCH("Inventories",C4)),ISNUMBER(SEARCH("Wholesale Inventories",C4)),ISNUMBER(SEARCH("JOLTS Job Openings",C4)),ISNUMBER(SEARCH("Inflation Expectations",C4))),-1,1) -> 1 | K4: =IF(OR(G4="",G4="(NA)"),"",J4*G4) -> 0 | L4: =IF(OR(H4="",H4="(NA)"),"",J4*H4) -> -0.003 | N4: 46006 | O4: US 10y | P4: 4.168 | Q4: 4.183 | R4: 4.188 | S4: 4.116 | T4: =IF(OR(P4="",Q4=""),"",P4-Q4) -> -0.015 | U4: =IF(OR(P4="",R4=""),"",P4-R4) -> -0.02 | V4: =IF(OR(P4="",S4=""),"",P4-S4) -> 0.052 | W4: =IF(P4="","",IF(AND(U4>0.03,V4>0),"Rising",IF(AND(U4<-0.03,V4<0),"Falling","Flat"))) -> Flat | X4: =IF(W4="","",IFERROR(VLOOKUP(W4,Macro_Dashboard!$D$5:$E$18,2,FALSE)*1,0)) -> 0 | Z4: 0 | AA4: JPY_CurrentRate
A5: 45986 | B5: Growth - US | C5: Retail Sales m/m | D5: 0.002 | E5: 0.004 | F5: -0.001 | G5: =IF(NOT(ISNUMBER(Table9[[#This Row],[Actual]])),"",IF(NOT(ISNUMBER(Table9[[#This Row],[Forecast]])),"",Table9[[#This Row],[Actual]]-Table9[[#This Row],[Forecast]])) -> -0.002 | H5: =IF(NOT(ISNUMBER(Table9[[#This Row],[Actual]])),"",IF(NOT(ISNUMBER(Table9[[#This Row],[Previous]])),"",Table9[[#This Row],[Actual]]-Table9[[#This Row],[Previous]])) -> 0.003 | I5: =IF(AND(K5="",L5=""),"N/A",IF(AND(ABS(N(K5))<0.0005,ABS(N(L5))<0.0005),"Stable",IF(AND(L5="",ABS(N(K5))>=0.0005),IF(N(K5)>0,"Accelerating","Slowing"),IF(AND(K5="",ABS(N(L5))>=0.0005),IF(N(L5)>0,"Accelerating","Slowing"),IF(AND(N(K5)>0,N(L5)>=0),"Accelerating",IF(AND(N(K5)<0,N(L5)<=0),"Slowing","Mixed")))))) -> Mixed | J5: =IF(OR(ISNUMBER(SEARCH("Unemployment",C5)),ISNUMBER(SEARCH("Claims",C5)),ISNUMBER(SEARCH("Jobless",C5)),ISNUMBER(SEARCH("Inventories",C5)),ISNUMBER(SEARCH("Wholesale Inventories",C5)),ISNUMBER(SEARCH("JOLTS Job Openings",C5)),ISNUMBER(SEARCH("Inflation Expectations",C5))),-1,1) -> 1 | K5: =IF(OR(G5="",G5="(NA)"),"",J5*G5) -> -0.002 | L5: =IF(OR(H5="",H5="(NA)"),"",J5*H5) -> 0.003 | N5: 46006 | O5: US 30y | P5: 4.844 | Q5: 4.58 | R5: 4.808 | S5: 4.753 | T5: =IF(OR(P5="",Q5=""),"",P5-Q5) -> 0.264 | U5: =IF(OR(P5="",R5=""),"",P5-R5) -> 0.036 | V5: =IF(OR(P5="",S5=""),"",P5-S5) -> 0.091 | W5: =IF(P5="","",IF(AND(U5>0.03,V5>0),"Rising",IF(AND(U5<-0.03,V5<0),"Falling","Flat"))) -> Rising | X5: =IF(W5="","",IFERROR(VLOOKUP(W5,Macro_Dashboard!$D$5:$E$18,2,FALSE)*1,0)) -> 1
A6: 45986 | B6: Growth - US | C6: CB Consumer Confidence | D6: 88.7 | E6: 93.4 | F6: 95.5 | G6: =IF(NOT(ISNUMBER(Table9[[#This Row],[Actual]])),"",IF(NOT(ISNUMBER(Table9[[#This Row],[Forecast]])),"",Table9[[#This Row],[Actual]]-Table9[[#This Row],[Forecast]])) -> -4.7 | H6: =IF(NOT(ISNUMBER(Table9[[#This Row],[Actual]])),"",IF(NOT(ISNUMBER(Table9[[#This Row],[Previous]])),"",Table9[[#This Row],[Actual]]-Table9[[#This Row],[Previous]])) -> -6.8 | I6: =IF(AND(K6="",L6=""),"N/A",IF(AND(ABS(N(K6))<0.0005,ABS(N(L6))<0.0005),"Stable",IF(AND(L6="",ABS(N(K6))>=0.0005),IF(N(K6)>0,"Accelerating","Slowing"),IF(AND(K6="",ABS(N(L6))>=0.0005),IF(N(L6)>0,"Accelerating","Slowing"),IF(AND(N(K6)>0,N(L6)>=0),"Accelerating",IF(AND(N(K6)<0,N(L6)<=0),"Slowing","Mixed")))))) -> Slowing | J6: =IF(OR(ISNUMBER(SEARCH("Unemployment",C6)),ISNUMBER(SEARCH("Claims",C6)),ISNUMBER(SEARCH("Jobless",C6)),ISNUMBER(SEARCH("Inventories",C6)),ISNUMBER(SEARCH("Wholesale Inventories",C6)),ISNUMBER(SEARCH("JOLTS Job Openings",C6)),ISNUMBER(SEARCH("Inflation Expectations",C6))),-1,1) -> 1 | K6: =IF(OR(G6="",G6="(NA)"),"",J6*G6) -> -4.7 | L6: =IF(OR(H6="",H6="(NA)"),"",J6*H6) -> -6.8 | N6: Date | O6: Tenor | P6: today's yield | Q6: yield 1 trading day ago | R6: yield 5 trading day ago | S6: yield 20 trading day ago | T6: Δd (1d) | U6: Δ5d | V6: Δ20d | W6: Trend | X6: TrendScore
A7: 45986 | B7: Inflation – US | C7: Core PPI m/m | D7: 0.001 | E7: 0.002 | F7: -0.001 | G7: =IF(NOT(ISNUMBER(Table9[[#This Row],[Actual]])),"",IF(NOT(ISNUMBER(Table9[[#This Row],[Forecast]])),"",Table9[[#This Row],[Actual]]-Table9[[#This Row],[Forecast]])) -> -0.001 | H7: =IF(NOT(ISNUMBER(Table9[[#This Row],[Actual]])),"",IF(NOT(ISNUMBER(Table9[[#This Row],[Previous]])),"",Table9[[#This Row],[Actual]]-Table9[[#This Row],[Previous]])) -> 0.002 | I7: =IF(AND(K7="",L7=""),"N/A",IF(AND(ABS(N(K7))<0.0005,ABS(N(L7))<0.0005),"Stable",IF(AND(L7="",ABS(N(K7))>=0.0005),IF(N(K7)>0,"Accelerating","Slowing"),IF(AND(K7="",ABS(N(L7))>=0.0005),IF(N(L7)>0,"Accelerating","Slowing"),IF(AND(N(K7)>0,N(L7)>=0),"Accelerating",IF(AND(N(K7)<0,N(L7)<=0),"Slowing","Mixed")))))) -> Mixed | J7: =IF(OR(ISNUMBER(SEARCH("Unemployment",C7)),ISNUMBER(SEARCH("Claims",C7)),ISNUMBER(SEARCH("Jobless",C7)),ISNUMBER(SEARCH("Inventories",C7)),ISNUMBER(SEARCH("Wholesale Inventories",C7)),ISNUMBER(SEARCH("JOLTS Job Openings",C7)),ISNUMBER(SEARCH("Inflation Expectations",C7))),-1,1) -> 1 | K7: =IF(OR(G7="",G7="(NA)"),"",J7*G7) -> -0.001 | L7: =IF(OR(H7="",H7="(NA)"),"",J7*H7) -> 0.002 | N7: 46006 | O7: US 2s10s | P7: =IF(OR(P2="",P4=""),"",P4-P2) -> 0.671 | Q7: =IF(OR(Q2="",Q4=""),"",Q4-Q2) -> 0.664 | R7: =IF(OR(R2="",R4=""),"",R4-R2) -> 0.578 | S7: =IF(OR(S2="",S4=""),"",S4-S2) -> 0.504 | T7: =IF(OR(P7="",Q7=""),"",P7-Q7) -> 0.007 | U7: =IF(OR(P7="",R7=""),"",P7-R7) -> 0.093 | V7: =IF(OR(P7="",S7=""),"",P7-S7) -> 0.167 | W7: =IF(P7="","",IF(AND(U7>0.03,V7>0),"Rising",IF(AND(U7<-0.03,V7<0),"Falling","Flat"))) -> Rising | X7: =IF(W7="","",IFERROR(VLOOKUP(W7,Macro_Dashboard!$D$5:$E$18,2,FALSE)*1,0)) -> 1
A8: 45987 | B8: Growth - US | C8: Core Durable Goods Orders m/m | D8: 0.006 | E8: 0.002 | F8: 0.003 | G8: =IF(NOT(ISNUMBER(Table9[[#This Row],[Actual]])),"",IF(NOT(ISNUMBER(Table9[[#This Row],[Forecast]])),"",Table9[[#This Row],[Actual]]-Table9[[#This Row],[Forecast]])) -> 0.004 | H8: =IF(NOT(ISNUMBER(Table9[[#This Row],[Actual]])),"",IF(NOT(ISNUMBER(Table9[[#This Row],[Previous]])),"",Table9[[#This Row],[Actual]]-Table9[[#This Row],[Previous]])) -> 0.003 | I8: =IF(AND(K8="",L8=""),"N/A",IF(AND(ABS(N(K8))<0.0005,ABS(N(L8))<0.0005),"Stable",IF(AND(L8="",ABS(N(K8))>=0.0005),IF(N(K8)>0,"Accelerating","Slowing"),IF(AND(K8="",ABS(N(L8))>=0.0005),IF(N(L8)>0,"Accelerating","Slowing"),IF(AND(N(K8)>0,N(L8)>=0),"Accelerating",IF(AND(N(K8)<0,N(L8)<=0),"Slowing","Mixed")))))) -> Accelerating | J8: =IF(OR(ISNUMBER(SEARCH("Unemployment",C8)),ISNUMBER(SEARCH("Claims",C8)),ISNUMBER(SEARCH("Jobless",C8)),ISNUMBER(SEARCH("Inventories",C8)),ISNUMBER(SEARCH("Wholesale Inventories",C8)),ISNUMBER(SEARCH("JOLTS Job Openings",C8)),ISNUMBER(SEARCH("Inflation Expectations",C8))),-1,1) -> 1 | K8: =IF(OR(G8="",G8="(NA)"),"",J8*G8) -> 0.004 | L8: =IF(OR(H8="",H8="(NA)"),"",J8*H8) -> 0.003 | N8: 46006 | O8: US 5s30s | P8: =IF(OR(P3="",P5=""),"",P5-P3) -> 1.125 | Q8: =IF(OR(Q3="",Q5=""),"",Q5-Q3) -> 0.839 | R8: =IF(OR(R3="",R5=""),"",R5-R3) -> 1.025 | S8: =IF(OR(S3="",S5=""),"",S5-S3) -> 1.049 | T8: =IF(OR(P8="",Q8=""),"",P8-Q8) -> 0.286 | U8: =IF(OR(P8="",R8=""),"",P8-R8) -> 0.1 | V8: =IF(OR(P8="",S8=""),"",P8-S8) -> 0.076 | W8: =IF(P8="","",IF(AND(U8>0.03,V8>0),"Rising",IF(AND(U8<-0.03,V8<0),"Falling","Flat"))) -> Rising | X8: =IF(W8="","",IFERROR(VLOOKUP(W8,Macro_Dashboard!$D$5:$E$18,2,FALSE)*1,0)) -> 1
A9: 45987 | B9: Growth - US | C9: Durable Goods Orders m/m | D9: 0.005 | E9: 0.005 | F9: 0.03 | G9: =IF(NOT(ISNUMBER(Table9[[#This Row],[Actual]])),"",IF(NOT(ISNUMBER(Table9[[#This Row],[Forecast]])),"",Table9[[#This Row],[Actual]]-Table9[[#This Row],[Forecast]])) -> 0 | H9: =IF(NOT(ISNUMBER(Table9[[#This Row],[Actual]])),"",IF(NOT(ISNUMBER(Table9[[#This Row],[Previous]])),"",Table9[[#This Row],[Actual]]-Table9[[#This Row],[Previous]])) -> -0.025 | I9: =IF(AND(K9="",L9=""),"N/A",IF(AND(ABS(N(K9))<0.0005,ABS(N(L9))<0.0005),"Stable",IF(AND(L9="",ABS(N(K9))>=0.0005),IF(N(K9)>0,"Accelerating","Slowing"),IF(AND(K9="",ABS(N(L9))>=0.0005),IF(N(L9)>0,"Accelerating","Slowing"),IF(AND(N(K9)>0,N(L9)>=0),"Accelerating",IF(AND(N(K9)<0,N(L9)<=0),"Slowing","Mixed")))))) -> Mixed | J9: =IF(OR(ISNUMBER(SEARCH("Unemployment",C9)),ISNUMBER(SEARCH("Claims",C9)),ISNUMBER(SEARCH("Jobless",C9)),ISNUMBER(SEARCH("Inventories",C9)),ISNUMBER(SEARCH("Wholesale Inventories",C9)),ISNUMBER(SEARCH("JOLTS Job Openings",C9)),ISNUMBER(SEARCH("Inflation Expectations",C9))),-1,1) -> 1 | K9: =IF(OR(G9="",G9="(NA)"),"",J9*G9) -> 0 | L9: =IF(OR(H9="",H9="(NA)"),"",J9*H9) -> -0.025
A10: 45987 | B10: Labour – US | C10: Unemployment Claims | D10: 216000 | E10: 226000 | F10: 222000 | G10: =IF(NOT(ISNUMBER(Table9[[#This Row],[Actual]])),"",IF(NOT(ISNUMBER(Table9[[#This Row],[Forecast]])),"",Table9[[#This Row],[Actual]]-Table9[[#This Row],[Forecast]])) -> -10000 | H10: =IF(NOT(ISNUMBER(Table9[[#This Row],[Actual]])),"",IF(NOT(ISNUMBER(Table9[[#This Row],[Previous]])),"",Table9[[#This Row],[Actual]]-Table9[[#This Row],[Previous]])) -> -6000 | I10: =IF(AND(K10="",L10=""),"N/A",IF(AND(ABS(N(K10))<0.0005,ABS(N(L10))<0.0005),"Stable",IF(AND(L10="",ABS(N(K10))>=0.0005),IF(N(K10)>0,"Accelerating","Slowing"),IF(AND(K10="",ABS(N(L10))>=0.0005),IF(N(L10)>0,"Accelerating","Slowing"),IF(AND(N(K10)>0,N(L10)>=0),"Accelerating",IF(AND(N(K10)<0,N(L10)<=0),"Slowing","Mixed")))))) -> Accelerating | J10: =IF(OR(ISNUMBER(SEARCH("Unemployment",C10)),ISNUMBER(SEARCH("Claims",C10)),ISNUMBER(SEARCH("Jobless",C10)),ISNUMBER(SEARCH("Inventories",C10)),ISNUMBER(SEARCH("Wholesale Inventories",C10)),ISNUMBER(SEARCH("JOLTS Job Openings",C10)),ISNUMBER(SEARCH("Inflation Expectations",C10))),-1,1) -> -1 | K10: =IF(OR(G10="",G10="(NA)"),"",J10*G10) -> 10000 | L10: =IF(OR(H10="",H10="(NA)"),"",J10*H10) -> 6000 | N10: Date | O10: Tenor | P10: today's yield | Q10: yield 1 trading day ago | R10: yield 5 trading day ago | S10: yield 20 trading day ago | T10: Δd (1d) | U10: Δ5d | V10: Δ20d | W10: Trend | X10: TrendScore
A11: 45988 | B11: Growth - EUR | C11: German GfK Consumer Climate | D11: -23.2 | E11: -23.6 | F11: -24.1 | G11: =IF(NOT(ISNUMBER(Table9[[#This Row],[Actual]])),"",IF(NOT(ISNUMBER(Table9[[#This Row],[Forecast]])),"",Table9[[#This Row],[Actual]]-Table9[[#This Row],[Forecast]])) -> 0.4 | H11: =IF(NOT(ISNUMBER(Table9[[#This Row],[Actual]])),"",IF(NOT(ISNUMBER(Table9[[#This Row],[Previous]])),"",Table9[[#This Row],[Actual]]-Table9[[#This Row],[Previous]])) -> 0.9 | I11: =IF(AND(K11="",L11=""),"N/A",IF(AND(ABS(N(K11))<0.0005,ABS(N(L11))<0.0005),"Stable",IF(AND(L11="",ABS(N(K11))>=0.0005),IF(N(K11)>0,"Accelerating","Slowing"),IF(AND(K11="",ABS(N(L11))>=0.0005),IF(N(L11)>0,"Accelerating","Slowing"),IF(AND(N(K11)>0,N(L11)>=0),"Accelerating",IF(AND(N(K11)<0,N(L11)<=0),"Slowing","Mixed")))))) -> Accelerating | J11: =IF(OR(ISNUMBER(SEARCH("Unemployment",C11)),ISNUMBER(SEARCH("Claims",C11)),ISNUMBER(SEARCH("Jobless",C11)),ISNUMBER(SEARCH("Inventories",C11)),ISNUMBER(SEARCH("Wholesale Inventories",C11)),ISNUMBER(SEARCH("JOLTS Job Openings",C11)),ISNUMBER(SEARCH("Inflation Expectations",C11))),-1,1) -> 1 | K11: =IF(OR(G11="",G11="(NA)"),"",J11*G11) -> 0.4 | L11: =IF(OR(H11="",H11="(NA)"),"",J11*H11) -> 0.9 | N11: 46006 | O11: DE 2y | T11: =IF(OR(P11="",Q11=""),"",P11-Q11) | U11: =IF(OR(P11="",R11=""),"",P11-R11) | V11: =IF(OR(P11="",S11=""),"",P11-S11) | W11: =IF(P11="","",IF(AND(U11>0.03,V11>0),"Rising",IF(AND(U11<-0.03,V11<0),"Falling","Flat")))
A12: 45989 | B12: Inflation – EUR | C12: German Prelim CPI m/m | D12: 0.002 | E12: 0 | F12: 0.003 | G12: =IF(NOT(ISNUMBER(Table9[[#This Row],[Actual]])),"",IF(NOT(ISNUMBER(Table9[[#This Row],[Forecast]])),"",Table9[[#This Row],[Actual]]-Table9[[#This Row],[Forecast]])) -> 0.002 | H12: =IF(NOT(ISNUMBER(Table9[[#This Row],[Actual]])),"",IF(NOT(ISNUMBER(Table9[[#This Row],[Previous]])),"",Table9[[#This Row],[Actual]]-Table9[[#This Row],[Previous]])) -> -0.001 | I12: =IF(AND(K12="",L12=""),"N/A",IF(AND(ABS(N(K12))<0.0005,ABS(N(L12))<0.0005),"Stable",IF(AND(L12="",ABS(N(K12))>=0.0005),IF(N(K12)>0,"Accelerating","Slowing"),IF(AND(K12="",ABS(N(L12))>=0.0005),IF(N(L12)>0,"Accelerating","Slowing"),IF(AND(N(K12)>0,N(L12)>=0),"Accelerating",IF(AND(N(K12)<0,N(L12)<=0),"Slowing","Mixed")))))) -> Mixed | J12: =IF(OR(ISNUMBER(SEARCH("Unemployment",C12)),ISNUMBER(SEARCH("Claims",C12)),ISNUMBER(SEARCH("Jobless",C12)),ISNUMBER(SEARCH("Inventories",C12)),ISNUMBER(SEARCH("Wholesale Inventories",C12)),ISNUMBER(SEARCH("JOLTS Job Openings",C12)),ISNUMBER(SEARCH("Inflation Expectations",C12))),-1,1) -> 1 | K12: =IF(OR(G12="",G12="(NA)"),"",J12*G12) -> 0.002 | L12: =IF(OR(H12="",H12="(NA)"),"",J12*H12) -> -0.001 | N12: 46006 | O12: DE 5y | T12: =IF(OR(P12="",Q12=""),"",P12-Q12) | U12: =IF(OR(P12="",R12=""),"",P12-R12) | V12: =IF(OR(P12="",S12=""),"",P12-S12) | W12: =IF(P12="","",IF(AND(U12>0.03,V12>0),"Rising",IF(AND(U12<-0.03,V12<0),"Falling","Flat")))
A13: 45989 | B13: Labour – EUR | C13: German Unemployment Change | D13: 1000 | E13: 4000 | F13: -2000 | G13: =IF(NOT(ISNUMBER(Table9[[#This Row],[Actual]])),"",IF(NOT(ISNUMBER(Table9[[#This Row],[Forecast]])),"",Table9[[#This Row],[Actual]]-Table9[[#This Row],[Forecast]])) -> -3000 | H13: =IF(NOT(ISNUMBER(Table9[[#This Row],[Actual]])),"",IF(NOT(ISNUMBER(Table9[[#This Row],[Previous]])),"",Table9[[#This Row],[Actual]]-Table9[[#This Row],[Previous]])) -> 3000 | I13: =IF(AND(K13="",L13=""),"N/A",IF(AND(ABS(N(K13))<0.0005,ABS(N(L13))<0.0005),"Stable",IF(AND(L13="",ABS(N(K13))>=0.0005),IF(N(K13)>0,"Accelerating","Slowing"),IF(AND(K13="",ABS(N(L13))>=0.0005),IF(N(L13)>0,"Accelerating","Slowing"),IF(AND(N(K13)>0,N(L13)>=0),"Accelerating",IF(AND(N(K13)<0,N(L13)<=0),"Slowing","Mixed")))))) -> Mixed | J13: =IF(OR(ISNUMBER(SEARCH("Unemployment",C13)),ISNUMBER(SEARCH("Claims",C13)),ISNUMBER(SEARCH("Jobless",C13)),ISNUMBER(SEARCH("Inventories",C13)),ISNUMBER(SEARCH("Wholesale Inventories",C13)),ISNUMBER(SEARCH("JOLTS Job Openings",C13)),ISNUMBER(SEARCH("Inflation Expectations",C13))),-1,1) -> -1 | K13: =IF(OR(G13="",G13="(NA)"),"",J13*G13) -> 3000 | L13: =IF(OR(H13="",H13="(NA)"),"",J13*H13) -> -3000 | N13: 46006 | O13: DE 10y | T13: =IF(OR(P13="",Q13=""),"",P13-Q13) | U13: =IF(OR(P13="",R13=""),"",P13-R13) | V13: =IF(OR(P13="",S13=""),"",P13-S13) | W13: =IF(P13="","",IF(AND(U13>0.03,V13>0),"Rising",IF(AND(U13<-0.03,V13<0),"Falling","Flat")))
A14: 45992 | B14: Growth - US | C14: Final Manufacturing PMI | D14: 52.2 | E14: 51.9 | F14: 51.9 | G14: =IF(NOT(ISNUMBER(Table9[[#This Row],[Actual]])),"",IF(NOT(ISNUMBER(Table9[[#This Row],[Forecast]])),"",Table9[[#This Row],[Actual]]-Table9[[#This Row],[Forecast]])) -> 0.3 | H14: =IF(NOT(ISNUMBER(Table9[[#This Row],[Actual]])),"",IF(NOT(ISNUMBER(Table9[[#This Row],[Previous]])),"",Table9[[#This Row],[Actual]]-Table9[[#This Row],[Previous]])) -> 0.3 | I14: =IF(AND(K14="",L14=""),"N/A",IF(AND(ABS(N(K14))<0.0005,ABS(N(L14))<0.0005),"Stable",IF(AND(L14="",ABS(N(K14))>=0.0005),IF(N(K14)>0,"Accelerating","Slowing"),IF(AND(K14="",ABS(N(L14))>=0.0005),IF(N(L14)>0,"Accelerating","Slowing"),IF(AND(N(K14)>0,N(L14)>=0),"Accelerating",IF(AND(N(K14)<0,N(L14)<=0),"Slowing","Mixed")))))) -> Accelerating | J14: =IF(OR(ISNUMBER(SEARCH("Unemployment",C14)),ISNUMBER(SEARCH("Claims",C14)),ISNUMBER(SEARCH("Jobless",C14)),ISNUMBER(SEARCH("Inventories",C14)),ISNUMBER(SEARCH("Wholesale Inventories",C14)),ISNUMBER(SEARCH("JOLTS Job Openings",C14)),ISNUMBER(SEARCH("Inflation Expectations",C14))),-1,1) -> 1 | K14: =IF(OR(G14="",G14="(NA)"),"",J14*G14) -> 0.3 | L14: =IF(OR(H14="",H14="(NA)"),"",J14*H14) -> 0.3 | N14: 46006 | O14: DE 30y | T14: =IF(OR(P14="",Q14=""),"",P14-Q14) | U14: =IF(OR(P14="",R14=""),"",P14-R14) | V14: =IF(OR(P14="",S14=""),"",P14-S14) | W14: =IF(P14="","",IF(AND(U14>0.03,V14>0),"Rising",IF(AND(U14<-0.03,V14<0),"Falling","Flat")))
A15: 45992 | B15: Growth - US | C15: ISM Manufacturing Prices | D15: 58.5 | E15: 59.5 | F15: 58 | G15: =IF(NOT(ISNUMBER(Table9[[#This Row],[Actual]])),"",IF(NOT(ISNUMBER(Table9[[#This Row],[Forecast]])),"",Table9[[#This Row],[Actual]]-Table9[[#This Row],[Forecast]])) -> -1 | H15: =IF(NOT(ISNUMBER(Table9[[#This Row],[Actual]])),"",IF(NOT(ISNUMBER(Table9[[#This Row],[Previous]])),"",Table9[[#This Row],[Actual]]-Table9[[#This Row],[Previous]])) -> 0.5 | I15: =IF(AND(K15="",L15=""),"N/A",IF(AND(ABS(N(K15))<0.0005,ABS(N(L15))<0.0005),"Stable",IF(AND(L15="",ABS(N(K15))>=0.0005),IF(N(K15)>0,"Accelerating","Slowing"),IF(AND(K15="",ABS(N(L15))>=0.0005),IF(N(L15)>0,"Accelerating","Slowing"),IF(AND(N(K15)>0,N(L15)>=0),"Accelerating",IF(AND(N(K15)<0,N(L15)<=0),"Slowing","Mixed")))))) -> Mixed | J15: =IF(OR(ISNUMBER(SEARCH("Unemployment",C15)),ISNUMBER(SEARCH("Claims",C15)),ISNUMBER(SEARCH("Jobless",C15)),ISNUMBER(SEARCH("Inventories",C15)),ISNUMBER(SEARCH("Wholesale Inventories",C15)),ISNUMBER(SEARCH("JOLTS Job Openings",C15)),ISNUMBER(SEARCH("Inflation Expectations",C15))),-1,1) -> 1 | K15: =IF(OR(G15="",G15="(NA)"),"",J15*G15) -> -1 | L15: =IF(OR(H15="",H15="(NA)"),"",J15*H15) -> 0.5 | N15: Date | O15: Tenor | P15: today's yield | Q15: yield 1 trading day ago | R15: yield 5 trading day ago | S15: yield 20 trading day ago | T15: Δd (1d) | U15: Δ5d | V15: Δ20d | W15: Trend | X15: TrendScore
A16: 45992 | B16: Growth - US | C16: ISM Manufacturing PMI | D16: 48.2 | E16: 49 | F16: 48.7 | G16: =IF(NOT(ISNUMBER(Table9[[#This Row],[Actual]])),"",IF(NOT(ISNUMBER(Table9[[#This Row],[Forecast]])),"",Table9[[#This Row],[Actual]]-Table9[[#This Row],[Forecast]])) -> -0.8 | H16: =IF(NOT(ISNUMBER(Table9[[#This Row],[Actual]])),"",IF(NOT(ISNUMBER(Table9[[#This Row],[Previous]])),"",Table9[[#This Row],[Actual]]-Table9[[#This Row],[Previous]])) -> -0.5 | I16: =IF(AND(K16="",L16=""),"N/A",IF(AND(ABS(N(K16))<0.0005,ABS(N(L16))<0.0005),"Stable",IF(AND(L16="",ABS(N(K16))>=0.0005),IF(N(K16)>0,"Accelerating","Slowing"),IF(AND(K16="",ABS(N(L16))>=0.0005),IF(N(L16)>0,"Accelerating","Slowing"),IF(AND(N(K16)>0,N(L16)>=0),"Accelerating",IF(AND(N(K16)<0,N(L16)<=0),"Slowing","Mixed")))))) -> Slowing | J16: =IF(OR(ISNUMBER(SEARCH("Unemployment",C16)),ISNUMBER(SEARCH("Claims",C16)),ISNUMBER(SEARCH("Jobless",C16)),ISNUMBER(SEARCH("Inventories",C16)),ISNUMBER(SEARCH("Wholesale Inventories",C16)),ISNUMBER(SEARCH("JOLTS Job Openings",C16)),ISNUMBER(SEARCH("Inflation Expectations",C16))),-1,1) -> 1 | K16: =IF(OR(G16="",G16="(NA)"),"",J16*G16) -> -0.8 | L16: =IF(OR(H16="",H16="(NA)"),"",J16*H16) -> -0.5 | N16: 46006 | O16: DE 2s10s | P16: =IF(OR(P11="",P13=""),"",(P13-P11)*100) | Q16: =IF(OR(Q11="",Q13=""),"",(Q13-Q11)*100) | R16: =IF(OR(R11="",R13=""),"",(R13-R11)*100) | S16: =IF(OR(S11="",S13=""),"",(S13-S11)*100) | T16: =IF(OR(P16="",Q16=""),"",P16-Q16) | U16: =IF(OR(P16="",R16=""),"",P16-R16) | V16: =IF(OR(P16="",S16=""),"",P16-S16) | W16: =IF(P16="","",IF(AND(U16>3,V16>0),"Rising",IF(AND(U16<-3,V16<0),"Falling","Flat")))
A17: 45992 | B17: Growth - US | C17: Final Manufacturing PMI | D17: 52.2 | E17: 51.9 | F17: 51.9 | G17: =IF(NOT(ISNUMBER(Table9[[#This Row],[Actual]])),"",IF(NOT(ISNUMBER(Table9[[#This Row],[Forecast]])),"",Table9[[#This Row],[Actual]]-Table9[[#This Row],[Forecast]])) -> 0.3 | H17: =IF(NOT(ISNUMBER(Table9[[#This Row],[Actual]])),"",IF(NOT(ISNUMBER(Table9[[#This Row],[Previous]])),"",Table9[[#This Row],[Actual]]-Table9[[#This Row],[Previous]])) -> 0.3 | I17: =IF(AND(K17="",L17=""),"N/A",IF(AND(ABS(N(K17))<0.0005,ABS(N(L17))<0.0005),"Stable",IF(AND(L17="",ABS(N(K17))>=0.0005),IF(N(K17)>0,"Accelerating","Slowing"),IF(AND(K17="",ABS(N(L17))>=0.0005),IF(N(L17)>0,"Accelerating","Slowing"),IF(AND(N(K17)>0,N(L17)>=0),"Accelerating",IF(AND(N(K17)<0,N(L17)<=0),"Slowing","Mixed")))))) -> Accelerating | J17: =IF(OR(ISNUMBER(SEARCH("Unemployment",C17)),ISNUMBER(SEARCH("Claims",C17)),ISNUMBER(SEARCH("Jobless",C17)),ISNUMBER(SEARCH("Inventories",C17)),ISNUMBER(SEARCH("Wholesale Inventories",C17)),ISNUMBER(SEARCH("JOLTS Job Openings",C17)),ISNUMBER(SEARCH("Inflation Expectations",C17))),-1,1) -> 1 | K17: =IF(OR(G17="",G17="(NA)"),"",J17*G17) -> 0.3 | L17: =IF(OR(H17="",H17="(NA)"),"",J17*H17) -> 0.3 | N17: 46006 | O17: DE 5s30s | P17: =IF(OR(P12="",P14=""),"",(P14-P12)*100) | Q17: =IF(OR(Q12="",Q14=""),"",(Q14-Q12)*100) | R17: =IF(OR(R12="",R14=""),"",(R14-R12)*100) | S17: =IF(OR(S12="",S14=""),"",(S14-S12)*100) | T17: =IF(OR(P17="",Q17=""),"",P17-Q17) | U17: =IF(OR(P17="",R17=""),"",P17-R17) | V17: =IF(OR(P17="",S17=""),"",P17-S17) | W17: =IF(P17="","",IF(AND(U17>3,V17>0),"Rising",IF(AND(U17<-3,V17<0),"Falling","Flat")))
A18: 45992 | B18: Growth - US | C18: ISM Manufacturing Prices | D18: 58.5 | E18: 59.5 | F18: 58 | G18: =IF(NOT(ISNUMBER(Table9[[#This Row],[Actual]])),"",IF(NOT(ISNUMBER(Table9[[#This Row],[Forecast]])),"",Table9[[#This Row],[Actual]]-Table9[[#This Row],[Forecast]])) -> -1 | H18: =IF(NOT(ISNUMBER(Table9[[#This Row],[Actual]])),"",IF(NOT(ISNUMBER(Table9[[#This Row],[Previous]])),"",Table9[[#This Row],[Actual]]-Table9[[#This Row],[Previous]])) -> 0.5 | I18: =IF(AND(K18="",L18=""),"N/A",IF(AND(ABS(N(K18))<0.0005,ABS(N(L18))<0.0005),"Stable",IF(AND(L18="",ABS(N(K18))>=0.0005),IF(N(K18)>0,"Accelerating","Slowing"),IF(AND(K18="",ABS(N(L18))>=0.0005),IF(N(L18)>0,"Accelerating","Slowing"),IF(AND(N(K18)>0,N(L18)>=0),"Accelerating",IF(AND(N(K18)<0,N(L18)<=0),"Slowing","Mixed")))))) -> Mixed | J18: =IF(OR(ISNUMBER(SEARCH("Unemployment",C18)),ISNUMBER(SEARCH("Claims",C18)),ISNUMBER(SEARCH("Jobless",C18)),ISNUMBER(SEARCH("Inventories",C18)),ISNUMBER(SEARCH("Wholesale Inventories",C18)),ISNUMBER(SEARCH("JOLTS Job Openings",C18)),ISNUMBER(SEARCH("Inflation Expectations",C18))),-1,1) -> 1 | K18: =IF(OR(G18="",G18="(NA)"),"",J18*G18) -> -1 | L18: =IF(OR(H18="",H18="(NA)"),"",J18*H18) -> 0.5
A19: 45992 | B19: Growth - US | C19: ISM Manufacturing PMI | D19: 48.2 | E19: 49 | F19: 48.7 | G19: =IF(NOT(ISNUMBER(Table9[[#This Row],[Actual]])),"",IF(NOT(ISNUMBER(Table9[[#This Row],[Forecast]])),"",Table9[[#This Row],[Actual]]-Table9[[#This Row],[Forecast]])) -> -0.8 | H19: =IF(NOT(ISNUMBER(Table9[[#This Row],[Actual]])),"",IF(NOT(ISNUMBER(Table9[[#This Row],[Previous]])),"",Table9[[#This Row],[Actual]]-Table9[[#This Row],[Previous]])) -> -0.5 | I19: =IF(AND(K19="",L19=""),"N/A",IF(AND(ABS(N(K19))<0.0005,ABS(N(L19))<0.0005),"Stable",IF(AND(L19="",ABS(N(K19))>=0.0005),IF(N(K19)>0,"Accelerating","Slowing"),IF(AND(K19="",ABS(N(L19))>=0.0005),IF(N(L19)>0,"Accelerating","Slowing"),IF(AND(N(K19)>0,N(L19)>=0),"Accelerating",IF(AND(N(K19)<0,N(L19)<=0),"Slowing","Mixed")))))) -> Slowing | J19: =IF(OR(ISNUMBER(SEARCH("Unemployment",C19)),ISNUMBER(SEARCH("Claims",C19)),ISNUMBER(SEARCH("Jobless",C19)),ISNUMBER(SEARCH("Inventories",C19)),ISNUMBER(SEARCH("Wholesale Inventories",C19)),ISNUMBER(SEARCH("JOLTS Job Openings",C19)),ISNUMBER(SEARCH("Inflation Expectations",C19))),-1,1) -> 1 | K19: =IF(OR(G19="",G19="(NA)"),"",J19*G19) -> -0.8 | L19: =IF(OR(H19="",H19="(NA)"),"",J19*H19) -> -0.5 | N19: Date | O19: Tenor | P19: today's yield | Q19: yield 1 trading day ago | R19: yield 5 trading day ago | S19: yield 20 trading day ago | T19: Δd (1d) | U19: Δ5d | V19: Δ20d | W19: Trend | X19: TrendScore
A20: 45993 | B20: Growth - US | C20: FOMC Member Bowman Speaks | D20: (NA) | E20: (NA) | F20: (NA) | G20: =IF(NOT(ISNUMBER(Table9[[#This Row],[Actual]])),"",IF(NOT(ISNUMBER(Table9[[#This Row],[Forecast]])),"",Table9[[#This Row],[Actual]]-Table9[[#This Row],[Forecast]])) | H20: =IF(NOT(ISNUMBER(Table9[[#This Row],[Actual]])),"",IF(NOT(ISNUMBER(Table9[[#This Row],[Previous]])),"",Table9[[#This Row],[Actual]]-Table9[[#This Row],[Previous]])) | I20: =IF(AND(K20="",L20=""),"N/A",IF(AND(ABS(N(K20))<0.0005,ABS(N(L20))<0.0005),"Stable",IF(AND(L20="",ABS(N(K20))>=0.0005),IF(N(K20)>0,"Accelerating","Slowing"),IF(AND(K20="",ABS(N(L20))>=0.0005),IF(N(L20)>0,"Accelerating","Slowing"),IF(AND(N(K20)>0,N(L20)>=0),"Accelerating",IF(AND(N(K20)<0,N(L20)<=0),"Slowing","Mixed")))))) -> N/A | J20: =IF(OR(ISNUMBER(SEARCH("Unemployment",C20)),ISNUMBER(SEARCH("Claims",C20)),ISNUMBER(SEARCH("Jobless",C20)),ISNUMBER(SEARCH("Inventories",C20)),ISNUMBER(SEARCH("Wholesale Inventories",C20)),ISNUMBER(SEARCH("JOLTS Job Openings",C20)),ISNUMBER(SEARCH("Inflation Expectations",C20))),-1,1) -> 1 | K20: =IF(OR(G20="",G20="(NA)"),"",J20*G20) | L20: =IF(OR(H20="",H20="(NA)"),"",J20*H20) | N20: 46006 | O20: JP 2y | T20: =IF(OR(P20="",Q20=""),"",P20-Q20) | U20: =IF(OR(P20="",R20=""),"",P20-R20) | V20: =IF(OR(P20="",S20=""),"",P20-S20) | W20: =IF(P20="","",IF(AND(U20>0.03,V20>0),"Rising",IF(AND(U20<-0.03,V20<0),"Falling","Flat")))
A21: 45993 | B21: Growth - US | C21: Import Prices m/m | D21: 0 | E21: 0.001 | F21: 0.001 | G21: =IF(NOT(ISNUMBER(Table9[[#This Row],[Actual]])),"",IF(NOT(ISNUMBER(Table9[[#This Row],[Forecast]])),"",Table9[[#This Row],[Actual]]-Table9[[#This Row],[Forecast]])) -> -0.001 | H21: =IF(NOT(ISNUMBER(Table9[[#This Row],[Actual]])),"",IF(NOT(ISNUMBER(Table9[[#This Row],[Previous]])),"",Table9[[#This Row],[Actual]]-Table9[[#This Row],[Previous]])) -> -0.001 | I21: =IF(AND(K21="",L21=""),"N/A",IF(AND(ABS(N(K21))<0.0005,ABS(N(L21))<0.0005),"Stable",IF(AND(L21="",ABS(N(K21))>=0.0005),IF(N(K21)>0,"Accelerating","Slowing"),IF(AND(K21="",ABS(N(L21))>=0.0005),IF(N(L21)>0,"Accelerating","Slowing"),IF(AND(N(K21)>0,N(L21)>=0),"Accelerating",IF(AND(N(K21)<0,N(L21)<=0),"Slowing","Mixed")))))) -> Slowing | J21: =IF(OR(ISNUMBER(SEARCH("Unemployment",C21)),ISNUMBER(SEARCH("Claims",C21)),ISNUMBER(SEARCH("Jobless",C21)),ISNUMBER(SEARCH("Inventories",C21)),ISNUMBER(SEARCH("Wholesale Inventories",C21)),ISNUMBER(SEARCH("JOLTS Job Openings",C21)),ISNUMBER(SEARCH("Inflation Expectations",C21))),-1,1) -> 1 | K21: =IF(OR(G21="",G21="(NA)"),"",J21*G21) -> -0.001 | L21: =IF(OR(H21="",H21="(NA)"),"",J21*H21) -> -0.001 | N21: 46006 | O21: JP 5y | T21: =IF(OR(P21="",Q21=""),"",P21-Q21) | U21: =IF(OR(P21="",R21=""),"",P21-R21) | V21: =IF(OR(P21="",S21=""),"",P21-S21) | W21: =IF(P21="","",IF(AND(U21>0.03,V21>0),"Rising",IF(AND(U21<-0.03,V21<0),"Falling","Flat")))
A22: 45993 | B22: Growth - US | C22: Capacity Utilization Rate | D22: 0.759 | E22: 0.769 | F22: 0.759 | G22: =IF(NOT(ISNUMBER(Table9[[#This Row],[Actual]])),"",IF(NOT(ISNUMBER(Table9[[#This Row],[Forecast]])),"",Table9[[#This Row],[Actual]]-Table9[[#This Row],[Forecast]])) -> -0.01 | H22: =IF(NOT(ISNUMBER(Table9[[#This Row],[Actual]])),"",IF(NOT(ISNUMBER(Table9[[#This Row],[Previous]])),"",Table9[[#This Row],[Actual]]-Table9[[#This Row],[Previous]])) -> 0 | I22: =IF(AND(K22="",L22=""),"N/A",IF(AND(ABS(N(K22))<0.0005,ABS(N(L22))<0.0005),"Stable",IF(AND(L22="",ABS(N(K22))>=0.0005),IF(N(K22)>0,"Accelerating","Slowing"),IF(AND(K22="",ABS(N(L22))>=0.0005),IF(N(L22)>0,"Accelerating","Slowing"),IF(AND(N(K22)>0,N(L22)>=0),"Accelerating",IF(AND(N(K22)<0,N(L22)<=0),"Slowing","Mixed")))))) -> Slowing | J22: =IF(OR(ISNUMBER(SEARCH("Unemployment",C22)),ISNUMBER(SEARCH("Claims",C22)),ISNUMBER(SEARCH("Jobless",C22)),ISNUMBER(SEARCH("Inventories",C22)),ISNUMBER(SEARCH("Wholesale Inventories",C22)),ISNUMBER(SEARCH("JOLTS Job Openings",C22)),ISNUMBER(SEARCH("Inflation Expectations",C22))),-1,1) -> 1 | K22: =IF(OR(G22="",G22="(NA)"),"",J22*G22) -> -0.01 | L22: =IF(OR(H22="",H22="(NA)"),"",J22*H22) -> 0 | N22: 46006 | O22: JP 10y | T22: =IF(OR(P22="",Q22=""),"",P22-Q22) | U22: =IF(OR(P22="",R22=""),"",P22-R22) | V22: =IF(OR(P22="",S22=""),"",P22-S22) | W22: =IF(P22="","",IF(AND(U22>0.03,V22>0),"Rising",IF(AND(U22<-0.03,V22<0),"Falling","Flat")))
A23: 45993 | B23: Growth - US | C23: ISM Services PMI | D23: 52.6 | E23: 52 | F23: 52.4 | G23: =IF(NOT(ISNUMBER(Table9[[#This Row],[Actual]])),"",IF(NOT(ISNUMBER(Table9[[#This Row],[Forecast]])),"",Table9[[#This Row],[Actual]]-Table9[[#This Row],[Forecast]])) -> 0.6 | H23: =IF(NOT(ISNUMBER(Table9[[#This Row],[Actual]])),"",IF(NOT(ISNUMBER(Table9[[#This Row],[Previous]])),"",Table9[[#This Row],[Actual]]-Table9[[#This Row],[Previous]])) -> 0.2 | I23: =IF(AND(K23="",L23=""),"N/A",IF(AND(ABS(N(K23))<0.0005,ABS(N(L23))<0.0005),"Stable",IF(AND(L23="",ABS(N(K23))>=0.0005),IF(N(K23)>0,"Accelerating","Slowing"),IF(AND(K23="",ABS(N(L23))>=0.0005),IF(N(L23)>0,"Accelerating","Slowing"),IF(AND(N(K23)>0,N(L23)>=0),"Accelerating",IF(AND(N(K23)<0,N(L23)<=0),"Slowing","Mixed")))))) -> Accelerating | J23: =IF(OR(ISNUMBER(SEARCH("Unemployment",C23)),ISNUMBER(SEARCH("Claims",C23)),ISNUMBER(SEARCH("Jobless",C23)),ISNUMBER(SEARCH("Inventories",C23)),ISNUMBER(SEARCH("Wholesale Inventories",C23)),ISNUMBER(SEARCH("JOLTS Job Openings",C23)),ISNUMBER(SEARCH("Inflation Expectations",C23))),-1,1) -> 1 | K23: =IF(OR(G23="",G23="(NA)"),"",J23*G23) -> 0.6 | L23: =IF(OR(H23="",H23="(NA)"),"",J23*H23) -> 0.2 | N23: 46006 | O23: JP 30y | T23: =IF(OR(P23="",Q23=""),"",P23-Q23) | U23: =IF(OR(P23="",R23=""),"",P23-R23) | V23: =IF(OR(P23="",S23=""),"",P23-S23) | W23: =IF(P23="","",IF(AND(U23>0.03,V23>0),"Rising",IF(AND(U23<-0.03,V23<0),"Falling","Flat")))
A24: 45995 | B24: Growth - US | C24: Factory Orders m/m | D24: 0.002 | E24: 0.003 | F24: -0.03 | G24: =IF(NOT(ISNUMBER(Table9[[#This Row],[Actual]])),"",IF(NOT(ISNUMBER(Table9[[#This Row],[Forecast]])),"",Table9[[#This Row],[Actual]]-Table9[[#This Row],[Forecast]])) -> -0.001 | H24: =IF(NOT(ISNUMBER(Table9[[#This Row],[Actual]])),"",IF(NOT(ISNUMBER(Table9[[#This Row],[Previous]])),"",Table9[[#This Row],[Actual]]-Table9[[#This Row],[Previous]])) -> 0.032 | I24: =IF(AND(K24="",L24=""),"N/A",IF(AND(ABS(N(K24))<0.0005,ABS(N(L24))<0.0005),"Stable",IF(AND(L24="",ABS(N(K24))>=0.0005),IF(N(K24)>0,"Accelerating","Slowing"),IF(AND(K24="",ABS(N(L24))>=0.0005),IF(N(L24)>0,"Accelerating","Slowing"),IF(AND(N(K24)>0,N(L24)>=0),"Accelerating",IF(AND(N(K24)<0,N(L24)<=0),"Slowing","Mixed")))))) -> Mixed | J24: =IF(OR(ISNUMBER(SEARCH("Unemployment",C24)),ISNUMBER(SEARCH("Claims",C24)),ISNUMBER(SEARCH("Jobless",C24)),ISNUMBER(SEARCH("Inventories",C24)),ISNUMBER(SEARCH("Wholesale Inventories",C24)),ISNUMBER(SEARCH("JOLTS Job Openings",C24)),ISNUMBER(SEARCH("Inflation Expectations",C24))),-1,1) -> 1 | K24: =IF(OR(G24="",G24="(NA)"),"",J24*G24) -> -0.001 | L24: =IF(OR(H24="",H24="(NA)"),"",J24*H24) -> 0.032 | N24: Date | O24: Tenor | P24: today's yield | Q24: yield 1 trading day ago | R24: yield 5 trading day ago | S24: yield 20 trading day ago | T24: Δd (1d) | U24: Δ5d | V24: Δ20d | W24: Trend | X24: TrendScore
A25: 45995 | B25: Labour – US | C25: Unemployment Claims | D25: 191000 | E25: 219000 | F25: 218000 | G25: =IF(NOT(ISNUMBER(Table9[[#This Row],[Actual]])),"",IF(NOT(ISNUMBER(Table9[[#This Row],[Forecast]])),"",Table9[[#This Row],[Actual]]-Table9[[#This Row],[Forecast]])) -> -28000 | H25: =IF(NOT(ISNUMBER(Table9[[#This Row],[Actual]])),"",IF(NOT(ISNUMBER(Table9[[#This Row],[Previous]])),"",Table9[[#This Row],[Actual]]-Table9[[#This Row],[Previous]])) -> -27000 | I25: =IF(AND(K25="",L25=""),"N/A",IF(AND(ABS(N(K25))<0.0005,ABS(N(L25))<0.0005),"Stable",IF(AND(L25="",ABS(N(K25))>=0.0005),IF(N(K25)>0,"Accelerating","Slowing"),IF(AND(K25="",ABS(N(L25))>=0.0005),IF(N(L25)>0,"Accelerating","Slowing"),IF(AND(N(K25)>0,N(L25)>=0),"Accelerating",IF(AND(N(K25)<0,N(L25)<=0),"Slowing","Mixed")))))) -> Accelerating | J25: =IF(OR(ISNUMBER(SEARCH("Unemployment",C25)),ISNUMBER(SEARCH("Claims",C25)),ISNUMBER(SEARCH("Jobless",C25)),ISNUMBER(SEARCH("Inventories",C25)),ISNUMBER(SEARCH("Wholesale Inventories",C25)),ISNUMBER(SEARCH("JOLTS Job Openings",C25)),ISNUMBER(SEARCH("Inflation Expectations",C25))),-1,1) -> -1 | K25: =IF(OR(G25="",G25="(NA)"),"",J25*G25) -> 28000 | L25: =IF(OR(H25="",H25="(NA)"),"",J25*H25) -> 27000 | N25: 46006 | O25: JP 2s10s | P25: =IF(OR(P20="",P22=""),"",(P22-P20)*100) | Q25: =IF(OR(Q20="",Q22=""),"",(Q22-Q20)*100) | R25: =IF(OR(R20="",R22=""),"",(R22-R20)*100) | S25: =IF(OR(S20="",S22=""),"",(S22-S20)*100) | T25: =IF(OR(P25="",Q25=""),"",P25-Q25) | U25: =IF(OR(P25="",R25=""),"",P25-R25) | V25: =IF(OR(P25="",S25=""),"",P25-S25) | W25: =IF(P25="","",IF(AND(U25>3,V25>0),"Rising",IF(AND(U25<-3,V25<0),"Falling","Flat")))
A26: 45996 | B26: Growth - EUR | C26: Italian Retail Sales m/m | D26: 0.005 | E26: 0.004 | F26: -0.004 | G26: =IF(NOT(ISNUMBER(Table9[[#This Row],[Actual]])),"",IF(NOT(ISNUMBER(Table9[[#This Row],[Forecast]])),"",Table9[[#This Row],[Actual]]-Table9[[#This Row],[Forecast]])) -> 0.001 | H26: =IF(NOT(ISNUMBER(Table9[[#This Row],[Actual]])),"",IF(NOT(ISNUMBER(Table9[[#This Row],[Previous]])),"",Table9[[#This Row],[Actual]]-Table9[[#This Row],[Previous]])) -> 0.009 | I26: =IF(AND(K26="",L26=""),"N/A",IF(AND(ABS(N(K26))<0.0005,ABS(N(L26))<0.0005),"Stable",IF(AND(L26="",ABS(N(K26))>=0.0005),IF(N(K26)>0,"Accelerating","Slowing"),IF(AND(K26="",ABS(N(L26))>=0.0005),IF(N(L26)>0,"Accelerating","Slowing"),IF(AND(N(K26)>0,N(L26)>=0),"Accelerating",IF(AND(N(K26)<0,N(L26)<=0),"Slowing","Mixed")))))) -> Accelerating | J26: =IF(OR(ISNUMBER(SEARCH("Unemployment",C26)),ISNUMBER(SEARCH("Claims",C26)),ISNUMBER(SEARCH("Jobless",C26)),ISNUMBER(SEARCH("Inventories",C26)),ISNUMBER(SEARCH("Wholesale Inventories",C26)),ISNUMBER(SEARCH("JOLTS Job Openings",C26)),ISNUMBER(SEARCH("Inflation Expectations",C26))),-1,1) -> 1 | K26: =IF(OR(G26="",G26="(NA)"),"",J26*G26) -> 0.001 | L26: =IF(OR(H26="",H26="(NA)"),"",J26*H26) -> 0.009 | N26: 46006 | O26: JP 5s30s | P26: =IF(OR(P21="",P23=""),"",(P23-P21)*100) | Q26: =IF(OR(Q21="",Q23=""),"",(Q23-Q21)*100) | R26: =IF(OR(R21="",R23=""),"",(R23-R21)*100) | S26: =IF(OR(S21="",S23=""),"",(S23-S21)*100) | T26: =IF(OR(P26="",Q26=""),"",P26-Q26) | U26: =IF(OR(P26="",R26=""),"",P26-R26) | V26: =IF(OR(P26="",S26=""),"",P26-S26) | W26: =IF(P26="","",IF(AND(U26>3,V26>0),"Rising",IF(AND(U26<-3,V26<0),"Falling","Flat")))
A27: 45996 | B27: Growth - EUR | C27: Revised GDP q/q | D27: 0.003 | E27: 0.002 | F27: 0.002 | G27: =IF(NOT(ISNUMBER(Table9[[#This Row],[Actual]])),"",IF(NOT(ISNUMBER(Table9[[#This Row],[Forecast]])),"",Table9[[#This Row],[Actual]]-Table9[[#This Row],[Forecast]])) -> 0.001 | H27: =IF(NOT(ISNUMBER(Table9[[#This Row],[Actual]])),"",IF(NOT(ISNUMBER(Table9[[#This Row],[Previous]])),"",Table9[[#This Row],[Actual]]-Table9[[#This Row],[Previous]])) -> 0.001 | I27: =IF(AND(K27="",L27=""),"N/A",IF(AND(ABS(N(K27))<0.0005,ABS(N(L27))<0.0005),"Stable",IF(AND(L27="",ABS(N(K27))>=0.0005),IF(N(K27)>0,"Accelerating","Slowing"),IF(AND(K27="",ABS(N(L27))>=0.0005),IF(N(L27)>0,"Accelerating","Slowing"),IF(AND(N(K27)>0,N(L27)>=0),"Accelerating",IF(AND(N(K27)<0,N(L27)<=0),"Slowing","Mixed")))))) -> Accelerating | J27: =IF(OR(ISNUMBER(SEARCH("Unemployment",C27)),ISNUMBER(SEARCH("Claims",C27)),ISNUMBER(SEARCH("Jobless",C27)),ISNUMBER(SEARCH("Inventories",C27)),ISNUMBER(SEARCH("Wholesale Inventories",C27)),ISNUMBER(SEARCH("JOLTS Job Openings",C27)),ISNUMBER(SEARCH("Inflation Expectations",C27))),-1,1) -> 1 | K27: =IF(OR(G27="",G27="(NA)"),"",J27*G27) -> 0.001 | L27: =IF(OR(H27="",H27="(NA)"),"",J27*H27) -> 0.001
A28: 45996 | B28: Growth - US | C28: Prelim UoM Consumer Sentiment | D28: 53.3 | E28: 52 | F28: 51 | G28: =IF(NOT(ISNUMBER(Table9[[#This Row],[Actual]])),"",IF(NOT(ISNUMBER(Table9[[#This Row],[Forecast]])),"",Table9[[#This Row],[Actual]]-Table9[[#This Row],[Forecast]])) -> 1.3 | H28: =IF(NOT(ISNUMBER(Table9[[#This Row],[Actual]])),"",IF(NOT(ISNUMBER(Table9[[#This Row],[Previous]])),"",Table9[[#This Row],[Actual]]-Table9[[#This Row],[Previous]])) -> 2.3 | I28: =IF(AND(K28="",L28=""),"N/A",IF(AND(ABS(N(K28))<0.0005,ABS(N(L28))<0.0005),"Stable",IF(AND(L28="",ABS(N(K28))>=0.0005),IF(N(K28)>0,"Accelerating","Slowing"),IF(AND(K28="",ABS(N(L28))>=0.0005),IF(N(L28)>0,"Accelerating","Slowing"),IF(AND(N(K28)>0,N(L28)>=0),"Accelerating",IF(AND(N(K28)<0,N(L28)<=0),"Slowing","Mixed")))))) -> Accelerating | J28: =IF(OR(ISNUMBER(SEARCH("Unemployment",C28)),ISNUMBER(SEARCH("Claims",C28)),ISNUMBER(SEARCH("Jobless",C28)),ISNUMBER(SEARCH("Inventories",C28)),ISNUMBER(SEARCH("Wholesale Inventories",C28)),ISNUMBER(SEARCH("JOLTS Job Openings",C28)),ISNUMBER(SEARCH("Inflation Expectations",C28))),-1,1) -> 1 | K28: =IF(OR(G28="",G28="(NA)"),"",J28*G28) -> 1.3 | L28: =IF(OR(H28="",H28="(NA)"),"",J28*H28) -> 2.3
A29: 45996 | B29: Growth - US | C29: Personal Income m/m | D29: 0.004 | E29: 0.003 | F29: 0.004 | G29: =IF(NOT(ISNUMBER(Table9[[#This Row],[Actual]])),"",IF(NOT(ISNUMBER(Table9[[#This Row],[Forecast]])),"",Table9[[#This Row],[Actual]]-Table9[[#This Row],[Forecast]])) -> 0.001 | H29: =IF(NOT(ISNUMBER(Table9[[#This Row],[Actual]])),"",IF(NOT(ISNUMBER(Table9[[#This Row],[Previous]])),"",Table9[[#This Row],[Actual]]-Table9[[#This Row],[Previous]])) -> 0 | I29: =IF(AND(K29="",L29=""),"N/A",IF(AND(ABS(N(K29))<0.0005,ABS(N(L29))<0.0005),"Stable",IF(AND(L29="",ABS(N(K29))>=0.0005),IF(N(K29)>0,"Accelerating","Slowing"),IF(AND(K29="",ABS(N(L29))>=0.0005),IF(N(L29)>0,"Accelerating","Slowing"),IF(AND(N(K29)>0,N(L29)>=0),"Accelerating",IF(AND(N(K29)<0,N(L29)<=0),"Slowing","Mixed")))))) -> Accelerating | J29: =IF(OR(ISNUMBER(SEARCH("Unemployment",C29)),ISNUMBER(SEARCH("Claims",C29)),ISNUMBER(SEARCH("Jobless",C29)),ISNUMBER(SEARCH("Inventories",C29)),ISNUMBER(SEARCH("Wholesale Inventories",C29)),ISNUMBER(SEARCH("JOLTS Job Openings",C29)),ISNUMBER(SEARCH("Inflation Expectations",C29))),-1,1) -> 1 | K29: =IF(OR(G29="",G29="(NA)"),"",J29*G29) -> 0.001 | L29: =IF(OR(H29="",H29="(NA)"),"",J29*H29) -> 0
A30: 45996 | B30: Growth - US | C30: Personal Spending m/m | D30: 0.003 | E30: 0.003 | F30: 0.005 | G30: =IF(NOT(ISNUMBER(Table9[[#This Row],[Actual]])),"",IF(NOT(ISNUMBER(Table9[[#This Row],[Forecast]])),"",Table9[[#This Row],[Actual]]-Table9[[#This Row],[Forecast]])) -> 0 | H30: =IF(NOT(ISNUMBER(Table9[[#This Row],[Actual]])),"",IF(NOT(ISNUMBER(Table9[[#This Row],[Previous]])),"",Table9[[#This Row],[Actual]]-Table9[[#This Row],[Previous]])) -> -0.002 | I30: =IF(AND(K30="",L30=""),"N/A",IF(AND(ABS(N(K30))<0.0005,ABS(N(L30))<0.0005),"Stable",IF(AND(L30="",ABS(N(K30))>=0.0005),IF(N(K30)>0,"Accelerating","Slowing"),IF(AND(K30="",ABS(N(L30))>=0.0005),IF(N(L30)>0,"Accelerating","Slowing"),IF(AND(N(K30)>0,N(L30)>=0),"Accelerating",IF(AND(N(K30)<0,N(L30)<=0),"Slowing","Mixed")))))) -> Mixed | J30: =IF(OR(ISNUMBER(SEARCH("Unemployment",C30)),ISNUMBER(SEARCH("Claims",C30)),ISNUMBER(SEARCH("Jobless",C30)),ISNUMBER(SEARCH("Inventories",C30)),ISNUMBER(SEARCH("Wholesale Inventories",C30)),ISNUMBER(SEARCH("JOLTS Job Openings",C30)),ISNUMBER(SEARCH("Inflation Expectations",C30))),-1,1) -> 1 | K30: =IF(OR(G30="",G30="(NA)"),"",J30*G30) -> 0 | L30: =IF(OR(H30="",H30="(NA)"),"",J30*H30) -> -0.002
A31: 45996 | B31: Growth - US | C31: Consumer Credit m/m | D31: 92000000 | E31: 118000000 | F31: 110000000 | G31: =IF(NOT(ISNUMBER(Table9[[#This Row],[Actual]])),"",IF(NOT(ISNUMBER(Table9[[#This Row],[Forecast]])),"",Table9[[#This Row],[Actual]]-Table9[[#This Row],[Forecast]])) -> -26000000 | H31: =IF(NOT(ISNUMBER(Table9[[#This Row],[Actual]])),"",IF(NOT(ISNUMBER(Table9[[#This Row],[Previous]])),"",Table9[[#This Row],[Actual]]-Table9[[#This Row],[Previous]])) -> -18000000 | I31: =IF(AND(K31="",L31=""),"N/A",IF(AND(ABS(N(K31))<0.0005,ABS(N(L31))<0.0005),"Stable",IF(AND(L31="",ABS(N(K31))>=0.0005),IF(N(K31)>0,"Accelerating","Slowing"),IF(AND(K31="",ABS(N(L31))>=0.0005),IF(N(L31)>0,"Accelerating","Slowing"),IF(AND(N(K31)>0,N(L31)>=0),"Accelerating",IF(AND(N(K31)<0,N(L31)<=0),"Slowing","Mixed")))))) -> Slowing | J31: =IF(OR(ISNUMBER(SEARCH("Unemployment",C31)),ISNUMBER(SEARCH("Claims",C31)),ISNUMBER(SEARCH("Jobless",C31)),ISNUMBER(SEARCH("Inventories",C31)),ISNUMBER(SEARCH("Wholesale Inventories",C31)),ISNUMBER(SEARCH("JOLTS Job Openings",C31)),ISNUMBER(SEARCH("Inflation Expectations",C31))),-1,1) -> 1 | K31: =IF(OR(G31="",G31="(NA)"),"",J31*G31) -> -26000000 | L31: =IF(OR(H31="",H31="(NA)"),"",J31*H31) -> -18000000
A32: 45996 | B32: Inflation – US | C32: Core PCE Price Index m/m | D32: 0.002 | E32: 0.002 | F32: 0.002 | G32: =IF(NOT(ISNUMBER(Table9[[#This Row],[Actual]])),"",IF(NOT(ISNUMBER(Table9[[#This Row],[Forecast]])),"",Table9[[#This Row],[Actual]]-Table9[[#This Row],[Forecast]])) -> 0 | H32: =IF(NOT(ISNUMBER(Table9[[#This Row],[Actual]])),"",IF(NOT(ISNUMBER(Table9[[#This Row],[Previous]])),"",Table9[[#This Row],[Actual]]-Table9[[#This Row],[Previous]])) -> 0 | I32: =IF(AND(K32="",L32=""),"N/A",IF(AND(ABS(N(K32))<0.0005,ABS(N(L32))<0.0005),"Stable",IF(AND(L32="",ABS(N(K32))>=0.0005),IF(N(K32)>0,"Accelerating","Slowing"),IF(AND(K32="",ABS(N(L32))>=0.0005),IF(N(L32)>0,"Accelerating","Slowing"),IF(AND(N(K32)>0,N(L32)>=0),"Accelerating",IF(AND(N(K32)<0,N(L32)<=0),"Slowing","Mixed")))))) -> Stable | J32: =IF(OR(ISNUMBER(SEARCH("Unemployment",C32)),ISNUMBER(SEARCH("Claims",C32)),ISNUMBER(SEARCH("Jobless",C32)),ISNUMBER(SEARCH("Inventories",C32)),ISNUMBER(SEARCH("Wholesale Inventories",C32)),ISNUMBER(SEARCH("JOLTS Job Openings",C32)),ISNUMBER(SEARCH("Inflation Expectations",C32))),-1,1) -> 1 | K32: =IF(OR(G32="",G32="(NA)"),"",J32*G32) -> 0 | L32: =IF(OR(H32="",H32="(NA)"),"",J32*H32) -> 0
A33: 45996 | B33: Inflation – US | C33: Prelim UoM Inflation Expectations | D33: 0.041 | E33: (NA) | F33: 0.045 | G33: =IF(NOT(ISNUMBER(Table9[[#This Row],[Actual]])),"",IF(NOT(ISNUMBER(Table9[[#This Row],[Forecast]])),"",Table9[[#This Row],[Actual]]-Table9[[#This Row],[Forecast]])) | H33: =IF(NOT(ISNUMBER(Table9[[#This Row],[Actual]])),"",IF(NOT(ISNUMBER(Table9[[#This Row],[Previous]])),"",Table9[[#This Row],[Actual]]-Table9[[#This Row],[Previous]])) -> -0.004 | I33: =IF(AND(K33="",L33=""),"N/A",IF(AND(ABS(N(K33))<0.0005,ABS(N(L33))<0.0005),"Stable",IF(AND(L33="",ABS(N(K33))>=0.0005),IF(N(K33)>0,"Accelerating","Slowing"),IF(AND(K33="",ABS(N(L33))>=0.0005),IF(N(L33)>0,"Accelerating","Slowing"),IF(AND(N(K33)>0,N(L33)>=0),"Accelerating",IF(AND(N(K33)<0,N(L33)<=0),"Slowing","Mixed")))))) -> Accelerating | J33: =IF(OR(ISNUMBER(SEARCH("Unemployment",C33)),ISNUMBER(SEARCH("Claims",C33)),ISNUMBER(SEARCH("Jobless",C33)),ISNUMBER(SEARCH("Inventories",C33)),ISNUMBER(SEARCH("Wholesale Inventories",C33)),ISNUMBER(SEARCH("JOLTS Job Openings",C33)),ISNUMBER(SEARCH("Inflation Expectations",C33))),-1,1) -> -1 | K33: =IF(OR(G33="",G33="(NA)"),"",J33*G33) | L33: =IF(OR(H33="",H33="(NA)"),"",J33*H33) -> 0.004
A34: 45996 | B34: Labour – CAD | C34: Employment Change | D34: 53600 | E34: -1500 | F34: 66600 | G34: =IF(NOT(ISNUMBER(Table9[[#This Row],[Actual]])),"",IF(NOT(ISNUMBER(Table9[[#This Row],[Forecast]])),"",Table9[[#This Row],[Actual]]-Table9[[#This Row],[Forecast]])) -> 55100 | H34: =IF(NOT(ISNUMBER(Table9[[#This Row],[Actual]])),"",IF(NOT(ISNUMBER(Table9[[#This Row],[Previous]])),"",Table9[[#This Row],[Actual]]-Table9[[#This Row],[Previous]])) -> -13000 | I34: =IF(AND(K34="",L34=""),"N/A",IF(AND(ABS(N(K34))<0.0005,ABS(N(L34))<0.0005),"Stable",IF(AND(L34="",ABS(N(K34))>=0.0005),IF(N(K34)>0,"Accelerating","Slowing"),IF(AND(K34="",ABS(N(L34))>=0.0005),IF(N(L34)>0,"Accelerating","Slowing"),IF(AND(N(K34)>0,N(L34)>=0),"Accelerating",IF(AND(N(K34)<0,N(L34)<=0),"Slowing","Mixed")))))) -> Mixed | J34: =IF(OR(ISNUMBER(SEARCH("Unemployment",C34)),ISNUMBER(SEARCH("Claims",C34)),ISNUMBER(SEARCH("Jobless",C34)),ISNUMBER(SEARCH("Inventories",C34)),ISNUMBER(SEARCH("Wholesale Inventories",C34)),ISNUMBER(SEARCH("JOLTS Job Openings",C34)),ISNUMBER(SEARCH("Inflation Expectations",C34))),-1,1) -> 1 | K34: =IF(OR(G34="",G34="(NA)"),"",J34*G34) -> 55100 | L34: =IF(OR(H34="",H34="(NA)"),"",J34*H34) -> -13000
A35: 46000 | B35: Growth - EUR | C35: German Trade Balance | D35: 16.9 | E35: 15.9 | F35: 15.3 | G35: =IF(NOT(ISNUMBER(Table9[[#This Row],[Actual]])),"",IF(NOT(ISNUMBER(Table9[[#This Row],[Forecast]])),"",Table9[[#This Row],[Actual]]-Table9[[#This Row],[Forecast]])) -> 1 | H35: =IF(NOT(ISNUMBER(Table9[[#This Row],[Actual]])),"",IF(NOT(ISNUMBER(Table9[[#This Row],[Previous]])),"",Table9[[#This Row],[Actual]]-Table9[[#This Row],[Previous]])) -> 1.6 | I35: =IF(AND(K35="",L35=""),"N/A",IF(AND(ABS(N(K35))<0.0005,ABS(N(L35))<0.0005),"Stable",IF(AND(L35="",ABS(N(K35))>=0.0005),IF(N(K35)>0,"Accelerating","Slowing"),IF(AND(K35="",ABS(N(L35))>=0.0005),IF(N(L35)>0,"Accelerating","Slowing"),IF(AND(N(K35)>0,N(L35)>=0),"Accelerating",IF(AND(N(K35)<0,N(L35)<=0),"Slowing","Mixed")))))) -> Accelerating | J35: =IF(OR(ISNUMBER(SEARCH("Unemployment",C35)),ISNUMBER(SEARCH("Claims",C35)),ISNUMBER(SEARCH("Jobless",C35)),ISNUMBER(SEARCH("Inventories",C35)),ISNUMBER(SEARCH("Wholesale Inventories",C35)),ISNUMBER(SEARCH("JOLTS Job Openings",C35)),ISNUMBER(SEARCH("Inflation Expectations",C35))),-1,1) -> 1 | K35: =IF(OR(G35="",G35="(NA)"),"",J35*G35) -> 1 | L35: =IF(OR(H35="",H35="(NA)"),"",J35*H35) -> 1.6
A36: 45996 | B36: Labour – CAD | C36: Unemployment Rate | D36: 0.065 | E36: 0.07 | F36: 0.069 | G36: =IF(NOT(ISNUMBER(Table9[[#This Row],[Actual]])),"",IF(NOT(ISNUMBER(Table9[[#This Row],[Forecast]])),"",Table9[[#This Row],[Actual]]-Table9[[#This Row],[Forecast]])) -> -0.005 | H36: =IF(NOT(ISNUMBER(Table9[[#This Row],[Actual]])),"",IF(NOT(ISNUMBER(Table9[[#This Row],[Previous]])),"",Table9[[#This Row],[Actual]]-Table9[[#This Row],[Previous]])) -> -0.004 | I36: =IF(AND(K36="",L36=""),"N/A",IF(AND(ABS(N(K36))<0.0005,ABS(N(L36))<0.0005),"Stable",IF(AND(L36="",ABS(N(K36))>=0.0005),IF(N(K36)>0,"Accelerating","Slowing"),IF(AND(K36="",ABS(N(L36))>=0.0005),IF(N(L36)>0,"Accelerating","Slowing"),IF(AND(N(K36)>0,N(L36)>=0),"Accelerating",IF(AND(N(K36)<0,N(L36)<=0),"Slowing","Mixed")))))) -> Accelerating | J36: =IF(OR(ISNUMBER(SEARCH("Unemployment",C36)),ISNUMBER(SEARCH("Claims",C36)),ISNUMBER(SEARCH("Jobless",C36)),ISNUMBER(SEARCH("Inventories",C36)),ISNUMBER(SEARCH("Wholesale Inventories",C36)),ISNUMBER(SEARCH("JOLTS Job Openings",C36)),ISNUMBER(SEARCH("Inflation Expectations",C36))),-1,1) -> -1 | K36: =IF(OR(G36="",G36="(NA)"),"",J36*G36) -> 0.005 | L36: =IF(OR(H36="",H36="(NA)"),"",J36*H36) -> 0.004
A37: 45997 | B37: Growth - EUR | C37: German Industrial Production m/m | D37: 0.018 | E37: 0.002 | F37: 0.013 | G37: =IF(NOT(ISNUMBER(Table9[[#This Row],[Actual]])),"",IF(NOT(ISNUMBER(Table9[[#This Row],[Forecast]])),"",Table9[[#This Row],[Actual]]-Table9[[#This Row],[Forecast]])) -> 0.016 | H37: =IF(NOT(ISNUMBER(Table9[[#This Row],[Actual]])),"",IF(NOT(ISNUMBER(Table9[[#This Row],[Previous]])),"",Table9[[#This Row],[Actual]]-Table9[[#This Row],[Previous]])) -> 0.005 | I37: =IF(AND(K37="",L37=""),"N/A",IF(AND(ABS(N(K37))<0.0005,ABS(N(L37))<0.0005),"Stable",IF(AND(L37="",ABS(N(K37))>=0.0005),IF(N(K37)>0,"Accelerating","Slowing"),IF(AND(K37="",ABS(N(L37))>=0.0005),IF(N(L37)>0,"Accelerating","Slowing"),IF(AND(N(K37)>0,N(L37)>=0),"Accelerating",IF(AND(N(K37)<0,N(L37)<=0),"Slowing","Mixed")))))) -> Accelerating | J37: =IF(OR(ISNUMBER(SEARCH("Unemployment",C37)),ISNUMBER(SEARCH("Claims",C37)),ISNUMBER(SEARCH("Jobless",C37)),ISNUMBER(SEARCH("Inventories",C37)),ISNUMBER(SEARCH("Wholesale Inventories",C37)),ISNUMBER(SEARCH("JOLTS Job Openings",C37)),ISNUMBER(SEARCH("Inflation Expectations",C37))),-1,1) -> 1 | K37: =IF(OR(G37="",G37="(NA)"),"",J37*G37) -> 0.016 | L37: =IF(OR(H37="",H37="(NA)"),"",J37*H37) -> 0.005
A38: 46000 | B38: Growth - EUR | C38: Sentix Investor Confidence | D38: -0.062 | E38: -0.062 | F38: -0.074 | G38: =IF(NOT(ISNUMBER(Table9[[#This Row],[Actual]])),"",IF(NOT(ISNUMBER(Table9[[#This Row],[Forecast]])),"",Table9[[#This Row],[Actual]]-Table9[[#This Row],[Forecast]])) -> 0 | H38: =IF(NOT(ISNUMBER(Table9[[#This Row],[Actual]])),"",IF(NOT(ISNUMBER(Table9[[#This Row],[Previous]])),"",Table9[[#This Row],[Actual]]-Table9[[#This Row],[Previous]])) -> 0.012 | I38: =IF(AND(K38="",L38=""),"N/A",IF(AND(ABS(N(K38))<0.0005,ABS(N(L38))<0.0005),"Stable",IF(AND(L38="",ABS(N(K38))>=0.0005),IF(N(K38)>0,"Accelerating","Slowing"),IF(AND(K38="",ABS(N(L38))>=0.0005),IF(N(L38)>0,"Accelerating","Slowing"),IF(AND(N(K38)>0,N(L38)>=0),"Accelerating",IF(AND(N(K38)<0,N(L38)<=0),"Slowing","Mixed")))))) -> Mixed | J38: =IF(OR(ISNUMBER(SEARCH("Unemployment",C38)),ISNUMBER(SEARCH("Claims",C38)),ISNUMBER(SEARCH("Jobless",C38)),ISNUMBER(SEARCH("Inventories",C38)),ISNUMBER(SEARCH("Wholesale Inventories",C38)),ISNUMBER(SEARCH("JOLTS Job Openings",C38)),ISNUMBER(SEARCH("Inflation Expectations",C38))),-1,1) -> 1 | K38: =IF(OR(G38="",G38="(NA)"),"",J38*G38) -> 0 | L38: =IF(OR(H38="",H38="(NA)"),"",J38*H38) -> 0.012
A39: 46000 | B39: Growth - US | C39: NFIB Small Business Index | D39: 99 | E39: 98.4 | F39: 98.2 | G39: =IF(NOT(ISNUMBER(Table9[[#This Row],[Actual]])),"",IF(NOT(ISNUMBER(Table9[[#This Row],[Forecast]])),"",Table9[[#This Row],[Actual]]-Table9[[#This Row],[Forecast]])) -> 0.6 | H39: =IF(NOT(ISNUMBER(Table9[[#This Row],[Actual]])),"",IF(NOT(ISNUMBER(Table9[[#This Row],[Previous]])),"",Table9[[#This Row],[Actual]]-Table9[[#This Row],[Previous]])) -> 0.8 | I39: =IF(AND(K39="",L39=""),"N/A",IF(AND(ABS(N(K39))<0.0005,ABS(N(L39))<0.0005),"Stable",IF(AND(L39="",ABS(N(K39))>=0.0005),IF(N(K39)>0,"Accelerating","Slowing"),IF(AND(K39="",ABS(N(L39))>=0.0005),IF(N(L39)>0,"Accelerating","Slowing"),IF(AND(N(K39)>0,N(L39)>=0),"Accelerating",IF(AND(N(K39)<0,N(L39)<=0),"Slowing","Mixed")))))) -> Accelerating | J39: =IF(OR(ISNUMBER(SEARCH("Unemployment",C39)),ISNUMBER(SEARCH("Claims",C39)),ISNUMBER(SEARCH("Jobless",C39)),ISNUMBER(SEARCH("Inventories",C39)),ISNUMBER(SEARCH("Wholesale Inventories",C39)),ISNUMBER(SEARCH("JOLTS Job Openings",C39)),ISNUMBER(SEARCH("Inflation Expectations",C39))),-1,1) -> 1 | K39: =IF(OR(G39="",G39="(NA)"),"",J39*G39) -> 0.6 | L39: =IF(OR(H39="",H39="(NA)"),"",J39*H39) -> 0.8
A40: 46000 | B40: Labour – US | C40: ADP Weekly Employment Change | D40: 4.8 | F40: -13.5 | G40: =IF(NOT(ISNUMBER(Table9[[#This Row],[Actual]])),"",IF(NOT(ISNUMBER(Table9[[#This Row],[Forecast]])),"",Table9[[#This Row],[Actual]]-Table9[[#This Row],[Forecast]])) | H40: =IF(NOT(ISNUMBER(Table9[[#This Row],[Actual]])),"",IF(NOT(ISNUMBER(Table9[[#This Row],[Previous]])),"",Table9[[#This Row],[Actual]]-Table9[[#This Row],[Previous]])) -> 18.3 | I40: =IF(AND(K40="",L40=""),"N/A",IF(AND(ABS(N(K40))<0.0005,ABS(N(L40))<0.0005),"Stable",IF(AND(L40="",ABS(N(K40))>=0.0005),IF(N(K40)>0,"Accelerating","Slowing"),IF(AND(K40="",ABS(N(L40))>=0.0005),IF(N(L40)>0,"Accelerating","Slowing"),IF(AND(N(K40)>0,N(L40)>=0),"Accelerating",IF(AND(N(K40)<0,N(L40)<=0),"Slowing","Mixed")))))) -> Accelerating | J40: =IF(OR(ISNUMBER(SEARCH("Unemployment",C40)),ISNUMBER(SEARCH("Claims",C40)),ISNUMBER(SEARCH("Jobless",C40)),ISNUMBER(SEARCH("Inventories",C40)),ISNUMBER(SEARCH("Wholesale Inventories",C40)),ISNUMBER(SEARCH("JOLTS Job Openings",C40)),ISNUMBER(SEARCH("Inflation Expectations",C40))),-1,1) -> 1 | K40: =IF(OR(G40="",G40="(NA)"),"",J40*G40) | L40: =IF(OR(H40="",H40="(NA)"),"",J40*H40) -> 18.3
A41: 45901 | B41: Labour – US | C41: JOLTS Job Openings | D41: 7.66 | F41: 7.23 | G41: =IF(NOT(ISNUMBER(Table9[[#This Row],[Actual]])),"",IF(NOT(ISNUMBER(Table9[[#This Row],[Forecast]])),"",Table9[[#This Row],[Actual]]-Table9[[#This Row],[Forecast]])) | H41: =IF(NOT(ISNUMBER(Table9[[#This Row],[Actual]])),"",IF(NOT(ISNUMBER(Table9[[#This Row],[Previous]])),"",Table9[[#This Row],[Actual]]-Table9[[#This Row],[Previous]])) -> 0.43 | I41: =IF(AND(K41="",L41=""),"N/A",IF(AND(ABS(N(K41))<0.0005,ABS(N(L41))<0.0005),"Stable",IF(AND(L41="",ABS(N(K41))>=0.0005),IF(N(K41)>0,"Accelerating","Slowing"),IF(AND(K41="",ABS(N(L41))>=0.0005),IF(N(L41)>0,"Accelerating","Slowing"),IF(AND(N(K41)>0,N(L41)>=0),"Accelerating",IF(AND(N(K41)<0,N(L41)<=0),"Slowing","Mixed")))))) -> Slowing | J41: =IF(OR(ISNUMBER(SEARCH("Unemployment",C41)),ISNUMBER(SEARCH("Claims",C41)),ISNUMBER(SEARCH("Jobless",C41)),ISNUMBER(SEARCH("Inventories",C41)),ISNUMBER(SEARCH("Wholesale Inventories",C41)),ISNUMBER(SEARCH("JOLTS Job Openings",C41)),ISNUMBER(SEARCH("Inflation Expectations",C41))),-1,1) -> -1 | K41: =IF(OR(G41="",G41="(NA)"),"",J41*G41) | L41: =IF(OR(H41="",H41="(NA)"),"",J41*H41) -> -0.43
A42: 46000 | B42: Labour – US | C42: JOLTS Job Openings | D42: 7.67 | E42: 7.14 | F42: 7.66 | G42: =IF(NOT(ISNUMBER(Table9[[#This Row],[Actual]])),"",IF(NOT(ISNUMBER(Table9[[#This Row],[Forecast]])),"",Table9[[#This Row],[Actual]]-Table9[[#This Row],[Forecast]])) -> 0.53 | H42: =IF(NOT(ISNUMBER(Table9[[#This Row],[Actual]])),"",IF(NOT(ISNUMBER(Table9[[#This Row],[Previous]])),"",Table9[[#This Row],[Actual]]-Table9[[#This Row],[Previous]])) -> 0.01 | I42: =IF(AND(K42="",L42=""),"N/A",IF(AND(ABS(N(K42))<0.0005,ABS(N(L42))<0.0005),"Stable",IF(AND(L42="",ABS(N(K42))>=0.0005),IF(N(K42)>0,"Accelerating","Slowing"),IF(AND(K42="",ABS(N(L42))>=0.0005),IF(N(L42)>0,"Accelerating","Slowing"),IF(AND(N(K42)>0,N(L42)>=0),"Accelerating",IF(AND(N(K42)<0,N(L42)<=0),"Slowing","Mixed")))))) -> Slowing | J42: =IF(OR(ISNUMBER(SEARCH("Unemployment",C42)),ISNUMBER(SEARCH("Claims",C42)),ISNUMBER(SEARCH("Jobless",C42)),ISNUMBER(SEARCH("Inventories",C42)),ISNUMBER(SEARCH("Wholesale Inventories",C42)),ISNUMBER(SEARCH("JOLTS Job Openings",C42)),ISNUMBER(SEARCH("Inflation Expectations",C42))),-1,1) -> -1 | K42: =IF(OR(G42="",G42="(NA)"),"",J42*G42) -> -0.53 | L42: =IF(OR(H42="",H42="(NA)"),"",J42*H42) -> -0.01
A43: 46000 | B43: Growth - US | C43: CB Leading Index m/m | D43: -0.3 | E43: -0.3 | F43: -0.3 | G43: =IF(NOT(ISNUMBER(Table9[[#This Row],[Actual]])),"",IF(NOT(ISNUMBER(Table9[[#This Row],[Forecast]])),"",Table9[[#This Row],[Actual]]-Table9[[#This Row],[Forecast]])) -> 0 | H43: =IF(NOT(ISNUMBER(Table9[[#This Row],[Actual]])),"",IF(NOT(ISNUMBER(Table9[[#This Row],[Previous]])),"",Table9[[#This Row],[Actual]]-Table9[[#This Row],[Previous]])) -> 0 | I43: =IF(AND(K43="",L43=""),"N/A",IF(AND(ABS(N(K43))<0.0005,ABS(N(L43))<0.0005),"Stable",IF(AND(L43="",ABS(N(K43))>=0.0005),IF(N(K43)>0,"Accelerating","Slowing"),IF(AND(K43="",ABS(N(L43))>=0.0005),IF(N(L43)>0,"Accelerating","Slowing"),IF(AND(N(K43)>0,N(L43)>=0),"Accelerating",IF(AND(N(K43)<0,N(L43)<=0),"Slowing","Mixed")))))) -> Stable | J43: =IF(OR(ISNUMBER(SEARCH("Unemployment",C43)),ISNUMBER(SEARCH("Claims",C43)),ISNUMBER(SEARCH("Jobless",C43)),ISNUMBER(SEARCH("Inventories",C43)),ISNUMBER(SEARCH("Wholesale Inventories",C43)),ISNUMBER(SEARCH("JOLTS Job Openings",C43)),ISNUMBER(SEARCH("Inflation Expectations",C43))),-1,1) -> 1 | K43: =IF(OR(G43="",G43="(NA)"),"",J43*G43) -> 0 | L43: =IF(OR(H43="",H43="(NA)"),"",J43*H43) -> 0
A44: 46001 | B44: Growth - EUR | C44: Italian Industrial Production m/m | D44: -1 | E44: -0.003 | F44: 0.028 | G44: =IF(NOT(ISNUMBER(Table9[[#This Row],[Actual]])),"",IF(NOT(ISNUMBER(Table9[[#This Row],[Forecast]])),"",Table9[[#This Row],[Actual]]-Table9[[#This Row],[Forecast]])) -> -0.997 | H44: =IF(NOT(ISNUMBER(Table9[[#This Row],[Actual]])),"",IF(NOT(ISNUMBER(Table9[[#This Row],[Previous]])),"",Table9[[#This Row],[Actual]]-Table9[[#This Row],[Previous]])) -> -1.028 | I44: =IF(AND(K44="",L44=""),"N/A",IF(AND(ABS(N(K44))<0.0005,ABS(N(L44))<0.0005),"Stable",IF(AND(L44="",ABS(N(K44))>=0.0005),IF(N(K44)>0,"Accelerating","Slowing"),IF(AND(K44="",ABS(N(L44))>=0.0005),IF(N(L44)>0,"Accelerating","Slowing"),IF(AND(N(K44)>0,N(L44)>=0),"Accelerating",IF(AND(N(K44)<0,N(L44)<=0),"Slowing","Mixed")))))) -> Slowing | J44: =IF(OR(ISNUMBER(SEARCH("Unemployment",C44)),ISNUMBER(SEARCH("Claims",C44)),ISNUMBER(SEARCH("Jobless",C44)),ISNUMBER(SEARCH("Inventories",C44)),ISNUMBER(SEARCH("Wholesale Inventories",C44)),ISNUMBER(SEARCH("JOLTS Job Openings",C44)),ISNUMBER(SEARCH("Inflation Expectations",C44))),-1,1) -> 1 | K44: =IF(OR(G44="",G44="(NA)"),"",J44*G44) -> -0.997 | L44: =IF(OR(H44="",H44="(NA)"),"",J44*H44) -> -1.028
A45: 46001 | B45: Inflation – US | C45: Employment Cost Index q/q | D45: 0.008 | E45: 0.009 | F45: 0.009 | G45: =IF(NOT(ISNUMBER(Table9[[#This Row],[Actual]])),"",IF(NOT(ISNUMBER(Table9[[#This Row],[Forecast]])),"",Table9[[#This Row],[Actual]]-Table9[[#This Row],[Forecast]])) -> -0.001 | H45: =IF(NOT(ISNUMBER(Table9[[#This Row],[Actual]])),"",IF(NOT(ISNUMBER(Table9[[#This Row],[Previous]])),"",Table9[[#This Row],[Actual]]-Table9[[#This Row],[Previous]])) -> -0.001 | I45: =IF(AND(K45="",L45=""),"N/A",IF(AND(ABS(N(K45))<0.0005,ABS(N(L45))<0.0005),"Stable",IF(AND(L45="",ABS(N(K45))>=0.0005),IF(N(K45)>0,"Accelerating","Slowing"),IF(AND(K45="",ABS(N(L45))>=0.0005),IF(N(L45)>0,"Accelerating","Slowing"),IF(AND(N(K45)>0,N(L45)>=0),"Accelerating",IF(AND(N(K45)<0,N(L45)<=0),"Slowing","Mixed")))))) -> Slowing | J45: =IF(OR(ISNUMBER(SEARCH("Unemployment",C45)),ISNUMBER(SEARCH("Claims",C45)),ISNUMBER(SEARCH("Jobless",C45)),ISNUMBER(SEARCH("Inventories",C45)),ISNUMBER(SEARCH("Wholesale Inventories",C45)),ISNUMBER(SEARCH("JOLTS Job Openings",C45)),ISNUMBER(SEARCH("Inflation Expectations",C45))),-1,1) -> 1 | K45: =IF(OR(G45="",G45="(NA)"),"",J45*G45) -> -0.001 | L45: =IF(OR(H45="",H45="(NA)"),"",J45*H45) -> -0.001
A46: 46001 | B46: Growth - US | C46: Federal Funds Rate | D46: 0.0375 | E46: 0.0375 | F46: 0.04 | G46: =IF(NOT(ISNUMBER(Table9[[#This Row],[Actual]])),"",IF(NOT(ISNUMBER(Table9[[#This Row],[Forecast]])),"",Table9[[#This Row],[Actual]]-Table9[[#This Row],[Forecast]])) -> 0 | H46: =IF(NOT(ISNUMBER(Table9[[#This Row],[Actual]])),"",IF(NOT(ISNUMBER(Table9[[#This Row],[Previous]])),"",Table9[[#This Row],[Actual]]-Table9[[#This Row],[Previous]])) -> -0.0025 | I46: =IF(AND(K46="",L46=""),"N/A",IF(AND(ABS(N(K46))<0.0005,ABS(N(L46))<0.0005),"Stable",IF(AND(L46="",ABS(N(K46))>=0.0005),IF(N(K46)>0,"Accelerating","Slowing"),IF(AND(K46="",ABS(N(L46))>=0.0005),IF(N(L46)>0,"Accelerating","Slowing"),IF(AND(N(K46)>0,N(L46)>=0),"Accelerating",IF(AND(N(K46)<0,N(L46)<=0),"Slowing","Mixed")))))) -> Mixed | J46: =IF(OR(ISNUMBER(SEARCH("Unemployment",C46)),ISNUMBER(SEARCH("Claims",C46)),ISNUMBER(SEARCH("Jobless",C46)),ISNUMBER(SEARCH("Inventories",C46)),ISNUMBER(SEARCH("Wholesale Inventories",C46)),ISNUMBER(SEARCH("JOLTS Job Openings",C46)),ISNUMBER(SEARCH("Inflation Expectations",C46))),-1,1) -> 1 | K46: =IF(OR(G46="",G46="(NA)"),"",J46*G46) -> 0 | L46: =IF(OR(H46="",H46="(NA)"),"",J46*H46) -> -0.0025
A47: 46001 | B47: Growth - US | C47: Federal Budget Balance | D47: -173.3 | E47: -186.5 | F47: -284.4 | G47: =IF(NOT(ISNUMBER(Table9[[#This Row],[Actual]])),"",IF(NOT(ISNUMBER(Table9[[#This Row],[Forecast]])),"",Table9[[#This Row],[Actual]]-Table9[[#This Row],[Forecast]])) -> 13.2 | H47: =IF(NOT(ISNUMBER(Table9[[#This Row],[Actual]])),"",IF(NOT(ISNUMBER(Table9[[#This Row],[Previous]])),"",Table9[[#This Row],[Actual]]-Table9[[#This Row],[Previous]])) -> 111.1 | I47: =IF(AND(K47="",L47=""),"N/A",IF(AND(ABS(N(K47))<0.0005,ABS(N(L47))<0.0005),"Stable",IF(AND(L47="",ABS(N(K47))>=0.0005),IF(N(K47)>0,"Accelerating","Slowing"),IF(AND(K47="",ABS(N(L47))>=0.0005),IF(N(L47)>0,"Accelerating","Slowing"),IF(AND(N(K47)>0,N(L47)>=0),"Accelerating",IF(AND(N(K47)<0,N(L47)<=0),"Slowing","Mixed")))))) -> Accelerating | J47: =IF(OR(ISNUMBER(SEARCH("Unemployment",C47)),ISNUMBER(SEARCH("Claims",C47)),ISNUMBER(SEARCH("Jobless",C47)),ISNUMBER(SEARCH("Inventories",C47)),ISNUMBER(SEARCH("Wholesale Inventories",C47)),ISNUMBER(SEARCH("JOLTS Job Openings",C47)),ISNUMBER(SEARCH("Inflation Expectations",C47))),-1,1) -> 1 | K47: =IF(OR(G47="",G47="(NA)"),"",J47*G47) -> 13.2 | L47: =IF(OR(H47="",H47="(NA)"),"",J47*H47) -> 111.1
A48: 46002 | B48: Labour – EUR | C48: Italian Quarterly Unemployment Rate | D48: 0.061 | E48: 0.063 | F48: 0.063 | G48: =IF(NOT(ISNUMBER(Table9[[#This Row],[Actual]])),"",IF(NOT(ISNUMBER(Table9[[#This Row],[Forecast]])),"",Table9[[#This Row],[Actual]]-Table9[[#This Row],[Forecast]])) -> -0.002 | H48: =IF(NOT(ISNUMBER(Table9[[#This Row],[Actual]])),"",IF(NOT(ISNUMBER(Table9[[#This Row],[Previous]])),"",Table9[[#This Row],[Actual]]-Table9[[#This Row],[Previous]])) -> -0.002 | I48: =IF(AND(K48="",L48=""),"N/A",IF(AND(ABS(N(K48))<0.0005,ABS(N(L48))<0.0005),"Stable",IF(AND(L48="",ABS(N(K48))>=0.0005),IF(N(K48)>0,"Accelerating","Slowing"),IF(AND(K48="",ABS(N(L48))>=0.0005),IF(N(L48)>0,"Accelerating","Slowing"),IF(AND(N(K48)>0,N(L48)>=0),"Accelerating",IF(AND(N(K48)<0,N(L48)<=0),"Slowing","Mixed")))))) -> Accelerating | J48: =IF(OR(ISNUMBER(SEARCH("Unemployment",C48)),ISNUMBER(SEARCH("Claims",C48)),ISNUMBER(SEARCH("Jobless",C48)),ISNUMBER(SEARCH("Inventories",C48)),ISNUMBER(SEARCH("Wholesale Inventories",C48)),ISNUMBER(SEARCH("JOLTS Job Openings",C48)),ISNUMBER(SEARCH("Inflation Expectations",C48))),-1,1) -> -1 | K48: =IF(OR(G48="",G48="(NA)"),"",J48*G48) -> 0.002 | L48: =IF(OR(H48="",H48="(NA)"),"",J48*H48) -> 0.002
A49: 46002 | B49: Labour – US | C49: Unemployment Claims | D49: 236 | E49: 220 | F49: 191 | G49: =IF(NOT(ISNUMBER(Table9[[#This Row],[Actual]])),"",IF(NOT(ISNUMBER(Table9[[#This Row],[Forecast]])),"",Table9[[#This Row],[Actual]]-Table9[[#This Row],[Forecast]])) -> 16 | H49: =IF(NOT(ISNUMBER(Table9[[#This Row],[Actual]])),"",IF(NOT(ISNUMBER(Table9[[#This Row],[Previous]])),"",Table9[[#This Row],[Actual]]-Table9[[#This Row],[Previous]])) -> 45 | I49: =IF(AND(K49="",L49=""),"N/A",IF(AND(ABS(N(K49))<0.0005,ABS(N(L49))<0.0005),"Stable",IF(AND(L49="",ABS(N(K49))>=0.0005),IF(N(K49)>0,"Accelerating","Slowing"),IF(AND(K49="",ABS(N(L49))>=0.0005),IF(N(L49)>0,"Accelerating","Slowing"),IF(AND(N(K49)>0,N(L49)>=0),"Accelerating",IF(AND(N(K49)<0,N(L49)<=0),"Slowing","Mixed")))))) -> Slowing | J49: =IF(OR(ISNUMBER(SEARCH("Unemployment",C49)),ISNUMBER(SEARCH("Claims",C49)),ISNUMBER(SEARCH("Jobless",C49)),ISNUMBER(SEARCH("Inventories",C49)),ISNUMBER(SEARCH("Wholesale Inventories",C49)),ISNUMBER(SEARCH("JOLTS Job Openings",C49)),ISNUMBER(SEARCH("Inflation Expectations",C49))),-1,1) -> -1 | K49: =IF(OR(G49="",G49="(NA)"),"",J49*G49) -> -16 | L49: =IF(OR(H49="",H49="(NA)"),"",J49*H49) -> -45
A50: 46002 | B50: Growth - US | C50: Trade Balance | D50: -52.8 | E50: -62.5 | F50: -59.6 | G50: =IF(NOT(ISNUMBER(Table9[[#This Row],[Actual]])),"",IF(NOT(ISNUMBER(Table9[[#This Row],[Forecast]])),"",Table9[[#This Row],[Actual]]-Table9[[#This Row],[Forecast]])) -> 9.7 | H50: =IF(NOT(ISNUMBER(Table9[[#This Row],[Actual]])),"",IF(NOT(ISNUMBER(Table9[[#This Row],[Previous]])),"",Table9[[#This Row],[Actual]]-Table9[[#This Row],[Previous]])) -> 6.8 | I50: =IF(AND(K50="",L50=""),"N/A",IF(AND(ABS(N(K50))<0.0005,ABS(N(L50))<0.0005),"Stable",IF(AND(L50="",ABS(N(K50))>=0.0005),IF(N(K50)>0,"Accelerating","Slowing"),IF(AND(K50="",ABS(N(L50))>=0.0005),IF(N(L50)>0,"Accelerating","Slowing"),IF(AND(N(K50)>0,N(L50)>=0),"Accelerating",IF(AND(N(K50)<0,N(L50)<=0),"Slowing","Mixed")))))) -> Accelerating | J50: =IF(OR(ISNUMBER(SEARCH("Unemployment",C50)),ISNUMBER(SEARCH("Claims",C50)),ISNUMBER(SEARCH("Jobless",C50)),ISNUMBER(SEARCH("Inventories",C50)),ISNUMBER(SEARCH("Wholesale Inventories",C50)),ISNUMBER(SEARCH("JOLTS Job Openings",C50)),ISNUMBER(SEARCH("Inflation Expectations",C50))),-1,1) -> 1 | K50: =IF(OR(G50="",G50="(NA)"),"",J50*G50) -> 9.7 | L50: =IF(OR(H50="",H50="(NA)"),"",J50*H50) -> 6.8
A51: 46002 | B51: Growth - US | C51: Final Wholesale Inventories m/m | D51: 0.005 | E51: 0.001 | F51: 0 | G51: =IF(NOT(ISNUMBER(Table9[[#This Row],[Actual]])),"",IF(NOT(ISNUMBER(Table9[[#This Row],[Forecast]])),"",Table9[[#This Row],[Actual]]-Table9[[#This Row],[Forecast]])) -> 0.004 | H51: =IF(NOT(ISNUMBER(Table9[[#This Row],[Actual]])),"",IF(NOT(ISNUMBER(Table9[[#This Row],[Previous]])),"",Table9[[#This Row],[Actual]]-Table9[[#This Row],[Previous]])) -> 0.005 | I51: =IF(AND(K51="",L51=""),"N/A",IF(AND(ABS(N(K51))<0.0005,ABS(N(L51))<0.0005),"Stable",IF(AND(L51="",ABS(N(K51))>=0.0005),IF(N(K51)>0,"Accelerating","Slowing"),IF(AND(K51="",ABS(N(L51))>=0.0005),IF(N(L51)>0,"Accelerating","Slowing"),IF(AND(N(K51)>0,N(L51)>=0),"Accelerating",IF(AND(N(K51)<0,N(L51)<=0),"Slowing","Mixed")))))) -> Slowing | J51: =IF(OR(ISNUMBER(SEARCH("Unemployment",C51)),ISNUMBER(SEARCH("Claims",C51)),ISNUMBER(SEARCH("Jobless",C51)),ISNUMBER(SEARCH("Inventories",C51)),ISNUMBER(SEARCH("Wholesale Inventories",C51)),ISNUMBER(SEARCH("JOLTS Job Openings",C51)),ISNUMBER(SEARCH("Inflation Expectations",C51))),-1,1) -> -1 | K51: =IF(OR(G51="",G51="(NA)"),"",J51*G51) -> -0.004 | L51: =IF(OR(H51="",H51="(NA)"),"",J51*H51) -> -0.005
A52: 46003 | B52: Inflation – EUR | C52: German Final CPI m/m | D52: -0.002 | E52: -0.002 | F52: -0.002 | G52: =IF(NOT(ISNUMBER(Table9[[#This Row],[Actual]])),"",IF(NOT(ISNUMBER(Table9[[#This Row],[Forecast]])),"",Table9[[#This Row],[Actual]]-Table9[[#This Row],[Forecast]])) -> 0 | H52: =IF(NOT(ISNUMBER(Table9[[#This Row],[Actual]])),"",IF(NOT(ISNUMBER(Table9[[#This Row],[Previous]])),"",Table9[[#This Row],[Actual]]-Table9[[#This Row],[Previous]])) -> 0 | I52: =IF(AND(K52="",L52=""),"N/A",IF(AND(ABS(N(K52))<0.0005,ABS(N(L52))<0.0005),"Stable",IF(AND(L52="",ABS(N(K52))>=0.0005),IF(N(K52)>0,"Accelerating","Slowing"),IF(AND(K52="",ABS(N(L52))>=0.0005),IF(N(L52)>0,"Accelerating","Slowing"),IF(AND(N(K52)>0,N(L52)>=0),"Accelerating",IF(AND(N(K52)<0,N(L52)<=0),"Slowing","Mixed")))))) -> Stable | J52: =IF(OR(ISNUMBER(SEARCH("Unemployment",C52)),ISNUMBER(SEARCH("Claims",C52)),ISNUMBER(SEARCH("Jobless",C52)),ISNUMBER(SEARCH("Inventories",C52)),ISNUMBER(SEARCH("Wholesale Inventories",C52)),ISNUMBER(SEARCH("JOLTS Job Openings",C52)),ISNUMBER(SEARCH("Inflation Expectations",C52))),-1,1) -> 1 | K52: =IF(OR(G52="",G52="(NA)"),"",J52*G52) -> 0 | L52: =IF(OR(H52="",H52="(NA)"),"",J52*H52) -> 0
A53: 46003 | B53: Inflation – EUR | C53: French Final CPI m/m | D53: -0.002 | E53: -0.001 | F53: -0.001 | G53: =IF(NOT(ISNUMBER(Table9[[#This Row],[Actual]])),"",IF(NOT(ISNUMBER(Table9[[#This Row],[Forecast]])),"",Table9[[#This Row],[Actual]]-Table9[[#This Row],[Forecast]])) -> -0.001 | H53: =IF(NOT(ISNUMBER(Table9[[#This Row],[Actual]])),"",IF(NOT(ISNUMBER(Table9[[#This Row],[Previous]])),"",Table9[[#This Row],[Actual]]-Table9[[#This Row],[Previous]])) -> -0.001 | I53: =IF(AND(K53="",L53=""),"N/A",IF(AND(ABS(N(K53))<0.0005,ABS(N(L53))<0.0005),"Stable",IF(AND(L53="",ABS(N(K53))>=0.0005),IF(N(K53)>0,"Accelerating","Slowing"),IF(AND(K53="",ABS(N(L53))>=0.0005),IF(N(L53)>0,"Accelerating","Slowing"),IF(AND(N(K53)>0,N(L53)>=0),"Accelerating",IF(AND(N(K53)<0,N(L53)<=0),"Slowing","Mixed")))))) -> Slowing | J53: =IF(OR(ISNUMBER(SEARCH("Unemployment",C53)),ISNUMBER(SEARCH("Claims",C53)),ISNUMBER(SEARCH("Jobless",C53)),ISNUMBER(SEARCH("Inventories",C53)),ISNUMBER(SEARCH("Wholesale Inventories",C53)),ISNUMBER(SEARCH("JOLTS Job Openings",C53)),ISNUMBER(SEARCH("Inflation Expectations",C53))),-1,1) -> 1 | K53: =IF(OR(G53="",G53="(NA)"),"",J53*G53) -> -0.001 | L53: =IF(OR(H53="",H53="(NA)"),"",J53*H53) -> -0.001
